Workbook
Name _INTERNAL_KEY1: '1. ГПП-АГПЗ+'!$9:$9
Name _INTERNAL_KEY10: '10. ГД Ноябрьск'!$10:$10
Name _INTERNAL_KEY11: '11. ГД Надым'!$9:$9
Name _INTERNAL_KEY12: '12. ГД Иркутск'!$9:$9
Name _INTERNAL_KEY13: '13. ГД Шельф'!$9:$9
Name _INTERNAL_KEY14: '14. ГП Благовещенск (Ам ГПЗ)'!$9:$9
Name _INTERNAL_KEY15: '15. КСПГ Портовая'!$9:$9
Name _INTERNAL_KEY16: '16. Востокгазпром'!$9:$9
Name _INTERNAL_KEY17: '17. Нефтехим Салават'!$9:$9
Name _INTERNAL_KEY18: '18. Газпром нефть'!$9:$9
Name _INTERNAL_KEY2: '2. ГПП-ОГХК'!$9:$9
Name _INTERNAL_KEY3: '3. ГПП-СГПЗ'!$9:$9
Name _INTERNAL_KEY4: '4. ГПП-УЗПКТ-СЗСК'!$10:$10
Name _INTERNAL_KEY5: '5. ГД Астрахань'!$9:$9
Name _INTERNAL_KEY6: '6. ГД Оренбург'!$9:$9
Name _INTERNAL_KEY7: '7. ГД Ямбург'!$9:$9
Name _INTERNAL_KEY8: '8. ГД Уренгой'!$9:$9
Name _INTERNAL_KEY9: '9. ГД Краснодар'!$9:$9
Name _SET_ROW1: '1. ГПП-АГПЗ+'!$E:$I
Name _SET_ROW10: '10. ГД Ноябрьск'!$E:$I
Name _SET_ROW11: '11. ГД Надым'!$E:$I
Name _SET_ROW12: '12. ГД Иркутск'!$E:$I
Name _SET_ROW13: '13. ГД Шельф'!$E:$I
Name _SET_ROW14: '14. ГП Благовещенск (Ам ГПЗ)'!$E:$I
Name _SET_ROW15: '15. КСПГ Портовая'!$E:$I
Name _SET_ROW16: '16. Востокгазпром'!$E:$I
Name _SET_ROW17: '17. Нефтехим Салават'!$E:$I
Name _SET_ROW18: '18. Газпром нефть'!$E:$I
Name _SET_ROW2: '2. ГПП-ОГХК'!$E:$I
Name _SET_ROW3: '3. ГПП-СГПЗ'!$E:$I
Name _SET_ROW4: '4. ГПП-УЗПКТ-СЗСК'!$E:$I
Name _SET_ROW5: '5. ГД Астрахань'!$E:$I
Name _SET_ROW6: '6. ГД Оренбург'!$E:$I
Name _SET_ROW7: '7. ГД Ямбург'!$E:$I
Name _SET_ROW8: '8. ГД Уренгой'!$E:$I
Name _SET_ROW9: '9. ГД Краснодар'!$E:$I
Name _SUM_REP_INTERNAL_KEY1: 'План общий'!$9:$9
Name _SUM_REP_INTERNAL_KEY2: 'Баланс ЗС'!$9:$9
Name _SUM_REP_SET_ROW1: 'План общий'!$D:$H
Name _SUM_REP_SET_ROW2: 'Баланс ЗС'!$D:$H

Sheet tech
A1: Имя | B1: Стиль
A2: FONT_SIMPLE | B2: 1.2345679e+09
A3: FONT_FORMULA | B3: 1.2345679e+09
A4: FONT_TITLE_LVL0 | B4: Текст пример 1234567890,1234567891
A5: FONT_TITLE_LVL1 | B5: Текст пример 1234567890,1234567891
A6: RULES_GREEN_RED_DASH | B6: 1.2345679e+09
A7: FULL_BORDER | B7: Текст пример 1234567890,1234567891
A8: FORMAT_PERCENTAGE | B8: 0.76
A9: FONT_TITLE_LVL1_GROUP1 | B9: Текст пример 1234567890,1234567891
A10: FONT_TITLE_LVL2_GROUP1 | B10: Текст пример 1234567890,1234567891
A11: FONT_CHECKER1 | B11: 1.2345679e+09
A12: RULE_DASH_FOR_ZERO | B12: 0

Sheet План общий
B3: Показатели по переработке углеводородного сырья и производству продукции Группы Газпром на _______________ год/годы
B6: Показатели | D6: Внутренние настройки листа | I6: Един. изм. | J6: 2026 | K6: 2025 | N6: 2026 год 1 квартал | O6: 2025 год 1 квартал | R6: 2026 год январь | S6: 2025 год январь | V6: 2026 год февраль | W6: 2025 год февраль | Z6: 2026 год март | AA6: 2025 год март | AD6: 2026 год 2 квартал | AE6: 2025 год 2 квартал | AH6: 2026 год апрель | AI6: 2025 год апрель | AL6: 2026 год май | AM6: 2025 год май | AP6: 2026 год июнь | AQ6: 2025 год июнь | AT6: 2026 год 3 квартал | AU6: 2025 год 3 квартал | AX6: 2026 год июль | AY6: 2025 год июль | BB6: 2026 год август | BC6: 2025 год август | BF6: 2026 год сентябрь | BG6: 2025 год сентябрь | BJ6: 2026 год 4 квартал | BK6: 2025 год 4 квартал | BN6: 2026 год октябрь | BO6: 2025 год октябрь | BR6: 2026 год ноябрь | BS6: 2025 год ноябрь | BV6: 2026 год декабрь | BW6: 2025 год декабрь
D7: Ключ статьи | E7: Ключ спец | F7: Ключ ввод данных | G7: Формулы месяца | H7: Формулы % выхода | J7: Среднесрочн. план 2026: Вариант утвержденный | K7: Факт | L7: Отклонение | N7: Среднесрочн. план 2026: Вариант утвержденный | O7: Факт | P7: Отклонение | R7: Среднесрочн. план 2026: Вариант утвержденный | S7: Факт | T7: Отклонение | V7: Среднесрочн. план 2026: Вариант утвержденный | W7: Факт | X7: Отклонение | Z7: Среднесрочн. план 2026: Вариант утвержденный | AA7: Факт | AB7: Отклонение | AD7: Среднесрочн. план 2026: Вариант утвержденный | AE7: Факт | AF7: Отклонение | AH7: Среднесрочн. план 2026: Вариант утвержденный | AI7: Факт | AJ7: Отклонение | AL7: Среднесрочн. план 2026: Вариант утвержденный | AM7: Факт | AN7: Отклонение | AP7: Среднесрочн. план 2026: Вариант утвержденный | AQ7: Факт | AR7: Отклонение | AT7: Среднесрочн. план 2026: Вариант утвержденный | AU7: Факт | AV7: Отклонение | AX7: Среднесрочн. план 2026: Вариант утвержденный | AY7: Факт | AZ7: Отклонение | BB7: Среднесрочн. план 2026: Вариант утвержденный | BC7: Факт | BD7: Отклонение | BF7: Среднесрочн. план 2026: Вариант утвержденный | BG7: Факт | BH7: Отклонение | BJ7: Среднесрочн. план 2026: Вариант утвержденный | BK7: Факт | BL7: Отклонение | BN7: Среднесрочн. план 2026: Вариант утвержденный | BO7: Факт | BP7: Отклонение | BR7: Среднесрочн. план 2026: Вариант утвержденный | BS7: Факт | BT7: Отклонение | BV7: Среднесрочн. план 2026: Вариант утвержденный | BW7: Факт | BX7: Отклонение
L8: + / - | M8: % вып. | P8: + / - | Q8: % вып. | T8: + / - | U8: % вып. | X8: + / - | Y8: % вып. | AB8: + / - | AC8: % вып. | AF8: + / - | AG8: % вып. | AJ8: + / - | AK8: % вып. | AN8: + / - | AO8: % вып. | AR8: + / - | AS8: % вып. | AV8: + / - | AW8: % вып. | AZ8: + / - | BA8: % вып. | BD8: + / - | BE8: % вып. | BH8: + / - | BI8: % вып. | BL8: + / - | BM8: % вып. | BP8: + / - | BQ8: % вып. | BT8: + / - | BU8: % вып. | BX8: + / - | BY8: % вып.
J9: year2026:1:2260099 | K9: year2025:15:None | N9: year2026:Q1:1:2260099 | O9: year2025:Q1:15:None | R9: year2026:M1_1:1:2260099 | S9: year2025:M1_1:15:None | V9: year2026:M1_2:1:2260099 | W9: year2025:M1_2:15:None | Z9: year2026:M1_3:1:2260099 | AA9: year2025:M1_3:15:None | AD9: year2026:Q2:1:2260099 | AE9: year2025:Q2:15:None | AH9: year2026:M2_1:1:2260099 | AI9: year2025:M2_1:15:None | AL9: year2026:M2_2:1:2260099 | AM9: year2025:M2_2:15:None | AP9: year2026:M2_3:1:2260099 | AQ9: year2025:M2_3:15:None | AT9: year2026:Q3:1:2260099 | AU9: year2025:Q3:15:None | AX9: year2026:M3_1:1:2260099 | AY9: year2025:M3_1:15:None | BB9: year2026:M3_2:1:2260099 | BC9: year2025:M3_2:15:None | BF9: year2026:M3_3:1:2260099 | BG9: year2025:M3_3:15:None | BJ9: year2026:Q4:1:2260099 | BK9: year2025:Q4:15:None | BN9: year2026:M4_1:1:2260099 | BO9: year2025:M4_1:15:None | BR9: year2026:M4_2:1:2260099 | BS9: year2025:M4_2:15:None | BV9: year2026:M4_3:1:2260099 | BW9: year2025:M4_3:15:None
B10: Раздел 1. Прогнозные показатели по переработке углеводородного сырья и производству продукции ПАО "Газпром" и основных дочерних обществ
C11: CЫРЬЕ
B12: 1. | C12: Переработка газа на ГПЗ-всего | G12: 1_1003335807+2_100332038+2_100332040+2_100332042+2_100332044+2_100332916+2_100332944+2_100335129+3_100330552+3_100330008+14_100335074+14_100335076 | I12: млн куб.м. | J12: =N12+AD12+AT12+BJ12 -> 58789.9 | K12: =O12+AE12+AU12+BK12 -> 0 | L12: =IFERROR(K12-J12,"-") -> -58789.9 | M12: =IFERROR(K12/J12,"-") -> 0 | N12: =R12+V12+Z12 -> 14950.5 | O12: =S12+W12+AA12 -> 0 | P12: =IFERROR(O12-N12,"-") -> -14950.5 | Q12: =IFERROR(O12/N12,"-") -> 0 | R12: ='1. ГПП-АГПЗ+'!W22+'2. ГПП-ОГХК'!W21+'2. ГПП-ОГХК'!W25+'2. ГПП-ОГХК'!W27+'2. ГПП-ОГХК'!W29+'2. ГПП-ОГХК'!W31+'2. ГПП-ОГХК'!W33+'2. ГПП-ОГХК'!W35+'3. ГПП-СГПЗ'!W18+'3. ГПП-СГПЗ'!W16+'14. ГП Благовещенск (Ам ГПЗ)'!W31+'14. ГП Благовещенск (Ам ГПЗ)'!W33 -> 5298.6 | S12: ='1. ГПП-АГПЗ+'!Y22+'2. ГПП-ОГХК'!Y21+'2. ГПП-ОГХК'!Y25+'2. ГПП-ОГХК'!Y27+'2. ГПП-ОГХК'!Y29+'2. ГПП-ОГХК'!Y31+'2. ГПП-ОГХК'!Y33+'2. ГПП-ОГХК'!Y35+'3. ГПП-СГПЗ'!Y18+'3. ГПП-СГПЗ'!Y16+'14. ГП Благовещенск (Ам ГПЗ)'!Y31+'14. ГП Благовещенск (Ам ГПЗ)'!Y33 -> 0 | T12: =IFERROR(S12-R12,"-") -> -5298.6 | U12: =IFERROR(S12/R12,"-") -> 0 | V12: ='1. ГПП-АГПЗ+'!AC22+'2. ГПП-ОГХК'!AC21+'2. ГПП-ОГХК'!AC25+'2. ГПП-ОГХК'!AC27+'2. ГПП-ОГХК'!AC29+'2. ГПП-ОГХК'!AC31+'2. ГПП-ОГХК'!AC33+'2. ГПП-ОГХК'!AC35+'3. ГПП-СГПЗ'!AC18+'3. ГПП-СГПЗ'!AC16+'14. ГП Благовещенск (Ам ГПЗ)'!AC31+'14. ГП Благовещенск (Ам ГПЗ)'!AC33 -> 4785.6 | W12: ='1. ГПП-АГПЗ+'!AE22+'2. ГПП-ОГХК'!AE21+'2. ГПП-ОГХК'!AE25+'2. ГПП-ОГХК'!AE27+'2. ГПП-ОГХК'!AE29+'2. ГПП-ОГХК'!AE31+'2. ГПП-ОГХК'!AE33+'2. ГПП-ОГХК'!AE35+'3. ГПП-СГПЗ'!AE18+'3. ГПП-СГПЗ'!AE16+'14. ГП Благовещенск (Ам ГПЗ)'!AE31+'14. ГП Благовещенск (Ам ГПЗ)'!AE33 -> 0 | X12: =IFERROR(W12-V12,"-") -> -4785.6 | Y12: =IFERROR(W12/V12,"-") -> 0 | Z12: ='1. ГПП-АГПЗ+'!AI22+'2. ГПП-ОГХК'!AI21+'2. ГПП-ОГХК'!AI25+'2. ГПП-ОГХК'!AI27+'2. ГПП-ОГХК'!AI29+'2. ГПП-ОГХК'!AI31+'2. ГПП-ОГХК'!AI33+'2. ГПП-ОГХК'!AI35+'3. ГПП-СГПЗ'!AI18+'3. ГПП-СГПЗ'!AI16+'14. ГП Благовещенск (Ам ГПЗ)'!AI31+'14. ГП Благовещенск (Ам ГПЗ)'!AI33 -> 4866.3 | AA12: ='1. ГПП-АГПЗ+'!AK22+'2. ГПП-ОГХК'!AK21+'2. ГПП-ОГХК'!AK25+'2. ГПП-ОГХК'!AK27+'2. ГПП-ОГХК'!AK29+'2. ГПП-ОГХК'!AK31+'2. ГПП-ОГХК'!AK33+'2. ГПП-ОГХК'!AK35+'3. ГПП-СГПЗ'!AK18+'3. ГПП-СГПЗ'!AK16+'14. ГП Благовещенск (Ам ГПЗ)'!AK31+'14. ГП Благовещенск (Ам ГПЗ)'!AK33 -> 0 | AB12: =IFERROR(AA12-Z12,"-") -> -4866.3 | AC12: =IFERROR(AA12/Z12,"-") -> 0 | AD12: =AH12+AL12+AP12 -> 13601 | AE12: =AI12+AM12+AQ12 -> 0 | AF12: =IFERROR(AE12-AD12,"-") -> -13601 | AG12: =IFERROR(AE12/AD12,"-") -> 0 | AH12: ='1. ГПП-АГПЗ+'!AU22+'2. ГПП-ОГХК'!AU21+'2. ГПП-ОГХК'!AU25+'2. ГПП-ОГХК'!AU27+'2. ГПП-ОГХК'!AU29+'2. ГПП-ОГХК'!AU31+'2. ГПП-ОГХК'!AU33+'2. ГПП-ОГХК'!AU35+'3. ГПП-СГПЗ'!AU18+'3. ГПП-СГПЗ'!AU16+'14. ГП Благовещенск (Ам ГПЗ)'!AU31+'14. ГП Благовещенск (Ам ГПЗ)'!AU33 -> 4158.4 | AI12: ='1. ГПП-АГПЗ+'!AW22+'2. ГПП-ОГХК'!AW21+'2. ГПП-ОГХК'!AW25+'2. ГПП-ОГХК'!AW27+'2. ГПП-ОГХК'!AW29+'2. ГПП-ОГХК'!AW31+'2. ГПП-ОГХК'!AW33+'2. ГПП-ОГХК'!AW35+'3. ГПП-СГПЗ'!AW18+'3. ГПП-СГПЗ'!AW16+'14. ГП Благовещенск (Ам ГПЗ)'!AW31+'14. ГП Благовещенск (Ам ГПЗ)'!AW33 -> 0 | AJ12: =IFERROR(AI12-AH12,"-") -> -4158.4 | AK12: =IFERROR(AI12/AH12,"-") -> 0 | AL12: ='1. ГПП-АГПЗ+'!BA22+'2. ГПП-ОГХК'!BA21+'2. ГПП-ОГХК'!BA25+'2. ГПП-ОГХК'!BA27+'2. ГПП-ОГХК'!BA29+'2. ГПП-ОГХК'!BA31+'2. ГПП-ОГХК'!BA33+'2. ГПП-ОГХК'!BA35+'3. ГПП-СГПЗ'!BA18+'3. ГПП-СГПЗ'!BA16+'14. ГП Благовещенск (Ам ГПЗ)'!BA31+'14. ГП Благовещенск (Ам ГПЗ)'!BA33 -> 4817.5 | AM12: ='1. ГПП-АГПЗ+'!BC22+'2. ГПП-ОГХК'!BC21+'2. ГПП-ОГХК'!BC25+'2. ГПП-ОГХК'!BC27+'2. ГПП-ОГХК'!BC29+'2. ГПП-ОГХК'!BC31+'2. ГПП-ОГХК'!BC33+'2. ГПП-ОГХК'!BC35+'3. ГПП-СГПЗ'!BC18+'3. ГПП-СГПЗ'!BC16+'14. ГП Благовещенск (Ам ГПЗ)'!BC31+'14. ГП Благовещенск (Ам ГПЗ)'!BC33 -> 0 | AN12: =IFERROR(AM12-AL12,"-") -> -4817.5 | AO12: =IFERROR(AM12/AL12,"-") -> 0 | AP12: ='1. ГПП-АГПЗ+'!BG22+'2. ГПП-ОГХК'!BG21+'2. ГПП-ОГХК'!BG25+'2. ГПП-ОГХК'!BG27+'2. ГПП-ОГХК'!BG29+'2. ГПП-ОГХК'!BG31+'2. ГПП-ОГХК'!BG33+'2. ГПП-ОГХК'!BG35+'3. ГПП-СГПЗ'!BG18+'3. ГПП-СГПЗ'!BG16+'14. ГП Благовещенск (Ам ГПЗ)'!BG31+'14. ГП Благовещенск (Ам ГПЗ)'!BG33 -> 4625.1 | AQ12: ='1. ГПП-АГПЗ+'!BI22+'2. ГПП-ОГХК'!BI21+'2. ГПП-ОГХК'!BI25+'2. ГПП-ОГХК'!BI27+'2. ГПП-ОГХК'!BI29+'2. ГПП-ОГХК'!BI31+'2. ГПП-ОГХК'!BI33+'2. ГПП-ОГХК'!BI35+'3. ГПП-СГПЗ'!BI18+'3. ГПП-СГПЗ'!BI16+'14. ГП Благовещенск (Ам ГПЗ)'!BI31+'14. ГП Благовещенск (Ам ГПЗ)'!BI33 -> 0 | AR12: =IFERROR(AQ12-AP12,"-") -> -4625.1 | AS12: =IFERROR(AQ12/AP12,"-") -> 0 | AT12: =AX12+BB12+BF12 -> 14143.7 | AU12: =AY12+BC12+BG12 -> 0 | AV12: =IFERROR(AU12-AT12,"-") -> -14143.7 | AW12: =IFERROR(AU12/AT12,"-") -> 0 | AX12: ='1. ГПП-АГПЗ+'!BS22+'2. ГПП-ОГХК'!BS21+'2. ГПП-ОГХК'!BS25+'2. ГПП-ОГХК'!BS27+'2. ГПП-ОГХК'!BS29+'2. ГПП-ОГХК'!BS31+'2. ГПП-ОГХК'!BS33+'2. ГПП-ОГХК'!BS35+'3. ГПП-СГПЗ'!BS18+'3. ГПП-СГПЗ'!BS16+'14. ГП Благовещенск (Ам ГПЗ)'!BS31+'14. ГП Благовещенск (Ам ГПЗ)'!BS33 -> 5191 | AY12: ='1. ГПП-АГПЗ+'!BU22+'2. ГПП-ОГХК'!BU21+'2. ГПП-ОГХК'!BU25+'2. ГПП-ОГХК'!BU27+'2. ГПП-ОГХК'!BU29+'2. ГПП-ОГХК'!BU31+'2. ГПП-ОГХК'!BU33+'2. ГПП-ОГХК'!BU35+'3. ГПП-СГПЗ'!BU18+'3. ГПП-СГПЗ'!BU16+'14. ГП Благовещенск (Ам ГПЗ)'!BU31+'14. ГП Благовещенск (Ам ГПЗ)'!BU33 -> 0 | AZ12: =IFERROR(AY12-AX12,"-") -> -5191 | BA12: =IFERROR(AY12/AX12,"-") -> 0 | BB12: ='1. ГПП-АГПЗ+'!BY22+'2. ГПП-ОГХК'!BY21+'2. ГПП-ОГХК'!BY25+'2. ГПП-ОГХК'!BY27+'2. ГПП-ОГХК'!BY29+'2. ГПП-ОГХК'!BY31+'2. ГПП-ОГХК'!BY33+'2. ГПП-ОГХК'!BY35+'3. ГПП-СГПЗ'!BY18+'3. ГПП-СГПЗ'!BY16+'14. ГП Благовещенск (Ам ГПЗ)'!BY31+'14. ГП Благовещенск (Ам ГПЗ)'!BY33 -> 5195.3 | BC12: ='1. ГПП-АГПЗ+'!CA22+'2. ГПП-ОГХК'!CA21+'2. ГПП-ОГХК'!CA25+'2. ГПП-ОГХК'!CA27+'2. ГПП-ОГХК'!CA29+'2. ГПП-ОГХК'!CA31+'2. ГПП-ОГХК'!CA33+'2. ГПП-ОГХК'!CA35+'3. ГПП-СГПЗ'!CA18+'3. ГПП-СГПЗ'!CA16+'14. ГП Благовещенск (Ам ГПЗ)'!CA31+'14. ГП Благовещенск (Ам ГПЗ)'!CA33 -> 0 | BD12: =IFERROR(BC12-BB12,"-") -> -5195.3 | BE12: =IFERROR(BC12/BB12,"-") -> 0 | BF12: ='1. ГПП-АГПЗ+'!CE22+'2. ГПП-ОГХК'!CE21+'2. ГПП-ОГХК'!CE25+'2. ГПП-ОГХК'!CE27+'2. ГПП-ОГХК'!CE29+'2. ГПП-ОГХК'!CE31+'2. ГПП-ОГХК'!CE33+'2. ГПП-ОГХК'!CE35+'3. ГПП-СГПЗ'!CE18+'3. ГПП-СГПЗ'!CE16+'14. ГП Благовещенск (Ам ГПЗ)'!CE31+'14. ГП Благовещенск (Ам ГПЗ)'!CE33 -> 3757.4 | BG12: ='1. ГПП-АГПЗ+'!CG22+'2. ГПП-ОГХК'!CG21+'2. ГПП-ОГХК'!CG25+'2. ГПП-ОГХК'!CG27+'2. ГПП-ОГХК'!CG29+'2. ГПП-ОГХК'!CG31+'2. ГПП-ОГХК'!CG33+'2. ГПП-ОГХК'!CG35+'3. ГПП-СГПЗ'!CG18+'3. ГПП-СГПЗ'!CG16+'14. ГП Благовещенск (Ам ГПЗ)'!CG31+'14. ГП Благовещенск (Ам ГПЗ)'!CG33 -> 0 | BH12: =IFERROR(BG12-BF12,"-") -> -3757.4 | BI12: =IFERROR(BG12/BF12,"-") -> 0 | BJ12: =BN12+BR12+BV12 -> 16094.7 | BK12: =BO12+BS12+BW12 -> 0 | BL12: =IFERROR(BK12-BJ12,"-") -> -16094.7 | BM12: =IFERROR(BK12/BJ12,"-") -> 0 | BN12: ='1. ГПП-АГПЗ+'!CQ22+'2. ГПП-ОГХК'!CQ21+'2. ГПП-ОГХК'!CQ25+'2. ГПП-ОГХК'!CQ27+'2. ГПП-ОГХК'!CQ29+'2. ГПП-ОГХК'!CQ31+'2. ГПП-ОГХК'!CQ33+'2. ГПП-ОГХК'!CQ35+'3. ГПП-СГПЗ'!CQ18+'3. ГПП-СГПЗ'!CQ16+'14. ГП Благовещенск (Ам ГПЗ)'!CQ31+'14. ГП Благовещенск (Ам ГПЗ)'!CQ33 -> 5362.8 | BO12: ='1. ГПП-АГПЗ+'!CS22+'2. ГПП-ОГХК'!CS21+'2. ГПП-ОГХК'!CS25+'2. ГПП-ОГХК'!CS27+'2. ГПП-ОГХК'!CS29+'2. ГПП-ОГХК'!CS31+'2. ГПП-ОГХК'!CS33+'2. ГПП-ОГХК'!CS35+'3. ГПП-СГПЗ'!CS18+'3. ГПП-СГПЗ'!CS16+'14. ГП Благовещенск (Ам ГПЗ)'!CS31+'14. ГП Благовещенск (Ам ГПЗ)'!CS33 -> 0 | BP12: =IFERROR(BO12-BN12,"-") -> -5362.8 | BQ12: =IFERROR(BO12/BN12,"-") -> 0 | BR12: ='1. ГПП-АГПЗ+'!CW22+'2. ГПП-ОГХК'!CW21+'2. ГПП-ОГХК'!CW25+'2. ГПП-ОГХК'!CW27+'2. ГПП-ОГХК'!CW29+'2. ГПП-ОГХК'!CW31+'2. ГПП-ОГХК'!CW33+'2. ГПП-ОГХК'!CW35+'3. ГПП-СГПЗ'!CW18+'3. ГПП-СГПЗ'!CW16+'14. ГП Благовещенск (Ам ГПЗ)'!CW31+'14. ГП Благовещенск (Ам ГПЗ)'!CW33 -> 5279.1 | BS12: ='1. ГПП-АГПЗ+'!CY22+'2. ГПП-ОГХК'!CY21+'2. ГПП-ОГХК'!CY25+'2. ГПП-ОГХК'!CY27+'2. ГПП-ОГХК'!CY29+'2. ГПП-ОГХК'!CY31+'2. ГПП-ОГХК'!CY33+'2. ГПП-ОГХК'!CY35+'3. ГПП-СГПЗ'!CY18+'3. ГПП-СГПЗ'!CY16+'14. ГП Благовещенск (Ам ГПЗ)'!CY31+'14. ГП Благовещенск (Ам ГПЗ)'!CY33 -> 0 | BT12: =IFERROR(BS12-BR12,"-") -> -5279.1 | BU12: =IFERROR(BS12/BR12,"-") -> 0 | BV12: ='1. ГПП-АГПЗ+'!DC22+'2. ГПП-ОГХК'!DC21+'2. ГПП-ОГХК'!DC25+'2. ГПП-ОГХК'!DC27+'2. ГПП-ОГХК'!DC29+'2. ГПП-ОГХК'!DC31+'2. ГПП-ОГХК'!DC33+'2. ГПП-ОГХК'!DC35+'3. ГПП-СГПЗ'!DC18+'3. ГПП-СГПЗ'!DC16+'14. ГП Благовещенск (Ам ГПЗ)'!DC31+'14. ГП Благовещенск (Ам ГПЗ)'!DC33 -> 5452.8 | BW12: ='1. ГПП-АГПЗ+'!DE22+'2. ГПП-ОГХК'!DE21+'2. ГПП-ОГХК'!DE25+'2. ГПП-ОГХК'!DE27+'2. ГПП-ОГХК'!DE29+'2. ГПП-ОГХК'!DE31+'2. ГПП-ОГХК'!DE33+'2. ГПП-ОГХК'!DE35+'3. ГПП-СГПЗ'!DE18+'3. ГПП-СГПЗ'!DE16+'14. ГП Благовещенск (Ам ГПЗ)'!DE31+'14. ГП Благовещенск (Ам ГПЗ)'!DE33 -> 0 | BX12: =IFERROR(BW12-BV12,"-") -> -5452.8 | BY12: =IFERROR(BW12/BV12,"-") -> 0
C13: Газпром переработка | G13: 1_1003335807+2_100332038+2_100332040+2_100332042+2_100332044+2_100332916+2_100332944+2_100335129+3_100330552+3_100330008 | I13: млн куб.м. | J13: =N13+AD13+AT13+BJ13 -> 23405.1 | K13: =O13+AE13+AU13+BK13 -> 0 | L13: =IFERROR(K13-J13,"-") -> -23405.1 | M13: =IFERROR(K13/J13,"-") -> 0 | N13: =R13+V13+Z13 -> 6101.1 | O13: =S13+W13+AA13 -> 0 | P13: =IFERROR(O13-N13,"-") -> -6101.1 | Q13: =IFERROR(O13/N13,"-") -> 0 | R13: ='1. ГПП-АГПЗ+'!W22+'2. ГПП-ОГХК'!W21+'2. ГПП-ОГХК'!W25+'2. ГПП-ОГХК'!W27+'2. ГПП-ОГХК'!W29+'2. ГПП-ОГХК'!W31+'2. ГПП-ОГХК'!W33+'2. ГПП-ОГХК'!W35+'3. ГПП-СГПЗ'!W18+'3. ГПП-СГПЗ'!W16 -> 2108.7 | S13: ='1. ГПП-АГПЗ+'!Y22+'2. ГПП-ОГХК'!Y21+'2. ГПП-ОГХК'!Y25+'2. ГПП-ОГХК'!Y27+'2. ГПП-ОГХК'!Y29+'2. ГПП-ОГХК'!Y31+'2. ГПП-ОГХК'!Y33+'2. ГПП-ОГХК'!Y35+'3. ГПП-СГПЗ'!Y18+'3. ГПП-СГПЗ'!Y16 -> 0 | T13: =IFERROR(S13-R13,"-") -> -2108.7 | U13: =IFERROR(S13/R13,"-") -> 0 | V13: ='1. ГПП-АГПЗ+'!AC22+'2. ГПП-ОГХК'!AC21+'2. ГПП-ОГХК'!AC25+'2. ГПП-ОГХК'!AC27+'2. ГПП-ОГХК'!AC29+'2. ГПП-ОГХК'!AC31+'2. ГПП-ОГХК'!AC33+'2. ГПП-ОГХК'!AC35+'3. ГПП-СГПЗ'!AC18+'3. ГПП-СГПЗ'!AC16 -> 1904.5 | W13: ='1. ГПП-АГПЗ+'!AE22+'2. ГПП-ОГХК'!AE21+'2. ГПП-ОГХК'!AE25+'2. ГПП-ОГХК'!AE27+'2. ГПП-ОГХК'!AE29+'2. ГПП-ОГХК'!AE31+'2. ГПП-ОГХК'!AE33+'2. ГПП-ОГХК'!AE35+'3. ГПП-СГПЗ'!AE18+'3. ГПП-СГПЗ'!AE16 -> 0 | X13: =IFERROR(W13-V13,"-") -> -1904.5 | Y13: =IFERROR(W13/V13,"-") -> 0 | Z13: ='1. ГПП-АГПЗ+'!AI22+'2. ГПП-ОГХК'!AI21+'2. ГПП-ОГХК'!AI25+'2. ГПП-ОГХК'!AI27+'2. ГПП-ОГХК'!AI29+'2. ГПП-ОГХК'!AI31+'2. ГПП-ОГХК'!AI33+'2. ГПП-ОГХК'!AI35+'3. ГПП-СГПЗ'!AI18+'3. ГПП-СГПЗ'!AI16 -> 2087.9 | AA13: ='1. ГПП-АГПЗ+'!AK22+'2. ГПП-ОГХК'!AK21+'2. ГПП-ОГХК'!AK25+'2. ГПП-ОГХК'!AK27+'2. ГПП-ОГХК'!AK29+'2. ГПП-ОГХК'!AK31+'2. ГПП-ОГХК'!AK33+'2. ГПП-ОГХК'!AK35+'3. ГПП-СГПЗ'!AK18+'3. ГПП-СГПЗ'!AK16 -> 0 | AB13: =IFERROR(AA13-Z13,"-") -> -2087.9 | AC13: =IFERROR(AA13/Z13,"-") -> 0 | AD13: =AH13+AL13+AP13 -> 4893.6 | AE13: =AI13+AM13+AQ13 -> 0 | AF13: =IFERROR(AE13-AD13,"-") -> -4893.6 | AG13: =IFERROR(AE13/AD13,"-") -> 0 | AH13: ='1. ГПП-АГПЗ+'!AU22+'2. ГПП-ОГХК'!AU21+'2. ГПП-ОГХК'!AU25+'2. ГПП-ОГХК'!AU27+'2. ГПП-ОГХК'!AU29+'2. ГПП-ОГХК'!AU31+'2. ГПП-ОГХК'!AU33+'2. ГПП-ОГХК'!AU35+'3. ГПП-СГПЗ'!AU18+'3. ГПП-СГПЗ'!AU16 -> 1802.5 | AI13: ='1. ГПП-АГПЗ+'!AW22+'2. ГПП-ОГХК'!AW21+'2. ГПП-ОГХК'!AW25+'2. ГПП-ОГХК'!AW27+'2. ГПП-ОГХК'!AW29+'2. ГПП-ОГХК'!AW31+'2. ГПП-ОГХК'!AW33+'2. ГПП-ОГХК'!AW35+'3. ГПП-СГПЗ'!AW18+'3. ГПП-СГПЗ'!AW16 -> 0 | AJ13: =IFERROR(AI13-AH13,"-") -> -1802.5 | AK13: =IFERROR(AI13/AH13,"-") -> 0 | AL13: ='1. ГПП-АГПЗ+'!BA22+'2. ГПП-ОГХК'!BA21+'2. ГПП-ОГХК'!BA25+'2. ГПП-ОГХК'!BA27+'2. ГПП-ОГХК'!BA29+'2. ГПП-ОГХК'!BA31+'2. ГПП-ОГХК'!BA33+'2. ГПП-ОГХК'!BA35+'3. ГПП-СГПЗ'!BA18+'3. ГПП-СГПЗ'!BA16 -> 1618.9 | AM13: ='1. ГПП-АГПЗ+'!BC22+'2. ГПП-ОГХК'!BC21+'2. ГПП-ОГХК'!BC25+'2. ГПП-ОГХК'!BC27+'2. ГПП-ОГХК'!BC29+'2. ГПП-ОГХК'!BC31+'2. ГПП-ОГХК'!BC33+'2. ГПП-ОГХК'!BC35+'3. ГПП-СГПЗ'!BC18+'3. ГПП-СГПЗ'!BC16 -> 0 | AN13: =IFERROR(AM13-AL13,"-") -> -1618.9 | AO13: =IFERROR(AM13/AL13,"-") -> 0 | AP13: ='1. ГПП-АГПЗ+'!BG22+'2. ГПП-ОГХК'!BG21+'2. ГПП-ОГХК'!BG25+'2. ГПП-ОГХК'!BG27+'2. ГПП-ОГХК'!BG29+'2. ГПП-ОГХК'!BG31+'2. ГПП-ОГХК'!BG33+'2. ГПП-ОГХК'!BG35+'3. ГПП-СГПЗ'!BG18+'3. ГПП-СГПЗ'!BG16 -> 1472.2 | AQ13: ='1. ГПП-АГПЗ+'!BI22+'2. ГПП-ОГХК'!BI21+'2. ГПП-ОГХК'!BI25+'2. ГПП-ОГХК'!BI27+'2. ГПП-ОГХК'!BI29+'2. ГПП-ОГХК'!BI31+'2. ГПП-ОГХК'!BI33+'2. ГПП-ОГХК'!BI35+'3. ГПП-СГПЗ'!BI18+'3. ГПП-СГПЗ'!BI16 -> 0 | AR13: =IFERROR(AQ13-AP13,"-") -> -1472.2 | AS13: =IFERROR(AQ13/AP13,"-") -> 0 | AT13: =AX13+BB13+BF13 -> 5948.2 | AU13: =AY13+BC13+BG13 -> 0 | AV13: =IFERROR(AU13-AT13,"-") -> -5948.2 | AW13: =IFERROR(AU13/AT13,"-") -> 0 | AX13: ='1. ГПП-АГПЗ+'!BS22+'2. ГПП-ОГХК'!BS21+'2. ГПП-ОГХК'!BS25+'2. ГПП-ОГХК'!BS27+'2. ГПП-ОГХК'!BS29+'2. ГПП-ОГХК'!BS31+'2. ГПП-ОГХК'!BS33+'2. ГПП-ОГХК'!BS35+'3. ГПП-СГПЗ'!BS18+'3. ГПП-СГПЗ'!BS16 -> 1933 | AY13: ='1. ГПП-АГПЗ+'!BU22+'2. ГПП-ОГХК'!BU21+'2. ГПП-ОГХК'!BU25+'2. ГПП-ОГХК'!BU27+'2. ГПП-ОГХК'!BU29+'2. ГПП-ОГХК'!BU31+'2. ГПП-ОГХК'!BU33+'2. ГПП-ОГХК'!BU35+'3. ГПП-СГПЗ'!BU18+'3. ГПП-СГПЗ'!BU16 -> 0 | AZ13: =IFERROR(AY13-AX13,"-") -> -1933 | BA13: =IFERROR(AY13/AX13,"-") -> 0 | BB13: ='1. ГПП-АГПЗ+'!BY22+'2. ГПП-ОГХК'!BY21+'2. ГПП-ОГХК'!BY25+'2. ГПП-ОГХК'!BY27+'2. ГПП-ОГХК'!BY29+'2. ГПП-ОГХК'!BY31+'2. ГПП-ОГХК'!BY33+'2. ГПП-ОГХК'!BY35+'3. ГПП-СГПЗ'!BY18+'3. ГПП-СГПЗ'!BY16 -> 1937.2 | BC13: ='1. ГПП-АГПЗ+'!CA22+'2. ГПП-ОГХК'!CA21+'2. ГПП-ОГХК'!CA25+'2. ГПП-ОГХК'!CA27+'2. ГПП-ОГХК'!CA29+'2. ГПП-ОГХК'!CA31+'2. ГПП-ОГХК'!CA33+'2. ГПП-ОГХК'!CA35+'3. ГПП-СГПЗ'!CA18+'3. ГПП-СГПЗ'!CA16 -> 0 | BD13: =IFERROR(BC13-BB13,"-") -> -1937.2 | BE13: =IFERROR(BC13/BB13,"-") -> 0 | BF13: ='1. ГПП-АГПЗ+'!CE22+'2. ГПП-ОГХК'!CE21+'2. ГПП-ОГХК'!CE25+'2. ГПП-ОГХК'!CE27+'2. ГПП-ОГХК'!CE29+'2. ГПП-ОГХК'!CE31+'2. ГПП-ОГХК'!CE33+'2. ГПП-ОГХК'!CE35+'3. ГПП-СГПЗ'!CE18+'3. ГПП-СГПЗ'!CE16 -> 2078 | BG13: ='1. ГПП-АГПЗ+'!CG22+'2. ГПП-ОГХК'!CG21+'2. ГПП-ОГХК'!CG25+'2. ГПП-ОГХК'!CG27+'2. ГПП-ОГХК'!CG29+'2. ГПП-ОГХК'!CG31+'2. ГПП-ОГХК'!CG33+'2. ГПП-ОГХК'!CG35+'3. ГПП-СГПЗ'!CG18+'3. ГПП-СГПЗ'!CG16 -> 0 | BH13: =IFERROR(BG13-BF13,"-") -> -2078 | BI13: =IFERROR(BG13/BF13,"-") -> 0 | BJ13: =BN13+BR13+BV13 -> 6462.2 | BK13: =BO13+BS13+BW13 -> 0 | BL13: =IFERROR(BK13-BJ13,"-") -> -6462.2 | BM13: =IFERROR(BK13/BJ13,"-") -> 0 | BN13: ='1. ГПП-АГПЗ+'!CQ22+'2. ГПП-ОГХК'!CQ21+'2. ГПП-ОГХК'!CQ25+'2. ГПП-ОГХК'!CQ27+'2. ГПП-ОГХК'!CQ29+'2. ГПП-ОГХК'!CQ31+'2. ГПП-ОГХК'!CQ33+'2. ГПП-ОГХК'!CQ35+'3. ГПП-СГПЗ'!CQ18+'3. ГПП-СГПЗ'!CQ16 -> 2141.4 | BO13: ='1. ГПП-АГПЗ+'!CS22+'2. ГПП-ОГХК'!CS21+'2. ГПП-ОГХК'!CS25+'2. ГПП-ОГХК'!CS27+'2. ГПП-ОГХК'!CS29+'2. ГПП-ОГХК'!CS31+'2. ГПП-ОГХК'!CS33+'2. ГПП-ОГХК'!CS35+'3. ГПП-СГПЗ'!CS18+'3. ГПП-СГПЗ'!CS16 -> 0 | BP13: =IFERROR(BO13-BN13,"-") -> -2141.4 | BQ13: =IFERROR(BO13/BN13,"-") -> 0 | BR13: ='1. ГПП-АГПЗ+'!CW22+'2. ГПП-ОГХК'!CW21+'2. ГПП-ОГХК'!CW25+'2. ГПП-ОГХК'!CW27+'2. ГПП-ОГХК'!CW29+'2. ГПП-ОГХК'!CW31+'2. ГПП-ОГХК'!CW33+'2. ГПП-ОГХК'!CW35+'3. ГПП-СГПЗ'!CW18+'3. ГПП-СГПЗ'!CW16 -> 2126.1 | BS13: ='1. ГПП-АГПЗ+'!CY22+'2. ГПП-ОГХК'!CY21+'2. ГПП-ОГХК'!CY25+'2. ГПП-ОГХК'!CY27+'2. ГПП-ОГХК'!CY29+'2. ГПП-ОГХК'!CY31+'2. ГПП-ОГХК'!CY33+'2. ГПП-ОГХК'!CY35+'3. ГПП-СГПЗ'!CY18+'3. ГПП-СГПЗ'!CY16 -> 0 | BT13: =IFERROR(BS13-BR13,"-") -> -2126.1 | BU13: =IFERROR(BS13/BR13,"-") -> 0 | BV13: ='1. ГПП-АГПЗ+'!DC22+'2. ГПП-ОГХК'!DC21+'2. ГПП-ОГХК'!DC25+'2. ГПП-ОГХК'!DC27+'2. ГПП-ОГХК'!DC29+'2. ГПП-ОГХК'!DC31+'2. ГПП-ОГХК'!DC33+'2. ГПП-ОГХК'!DC35+'3. ГПП-СГПЗ'!DC18+'3. ГПП-СГПЗ'!DC16 -> 2194.7 | BW13: ='1. ГПП-АГПЗ+'!DE22+'2. ГПП-ОГХК'!DE21+'2. ГПП-ОГХК'!DE25+'2. ГПП-ОГХК'!DE27+'2. ГПП-ОГХК'!DE29+'2. ГПП-ОГХК'!DE31+'2. ГПП-ОГХК'!DE33+'2. ГПП-ОГХК'!DE35+'3. ГПП-СГПЗ'!DE18+'3. ГПП-СГПЗ'!DE16 -> 0 | BX13: =IFERROR(BW13-BV13,"-") -> -2194.7 | BY13: =IFERROR(BW13/BV13,"-") -> 0
C14: Астраханский ГПЗ | G14: 1_1003335807 | I14: млн куб.м. | J14: =N14+AD14+AT14+BJ14 -> 9676.5 | K14: =O14+AE14+AU14+BK14 -> 0 | L14: =IFERROR(K14-J14,"-") -> -9676.5 | M14: =IFERROR(K14/J14,"-") -> 0 | N14: =R14+V14+Z14 -> 2427.6 | O14: =S14+W14+AA14 -> 0 | P14: =IFERROR(O14-N14,"-") -> -2427.6 | Q14: =IFERROR(O14/N14,"-") -> 0 | R14: ='1. ГПП-АГПЗ+'!W22 -> 836.1 | S14: ='1. ГПП-АГПЗ+'!Y22 -> 0 | T14: =IFERROR(S14-R14,"-") -> -836.1 | U14: =IFERROR(S14/R14,"-") -> 0 | V14: ='1. ГПП-АГПЗ+'!AC22 -> 755.3 | W14: ='1. ГПП-АГПЗ+'!AE22 -> 0 | X14: =IFERROR(W14-V14,"-") -> -755.3 | Y14: =IFERROR(W14/V14,"-") -> 0 | Z14: ='1. ГПП-АГПЗ+'!AI22 -> 836.2 | AA14: ='1. ГПП-АГПЗ+'!AK22 -> 0 | AB14: =IFERROR(AA14-Z14,"-") -> -836.2 | AC14: =IFERROR(AA14/Z14,"-") -> 0 | AD14: =AH14+AL14+AP14 -> 1851.5 | AE14: =AI14+AM14+AQ14 -> 0 | AF14: =IFERROR(AE14-AD14,"-") -> -1851.5 | AG14: =IFERROR(AE14/AD14,"-") -> 0 | AH14: ='1. ГПП-АГПЗ+'!AU22 -> 809.2 | AI14: ='1. ГПП-АГПЗ+'!AW22 -> 0 | AJ14: =IFERROR(AI14-AH14,"-") -> -809.2 | AK14: =IFERROR(AI14/AH14,"-") -> 0 | AL14: ='1. ГПП-АГПЗ+'!BA22 -> 574.9 | AM14: ='1. ГПП-АГПЗ+'!BC22 -> 0 | AN14: =IFERROR(AM14-AL14,"-") -> -574.9 | AO14: =IFERROR(AM14/AL14,"-") -> 0 | AP14: ='1. ГПП-АГПЗ+'!BG22 -> 467.4 | AQ14: ='1. ГПП-АГПЗ+'!BI22 -> 0 | AR14: =IFERROR(AQ14-AP14,"-") -> -467.4 | AS14: =IFERROR(AQ14/AP14,"-") -> 0 | AT14: =AX14+BB14+BF14 -> 2641.8 | AU14: =AY14+BC14+BG14 -> 0 | AV14: =IFERROR(AU14-AT14,"-") -> -2641.8 | AW14: =IFERROR(AU14/AT14,"-") -> 0 | AX14: ='1. ГПП-АГПЗ+'!BS22 -> 869.4 | AY14: ='1. ГПП-АГПЗ+'!BU22 -> 0 | AZ14: =IFERROR(AY14-AX14,"-") -> -869.4 | BA14: =IFERROR(AY14/AX14,"-") -> 0 | BB14: ='1. ГПП-АГПЗ+'!BY22 -> 873.4 | BC14: ='1. ГПП-АГПЗ+'!CA22 -> 0 | BD14: =IFERROR(BC14-BB14,"-") -> -873.4 | BE14: =IFERROR(BC14/BB14,"-") -> 0 | BF14: ='1. ГПП-АГПЗ+'!CE22 -> 899 | BG14: ='1. ГПП-АГПЗ+'!CG22 -> 0 | BH14: =IFERROR(BG14-BF14,"-") -> -899 | BI14: =IFERROR(BG14/BF14,"-") -> 0 | BJ14: =BN14+BR14+BV14 -> 2755.6 | BK14: =BO14+BS14+BW14 -> 0 | BL14: =IFERROR(BK14-BJ14,"-") -> -2755.6 | BM14: =IFERROR(BK14/BJ14,"-") -> 0 | BN14: ='1. ГПП-АГПЗ+'!CQ22 -> 929.1 | BO14: ='1. ГПП-АГПЗ+'!CS22 -> 0 | BP14: =IFERROR(BO14-BN14,"-") -> -929.1 | BQ14: =IFERROR(BO14/BN14,"-") -> 0 | BR14: ='1. ГПП-АГПЗ+'!CW22 -> 899.1 | BS14: ='1. ГПП-АГПЗ+'!CY22 -> 0 | BT14: =IFERROR(BS14-BR14,"-") -> -899.1 | BU14: =IFERROR(BS14/BR14,"-") -> 0 | BV14: ='1. ГПП-АГПЗ+'!DC22 -> 927.4 | BW14: ='1. ГПП-АГПЗ+'!DE22 -> 0 | BX14: =IFERROR(BW14-BV14,"-") -> -927.4 | BY14: =IFERROR(BW14/BV14,"-") -> 0
C15: Оренбургский ГХК | G15: 2_100332038+2_100332040+2_100332042+2_100332044+2_100332916+2_100332944+2_100335129 | I15: млн куб.м. | J15: =N15+AD15+AT15+BJ15 -> 11699.1 | K15: =O15+AE15+AU15+BK15 -> 0 | L15: =IFERROR(K15-J15,"-") -> -11699.1 | M15: =IFERROR(K15/J15,"-") -> 0 | N15: =R15+V15+Z15 -> 3146.3 | O15: =S15+W15+AA15 -> 0 | P15: =IFERROR(O15-N15,"-") -> -3146.3 | Q15: =IFERROR(O15/N15,"-") -> 0 | R15: ='2. ГПП-ОГХК'!W21+'2. ГПП-ОГХК'!W25+'2. ГПП-ОГХК'!W27+'2. ГПП-ОГХК'!W29+'2. ГПП-ОГХК'!W31+'2. ГПП-ОГХК'!W33+'2. ГПП-ОГХК'!W35 -> 1091.1 | S15: ='2. ГПП-ОГХК'!Y21+'2. ГПП-ОГХК'!Y25+'2. ГПП-ОГХК'!Y27+'2. ГПП-ОГХК'!Y29+'2. ГПП-ОГХК'!Y31+'2. ГПП-ОГХК'!Y33+'2. ГПП-ОГХК'!Y35 -> 0 | T15: =IFERROR(S15-R15,"-") -> -1091.1 | U15: =IFERROR(S15/R15,"-") -> 0 | V15: ='2. ГПП-ОГХК'!AC21+'2. ГПП-ОГХК'!AC25+'2. ГПП-ОГХК'!AC27+'2. ГПП-ОГХК'!AC29+'2. ГПП-ОГХК'!AC31+'2. ГПП-ОГХК'!AC33+'2. ГПП-ОГХК'!AC35 -> 985.3 | W15: ='2. ГПП-ОГХК'!AE21+'2. ГПП-ОГХК'!AE25+'2. ГПП-ОГХК'!AE27+'2. ГПП-ОГХК'!AE29+'2. ГПП-ОГХК'!AE31+'2. ГПП-ОГХК'!AE33+'2. ГПП-ОГХК'!AE35 -> 0 | X15: =IFERROR(W15-V15,"-") -> -985.3 | Y15: =IFERROR(W15/V15,"-") -> 0 | Z15: ='2. ГПП-ОГХК'!AI21+'2. ГПП-ОГХК'!AI25+'2. ГПП-ОГХК'!AI27+'2. ГПП-ОГХК'!AI29+'2. ГПП-ОГХК'!AI31+'2. ГПП-ОГХК'!AI33+'2. ГПП-ОГХК'!AI35 -> 1069.9 | AA15: ='2. ГПП-ОГХК'!AK21+'2. ГПП-ОГХК'!AK25+'2. ГПП-ОГХК'!AK27+'2. ГПП-ОГХК'!AK29+'2. ГПП-ОГХК'!AK31+'2. ГПП-ОГХК'!AK33+'2. ГПП-ОГХК'!AK35 -> 0 | AB15: =IFERROR(AA15-Z15,"-") -> -1069.9 | AC15: =IFERROR(AA15/Z15,"-") -> 0 | AD15: =AH15+AL15+AP15 -> 2580 | AE15: =AI15+AM15+AQ15 -> 0 | AF15: =IFERROR(AE15-AD15,"-") -> -2580 | AG15: =IFERROR(AE15/AD15,"-") -> 0 | AH15: ='2. ГПП-ОГХК'!AU21+'2. ГПП-ОГХК'!AU25+'2. ГПП-ОГХК'!AU27+'2. ГПП-ОГХК'!AU29+'2. ГПП-ОГХК'!AU31+'2. ГПП-ОГХК'!AU33+'2. ГПП-ОГХК'!AU35 -> 894.5 | AI15: ='2. ГПП-ОГХК'!AW21+'2. ГПП-ОГХК'!AW25+'2. ГПП-ОГХК'!AW27+'2. ГПП-ОГХК'!AW29+'2. ГПП-ОГХК'!AW31+'2. ГПП-ОГХК'!AW33+'2. ГПП-ОГХК'!AW35 -> 0 | AJ15: =IFERROR(AI15-AH15,"-") -> -894.5 | AK15: =IFERROR(AI15/AH15,"-") -> 0 | AL15: ='2. ГПП-ОГХК'!BA21+'2. ГПП-ОГХК'!BA25+'2. ГПП-ОГХК'!BA27+'2. ГПП-ОГХК'!BA29+'2. ГПП-ОГХК'!BA31+'2. ГПП-ОГХК'!BA33+'2. ГПП-ОГХК'!BA35 -> 861.1 | AM15: ='2. ГПП-ОГХК'!BC21+'2. ГПП-ОГХК'!BC25+'2. ГПП-ОГХК'!BC27+'2. ГПП-ОГХК'!BC29+'2. ГПП-ОГХК'!BC31+'2. ГПП-ОГХК'!BC33+'2. ГПП-ОГХК'!BC35 -> 0 | AN15: =IFERROR(AM15-AL15,"-") -> -861.1 | AO15: =IFERROR(AM15/AL15,"-") -> 0 | AP15: ='2. ГПП-ОГХК'!BG21+'2. ГПП-ОГХК'!BG25+'2. ГПП-ОГХК'!BG27+'2. ГПП-ОГХК'!BG29+'2. ГПП-ОГХК'!BG31+'2. ГПП-ОГХК'!BG33+'2. ГПП-ОГХК'!BG35 -> 824.4 | AQ15: ='2. ГПП-ОГХК'!BI21+'2. ГПП-ОГХК'!BI25+'2. ГПП-ОГХК'!BI27+'2. ГПП-ОГХК'!BI29+'2. ГПП-ОГХК'!BI31+'2. ГПП-ОГХК'!BI33+'2. ГПП-ОГХК'!BI35 -> 0 | AR15: =IFERROR(AQ15-AP15,"-") -> -824.4 | AS15: =IFERROR(AQ15/AP15,"-") -> 0 | AT15: =AX15+BB15+BF15 -> 2756.3 | AU15: =AY15+BC15+BG15 -> 0 | AV15: =IFERROR(AU15-AT15,"-") -> -2756.3 | AW15: =IFERROR(AU15/AT15,"-") -> 0 | AX15: ='2. ГПП-ОГХК'!BS21+'2. ГПП-ОГХК'!BS25+'2. ГПП-ОГХК'!BS27+'2. ГПП-ОГХК'!BS29+'2. ГПП-ОГХК'!BS31+'2. ГПП-ОГХК'!BS33+'2. ГПП-ОГХК'!BS35 -> 877 | AY15: ='2. ГПП-ОГХК'!BU21+'2. ГПП-ОГХК'!BU25+'2. ГПП-ОГХК'!BU27+'2. ГПП-ОГХК'!BU29+'2. ГПП-ОГХК'!BU31+'2. ГПП-ОГХК'!BU33+'2. ГПП-ОГХК'!BU35 -> 0 | AZ15: =IFERROR(AY15-AX15,"-") -> -877 | BA15: =IFERROR(AY15/AX15,"-") -> 0 | BB15: ='2. ГПП-ОГХК'!BY21+'2. ГПП-ОГХК'!BY25+'2. ГПП-ОГХК'!BY27+'2. ГПП-ОГХК'!BY29+'2. ГПП-ОГХК'!BY31+'2. ГПП-ОГХК'!BY33+'2. ГПП-ОГХК'!BY35 -> 877.6 | BC15: ='2. ГПП-ОГХК'!CA21+'2. ГПП-ОГХК'!CA25+'2. ГПП-ОГХК'!CA27+'2. ГПП-ОГХК'!CA29+'2. ГПП-ОГХК'!CA31+'2. ГПП-ОГХК'!CA33+'2. ГПП-ОГХК'!CA35 -> 0 | BD15: =IFERROR(BC15-BB15,"-") -> -877.6 | BE15: =IFERROR(BC15/BB15,"-") -> 0 | BF15: ='2. ГПП-ОГХК'!CE21+'2. ГПП-ОГХК'!CE25+'2. ГПП-ОГХК'!CE27+'2. ГПП-ОГХК'!CE29+'2. ГПП-ОГХК'!CE31+'2. ГПП-ОГХК'!CE33+'2. ГПП-ОГХК'!CE35 -> 1001.7 | BG15: ='2. ГПП-ОГХК'!CG21+'2. ГПП-ОГХК'!CG25+'2. ГПП-ОГХК'!CG27+'2. ГПП-ОГХК'!CG29+'2. ГПП-ОГХК'!CG31+'2. ГПП-ОГХК'!CG33+'2. ГПП-ОГХК'!CG35 -> 0 | BH15: =IFERROR(BG15-BF15,"-") -> -1001.7 | BI15: =IFERROR(BG15/BF15,"-") -> 0 | BJ15: =BN15+BR15+BV15 -> 3216.5 | BK15: =BO15+BS15+BW15 -> 0 | BL15: =IFERROR(BK15-BJ15,"-") -> -3216.5 | BM15: =IFERROR(BK15/BJ15,"-") -> 0 | BN15: ='2. ГПП-ОГХК'!CQ21+'2. ГПП-ОГХК'!CQ25+'2. ГПП-ОГХК'!CQ27+'2. ГПП-ОГХК'!CQ29+'2. ГПП-ОГХК'!CQ31+'2. ГПП-ОГХК'!CQ33+'2. ГПП-ОГХК'!CQ35 -> 1084.8 | BO15: ='2. ГПП-ОГХК'!CS21+'2. ГПП-ОГХК'!CS25+'2. ГПП-ОГХК'!CS27+'2. ГПП-ОГХК'!CS29+'2. ГПП-ОГХК'!CS31+'2. ГПП-ОГХК'!CS33+'2. ГПП-ОГХК'!CS35 -> 0 | BP15: =IFERROR(BO15-BN15,"-") -> -1084.8 | BQ15: =IFERROR(BO15/BN15,"-") -> 0 | BR15: ='2. ГПП-ОГХК'!CW21+'2. ГПП-ОГХК'!CW25+'2. ГПП-ОГХК'!CW27+'2. ГПП-ОГХК'!CW29+'2. ГПП-ОГХК'!CW31+'2. ГПП-ОГХК'!CW33+'2. ГПП-ОГХК'!CW35 -> 1048.7 | BS15: ='2. ГПП-ОГХК'!CY21+'2. ГПП-ОГХК'!CY25+'2. ГПП-ОГХК'!CY27+'2. ГПП-ОГХК'!CY29+'2. ГПП-ОГХК'!CY31+'2. ГПП-ОГХК'!CY33+'2. ГПП-ОГХК'!CY35 -> 0 | BT15: =IFERROR(BS15-BR15,"-") -> -1048.7 | BU15: =IFERROR(BS15/BR15,"-") -> 0 | BV15: ='2. ГПП-ОГХК'!DC21+'2. ГПП-ОГХК'!DC25+'2. ГПП-ОГХК'!DC27+'2. ГПП-ОГХК'!DC29+'2. ГПП-ОГХК'!DC31+'2. ГПП-ОГХК'!DC33+'2. ГПП-ОГХК'!DC35 -> 1083 | BW15: ='2. ГПП-ОГХК'!DE21+'2. ГПП-ОГХК'!DE25+'2. ГПП-ОГХК'!DE27+'2. ГПП-ОГХК'!DE29+'2. ГПП-ОГХК'!DE31+'2. ГПП-ОГХК'!DE33+'2. ГПП-ОГХК'!DE35 -> 0 | BX15: =IFERROR(BW15-BV15,"-") -> -1083 | BY15: =IFERROR(BW15/BV15,"-") -> 0
C16: Сосногорский ГПЗ | G16: 3_100330552+3_100330008 | I16: млн куб.м. | J16: =N16+AD16+AT16+BJ16 -> 2029.5 | K16: =O16+AE16+AU16+BK16 -> 0 | L16: =IFERROR(K16-J16,"-") -> -2029.5 | M16: =IFERROR(K16/J16,"-") -> 0 | N16: =R16+V16+Z16 -> 527.2 | O16: =S16+W16+AA16 -> 0 | P16: =IFERROR(O16-N16,"-") -> -527.2 | Q16: =IFERROR(O16/N16,"-") -> 0 | R16: ='3. ГПП-СГПЗ'!W18+'3. ГПП-СГПЗ'!W16 -> 181.5 | S16: ='3. ГПП-СГПЗ'!Y18+'3. ГПП-СГПЗ'!Y16 -> 0 | T16: =IFERROR(S16-R16,"-") -> -181.5 | U16: =IFERROR(S16/R16,"-") -> 0 | V16: ='3. ГПП-СГПЗ'!AC18+'3. ГПП-СГПЗ'!AC16 -> 163.9 | W16: ='3. ГПП-СГПЗ'!AE18+'3. ГПП-СГПЗ'!AE16 -> 0 | X16: =IFERROR(W16-V16,"-") -> -163.9 | Y16: =IFERROR(W16/V16,"-") -> 0 | Z16: ='3. ГПП-СГПЗ'!AI18+'3. ГПП-СГПЗ'!AI16 -> 181.8 | AA16: ='3. ГПП-СГПЗ'!AK18+'3. ГПП-СГПЗ'!AK16 -> 0 | AB16: =IFERROR(AA16-Z16,"-") -> -181.8 | AC16: =IFERROR(AA16/Z16,"-") -> 0 | AD16: =AH16+AL16+AP16 -> 462.1 | AE16: =AI16+AM16+AQ16 -> 0 | AF16: =IFERROR(AE16-AD16,"-") -> -462.1 | AG16: =IFERROR(AE16/AD16,"-") -> 0 | AH16: ='3. ГПП-СГПЗ'!AU18+'3. ГПП-СГПЗ'!AU16 -> 98.8 | AI16: ='3. ГПП-СГПЗ'!AW18+'3. ГПП-СГПЗ'!AW16 -> 0 | AJ16: =IFERROR(AI16-AH16,"-") -> -98.8 | AK16: =IFERROR(AI16/AH16,"-") -> 0 | AL16: ='3. ГПП-СГПЗ'!BA18+'3. ГПП-СГПЗ'!BA16 -> 182.9 | AM16: ='3. ГПП-СГПЗ'!BC18+'3. ГПП-СГПЗ'!BC16 -> 0 | AN16: =IFERROR(AM16-AL16,"-") -> -182.9 | AO16: =IFERROR(AM16/AL16,"-") -> 0 | AP16: ='3. ГПП-СГПЗ'!BG18+'3. ГПП-СГПЗ'!BG16 -> 180.4 | AQ16: ='3. ГПП-СГПЗ'!BI18+'3. ГПП-СГПЗ'!BI16 -> 0 | AR16: =IFERROR(AQ16-AP16,"-") -> -180.4 | AS16: =IFERROR(AQ16/AP16,"-") -> 0 | AT16: =AX16+BB16+BF16 -> 550.1 | AU16: =AY16+BC16+BG16 -> 0 | AV16: =IFERROR(AU16-AT16,"-") -> -550.1 | AW16: =IFERROR(AU16/AT16,"-") -> 0 | AX16: ='3. ГПП-СГПЗ'!BS18+'3. ГПП-СГПЗ'!BS16 -> 186.6 | AY16: ='3. ГПП-СГПЗ'!BU18+'3. ГПП-СГПЗ'!BU16 -> 0 | AZ16: =IFERROR(AY16-AX16,"-") -> -186.6 | BA16: =IFERROR(AY16/AX16,"-") -> 0 | BB16: ='3. ГПП-СГПЗ'!BY18+'3. ГПП-СГПЗ'!BY16 -> 186.2 | BC16: ='3. ГПП-СГПЗ'!CA18+'3. ГПП-СГПЗ'!CA16 -> 0 | BD16: =IFERROR(BC16-BB16,"-") -> -186.2 | BE16: =IFERROR(BC16/BB16,"-") -> 0 | BF16: ='3. ГПП-СГПЗ'!CE18+'3. ГПП-СГПЗ'!CE16 -> 177.3 | BG16: ='3. ГПП-СГПЗ'!CG18+'3. ГПП-СГПЗ'!CG16 -> 0 | BH16: =IFERROR(BG16-BF16,"-") -> -177.3 | BI16: =IFERROR(BG16/BF16,"-") -> 0 | BJ16: =BN16+BR16+BV16 -> 490.1 | BK16: =BO16+BS16+BW16 -> 0 | BL16: =IFERROR(BK16-BJ16,"-") -> -490.1 | BM16: =IFERROR(BK16/BJ16,"-") -> 0 | BN16: ='3. ГПП-СГПЗ'!CQ18+'3. ГПП-СГПЗ'!CQ16 -> 127.5 | BO16: ='3. ГПП-СГПЗ'!CS18+'3. ГПП-СГПЗ'!CS16 -> 0 | BP16: =IFERROR(BO16-BN16,"-") -> -127.5 | BQ16: =IFERROR(BO16/BN16,"-") -> 0 | BR16: ='3. ГПП-СГПЗ'!CW18+'3. ГПП-СГПЗ'!CW16 -> 178.3 | BS16: ='3. ГПП-СГПЗ'!CY18+'3. ГПП-СГПЗ'!CY16 -> 0 | BT16: =IFERROR(BS16-BR16,"-") -> -178.3 | BU16: =IFERROR(BS16/BR16,"-") -> 0 | BV16: ='3. ГПП-СГПЗ'!DC18+'3. ГПП-СГПЗ'!DC16 -> 184.3 | BW16: ='3. ГПП-СГПЗ'!DE18+'3. ГПП-СГПЗ'!DE16 -> 0 | BX16: =IFERROR(BW16-BV16,"-") -> -184.3 | BY16: =IFERROR(BW16/BV16,"-") -> 0
C17: Газпром переработка Благовещенск | G17: 14_100335074+14_100335076 | I17: млн куб.м. | J17: =N17+AD17+AT17+BJ17 -> 35384.8 | K17: =O17+AE17+AU17+BK17 -> 0 | L17: =IFERROR(K17-J17,"-") -> -35384.8 | M17: =IFERROR(K17/J17,"-") -> 0 | N17: =R17+V17+Z17 -> 8849.4 | O17: =S17+W17+AA17 -> 0 | P17: =IFERROR(O17-N17,"-") -> -8849.4 | Q17: =IFERROR(O17/N17,"-") -> 0 | R17: ='14. ГП Благовещенск (Ам ГПЗ)'!W31+'14. ГП Благовещенск (Ам ГПЗ)'!W33 -> 3189.9 | S17: ='14. ГП Благовещенск (Ам ГПЗ)'!Y31+'14. ГП Благовещенск (Ам ГПЗ)'!Y33 -> 0 | T17: =IFERROR(S17-R17,"-") -> -3189.9 | U17: =IFERROR(S17/R17,"-") -> 0 | V17: ='14. ГП Благовещенск (Ам ГПЗ)'!AC31+'14. ГП Благовещенск (Ам ГПЗ)'!AC33 -> 2881.1 | W17: ='14. ГП Благовещенск (Ам ГПЗ)'!AE31+'14. ГП Благовещенск (Ам ГПЗ)'!AE33 -> 0 | X17: =IFERROR(W17-V17,"-") -> -2881.1 | Y17: =IFERROR(W17/V17,"-") -> 0 | Z17: ='14. ГП Благовещенск (Ам ГПЗ)'!AI31+'14. ГП Благовещенск (Ам ГПЗ)'!AI33 -> 2778.4 | AA17: ='14. ГП Благовещенск (Ам ГПЗ)'!AK31+'14. ГП Благовещенск (Ам ГПЗ)'!AK33 -> 0 | AB17: =IFERROR(AA17-Z17,"-") -> -2778.4 | AC17: =IFERROR(AA17/Z17,"-") -> 0 | AD17: =AH17+AL17+AP17 -> 8707.4 | AE17: =AI17+AM17+AQ17 -> 0 | AF17: =IFERROR(AE17-AD17,"-") -> -8707.4 | AG17: =IFERROR(AE17/AD17,"-") -> 0 | AH17: ='14. ГП Благовещенск (Ам ГПЗ)'!AU31+'14. ГП Благовещенск (Ам ГПЗ)'!AU33 -> 2355.9 | AI17: ='14. ГП Благовещенск (Ам ГПЗ)'!AW31+'14. ГП Благовещенск (Ам ГПЗ)'!AW33 -> 0 | AJ17: =IFERROR(AI17-AH17,"-") -> -2355.9 | AK17: =IFERROR(AI17/AH17,"-") -> 0 | AL17: ='14. ГП Благовещенск (Ам ГПЗ)'!BA31+'14. ГП Благовещенск (Ам ГПЗ)'!BA33 -> 3198.6 | AM17: ='14. ГП Благовещенск (Ам ГПЗ)'!BC31+'14. ГП Благовещенск (Ам ГПЗ)'!BC33 -> 0 | AN17: =IFERROR(AM17-AL17,"-") -> -3198.6 | AO17: =IFERROR(AM17/AL17,"-") -> 0 | AP17: ='14. ГП Благовещенск (Ам ГПЗ)'!BG31+'14. ГП Благовещенск (Ам ГПЗ)'!BG33 -> 3152.9 | AQ17: ='14. ГП Благовещенск (Ам ГПЗ)'!BI31+'14. ГП Благовещенск (Ам ГПЗ)'!BI33 -> 0 | AR17: =IFERROR(AQ17-AP17,"-") -> -3152.9 | AS17: =IFERROR(AQ17/AP17,"-") -> 0 | AT17: =AX17+BB17+BF17 -> 8195.5 | AU17: =AY17+BC17+BG17 -> 0 | AV17: =IFERROR(AU17-AT17,"-") -> -8195.5 | AW17: =IFERROR(AU17/AT17,"-") -> 0 | AX17: ='14. ГП Благовещенск (Ам ГПЗ)'!BS31+'14. ГП Благовещенск (Ам ГПЗ)'!BS33 -> 3258 | AY17: ='14. ГП Благовещенск (Ам ГПЗ)'!BU31+'14. ГП Благовещенск (Ам ГПЗ)'!BU33 -> 0 | AZ17: =IFERROR(AY17-AX17,"-") -> -3258 | BA17: =IFERROR(AY17/AX17,"-") -> 0 | BB17: ='14. ГП Благовещенск (Ам ГПЗ)'!BY31+'14. ГП Благовещенск (Ам ГПЗ)'!BY33 -> 3258.1 | BC17: ='14. ГП Благовещенск (Ам ГПЗ)'!CA31+'14. ГП Благовещенск (Ам ГПЗ)'!CA33 -> 0 | BD17: =IFERROR(BC17-BB17,"-") -> -3258.1 | BE17: =IFERROR(BC17/BB17,"-") -> 0 | BF17: ='14. ГП Благовещенск (Ам ГПЗ)'!CE31+'14. ГП Благовещенск (Ам ГПЗ)'!CE33 -> 1679.4 | BG17: ='14. ГП Благовещенск (Ам ГПЗ)'!CG31+'14. ГП Благовещенск (Ам ГПЗ)'!CG33 -> 0 | BH17: =IFERROR(BG17-BF17,"-") -> -1679.4 | BI17: =IFERROR(BG17/BF17,"-") -> 0 | BJ17: =BN17+BR17+BV17 -> 9632.5 | BK17: =BO17+BS17+BW17 -> 0 | BL17: =IFERROR(BK17-BJ17,"-") -> -9632.5 | BM17: =IFERROR(BK17/BJ17,"-") -> 0 | BN17: ='14. ГП Благовещенск (Ам ГПЗ)'!CQ31+'14. ГП Благовещенск (Ам ГПЗ)'!CQ33 -> 3221.4 | BO17: ='14. ГП Благовещенск (Ам ГПЗ)'!CS31+'14. ГП Благовещенск (Ам ГПЗ)'!CS33 -> 0 | BP17: =IFERROR(BO17-BN17,"-") -> -3221.4 | BQ17: =IFERROR(BO17/BN17,"-") -> 0 | BR17: ='14. ГП Благовещенск (Ам ГПЗ)'!CW31+'14. ГП Благовещенск (Ам ГПЗ)'!CW33 -> 3153 | BS17: ='14. ГП Благовещенск (Ам ГПЗ)'!CY31+'14. ГП Благовещенск (Ам ГПЗ)'!CY33 -> 0 | BT17: =IFERROR(BS17-BR17,"-") -> -3153 | BU17: =IFERROR(BS17/BR17,"-") -> 0 | BV17: ='14. ГП Благовещенск (Ам ГПЗ)'!DC31+'14. ГП Благовещенск (Ам ГПЗ)'!DC33 -> 3258.1 | BW17: ='14. ГП Благовещенск (Ам ГПЗ)'!DE31+'14. ГП Благовещенск (Ам ГПЗ)'!DE33 -> 0 | BX17: =IFERROR(BW17-BV17,"-") -> -3258.1 | BY17: =IFERROR(BW17/BV17,"-") -> 0
C18: Амурский ГПЗ | G18: 14_100335074+14_100335076 | I18: млн куб.м. | J18: =N18+AD18+AT18+BJ18 -> 35384.8 | K18: =O18+AE18+AU18+BK18 -> 0 | L18: =IFERROR(K18-J18,"-") -> -35384.8 | M18: =IFERROR(K18/J18,"-") -> 0 | N18: =R18+V18+Z18 -> 8849.4 | O18: =S18+W18+AA18 -> 0 | P18: =IFERROR(O18-N18,"-") -> -8849.4 | Q18: =IFERROR(O18/N18,"-") -> 0 | R18: ='14. ГП Благовещенск (Ам ГПЗ)'!W31+'14. ГП Благовещенск (Ам ГПЗ)'!W33 -> 3189.9 | S18: ='14. ГП Благовещенск (Ам ГПЗ)'!Y31+'14. ГП Благовещенск (Ам ГПЗ)'!Y33 -> 0 | T18: =IFERROR(S18-R18,"-") -> -3189.9 | U18: =IFERROR(S18/R18,"-") -> 0 | V18: ='14. ГП Благовещенск (Ам ГПЗ)'!AC31+'14. ГП Благовещенск (Ам ГПЗ)'!AC33 -> 2881.1 | W18: ='14. ГП Благовещенск (Ам ГПЗ)'!AE31+'14. ГП Благовещенск (Ам ГПЗ)'!AE33 -> 0 | X18: =IFERROR(W18-V18,"-") -> -2881.1 | Y18: =IFERROR(W18/V18,"-") -> 0 | Z18: ='14. ГП Благовещенск (Ам ГПЗ)'!AI31+'14. ГП Благовещенск (Ам ГПЗ)'!AI33 -> 2778.4 | AA18: ='14. ГП Благовещенск (Ам ГПЗ)'!AK31+'14. ГП Благовещенск (Ам ГПЗ)'!AK33 -> 0 | AB18: =IFERROR(AA18-Z18,"-") -> -2778.4 | AC18: =IFERROR(AA18/Z18,"-") -> 0 | AD18: =AH18+AL18+AP18 -> 8707.4 | AE18: =AI18+AM18+AQ18 -> 0 | AF18: =IFERROR(AE18-AD18,"-") -> -8707.4 | AG18: =IFERROR(AE18/AD18,"-") -> 0 | AH18: ='14. ГП Благовещенск (Ам ГПЗ)'!AU31+'14. ГП Благовещенск (Ам ГПЗ)'!AU33 -> 2355.9 | AI18: ='14. ГП Благовещенск (Ам ГПЗ)'!AW31+'14. ГП Благовещенск (Ам ГПЗ)'!AW33 -> 0 | AJ18: =IFERROR(AI18-AH18,"-") -> -2355.9 | AK18: =IFERROR(AI18/AH18,"-") -> 0 | AL18: ='14. ГП Благовещенск (Ам ГПЗ)'!BA31+'14. ГП Благовещенск (Ам ГПЗ)'!BA33 -> 3198.6 | AM18: ='14. ГП Благовещенск (Ам ГПЗ)'!BC31+'14. ГП Благовещенск (Ам ГПЗ)'!BC33 -> 0 | AN18: =IFERROR(AM18-AL18,"-") -> -3198.6 | AO18: =IFERROR(AM18/AL18,"-") -> 0 | AP18: ='14. ГП Благовещенск (Ам ГПЗ)'!BG31+'14. ГП Благовещенск (Ам ГПЗ)'!BG33 -> 3152.9 | AQ18: ='14. ГП Благовещенск (Ам ГПЗ)'!BI31+'14. ГП Благовещенск (Ам ГПЗ)'!BI33 -> 0 | AR18: =IFERROR(AQ18-AP18,"-") -> -3152.9 | AS18: =IFERROR(AQ18/AP18,"-") -> 0 | AT18: =AX18+BB18+BF18 -> 8195.5 | AU18: =AY18+BC18+BG18 -> 0 | AV18: =IFERROR(AU18-AT18,"-") -> -8195.5 | AW18: =IFERROR(AU18/AT18,"-") -> 0 | AX18: ='14. ГП Благовещенск (Ам ГПЗ)'!BS31+'14. ГП Благовещенск (Ам ГПЗ)'!BS33 -> 3258 | AY18: ='14. ГП Благовещенск (Ам ГПЗ)'!BU31+'14. ГП Благовещенск (Ам ГПЗ)'!BU33 -> 0 | AZ18: =IFERROR(AY18-AX18,"-") -> -3258 | BA18: =IFERROR(AY18/AX18,"-") -> 0 | BB18: ='14. ГП Благовещенск (Ам ГПЗ)'!BY31+'14. ГП Благовещенск (Ам ГПЗ)'!BY33 -> 3258.1 | BC18: ='14. ГП Благовещенск (Ам ГПЗ)'!CA31+'14. ГП Благовещенск (Ам ГПЗ)'!CA33 -> 0 | BD18: =IFERROR(BC18-BB18,"-") -> -3258.1 | BE18: =IFERROR(BC18/BB18,"-") -> 0 | BF18: ='14. ГП Благовещенск (Ам ГПЗ)'!CE31+'14. ГП Благовещенск (Ам ГПЗ)'!CE33 -> 1679.4 | BG18: ='14. ГП Благовещенск (Ам ГПЗ)'!CG31+'14. ГП Благовещенск (Ам ГПЗ)'!CG33 -> 0 | BH18: =IFERROR(BG18-BF18,"-") -> -1679.4 | BI18: =IFERROR(BG18/BF18,"-") -> 0 | BJ18: =BN18+BR18+BV18 -> 9632.5 | BK18: =BO18+BS18+BW18 -> 0 | BL18: =IFERROR(BK18-BJ18,"-") -> -9632.5 | BM18: =IFERROR(BK18/BJ18,"-") -> 0 | BN18: ='14. ГП Благовещенск (Ам ГПЗ)'!CQ31+'14. ГП Благовещенск (Ам ГПЗ)'!CQ33 -> 3221.4 | BO18: ='14. ГП Благовещенск (Ам ГПЗ)'!CS31+'14. ГП Благовещенск (Ам ГПЗ)'!CS33 -> 0 | BP18: =IFERROR(BO18-BN18,"-") -> -3221.4 | BQ18: =IFERROR(BO18/BN18,"-") -> 0 | BR18: ='14. ГП Благовещенск (Ам ГПЗ)'!CW31+'14. ГП Благовещенск (Ам ГПЗ)'!CW33 -> 3153 | BS18: ='14. ГП Благовещенск (Ам ГПЗ)'!CY31+'14. ГП Благовещенск (Ам ГПЗ)'!CY33 -> 0 | BT18: =IFERROR(BS18-BR18,"-") -> -3153 | BU18: =IFERROR(BS18/BR18,"-") -> 0 | BV18: ='14. ГП Благовещенск (Ам ГПЗ)'!DC31+'14. ГП Благовещенск (Ам ГПЗ)'!DC33 -> 3258.1 | BW18: ='14. ГП Благовещенск (Ам ГПЗ)'!DE31+'14. ГП Благовещенск (Ам ГПЗ)'!DE33 -> 0 | BX18: =IFERROR(BW18-BV18,"-") -> -3258.1 | BY18: =IFERROR(BW18/BV18,"-") -> 0
C19: Газпром СПГ Портовая | I19: млн куб.м.
C20: КСПГ Портовая | I20: млн куб.м.
B21: 1.1 | C21: Газпром | G21: 3_100330008+1_1003335807+14_100335074 | I21: млн куб.м. | J21: =N21+AD21+AT21+BJ21 -> 47078.8 | K21: =O21+AE21+AU21+BK21 -> 0 | L21: =IFERROR(K21-J21,"-") -> -47078.8 | M21: =IFERROR(K21/J21,"-") -> 0 | N21: =R21+V21+Z21 -> 11801.2 | O21: =S21+W21+AA21 -> 0 | P21: =IFERROR(O21-N21,"-") -> -11801.2 | Q21: =IFERROR(O21/N21,"-") -> 0 | R21: ='3. ГПП-СГПЗ'!W16+'1. ГПП-АГПЗ+'!W22+'14. ГП Благовещенск (Ам ГПЗ)'!W31 -> 4206.5 | S21: ='3. ГПП-СГПЗ'!Y16+'1. ГПП-АГПЗ+'!Y22+'14. ГП Благовещенск (Ам ГПЗ)'!Y31 -> 0 | T21: =IFERROR(S21-R21,"-") -> -4206.5 | U21: =IFERROR(S21/R21,"-") -> 0 | V21: ='3. ГПП-СГПЗ'!AC16+'1. ГПП-АГПЗ+'!AC22+'14. ГП Благовещенск (Ам ГПЗ)'!AC31 -> 3799.3 | W21: ='3. ГПП-СГПЗ'!AE16+'1. ГПП-АГПЗ+'!AE22+'14. ГП Благовещенск (Ам ГПЗ)'!AE31 -> 0 | X21: =IFERROR(W21-V21,"-") -> -3799.3 | Y21: =IFERROR(W21/V21,"-") -> 0 | Z21: ='3. ГПП-СГПЗ'!AI16+'1. ГПП-АГПЗ+'!AI22+'14. ГП Благовещенск (Ам ГПЗ)'!AI31 -> 3795.4 | AA21: ='3. ГПП-СГПЗ'!AK16+'1. ГПП-АГПЗ+'!AK22+'14. ГП Благовещенск (Ам ГПЗ)'!AK31 -> 0 | AB21: =IFERROR(AA21-Z21,"-") -> -3795.4 | AC21: =IFERROR(AA21/Z21,"-") -> 0 | AD21: =AH21+AL21+AP21 -> 11018 | AE21: =AI21+AM21+AQ21 -> 0 | AF21: =IFERROR(AE21-AD21,"-") -> -11018 | AG21: =IFERROR(AE21/AD21,"-") -> 0 | AH21: ='3. ГПП-СГПЗ'!AU16+'1. ГПП-АГПЗ+'!AU22+'14. ГП Благовещенск (Ам ГПЗ)'!AU31 -> 3262.9 | AI21: ='3. ГПП-СГПЗ'!AW16+'1. ГПП-АГПЗ+'!AW22+'14. ГП Благовещенск (Ам ГПЗ)'!AW31 -> 0 | AJ21: =IFERROR(AI21-AH21,"-") -> -3262.9 | AK21: =IFERROR(AI21/AH21,"-") -> 0 | AL21: ='3. ГПП-СГПЗ'!BA16+'1. ГПП-АГПЗ+'!BA22+'14. ГП Благовещенск (Ам ГПЗ)'!BA31 -> 3955.4 | AM21: ='3. ГПП-СГПЗ'!BC16+'1. ГПП-АГПЗ+'!BC22+'14. ГП Благовещенск (Ам ГПЗ)'!BC31 -> 0 | AN21: =IFERROR(AM21-AL21,"-") -> -3955.4 | AO21: =IFERROR(AM21/AL21,"-") -> 0 | AP21: ='3. ГПП-СГПЗ'!BG16+'1. ГПП-АГПЗ+'!BG22+'14. ГП Благовещенск (Ам ГПЗ)'!BG31 -> 3799.7 | AQ21: ='3. ГПП-СГПЗ'!BI16+'1. ГПП-АГПЗ+'!BI22+'14. ГП Благовещенск (Ам ГПЗ)'!BI31 -> 0 | AR21: =IFERROR(AQ21-AP21,"-") -> -3799.7 | AS21: =IFERROR(AQ21/AP21,"-") -> 0 | AT21: =AX21+BB21+BF21 -> 11384.4 | AU21: =AY21+BC21+BG21 -> 0 | AV21: =IFERROR(AU21-AT21,"-") -> -11384.4 | AW21: =IFERROR(AU21/AT21,"-") -> 0 | AX21: ='3. ГПП-СГПЗ'!BS16+'1. ГПП-АГПЗ+'!BS22+'14. ГП Благовещенск (Ам ГПЗ)'!BS31 -> 4313 | AY21: ='3. ГПП-СГПЗ'!BU16+'1. ГПП-АГПЗ+'!BU22+'14. ГП Благовещенск (Ам ГПЗ)'!BU31 -> 0 | AZ21: =IFERROR(AY21-AX21,"-") -> -4313 | BA21: =IFERROR(AY21/AX21,"-") -> 0 | BB21: ='3. ГПП-СГПЗ'!BY16+'1. ГПП-АГПЗ+'!BY22+'14. ГП Благовещенск (Ам ГПЗ)'!BY31 -> 4316.7 | BC21: ='3. ГПП-СГПЗ'!CA16+'1. ГПП-АГПЗ+'!CA22+'14. ГП Благовещенск (Ам ГПЗ)'!CA31 -> 0 | BD21: =IFERROR(BC21-BB21,"-") -> -4316.7 | BE21: =IFERROR(BC21/BB21,"-") -> 0 | BF21: ='3. ГПП-СГПЗ'!CE16+'1. ГПП-АГПЗ+'!CE22+'14. ГП Благовещенск (Ам ГПЗ)'!CE31 -> 2754.7 | BG21: ='3. ГПП-СГПЗ'!CG16+'1. ГПП-АГПЗ+'!CG22+'14. ГП Благовещенск (Ам ГПЗ)'!CG31 -> 0 | BH21: =IFERROR(BG21-BF21,"-") -> -2754.7 | BI21: =IFERROR(BG21/BF21,"-") -> 0 | BJ21: =BN21+BR21+BV21 -> 12875.2 | BK21: =BO21+BS21+BW21 -> 0 | BL21: =IFERROR(BK21-BJ21,"-") -> -12875.2 | BM21: =IFERROR(BK21/BJ21,"-") -> 0 | BN21: ='3. ГПП-СГПЗ'!CQ16+'1. ГПП-АГПЗ+'!CQ22+'14. ГП Благовещенск (Ам ГПЗ)'!CQ31 -> 4277 | BO21: ='3. ГПП-СГПЗ'!CS16+'1. ГПП-АГПЗ+'!CS22+'14. ГП Благовещенск (Ам ГПЗ)'!CS31 -> 0 | BP21: =IFERROR(BO21-BN21,"-") -> -4277 | BQ21: =IFERROR(BO21/BN21,"-") -> 0 | BR21: ='3. ГПП-СГПЗ'!CW16+'1. ГПП-АГПЗ+'!CW22+'14. ГП Благовещенск (Ам ГПЗ)'!CW31 -> 4229.4 | BS21: ='3. ГПП-СГПЗ'!CY16+'1. ГПП-АГПЗ+'!CY22+'14. ГП Благовещенск (Ам ГПЗ)'!CY31 -> 0 | BT21: =IFERROR(BS21-BR21,"-") -> -4229.4 | BU21: =IFERROR(BS21/BR21,"-") -> 0 | BV21: ='3. ГПП-СГПЗ'!DC16+'1. ГПП-АГПЗ+'!DC22+'14. ГП Благовещенск (Ам ГПЗ)'!DC31 -> 4368.8 | BW21: ='3. ГПП-СГПЗ'!DE16+'1. ГПП-АГПЗ+'!DE22+'14. ГП Благовещенск (Ам ГПЗ)'!DE31 -> 0 | BX21: =IFERROR(BW21-BV21,"-") -> -4368.8 | BY21: =IFERROR(BW21/BV21,"-") -> 0
C22: Газпром переработка | G22: 3_100330008+1_1003335807 | I22: млн куб.м. | J22: =N22+AD22+AT22+BJ22 -> 11694 | K22: =O22+AE22+AU22+BK22 -> 0 | L22: =IFERROR(K22-J22,"-") -> -11694 | M22: =IFERROR(K22/J22,"-") -> 0 | N22: =R22+V22+Z22 -> 2951.8 | O22: =S22+W22+AA22 -> 0 | P22: =IFERROR(O22-N22,"-") -> -2951.8 | Q22: =IFERROR(O22/N22,"-") -> 0 | R22: ='3. ГПП-СГПЗ'!W16+'1. ГПП-АГПЗ+'!W22 -> 1016.6 | S22: ='3. ГПП-СГПЗ'!Y16+'1. ГПП-АГПЗ+'!Y22 -> 0 | T22: =IFERROR(S22-R22,"-") -> -1016.6 | U22: =IFERROR(S22/R22,"-") -> 0 | V22: ='3. ГПП-СГПЗ'!AC16+'1. ГПП-АГПЗ+'!AC22 -> 918.2 | W22: ='3. ГПП-СГПЗ'!AE16+'1. ГПП-АГПЗ+'!AE22 -> 0 | X22: =IFERROR(W22-V22,"-") -> -918.2 | Y22: =IFERROR(W22/V22,"-") -> 0 | Z22: ='3. ГПП-СГПЗ'!AI16+'1. ГПП-АГПЗ+'!AI22 -> 1017 | AA22: ='3. ГПП-СГПЗ'!AK16+'1. ГПП-АГПЗ+'!AK22 -> 0 | AB22: =IFERROR(AA22-Z22,"-") -> -1017 | AC22: =IFERROR(AA22/Z22,"-") -> 0 | AD22: =AH22+AL22+AP22 -> 2310.6 | AE22: =AI22+AM22+AQ22 -> 0 | AF22: =IFERROR(AE22-AD22,"-") -> -2310.6 | AG22: =IFERROR(AE22/AD22,"-") -> 0 | AH22: ='3. ГПП-СГПЗ'!AU16+'1. ГПП-АГПЗ+'!AU22 -> 907 | AI22: ='3. ГПП-СГПЗ'!AW16+'1. ГПП-АГПЗ+'!AW22 -> 0 | AJ22: =IFERROR(AI22-AH22,"-") -> -907 | AK22: =IFERROR(AI22/AH22,"-") -> 0 | AL22: ='3. ГПП-СГПЗ'!BA16+'1. ГПП-АГПЗ+'!BA22 -> 756.8 | AM22: ='3. ГПП-СГПЗ'!BC16+'1. ГПП-АГПЗ+'!BC22 -> 0 | AN22: =IFERROR(AM22-AL22,"-") -> -756.8 | AO22: =IFERROR(AM22/AL22,"-") -> 0 | AP22: ='3. ГПП-СГПЗ'!BG16+'1. ГПП-АГПЗ+'!BG22 -> 646.8 | AQ22: ='3. ГПП-СГПЗ'!BI16+'1. ГПП-АГПЗ+'!BI22 -> 0 | AR22: =IFERROR(AQ22-AP22,"-") -> -646.8 | AS22: =IFERROR(AQ22/AP22,"-") -> 0 | AT22: =AX22+BB22+BF22 -> 3188.9 | AU22: =AY22+BC22+BG22 -> 0 | AV22: =IFERROR(AU22-AT22,"-") -> -3188.9 | AW22: =IFERROR(AU22/AT22,"-") -> 0 | AX22: ='3. ГПП-СГПЗ'!BS16+'1. ГПП-АГПЗ+'!BS22 -> 1055 | AY22: ='3. ГПП-СГПЗ'!BU16+'1. ГПП-АГПЗ+'!BU22 -> 0 | AZ22: =IFERROR(AY22-AX22,"-") -> -1055 | BA22: =IFERROR(AY22/AX22,"-") -> 0 | BB22: ='3. ГПП-СГПЗ'!BY16+'1. ГПП-АГПЗ+'!BY22 -> 1058.6 | BC22: ='3. ГПП-СГПЗ'!CA16+'1. ГПП-АГПЗ+'!CA22 -> 0 | BD22: =IFERROR(BC22-BB22,"-") -> -1058.6 | BE22: =IFERROR(BC22/BB22,"-") -> 0 | BF22: ='3. ГПП-СГПЗ'!CE16+'1. ГПП-АГПЗ+'!CE22 -> 1075.3 | BG22: ='3. ГПП-СГПЗ'!CG16+'1. ГПП-АГПЗ+'!CG22 -> 0 | BH22: =IFERROR(BG22-BF22,"-") -> -1075.3 | BI22: =IFERROR(BG22/BF22,"-") -> 0 | BJ22: =BN22+BR22+BV22 -> 3242.7 | BK22: =BO22+BS22+BW22 -> 0 | BL22: =IFERROR(BK22-BJ22,"-") -> -3242.7 | BM22: =IFERROR(BK22/BJ22,"-") -> 0 | BN22: ='3. ГПП-СГПЗ'!CQ16+'1. ГПП-АГПЗ+'!CQ22 -> 1055.6 | BO22: ='3. ГПП-СГПЗ'!CS16+'1. ГПП-АГПЗ+'!CS22 -> 0 | BP22: =IFERROR(BO22-BN22,"-") -> -1055.6 | BQ22: =IFERROR(BO22/BN22,"-") -> 0 | BR22: ='3. ГПП-СГПЗ'!CW16+'1. ГПП-АГПЗ+'!CW22 -> 1076.4 | BS22: ='3. ГПП-СГПЗ'!CY16+'1. ГПП-АГПЗ+'!CY22 -> 0 | BT22: =IFERROR(BS22-BR22,"-") -> -1076.4 | BU22: =IFERROR(BS22/BR22,"-") -> 0 | BV22: ='3. ГПП-СГПЗ'!DC16+'1. ГПП-АГПЗ+'!DC22 -> 1110.7 | BW22: ='3. ГПП-СГПЗ'!DE16+'1. ГПП-АГПЗ+'!DE22 -> 0 | BX22: =IFERROR(BW22-BV22,"-") -> -1110.7 | BY22: =IFERROR(BW22/BV22,"-") -> 0
C23: Астраханский ГПЗ | G23: 1_1003335807 | I23: млн куб.м. | J23: =N23+AD23+AT23+BJ23 -> 9676.5 | K23: =O23+AE23+AU23+BK23 -> 0 | L23: =IFERROR(K23-J23,"-") -> -9676.5 | M23: =IFERROR(K23/J23,"-") -> 0 | N23: =R23+V23+Z23 -> 2427.6 | O23: =S23+W23+AA23 -> 0 | P23: =IFERROR(O23-N23,"-") -> -2427.6 | Q23: =IFERROR(O23/N23,"-") -> 0 | R23: ='1. ГПП-АГПЗ+'!W22 -> 836.1 | S23: ='1. ГПП-АГПЗ+'!Y22 -> 0 | T23: =IFERROR(S23-R23,"-") -> -836.1 | U23: =IFERROR(S23/R23,"-") -> 0 | V23: ='1. ГПП-АГПЗ+'!AC22 -> 755.3 | W23: ='1. ГПП-АГПЗ+'!AE22 -> 0 | X23: =IFERROR(W23-V23,"-") -> -755.3 | Y23: =IFERROR(W23/V23,"-") -> 0 | Z23: ='1. ГПП-АГПЗ+'!AI22 -> 836.2 | AA23: ='1. ГПП-АГПЗ+'!AK22 -> 0 | AB23: =IFERROR(AA23-Z23,"-") -> -836.2 | AC23: =IFERROR(AA23/Z23,"-") -> 0 | AD23: =AH23+AL23+AP23 -> 1851.5 | AE23: =AI23+AM23+AQ23 -> 0 | AF23: =IFERROR(AE23-AD23,"-") -> -1851.5 | AG23: =IFERROR(AE23/AD23,"-") -> 0 | AH23: ='1. ГПП-АГПЗ+'!AU22 -> 809.2 | AI23: ='1. ГПП-АГПЗ+'!AW22 -> 0 | AJ23: =IFERROR(AI23-AH23,"-") -> -809.2 | AK23: =IFERROR(AI23/AH23,"-") -> 0 | AL23: ='1. ГПП-АГПЗ+'!BA22 -> 574.9 | AM23: ='1. ГПП-АГПЗ+'!BC22 -> 0 | AN23: =IFERROR(AM23-AL23,"-") -> -574.9 | AO23: =IFERROR(AM23/AL23,"-") -> 0 | AP23: ='1. ГПП-АГПЗ+'!BG22 -> 467.4 | AQ23: ='1. ГПП-АГПЗ+'!BI22 -> 0 | AR23: =IFERROR(AQ23-AP23,"-") -> -467.4 | AS23: =IFERROR(AQ23/AP23,"-") -> 0 | AT23: =AX23+BB23+BF23 -> 2641.8 | AU23: =AY23+BC23+BG23 -> 0 | AV23: =IFERROR(AU23-AT23,"-") -> -2641.8 | AW23: =IFERROR(AU23/AT23,"-") -> 0 | AX23: ='1. ГПП-АГПЗ+'!BS22 -> 869.4 | AY23: ='1. ГПП-АГПЗ+'!BU22 -> 0 | AZ23: =IFERROR(AY23-AX23,"-") -> -869.4 | BA23: =IFERROR(AY23/AX23,"-") -> 0 | BB23: ='1. ГПП-АГПЗ+'!BY22 -> 873.4 | BC23: ='1. ГПП-АГПЗ+'!CA22 -> 0 | BD23: =IFERROR(BC23-BB23,"-") -> -873.4 | BE23: =IFERROR(BC23/BB23,"-") -> 0 | BF23: ='1. ГПП-АГПЗ+'!CE22 -> 899 | BG23: ='1. ГПП-АГПЗ+'!CG22 -> 0 | BH23: =IFERROR(BG23-BF23,"-") -> -899 | BI23: =IFERROR(BG23/BF23,"-") -> 0 | BJ23: =BN23+BR23+BV23 -> 2755.6 | BK23: =BO23+BS23+BW23 -> 0 | BL23: =IFERROR(BK23-BJ23,"-") -> -2755.6 | BM23: =IFERROR(BK23/BJ23,"-") -> 0 | BN23: ='1. ГПП-АГПЗ+'!CQ22 -> 929.1 | BO23: ='1. ГПП-АГПЗ+'!CS22 -> 0 | BP23: =IFERROR(BO23-BN23,"-") -> -929.1 | BQ23: =IFERROR(BO23/BN23,"-") -> 0 | BR23: ='1. ГПП-АГПЗ+'!CW22 -> 899.1 | BS23: ='1. ГПП-АГПЗ+'!CY22 -> 0 | BT23: =IFERROR(BS23-BR23,"-") -> -899.1 | BU23: =IFERROR(BS23/BR23,"-") -> 0 | BV23: ='1. ГПП-АГПЗ+'!DC22 -> 927.4 | BW23: ='1. ГПП-АГПЗ+'!DE22 -> 0 | BX23: =IFERROR(BW23-BV23,"-") -> -927.4 | BY23: =IFERROR(BW23/BV23,"-") -> 0
C24: Сосногорский ГПЗ | G24: 3_100330008 | I24: млн куб.м. | J24: =N24+AD24+AT24+BJ24 -> 2017.5 | K24: =O24+AE24+AU24+BK24 -> 0 | L24: =IFERROR(K24-J24,"-") -> -2017.5 | M24: =IFERROR(K24/J24,"-") -> 0 | N24: =R24+V24+Z24 -> 524.2 | O24: =S24+W24+AA24 -> 0 | P24: =IFERROR(O24-N24,"-") -> -524.2 | Q24: =IFERROR(O24/N24,"-") -> 0 | R24: ='3. ГПП-СГПЗ'!W16 -> 180.5 | S24: ='3. ГПП-СГПЗ'!Y16 -> 0 | T24: =IFERROR(S24-R24,"-") -> -180.5 | U24: =IFERROR(S24/R24,"-") -> 0 | V24: ='3. ГПП-СГПЗ'!AC16 -> 162.9 | W24: ='3. ГПП-СГПЗ'!AE16 -> 0 | X24: =IFERROR(W24-V24,"-") -> -162.9 | Y24: =IFERROR(W24/V24,"-") -> 0 | Z24: ='3. ГПП-СГПЗ'!AI16 -> 180.8 | AA24: ='3. ГПП-СГПЗ'!AK16 -> 0 | AB24: =IFERROR(AA24-Z24,"-") -> -180.8 | AC24: =IFERROR(AA24/Z24,"-") -> 0 | AD24: =AH24+AL24+AP24 -> 459.1 | AE24: =AI24+AM24+AQ24 -> 0 | AF24: =IFERROR(AE24-AD24,"-") -> -459.1 | AG24: =IFERROR(AE24/AD24,"-") -> 0 | AH24: ='3. ГПП-СГПЗ'!AU16 -> 97.8 | AI24: ='3. ГПП-СГПЗ'!AW16 -> 0 | AJ24: =IFERROR(AI24-AH24,"-") -> -97.8 | AK24: =IFERROR(AI24/AH24,"-") -> 0 | AL24: ='3. ГПП-СГПЗ'!BA16 -> 181.9 | AM24: ='3. ГПП-СГПЗ'!BC16 -> 0 | AN24: =IFERROR(AM24-AL24,"-") -> -181.9 | AO24: =IFERROR(AM24/AL24,"-") -> 0 | AP24: ='3. ГПП-СГПЗ'!BG16 -> 179.4 | AQ24: ='3. ГПП-СГПЗ'!BI16 -> 0 | AR24: =IFERROR(AQ24-AP24,"-") -> -179.4 | AS24: =IFERROR(AQ24/AP24,"-") -> 0 | AT24: =AX24+BB24+BF24 -> 547.1 | AU24: =AY24+BC24+BG24 -> 0 | AV24: =IFERROR(AU24-AT24,"-") -> -547.1 | AW24: =IFERROR(AU24/AT24,"-") -> 0 | AX24: ='3. ГПП-СГПЗ'!BS16 -> 185.6 | AY24: ='3. ГПП-СГПЗ'!BU16 -> 0 | AZ24: =IFERROR(AY24-AX24,"-") -> -185.6 | BA24: =IFERROR(AY24/AX24,"-") -> 0 | BB24: ='3. ГПП-СГПЗ'!BY16 -> 185.2 | BC24: ='3. ГПП-СГПЗ'!CA16 -> 0 | BD24: =IFERROR(BC24-BB24,"-") -> -185.2 | BE24: =IFERROR(BC24/BB24,"-") -> 0 | BF24: ='3. ГПП-СГПЗ'!CE16 -> 176.3 | BG24: ='3. ГПП-СГПЗ'!CG16 -> 0 | BH24: =IFERROR(BG24-BF24,"-") -> -176.3 | BI24: =IFERROR(BG24/BF24,"-") -> 0 | BJ24: =BN24+BR24+BV24 -> 487.1 | BK24: =BO24+BS24+BW24 -> 0 | BL24: =IFERROR(BK24-BJ24,"-") -> -487.1 | BM24: =IFERROR(BK24/BJ24,"-") -> 0 | BN24: ='3. ГПП-СГПЗ'!CQ16 -> 126.5 | BO24: ='3. ГПП-СГПЗ'!CS16 -> 0 | BP24: =IFERROR(BO24-BN24,"-") -> -126.5 | BQ24: =IFERROR(BO24/BN24,"-") -> 0 | BR24: ='3. ГПП-СГПЗ'!CW16 -> 177.3 | BS24: ='3. ГПП-СГПЗ'!CY16 -> 0 | BT24: =IFERROR(BS24-BR24,"-") -> -177.3 | BU24: =IFERROR(BS24/BR24,"-") -> 0 | BV24: ='3. ГПП-СГПЗ'!DC16 -> 183.3 | BW24: ='3. ГПП-СГПЗ'!DE16 -> 0 | BX24: =IFERROR(BW24-BV24,"-") -> -183.3 | BY24: =IFERROR(BW24/BV24,"-") -> 0
C25: Газпром добыча Краснодар | G25: 3_100330008 | I25: млн куб.м. | J25: =N25+AD25+AT25+BJ25 -> 2017.5 | K25: =O25+AE25+AU25+BK25 -> 0 | L25: =IFERROR(K25-J25,"-") -> -2017.5 | M25: =IFERROR(K25/J25,"-") -> 0 | N25: =R25+V25+Z25 -> 524.2 | O25: =S25+W25+AA25 -> 0 | P25: =IFERROR(O25-N25,"-") -> -524.2 | Q25: =IFERROR(O25/N25,"-") -> 0 | R25: ='3. ГПП-СГПЗ'!W16 -> 180.5 | S25: ='3. ГПП-СГПЗ'!Y16 -> 0 | T25: =IFERROR(S25-R25,"-") -> -180.5 | U25: =IFERROR(S25/R25,"-") -> 0 | V25: ='3. ГПП-СГПЗ'!AC16 -> 162.9 | W25: ='3. ГПП-СГПЗ'!AE16 -> 0 | X25: =IFERROR(W25-V25,"-") -> -162.9 | Y25: =IFERROR(W25/V25,"-") -> 0 | Z25: ='3. ГПП-СГПЗ'!AI16 -> 180.8 | AA25: ='3. ГПП-СГПЗ'!AK16 -> 0 | AB25: =IFERROR(AA25-Z25,"-") -> -180.8 | AC25: =IFERROR(AA25/Z25,"-") -> 0 | AD25: =AH25+AL25+AP25 -> 459.1 | AE25: =AI25+AM25+AQ25 -> 0 | AF25: =IFERROR(AE25-AD25,"-") -> -459.1 | AG25: =IFERROR(AE25/AD25,"-") -> 0 | AH25: ='3. ГПП-СГПЗ'!AU16 -> 97.8 | AI25: ='3. ГПП-СГПЗ'!AW16 -> 0 | AJ25: =IFERROR(AI25-AH25,"-") -> -97.8 | AK25: =IFERROR(AI25/AH25,"-") -> 0 | AL25: ='3. ГПП-СГПЗ'!BA16 -> 181.9 | AM25: ='3. ГПП-СГПЗ'!BC16 -> 0 | AN25: =IFERROR(AM25-AL25,"-") -> -181.9 | AO25: =IFERROR(AM25/AL25,"-") -> 0 | AP25: ='3. ГПП-СГПЗ'!BG16 -> 179.4 | AQ25: ='3. ГПП-СГПЗ'!BI16 -> 0 | AR25: =IFERROR(AQ25-AP25,"-") -> -179.4 | AS25: =IFERROR(AQ25/AP25,"-") -> 0 | AT25: =AX25+BB25+BF25 -> 547.1 | AU25: =AY25+BC25+BG25 -> 0 | AV25: =IFERROR(AU25-AT25,"-") -> -547.1 | AW25: =IFERROR(AU25/AT25,"-") -> 0 | AX25: ='3. ГПП-СГПЗ'!BS16 -> 185.6 | AY25: ='3. ГПП-СГПЗ'!BU16 -> 0 | AZ25: =IFERROR(AY25-AX25,"-") -> -185.6 | BA25: =IFERROR(AY25/AX25,"-") -> 0 | BB25: ='3. ГПП-СГПЗ'!BY16 -> 185.2 | BC25: ='3. ГПП-СГПЗ'!CA16 -> 0 | BD25: =IFERROR(BC25-BB25,"-") -> -185.2 | BE25: =IFERROR(BC25/BB25,"-") -> 0 | BF25: ='3. ГПП-СГПЗ'!CE16 -> 176.3 | BG25: ='3. ГПП-СГПЗ'!CG16 -> 0 | BH25: =IFERROR(BG25-BF25,"-") -> -176.3 | BI25: =IFERROR(BG25/BF25,"-") -> 0 | BJ25: =BN25+BR25+BV25 -> 487.1 | BK25: =BO25+BS25+BW25 -> 0 | BL25: =IFERROR(BK25-BJ25,"-") -> -487.1 | BM25: =IFERROR(BK25/BJ25,"-") -> 0 | BN25: ='3. ГПП-СГПЗ'!CQ16 -> 126.5 | BO25: ='3. ГПП-СГПЗ'!CS16 -> 0 | BP25: =IFERROR(BO25-BN25,"-") -> -126.5 | BQ25: =IFERROR(BO25/BN25,"-") -> 0 | BR25: ='3. ГПП-СГПЗ'!CW16 -> 177.3 | BS25: ='3. ГПП-СГПЗ'!CY16 -> 0 | BT25: =IFERROR(BS25-BR25,"-") -> -177.3 | BU25: =IFERROR(BS25/BR25,"-") -> 0 | BV25: ='3. ГПП-СГПЗ'!DC16 -> 183.3 | BW25: ='3. ГПП-СГПЗ'!DE16 -> 0 | BX25: =IFERROR(BW25-BV25,"-") -> -183.3 | BY25: =IFERROR(BW25/BV25,"-") -> 0
C26: Газпром переработка Благовещенск | G26: 14_100335074 | I26: млн куб.м. | J26: =N26+AD26+AT26+BJ26 -> 35384.8 | K26: =O26+AE26+AU26+BK26 -> 0 | L26: =IFERROR(K26-J26,"-") -> -35384.8 | M26: =IFERROR(K26/J26,"-") -> 0 | N26: =R26+V26+Z26 -> 8849.4 | O26: =S26+W26+AA26 -> 0 | P26: =IFERROR(O26-N26,"-") -> -8849.4 | Q26: =IFERROR(O26/N26,"-") -> 0 | R26: ='14. ГП Благовещенск (Ам ГПЗ)'!W31 -> 3189.9 | S26: ='14. ГП Благовещенск (Ам ГПЗ)'!Y31 -> 0 | T26: =IFERROR(S26-R26,"-") -> -3189.9 | U26: =IFERROR(S26/R26,"-") -> 0 | V26: ='14. ГП Благовещенск (Ам ГПЗ)'!AC31 -> 2881.1 | W26: ='14. ГП Благовещенск (Ам ГПЗ)'!AE31 -> 0 | X26: =IFERROR(W26-V26,"-") -> -2881.1 | Y26: =IFERROR(W26/V26,"-") -> 0 | Z26: ='14. ГП Благовещенск (Ам ГПЗ)'!AI31 -> 2778.4 | AA26: ='14. ГП Благовещенск (Ам ГПЗ)'!AK31 -> 0 | AB26: =IFERROR(AA26-Z26,"-") -> -2778.4 | AC26: =IFERROR(AA26/Z26,"-") -> 0 | AD26: =AH26+AL26+AP26 -> 8707.4 | AE26: =AI26+AM26+AQ26 -> 0 | AF26: =IFERROR(AE26-AD26,"-") -> -8707.4 | AG26: =IFERROR(AE26/AD26,"-") -> 0 | AH26: ='14. ГП Благовещенск (Ам ГПЗ)'!AU31 -> 2355.9 | AI26: ='14. ГП Благовещенск (Ам ГПЗ)'!AW31 -> 0 | AJ26: =IFERROR(AI26-AH26,"-") -> -2355.9 | AK26: =IFERROR(AI26/AH26,"-") -> 0 | AL26: ='14. ГП Благовещенск (Ам ГПЗ)'!BA31 -> 3198.6 | AM26: ='14. ГП Благовещенск (Ам ГПЗ)'!BC31 -> 0 | AN26: =IFERROR(AM26-AL26,"-") -> -3198.6 | AO26: =IFERROR(AM26/AL26,"-") -> 0 | AP26: ='14. ГП Благовещенск (Ам ГПЗ)'!BG31 -> 3152.9 | AQ26: ='14. ГП Благовещенск (Ам ГПЗ)'!BI31 -> 0 | AR26: =IFERROR(AQ26-AP26,"-") -> -3152.9 | AS26: =IFERROR(AQ26/AP26,"-") -> 0 | AT26: =AX26+BB26+BF26 -> 8195.5 | AU26: =AY26+BC26+BG26 -> 0 | AV26: =IFERROR(AU26-AT26,"-") -> -8195.5 | AW26: =IFERROR(AU26/AT26,"-") -> 0 | AX26: ='14. ГП Благовещенск (Ам ГПЗ)'!BS31 -> 3258 | AY26: ='14. ГП Благовещенск (Ам ГПЗ)'!BU31 -> 0 | AZ26: =IFERROR(AY26-AX26,"-") -> -3258 | BA26: =IFERROR(AY26/AX26,"-") -> 0 | BB26: ='14. ГП Благовещенск (Ам ГПЗ)'!BY31 -> 3258.1 | BC26: ='14. ГП Благовещенск (Ам ГПЗ)'!CA31 -> 0 | BD26: =IFERROR(BC26-BB26,"-") -> -3258.1 | BE26: =IFERROR(BC26/BB26,"-") -> 0 | BF26: ='14. ГП Благовещенск (Ам ГПЗ)'!CE31 -> 1679.4 | BG26: ='14. ГП Благовещенск (Ам ГПЗ)'!CG31 -> 0 | BH26: =IFERROR(BG26-BF26,"-") -> -1679.4 | BI26: =IFERROR(BG26/BF26,"-") -> 0 | BJ26: =BN26+BR26+BV26 -> 9632.5 | BK26: =BO26+BS26+BW26 -> 0 | BL26: =IFERROR(BK26-BJ26,"-") -> -9632.5 | BM26: =IFERROR(BK26/BJ26,"-") -> 0 | BN26: ='14. ГП Благовещенск (Ам ГПЗ)'!CQ31 -> 3221.4 | BO26: ='14. ГП Благовещенск (Ам ГПЗ)'!CS31 -> 0 | BP26: =IFERROR(BO26-BN26,"-") -> -3221.4 | BQ26: =IFERROR(BO26/BN26,"-") -> 0 | BR26: ='14. ГП Благовещенск (Ам ГПЗ)'!CW31 -> 3153 | BS26: ='14. ГП Благовещенск (Ам ГПЗ)'!CY31 -> 0 | BT26: =IFERROR(BS26-BR26,"-") -> -3153 | BU26: =IFERROR(BS26/BR26,"-") -> 0 | BV26: ='14. ГП Благовещенск (Ам ГПЗ)'!DC31 -> 3258.1 | BW26: ='14. ГП Благовещенск (Ам ГПЗ)'!DE31 -> 0 | BX26: =IFERROR(BW26-BV26,"-") -> -3258.1 | BY26: =IFERROR(BW26/BV26,"-") -> 0
C27: Амурский ГПЗ | G27: 14_100335074 | I27: млн куб.м. | J27: =N27+AD27+AT27+BJ27 -> 35384.8 | K27: =O27+AE27+AU27+BK27 -> 0 | L27: =IFERROR(K27-J27,"-") -> -35384.8 | M27: =IFERROR(K27/J27,"-") -> 0 | N27: =R27+V27+Z27 -> 8849.4 | O27: =S27+W27+AA27 -> 0 | P27: =IFERROR(O27-N27,"-") -> -8849.4 | Q27: =IFERROR(O27/N27,"-") -> 0 | R27: ='14. ГП Благовещенск (Ам ГПЗ)'!W31 -> 3189.9 | S27: ='14. ГП Благовещенск (Ам ГПЗ)'!Y31 -> 0 | T27: =IFERROR(S27-R27,"-") -> -3189.9 | U27: =IFERROR(S27/R27,"-") -> 0 | V27: ='14. ГП Благовещенск (Ам ГПЗ)'!AC31 -> 2881.1 | W27: ='14. ГП Благовещенск (Ам ГПЗ)'!AE31 -> 0 | X27: =IFERROR(W27-V27,"-") -> -2881.1 | Y27: =IFERROR(W27/V27,"-") -> 0 | Z27: ='14. ГП Благовещенск (Ам ГПЗ)'!AI31 -> 2778.4 | AA27: ='14. ГП Благовещенск (Ам ГПЗ)'!AK31 -> 0 | AB27: =IFERROR(AA27-Z27,"-") -> -2778.4 | AC27: =IFERROR(AA27/Z27,"-") -> 0 | AD27: =AH27+AL27+AP27 -> 8707.4 | AE27: =AI27+AM27+AQ27 -> 0 | AF27: =IFERROR(AE27-AD27,"-") -> -8707.4 | AG27: =IFERROR(AE27/AD27,"-") -> 0 | AH27: ='14. ГП Благовещенск (Ам ГПЗ)'!AU31 -> 2355.9 | AI27: ='14. ГП Благовещенск (Ам ГПЗ)'!AW31 -> 0 | AJ27: =IFERROR(AI27-AH27,"-") -> -2355.9 | AK27: =IFERROR(AI27/AH27,"-") -> 0 | AL27: ='14. ГП Благовещенск (Ам ГПЗ)'!BA31 -> 3198.6 | AM27: ='14. ГП Благовещенск (Ам ГПЗ)'!BC31 -> 0 | AN27: =IFERROR(AM27-AL27,"-") -> -3198.6 | AO27: =IFERROR(AM27/AL27,"-") -> 0 | AP27: ='14. ГП Благовещенск (Ам ГПЗ)'!BG31 -> 3152.9 | AQ27: ='14. ГП Благовещенск (Ам ГПЗ)'!BI31 -> 0 | AR27: =IFERROR(AQ27-AP27,"-") -> -3152.9 | AS27: =IFERROR(AQ27/AP27,"-") -> 0 | AT27: =AX27+BB27+BF27 -> 8195.5 | AU27: =AY27+BC27+BG27 -> 0 | AV27: =IFERROR(AU27-AT27,"-") -> -8195.5 | AW27: =IFERROR(AU27/AT27,"-") -> 0 | AX27: ='14. ГП Благовещенск (Ам ГПЗ)'!BS31 -> 3258 | AY27: ='14. ГП Благовещенск (Ам ГПЗ)'!BU31 -> 0 | AZ27: =IFERROR(AY27-AX27,"-") -> -3258 | BA27: =IFERROR(AY27/AX27,"-") -> 0 | BB27: ='14. ГП Благовещенск (Ам ГПЗ)'!BY31 -> 3258.1 | BC27: ='14. ГП Благовещенск (Ам ГПЗ)'!CA31 -> 0 | BD27: =IFERROR(BC27-BB27,"-") -> -3258.1 | BE27: =IFERROR(BC27/BB27,"-") -> 0 | BF27: ='14. ГП Благовещенск (Ам ГПЗ)'!CE31 -> 1679.4 | BG27: ='14. ГП Благовещенск (Ам ГПЗ)'!CG31 -> 0 | BH27: =IFERROR(BG27-BF27,"-") -> -1679.4 | BI27: =IFERROR(BG27/BF27,"-") -> 0 | BJ27: =BN27+BR27+BV27 -> 9632.5 | BK27: =BO27+BS27+BW27 -> 0 | BL27: =IFERROR(BK27-BJ27,"-") -> -9632.5 | BM27: =IFERROR(BK27/BJ27,"-") -> 0 | BN27: ='14. ГП Благовещенск (Ам ГПЗ)'!CQ31 -> 3221.4 | BO27: ='14. ГП Благовещенск (Ам ГПЗ)'!CS31 -> 0 | BP27: =IFERROR(BO27-BN27,"-") -> -3221.4 | BQ27: =IFERROR(BO27/BN27,"-") -> 0 | BR27: ='14. ГП Благовещенск (Ам ГПЗ)'!CW31 -> 3153 | BS27: ='14. ГП Благовещенск (Ам ГПЗ)'!CY31 -> 0 | BT27: =IFERROR(BS27-BR27,"-") -> -3153 | BU27: =IFERROR(BS27/BR27,"-") -> 0 | BV27: ='14. ГП Благовещенск (Ам ГПЗ)'!DC31 -> 3258.1 | BW27: ='14. ГП Благовещенск (Ам ГПЗ)'!DE31 -> 0 | BX27: =IFERROR(BW27-BV27,"-") -> -3258.1 | BY27: =IFERROR(BW27/BV27,"-") -> 0
C28: Газпром СПГ Портовая | I28: млн куб.м.
C29: КСПГ Портовая | I29: млн куб.м.
C30: в т.ч. на ПНР | I30: млн куб.м.
C31: в т.ч. СТН | I31: млн куб.м.
C32: в т.ч. на переработку | I32: млн куб.м.
B33: 1.2 | C33: Дочерние общества | G33: 2_100332038+2_100332040+2_100332042+2_100332044+2_100332916+2_100332944+2_100335129+3_100330552+14_100335076 | I33: млн куб.м. | J33: =N33+AD33+AT33+BJ33 -> 11711.1 | K33: =O33+AE33+AU33+BK33 -> 0 | L33: =IFERROR(K33-J33,"-") -> -11711.1 | M33: =IFERROR(K33/J33,"-") -> 0 | N33: =R33+V33+Z33 -> 3149.3 | O33: =S33+W33+AA33 -> 0 | P33: =IFERROR(O33-N33,"-") -> -3149.3 | Q33: =IFERROR(O33/N33,"-") -> 0 | R33: ='2. ГПП-ОГХК'!W21+'2. ГПП-ОГХК'!W25+'2. ГПП-ОГХК'!W27+'2. ГПП-ОГХК'!W29+'2. ГПП-ОГХК'!W31+'2. ГПП-ОГХК'!W33+'2. ГПП-ОГХК'!W35+'3. ГПП-СГПЗ'!W18+'14. ГП Благовещенск (Ам ГПЗ)'!W33 -> 1092.1 | S33: ='2. ГПП-ОГХК'!Y21+'2. ГПП-ОГХК'!Y25+'2. ГПП-ОГХК'!Y27+'2. ГПП-ОГХК'!Y29+'2. ГПП-ОГХК'!Y31+'2. ГПП-ОГХК'!Y33+'2. ГПП-ОГХК'!Y35+'3. ГПП-СГПЗ'!Y18+'14. ГП Благовещенск (Ам ГПЗ)'!Y33 -> 0 | T33: =IFERROR(S33-R33,"-") -> -1092.1 | U33: =IFERROR(S33/R33,"-") -> 0 | V33: ='2. ГПП-ОГХК'!AC21+'2. ГПП-ОГХК'!AC25+'2. ГПП-ОГХК'!AC27+'2. ГПП-ОГХК'!AC29+'2. ГПП-ОГХК'!AC31+'2. ГПП-ОГХК'!AC33+'2. ГПП-ОГХК'!AC35+'3. ГПП-СГПЗ'!AC18+'14. ГП Благовещенск (Ам ГПЗ)'!AC33 -> 986.3 | W33: ='2. ГПП-ОГХК'!AE21+'2. ГПП-ОГХК'!AE25+'2. ГПП-ОГХК'!AE27+'2. ГПП-ОГХК'!AE29+'2. ГПП-ОГХК'!AE31+'2. ГПП-ОГХК'!AE33+'2. ГПП-ОГХК'!AE35+'3. ГПП-СГПЗ'!AE18+'14. ГП Благовещенск (Ам ГПЗ)'!AE33 -> 0 | X33: =IFERROR(W33-V33,"-") -> -986.3 | Y33: =IFERROR(W33/V33,"-") -> 0 | Z33: ='2. ГПП-ОГХК'!AI21+'2. ГПП-ОГХК'!AI25+'2. ГПП-ОГХК'!AI27+'2. ГПП-ОГХК'!AI29+'2. ГПП-ОГХК'!AI31+'2. ГПП-ОГХК'!AI33+'2. ГПП-ОГХК'!AI35+'3. ГПП-СГПЗ'!AI18+'14. ГП Благовещенск (Ам ГПЗ)'!AI33 -> 1070.9 | AA33: ='2. ГПП-ОГХК'!AK21+'2. ГПП-ОГХК'!AK25+'2. ГПП-ОГХК'!AK27+'2. ГПП-ОГХК'!AK29+'2. ГПП-ОГХК'!AK31+'2. ГПП-ОГХК'!AK33+'2. ГПП-ОГХК'!AK35+'3. ГПП-СГПЗ'!AK18+'14. ГП Благовещенск (Ам ГПЗ)'!AK33 -> 0 | AB33: =IFERROR(AA33-Z33,"-") -> -1070.9 | AC33: =IFERROR(AA33/Z33,"-") -> 0 | AD33: =AH33+AL33+AP33 -> 2583 | AE33: =AI33+AM33+AQ33 -> 0 | AF33: =IFERROR(AE33-AD33,"-") -> -2583 | AG33: =IFERROR(AE33/AD33,"-") -> 0 | AH33: ='2. ГПП-ОГХК'!AU21+'2. ГПП-ОГХК'!AU25+'2. ГПП-ОГХК'!AU27+'2. ГПП-ОГХК'!AU29+'2. ГПП-ОГХК'!AU31+'2. ГПП-ОГХК'!AU33+'2. ГПП-ОГХК'!AU35+'3. ГПП-СГПЗ'!AU18+'14. ГП Благовещенск (Ам ГПЗ)'!AU33 -> 895.5 | AI33: ='2. ГПП-ОГХК'!AW21+'2. ГПП-ОГХК'!AW25+'2. ГПП-ОГХК'!AW27+'2. ГПП-ОГХК'!AW29+'2. ГПП-ОГХК'!AW31+'2. ГПП-ОГХК'!AW33+'2. ГПП-ОГХК'!AW35+'3. ГПП-СГПЗ'!AW18+'14. ГП Благовещенск (Ам ГПЗ)'!AW33 -> 0 | AJ33: =IFERROR(AI33-AH33,"-") -> -895.5 | AK33: =IFERROR(AI33/AH33,"-") -> 0 | AL33: ='2. ГПП-ОГХК'!BA21+'2. ГПП-ОГХК'!BA25+'2. ГПП-ОГХК'!BA27+'2. ГПП-ОГХК'!BA29+'2. ГПП-ОГХК'!BA31+'2. ГПП-ОГХК'!BA33+'2. ГПП-ОГХК'!BA35+'3. ГПП-СГПЗ'!BA18+'14. ГП Благовещенск (Ам ГПЗ)'!BA33 -> 862.1 | AM33: ='2. ГПП-ОГХК'!BC21+'2. ГПП-ОГХК'!BC25+'2. ГПП-ОГХК'!BC27+'2. ГПП-ОГХК'!BC29+'2. ГПП-ОГХК'!BC31+'2. ГПП-ОГХК'!BC33+'2. ГПП-ОГХК'!BC35+'3. ГПП-СГПЗ'!BC18+'14. ГП Благовещенск (Ам ГПЗ)'!BC33 -> 0 | AN33: =IFERROR(AM33-AL33,"-") -> -862.1 | AO33: =IFERROR(AM33/AL33,"-") -> 0 | AP33: ='2. ГПП-ОГХК'!BG21+'2. ГПП-ОГХК'!BG25+'2. ГПП-ОГХК'!BG27+'2. ГПП-ОГХК'!BG29+'2. ГПП-ОГХК'!BG31+'2. ГПП-ОГХК'!BG33+'2. ГПП-ОГХК'!BG35+'3. ГПП-СГПЗ'!BG18+'14. ГП Благовещенск (Ам ГПЗ)'!BG33 -> 825.4 | AQ33: ='2. ГПП-ОГХК'!BI21+'2. ГПП-ОГХК'!BI25+'2. ГПП-ОГХК'!BI27+'2. ГПП-ОГХК'!BI29+'2. ГПП-ОГХК'!BI31+'2. ГПП-ОГХК'!BI33+'2. ГПП-ОГХК'!BI35+'3. ГПП-СГПЗ'!BI18+'14. ГП Благовещенск (Ам ГПЗ)'!BI33 -> 0 | AR33: =IFERROR(AQ33-AP33,"-") -> -825.4 | AS33: =IFERROR(AQ33/AP33,"-") -> 0 | AT33: =AX33+BB33+BF33 -> 2759.3 | AU33: =AY33+BC33+BG33 -> 0 | AV33: =IFERROR(AU33-AT33,"-") -> -2759.3 | AW33: =IFERROR(AU33/AT33,"-") -> 0 | AX33: ='2. ГПП-ОГХК'!BS21+'2. ГПП-ОГХК'!BS25+'2. ГПП-ОГХК'!BS27+'2. ГПП-ОГХК'!BS29+'2. ГПП-ОГХК'!BS31+'2. ГПП-ОГХК'!BS33+'2. ГПП-ОГХК'!BS35+'3. ГПП-СГПЗ'!BS18+'14. ГП Благовещенск (Ам ГПЗ)'!BS33 -> 878 | AY33: ='2. ГПП-ОГХК'!BU21+'2. ГПП-ОГХК'!BU25+'2. ГПП-ОГХК'!BU27+'2. ГПП-ОГХК'!BU29+'2. ГПП-ОГХК'!BU31+'2. ГПП-ОГХК'!BU33+'2. ГПП-ОГХК'!BU35+'3. ГПП-СГПЗ'!BU18+'14. ГП Благовещенск (Ам ГПЗ)'!BU33 -> 0 | AZ33: =IFERROR(AY33-AX33,"-") -> -878 | BA33: =IFERROR(AY33/AX33,"-") -> 0 | BB33: ='2. ГПП-ОГХК'!BY21+'2. ГПП-ОГХК'!BY25+'2. ГПП-ОГХК'!BY27+'2. ГПП-ОГХК'!BY29+'2. ГПП-ОГХК'!BY31+'2. ГПП-ОГХК'!BY33+'2. ГПП-ОГХК'!BY35+'3. ГПП-СГПЗ'!BY18+'14. ГП Благовещенск (Ам ГПЗ)'!BY33 -> 878.6 | BC33: ='2. ГПП-ОГХК'!CA21+'2. ГПП-ОГХК'!CA25+'2. ГПП-ОГХК'!CA27+'2. ГПП-ОГХК'!CA29+'2. ГПП-ОГХК'!CA31+'2. ГПП-ОГХК'!CA33+'2. ГПП-ОГХК'!CA35+'3. ГПП-СГПЗ'!CA18+'14. ГП Благовещенск (Ам ГПЗ)'!CA33 -> 0 | BD33: =IFERROR(BC33-BB33,"-") -> -878.6 | BE33: =IFERROR(BC33/BB33,"-") -> 0 | BF33: ='2. ГПП-ОГХК'!CE21+'2. ГПП-ОГХК'!CE25+'2. ГПП-ОГХК'!CE27+'2. ГПП-ОГХК'!CE29+'2. ГПП-ОГХК'!CE31+'2. ГПП-ОГХК'!CE33+'2. ГПП-ОГХК'!CE35+'3. ГПП-СГПЗ'!CE18+'14. ГП Благовещенск (Ам ГПЗ)'!CE33 -> 1002.7 | BG33: ='2. ГПП-ОГХК'!CG21+'2. ГПП-ОГХК'!CG25+'2. ГПП-ОГХК'!CG27+'2. ГПП-ОГХК'!CG29+'2. ГПП-ОГХК'!CG31+'2. ГПП-ОГХК'!CG33+'2. ГПП-ОГХК'!CG35+'3. ГПП-СГПЗ'!CG18+'14. ГП Благовещенск (Ам ГПЗ)'!CG33 -> 0 | BH33: =IFERROR(BG33-BF33,"-") -> -1002.7 | BI33: =IFERROR(BG33/BF33,"-") -> 0 | BJ33: =BN33+BR33+BV33 -> 3219.5 | BK33: =BO33+BS33+BW33 -> 0 | BL33: =IFERROR(BK33-BJ33,"-") -> -3219.5 | BM33: =IFERROR(BK33/BJ33,"-") -> 0 | BN33: ='2. ГПП-ОГХК'!CQ21+'2. ГПП-ОГХК'!CQ25+'2. ГПП-ОГХК'!CQ27+'2. ГПП-ОГХК'!CQ29+'2. ГПП-ОГХК'!CQ31+'2. ГПП-ОГХК'!CQ33+'2. ГПП-ОГХК'!CQ35+'3. ГПП-СГПЗ'!CQ18+'14. ГП Благовещенск (Ам ГПЗ)'!CQ33 -> 1085.8 | BO33: ='2. ГПП-ОГХК'!CS21+'2. ГПП-ОГХК'!CS25+'2. ГПП-ОГХК'!CS27+'2. ГПП-ОГХК'!CS29+'2. ГПП-ОГХК'!CS31+'2. ГПП-ОГХК'!CS33+'2. ГПП-ОГХК'!CS35+'3. ГПП-СГПЗ'!CS18+'14. ГП Благовещенск (Ам ГПЗ)'!CS33 -> 0 | BP33: =IFERROR(BO33-BN33,"-") -> -1085.8 | BQ33: =IFERROR(BO33/BN33,"-") -> 0 | BR33: ='2. ГПП-ОГХК'!CW21+'2. ГПП-ОГХК'!CW25+'2. ГПП-ОГХК'!CW27+'2. ГПП-ОГХК'!CW29+'2. ГПП-ОГХК'!CW31+'2. ГПП-ОГХК'!CW33+'2. ГПП-ОГХК'!CW35+'3. ГПП-СГПЗ'!CW18+'14. ГП Благовещенск (Ам ГПЗ)'!CW33 -> 1049.7 | BS33: ='2. ГПП-ОГХК'!CY21+'2. ГПП-ОГХК'!CY25+'2. ГПП-ОГХК'!CY27+'2. ГПП-ОГХК'!CY29+'2. ГПП-ОГХК'!CY31+'2. ГПП-ОГХК'!CY33+'2. ГПП-ОГХК'!CY35+'3. ГПП-СГПЗ'!CY18+'14. ГП Благовещенск (Ам ГПЗ)'!CY33 -> 0 | BT33: =IFERROR(BS33-BR33,"-") -> -1049.7 | BU33: =IFERROR(BS33/BR33,"-") -> 0 | BV33: ='2. ГПП-ОГХК'!DC21+'2. ГПП-ОГХК'!DC25+'2. ГПП-ОГХК'!DC27+'2. ГПП-ОГХК'!DC29+'2. ГПП-ОГХК'!DC31+'2. ГПП-ОГХК'!DC33+'2. ГПП-ОГХК'!DC35+'3. ГПП-СГПЗ'!DC18+'14. ГП Благовещенск (Ам ГПЗ)'!DC33 -> 1084 | BW33: ='2. ГПП-ОГХК'!DE21+'2. ГПП-ОГХК'!DE25+'2. ГПП-ОГХК'!DE27+'2. ГПП-ОГХК'!DE29+'2. ГПП-ОГХК'!DE31+'2. ГПП-ОГХК'!DE33+'2. ГПП-ОГХК'!DE35+'3. ГПП-СГПЗ'!DE18+'14. ГП Благовещенск (Ам ГПЗ)'!DE33 -> 0 | BX33: =IFERROR(BW33-BV33,"-") -> -1084 | BY33: =IFERROR(BW33/BV33,"-") -> 0
C34: Газпром добыча Астрахань | G34: 0 | I34: млн куб.м.
C35: Астраханский ГПЗ | G35: 0 | I35: млн куб.м.
C36: Газпром добыча Астрахань | I36: млн куб.м.
C37: Газпром переработка | G37: 2_100332038+2_100332040+2_100332042+2_100332044+2_100332916+2_100332944+2_100335129 | I37: млн куб.м. | J37: =N37+AD37+AT37+BJ37 -> 11699.1 | K37: =O37+AE37+AU37+BK37 -> 0 | L37: =IFERROR(K37-J37,"-") -> -11699.1 | M37: =IFERROR(K37/J37,"-") -> 0 | N37: =R37+V37+Z37 -> 3146.3 | O37: =S37+W37+AA37 -> 0 | P37: =IFERROR(O37-N37,"-") -> -3146.3 | Q37: =IFERROR(O37/N37,"-") -> 0 | R37: ='2. ГПП-ОГХК'!W21+'2. ГПП-ОГХК'!W25+'2. ГПП-ОГХК'!W27+'2. ГПП-ОГХК'!W29+'2. ГПП-ОГХК'!W31+'2. ГПП-ОГХК'!W33+'2. ГПП-ОГХК'!W35 -> 1091.1 | S37: ='2. ГПП-ОГХК'!Y21+'2. ГПП-ОГХК'!Y25+'2. ГПП-ОГХК'!Y27+'2. ГПП-ОГХК'!Y29+'2. ГПП-ОГХК'!Y31+'2. ГПП-ОГХК'!Y33+'2. ГПП-ОГХК'!Y35 -> 0 | T37: =IFERROR(S37-R37,"-") -> -1091.1 | U37: =IFERROR(S37/R37,"-") -> 0 | V37: ='2. ГПП-ОГХК'!AC21+'2. ГПП-ОГХК'!AC25+'2. ГПП-ОГХК'!AC27+'2. ГПП-ОГХК'!AC29+'2. ГПП-ОГХК'!AC31+'2. ГПП-ОГХК'!AC33+'2. ГПП-ОГХК'!AC35 -> 985.3 | W37: ='2. ГПП-ОГХК'!AE21+'2. ГПП-ОГХК'!AE25+'2. ГПП-ОГХК'!AE27+'2. ГПП-ОГХК'!AE29+'2. ГПП-ОГХК'!AE31+'2. ГПП-ОГХК'!AE33+'2. ГПП-ОГХК'!AE35 -> 0 | X37: =IFERROR(W37-V37,"-") -> -985.3 | Y37: =IFERROR(W37/V37,"-") -> 0 | Z37: ='2. ГПП-ОГХК'!AI21+'2. ГПП-ОГХК'!AI25+'2. ГПП-ОГХК'!AI27+'2. ГПП-ОГХК'!AI29+'2. ГПП-ОГХК'!AI31+'2. ГПП-ОГХК'!AI33+'2. ГПП-ОГХК'!AI35 -> 1069.9 | AA37: ='2. ГПП-ОГХК'!AK21+'2. ГПП-ОГХК'!AK25+'2. ГПП-ОГХК'!AK27+'2. ГПП-ОГХК'!AK29+'2. ГПП-ОГХК'!AK31+'2. ГПП-ОГХК'!AK33+'2. ГПП-ОГХК'!AK35 -> 0 | AB37: =IFERROR(AA37-Z37,"-") -> -1069.9 | AC37: =IFERROR(AA37/Z37,"-") -> 0 | AD37: =AH37+AL37+AP37 -> 2580 | AE37: =AI37+AM37+AQ37 -> 0 | AF37: =IFERROR(AE37-AD37,"-") -> -2580 | AG37: =IFERROR(AE37/AD37,"-") -> 0 | AH37: ='2. ГПП-ОГХК'!AU21+'2. ГПП-ОГХК'!AU25+'2. ГПП-ОГХК'!AU27+'2. ГПП-ОГХК'!AU29+'2. ГПП-ОГХК'!AU31+'2. ГПП-ОГХК'!AU33+'2. ГПП-ОГХК'!AU35 -> 894.5 | AI37: ='2. ГПП-ОГХК'!AW21+'2. ГПП-ОГХК'!AW25+'2. ГПП-ОГХК'!AW27+'2. ГПП-ОГХК'!AW29+'2. ГПП-ОГХК'!AW31+'2. ГПП-ОГХК'!AW33+'2. ГПП-ОГХК'!AW35 -> 0 | AJ37: =IFERROR(AI37-AH37,"-") -> -894.5 | AK37: =IFERROR(AI37/AH37,"-") -> 0 | AL37: ='2. ГПП-ОГХК'!BA21+'2. ГПП-ОГХК'!BA25+'2. ГПП-ОГХК'!BA27+'2. ГПП-ОГХК'!BA29+'2. ГПП-ОГХК'!BA31+'2. ГПП-ОГХК'!BA33+'2. ГПП-ОГХК'!BA35 -> 861.1 | AM37: ='2. ГПП-ОГХК'!BC21+'2. ГПП-ОГХК'!BC25+'2. ГПП-ОГХК'!BC27+'2. ГПП-ОГХК'!BC29+'2. ГПП-ОГХК'!BC31+'2. ГПП-ОГХК'!BC33+'2. ГПП-ОГХК'!BC35 -> 0 | AN37: =IFERROR(AM37-AL37,"-") -> -861.1 | AO37: =IFERROR(AM37/AL37,"-") -> 0 | AP37: ='2. ГПП-ОГХК'!BG21+'2. ГПП-ОГХК'!BG25+'2. ГПП-ОГХК'!BG27+'2. ГПП-ОГХК'!BG29+'2. ГПП-ОГХК'!BG31+'2. ГПП-ОГХК'!BG33+'2. ГПП-ОГХК'!BG35 -> 824.4 | AQ37: ='2. ГПП-ОГХК'!BI21+'2. ГПП-ОГХК'!BI25+'2. ГПП-ОГХК'!BI27+'2. ГПП-ОГХК'!BI29+'2. ГПП-ОГХК'!BI31+'2. ГПП-ОГХК'!BI33+'2. ГПП-ОГХК'!BI35 -> 0 | AR37: =IFERROR(AQ37-AP37,"-") -> -824.4 | AS37: =IFERROR(AQ37/AP37,"-") -> 0 | AT37: =AX37+BB37+BF37 -> 2756.3 | AU37: =AY37+BC37+BG37 -> 0 | AV37: =IFERROR(AU37-AT37,"-") -> -2756.3 | AW37: =IFERROR(AU37/AT37,"-") -> 0 | AX37: ='2. ГПП-ОГХК'!BS21+'2. ГПП-ОГХК'!BS25+'2. ГПП-ОГХК'!BS27+'2. ГПП-ОГХК'!BS29+'2. ГПП-ОГХК'!BS31+'2. ГПП-ОГХК'!BS33+'2. ГПП-ОГХК'!BS35 -> 877 | AY37: ='2. ГПП-ОГХК'!BU21+'2. ГПП-ОГХК'!BU25+'2. ГПП-ОГХК'!BU27+'2. ГПП-ОГХК'!BU29+'2. ГПП-ОГХК'!BU31+'2. ГПП-ОГХК'!BU33+'2. ГПП-ОГХК'!BU35 -> 0 | AZ37: =IFERROR(AY37-AX37,"-") -> -877 | BA37: =IFERROR(AY37/AX37,"-") -> 0 | BB37: ='2. ГПП-ОГХК'!BY21+'2. ГПП-ОГХК'!BY25+'2. ГПП-ОГХК'!BY27+'2. ГПП-ОГХК'!BY29+'2. ГПП-ОГХК'!BY31+'2. ГПП-ОГХК'!BY33+'2. ГПП-ОГХК'!BY35 -> 877.6 | BC37: ='2. ГПП-ОГХК'!CA21+'2. ГПП-ОГХК'!CA25+'2. ГПП-ОГХК'!CA27+'2. ГПП-ОГХК'!CA29+'2. ГПП-ОГХК'!CA31+'2. ГПП-ОГХК'!CA33+'2. ГПП-ОГХК'!CA35 -> 0 | BD37: =IFERROR(BC37-BB37,"-") -> -877.6 | BE37: =IFERROR(BC37/BB37,"-") -> 0 | BF37: ='2. ГПП-ОГХК'!CE21+'2. ГПП-ОГХК'!CE25+'2. ГПП-ОГХК'!CE27+'2. ГПП-ОГХК'!CE29+'2. ГПП-ОГХК'!CE31+'2. ГПП-ОГХК'!CE33+'2. ГПП-ОГХК'!CE35 -> 1001.7 | BG37: ='2. ГПП-ОГХК'!CG21+'2. ГПП-ОГХК'!CG25+'2. ГПП-ОГХК'!CG27+'2. ГПП-ОГХК'!CG29+'2. ГПП-ОГХК'!CG31+'2. ГПП-ОГХК'!CG33+'2. ГПП-ОГХК'!CG35 -> 0 | BH37: =IFERROR(BG37-BF37,"-") -> -1001.7 | BI37: =IFERROR(BG37/BF37,"-") -> 0 | BJ37: =BN37+BR37+BV37 -> 3216.5 | BK37: =BO37+BS37+BW37 -> 0 | BL37: =IFERROR(BK37-BJ37,"-") -> -3216.5 | BM37: =IFERROR(BK37/BJ37,"-") -> 0 | BN37: ='2. ГПП-ОГХК'!CQ21+'2. ГПП-ОГХК'!CQ25+'2. ГПП-ОГХК'!CQ27+'2. ГПП-ОГХК'!CQ29+'2. ГПП-ОГХК'!CQ31+'2. ГПП-ОГХК'!CQ33+'2. ГПП-ОГХК'!CQ35 -> 1084.8 | BO37: ='2. ГПП-ОГХК'!CS21+'2. ГПП-ОГХК'!CS25+'2. ГПП-ОГХК'!CS27+'2. ГПП-ОГХК'!CS29+'2. ГПП-ОГХК'!CS31+'2. ГПП-ОГХК'!CS33+'2. ГПП-ОГХК'!CS35 -> 0 | BP37: =IFERROR(BO37-BN37,"-") -> -1084.8 | BQ37: =IFERROR(BO37/BN37,"-") -> 0 | BR37: ='2. ГПП-ОГХК'!CW21+'2. ГПП-ОГХК'!CW25+'2. ГПП-ОГХК'!CW27+'2. ГПП-ОГХК'!CW29+'2. ГПП-ОГХК'!CW31+'2. ГПП-ОГХК'!CW33+'2. ГПП-ОГХК'!CW35 -> 1048.7 | BS37: ='2. ГПП-ОГХК'!CY21+'2. ГПП-ОГХК'!CY25+'2. ГПП-ОГХК'!CY27+'2. ГПП-ОГХК'!CY29+'2. ГПП-ОГХК'!CY31+'2. ГПП-ОГХК'!CY33+'2. ГПП-ОГХК'!CY35 -> 0 | BT37: =IFERROR(BS37-BR37,"-") -> -1048.7 | BU37: =IFERROR(BS37/BR37,"-") -> 0 | BV37: ='2. ГПП-ОГХК'!DC21+'2. ГПП-ОГХК'!DC25+'2. ГПП-ОГХК'!DC27+'2. ГПП-ОГХК'!DC29+'2. ГПП-ОГХК'!DC31+'2. ГПП-ОГХК'!DC33+'2. ГПП-ОГХК'!DC35 -> 1083 | BW37: ='2. ГПП-ОГХК'!DE21+'2. ГПП-ОГХК'!DE25+'2. ГПП-ОГХК'!DE27+'2. ГПП-ОГХК'!DE29+'2. ГПП-ОГХК'!DE31+'2. ГПП-ОГХК'!DE33+'2. ГПП-ОГХК'!DE35 -> 0 | BX37: =IFERROR(BW37-BV37,"-") -> -1083 | BY37: =IFERROR(BW37/BV37,"-") -> 0
C38: Оренбургский ГХК | G38: 2_100332038+2_100332040+2_100332042+2_100332044+2_100332916+2_100332944+2_100335129 | I38: млн куб.м. | J38: =N38+AD38+AT38+BJ38 -> 11699.1 | K38: =O38+AE38+AU38+BK38 -> 0 | L38: =IFERROR(K38-J38,"-") -> -11699.1 | M38: =IFERROR(K38/J38,"-") -> 0 | N38: =R38+V38+Z38 -> 3146.3 | O38: =S38+W38+AA38 -> 0 | P38: =IFERROR(O38-N38,"-") -> -3146.3 | Q38: =IFERROR(O38/N38,"-") -> 0 | R38: ='2. ГПП-ОГХК'!W21+'2. ГПП-ОГХК'!W25+'2. ГПП-ОГХК'!W27+'2. ГПП-ОГХК'!W29+'2. ГПП-ОГХК'!W31+'2. ГПП-ОГХК'!W33+'2. ГПП-ОГХК'!W35 -> 1091.1 | S38: ='2. ГПП-ОГХК'!Y21+'2. ГПП-ОГХК'!Y25+'2. ГПП-ОГХК'!Y27+'2. ГПП-ОГХК'!Y29+'2. ГПП-ОГХК'!Y31+'2. ГПП-ОГХК'!Y33+'2. ГПП-ОГХК'!Y35 -> 0 | T38: =IFERROR(S38-R38,"-") -> -1091.1 | U38: =IFERROR(S38/R38,"-") -> 0 | V38: ='2. ГПП-ОГХК'!AC21+'2. ГПП-ОГХК'!AC25+'2. ГПП-ОГХК'!AC27+'2. ГПП-ОГХК'!AC29+'2. ГПП-ОГХК'!AC31+'2. ГПП-ОГХК'!AC33+'2. ГПП-ОГХК'!AC35 -> 985.3 | W38: ='2. ГПП-ОГХК'!AE21+'2. ГПП-ОГХК'!AE25+'2. ГПП-ОГХК'!AE27+'2. ГПП-ОГХК'!AE29+'2. ГПП-ОГХК'!AE31+'2. ГПП-ОГХК'!AE33+'2. ГПП-ОГХК'!AE35 -> 0 | X38: =IFERROR(W38-V38,"-") -> -985.3 | Y38: =IFERROR(W38/V38,"-") -> 0 | Z38: ='2. ГПП-ОГХК'!AI21+'2. ГПП-ОГХК'!AI25+'2. ГПП-ОГХК'!AI27+'2. ГПП-ОГХК'!AI29+'2. ГПП-ОГХК'!AI31+'2. ГПП-ОГХК'!AI33+'2. ГПП-ОГХК'!AI35 -> 1069.9 | AA38: ='2. ГПП-ОГХК'!AK21+'2. ГПП-ОГХК'!AK25+'2. ГПП-ОГХК'!AK27+'2. ГПП-ОГХК'!AK29+'2. ГПП-ОГХК'!AK31+'2. ГПП-ОГХК'!AK33+'2. ГПП-ОГХК'!AK35 -> 0 | AB38: =IFERROR(AA38-Z38,"-") -> -1069.9 | AC38: =IFERROR(AA38/Z38,"-") -> 0 | AD38: =AH38+AL38+AP38 -> 2580 | AE38: =AI38+AM38+AQ38 -> 0 | AF38: =IFERROR(AE38-AD38,"-") -> -2580 | AG38: =IFERROR(AE38/AD38,"-") -> 0 | AH38: ='2. ГПП-ОГХК'!AU21+'2. ГПП-ОГХК'!AU25+'2. ГПП-ОГХК'!AU27+'2. ГПП-ОГХК'!AU29+'2. ГПП-ОГХК'!AU31+'2. ГПП-ОГХК'!AU33+'2. ГПП-ОГХК'!AU35 -> 894.5 | AI38: ='2. ГПП-ОГХК'!AW21+'2. ГПП-ОГХК'!AW25+'2. ГПП-ОГХК'!AW27+'2. ГПП-ОГХК'!AW29+'2. ГПП-ОГХК'!AW31+'2. ГПП-ОГХК'!AW33+'2. ГПП-ОГХК'!AW35 -> 0 | AJ38: =IFERROR(AI38-AH38,"-") -> -894.5 | AK38: =IFERROR(AI38/AH38,"-") -> 0 | AL38: ='2. ГПП-ОГХК'!BA21+'2. ГПП-ОГХК'!BA25+'2. ГПП-ОГХК'!BA27+'2. ГПП-ОГХК'!BA29+'2. ГПП-ОГХК'!BA31+'2. ГПП-ОГХК'!BA33+'2. ГПП-ОГХК'!BA35 -> 861.1 | AM38: ='2. ГПП-ОГХК'!BC21+'2. ГПП-ОГХК'!BC25+'2. ГПП-ОГХК'!BC27+'2. ГПП-ОГХК'!BC29+'2. ГПП-ОГХК'!BC31+'2. ГПП-ОГХК'!BC33+'2. ГПП-ОГХК'!BC35 -> 0 | AN38: =IFERROR(AM38-AL38,"-") -> -861.1 | AO38: =IFERROR(AM38/AL38,"-") -> 0 | AP38: ='2. ГПП-ОГХК'!BG21+'2. ГПП-ОГХК'!BG25+'2. ГПП-ОГХК'!BG27+'2. ГПП-ОГХК'!BG29+'2. ГПП-ОГХК'!BG31+'2. ГПП-ОГХК'!BG33+'2. ГПП-ОГХК'!BG35 -> 824.4 | AQ38: ='2. ГПП-ОГХК'!BI21+'2. ГПП-ОГХК'!BI25+'2. ГПП-ОГХК'!BI27+'2. ГПП-ОГХК'!BI29+'2. ГПП-ОГХК'!BI31+'2. ГПП-ОГХК'!BI33+'2. ГПП-ОГХК'!BI35 -> 0 | AR38: =IFERROR(AQ38-AP38,"-") -> -824.4 | AS38: =IFERROR(AQ38/AP38,"-") -> 0 | AT38: =AX38+BB38+BF38 -> 2756.3 | AU38: =AY38+BC38+BG38 -> 0 | AV38: =IFERROR(AU38-AT38,"-") -> -2756.3 | AW38: =IFERROR(AU38/AT38,"-") -> 0 | AX38: ='2. ГПП-ОГХК'!BS21+'2. ГПП-ОГХК'!BS25+'2. ГПП-ОГХК'!BS27+'2. ГПП-ОГХК'!BS29+'2. ГПП-ОГХК'!BS31+'2. ГПП-ОГХК'!BS33+'2. ГПП-ОГХК'!BS35 -> 877 | AY38: ='2. ГПП-ОГХК'!BU21+'2. ГПП-ОГХК'!BU25+'2. ГПП-ОГХК'!BU27+'2. ГПП-ОГХК'!BU29+'2. ГПП-ОГХК'!BU31+'2. ГПП-ОГХК'!BU33+'2. ГПП-ОГХК'!BU35 -> 0 | AZ38: =IFERROR(AY38-AX38,"-") -> -877 | BA38: =IFERROR(AY38/AX38,"-") -> 0 | BB38: ='2. ГПП-ОГХК'!BY21+'2. ГПП-ОГХК'!BY25+'2. ГПП-ОГХК'!BY27+'2. ГПП-ОГХК'!BY29+'2. ГПП-ОГХК'!BY31+'2. ГПП-ОГХК'!BY33+'2. ГПП-ОГХК'!BY35 -> 877.6 | BC38: ='2. ГПП-ОГХК'!CA21+'2. ГПП-ОГХК'!CA25+'2. ГПП-ОГХК'!CA27+'2. ГПП-ОГХК'!CA29+'2. ГПП-ОГХК'!CA31+'2. ГПП-ОГХК'!CA33+'2. ГПП-ОГХК'!CA35 -> 0 | BD38: =IFERROR(BC38-BB38,"-") -> -877.6 | BE38: =IFERROR(BC38/BB38,"-") -> 0 | BF38: ='2. ГПП-ОГХК'!CE21+'2. ГПП-ОГХК'!CE25+'2. ГПП-ОГХК'!CE27+'2. ГПП-ОГХК'!CE29+'2. ГПП-ОГХК'!CE31+'2. ГПП-ОГХК'!CE33+'2. ГПП-ОГХК'!CE35 -> 1001.7 | BG38: ='2. ГПП-ОГХК'!CG21+'2. ГПП-ОГХК'!CG25+'2. ГПП-ОГХК'!CG27+'2. ГПП-ОГХК'!CG29+'2. ГПП-ОГХК'!CG31+'2. ГПП-ОГХК'!CG33+'2. ГПП-ОГХК'!CG35 -> 0 | BH38: =IFERROR(BG38-BF38,"-") -> -1001.7 | BI38: =IFERROR(BG38/BF38,"-") -> 0 | BJ38: =BN38+BR38+BV38 -> 3216.5 | BK38: =BO38+BS38+BW38 -> 0 | BL38: =IFERROR(BK38-BJ38,"-") -> -3216.5 | BM38: =IFERROR(BK38/BJ38,"-") -> 0 | BN38: ='2. ГПП-ОГХК'!CQ21+'2. ГПП-ОГХК'!CQ25+'2. ГПП-ОГХК'!CQ27+'2. ГПП-ОГХК'!CQ29+'2. ГПП-ОГХК'!CQ31+'2. ГПП-ОГХК'!CQ33+'2. ГПП-ОГХК'!CQ35 -> 1084.8 | BO38: ='2. ГПП-ОГХК'!CS21+'2. ГПП-ОГХК'!CS25+'2. ГПП-ОГХК'!CS27+'2. ГПП-ОГХК'!CS29+'2. ГПП-ОГХК'!CS31+'2. ГПП-ОГХК'!CS33+'2. ГПП-ОГХК'!CS35 -> 0 | BP38: =IFERROR(BO38-BN38,"-") -> -1084.8 | BQ38: =IFERROR(BO38/BN38,"-") -> 0 | BR38: ='2. ГПП-ОГХК'!CW21+'2. ГПП-ОГХК'!CW25+'2. ГПП-ОГХК'!CW27+'2. ГПП-ОГХК'!CW29+'2. ГПП-ОГХК'!CW31+'2. ГПП-ОГХК'!CW33+'2. ГПП-ОГХК'!CW35 -> 1048.7 | BS38: ='2. ГПП-ОГХК'!CY21+'2. ГПП-ОГХК'!CY25+'2. ГПП-ОГХК'!CY27+'2. ГПП-ОГХК'!CY29+'2. ГПП-ОГХК'!CY31+'2. ГПП-ОГХК'!CY33+'2. ГПП-ОГХК'!CY35 -> 0 | BT38: =IFERROR(BS38-BR38,"-") -> -1048.7 | BU38: =IFERROR(BS38/BR38,"-") -> 0 | BV38: ='2. ГПП-ОГХК'!DC21+'2. ГПП-ОГХК'!DC25+'2. ГПП-ОГХК'!DC27+'2. ГПП-ОГХК'!DC29+'2. ГПП-ОГХК'!DC31+'2. ГПП-ОГХК'!DC33+'2. ГПП-ОГХК'!DC35 -> 1083 | BW38: ='2. ГПП-ОГХК'!DE21+'2. ГПП-ОГХК'!DE25+'2. ГПП-ОГХК'!DE27+'2. ГПП-ОГХК'!DE29+'2. ГПП-ОГХК'!DE31+'2. ГПП-ОГХК'!DE33+'2. ГПП-ОГХК'!DE35 -> 0 | BX38: =IFERROR(BW38-BV38,"-") -> -1083 | BY38: =IFERROR(BW38/BV38,"-") -> 0
C39: покупка у Газпром добыча Оренбург, всего | G39: 2_100332038+2_100332040+2_100332042+2_100332044+2_100332916+2_100332944+2_100335129 | I39: млн куб.м. | J39: =N39+AD39+AT39+BJ39 -> 11699.1 | K39: =O39+AE39+AU39+BK39 -> 0 | L39: =IFERROR(K39-J39,"-") -> -11699.1 | M39: =IFERROR(K39/J39,"-") -> 0 | N39: =R39+V39+Z39 -> 3146.3 | O39: =S39+W39+AA39 -> 0 | P39: =IFERROR(O39-N39,"-") -> -3146.3 | Q39: =IFERROR(O39/N39,"-") -> 0 | R39: ='2. ГПП-ОГХК'!W21+'2. ГПП-ОГХК'!W25+'2. ГПП-ОГХК'!W27+'2. ГПП-ОГХК'!W29+'2. ГПП-ОГХК'!W31+'2. ГПП-ОГХК'!W33+'2. ГПП-ОГХК'!W35 -> 1091.1 | S39: ='2. ГПП-ОГХК'!Y21+'2. ГПП-ОГХК'!Y25+'2. ГПП-ОГХК'!Y27+'2. ГПП-ОГХК'!Y29+'2. ГПП-ОГХК'!Y31+'2. ГПП-ОГХК'!Y33+'2. ГПП-ОГХК'!Y35 -> 0 | T39: =IFERROR(S39-R39,"-") -> -1091.1 | U39: =IFERROR(S39/R39,"-") -> 0 | V39: ='2. ГПП-ОГХК'!AC21+'2. ГПП-ОГХК'!AC25+'2. ГПП-ОГХК'!AC27+'2. ГПП-ОГХК'!AC29+'2. ГПП-ОГХК'!AC31+'2. ГПП-ОГХК'!AC33+'2. ГПП-ОГХК'!AC35 -> 985.3 | W39: ='2. ГПП-ОГХК'!AE21+'2. ГПП-ОГХК'!AE25+'2. ГПП-ОГХК'!AE27+'2. ГПП-ОГХК'!AE29+'2. ГПП-ОГХК'!AE31+'2. ГПП-ОГХК'!AE33+'2. ГПП-ОГХК'!AE35 -> 0 | X39: =IFERROR(W39-V39,"-") -> -985.3 | Y39: =IFERROR(W39/V39,"-") -> 0 | Z39: ='2. ГПП-ОГХК'!AI21+'2. ГПП-ОГХК'!AI25+'2. ГПП-ОГХК'!AI27+'2. ГПП-ОГХК'!AI29+'2. ГПП-ОГХК'!AI31+'2. ГПП-ОГХК'!AI33+'2. ГПП-ОГХК'!AI35 -> 1069.9 | AA39: ='2. ГПП-ОГХК'!AK21+'2. ГПП-ОГХК'!AK25+'2. ГПП-ОГХК'!AK27+'2. ГПП-ОГХК'!AK29+'2. ГПП-ОГХК'!AK31+'2. ГПП-ОГХК'!AK33+'2. ГПП-ОГХК'!AK35 -> 0 | AB39: =IFERROR(AA39-Z39,"-") -> -1069.9 | AC39: =IFERROR(AA39/Z39,"-") -> 0 | AD39: =AH39+AL39+AP39 -> 2580 | AE39: =AI39+AM39+AQ39 -> 0 | AF39: =IFERROR(AE39-AD39,"-") -> -2580 | AG39: =IFERROR(AE39/AD39,"-") -> 0 | AH39: ='2. ГПП-ОГХК'!AU21+'2. ГПП-ОГХК'!AU25+'2. ГПП-ОГХК'!AU27+'2. ГПП-ОГХК'!AU29+'2. ГПП-ОГХК'!AU31+'2. ГПП-ОГХК'!AU33+'2. ГПП-ОГХК'!AU35 -> 894.5 | AI39: ='2. ГПП-ОГХК'!AW21+'2. ГПП-ОГХК'!AW25+'2. ГПП-ОГХК'!AW27+'2. ГПП-ОГХК'!AW29+'2. ГПП-ОГХК'!AW31+'2. ГПП-ОГХК'!AW33+'2. ГПП-ОГХК'!AW35 -> 0 | AJ39: =IFERROR(AI39-AH39,"-") -> -894.5 | AK39: =IFERROR(AI39/AH39,"-") -> 0 | AL39: ='2. ГПП-ОГХК'!BA21+'2. ГПП-ОГХК'!BA25+'2. ГПП-ОГХК'!BA27+'2. ГПП-ОГХК'!BA29+'2. ГПП-ОГХК'!BA31+'2. ГПП-ОГХК'!BA33+'2. ГПП-ОГХК'!BA35 -> 861.1 | AM39: ='2. ГПП-ОГХК'!BC21+'2. ГПП-ОГХК'!BC25+'2. ГПП-ОГХК'!BC27+'2. ГПП-ОГХК'!BC29+'2. ГПП-ОГХК'!BC31+'2. ГПП-ОГХК'!BC33+'2. ГПП-ОГХК'!BC35 -> 0 | AN39: =IFERROR(AM39-AL39,"-") -> -861.1 | AO39: =IFERROR(AM39/AL39,"-") -> 0 | AP39: ='2. ГПП-ОГХК'!BG21+'2. ГПП-ОГХК'!BG25+'2. ГПП-ОГХК'!BG27+'2. ГПП-ОГХК'!BG29+'2. ГПП-ОГХК'!BG31+'2. ГПП-ОГХК'!BG33+'2. ГПП-ОГХК'!BG35 -> 824.4 | AQ39: ='2. ГПП-ОГХК'!BI21+'2. ГПП-ОГХК'!BI25+'2. ГПП-ОГХК'!BI27+'2. ГПП-ОГХК'!BI29+'2. ГПП-ОГХК'!BI31+'2. ГПП-ОГХК'!BI33+'2. ГПП-ОГХК'!BI35 -> 0 | AR39: =IFERROR(AQ39-AP39,"-") -> -824.4 | AS39: =IFERROR(AQ39/AP39,"-") -> 0 | AT39: =AX39+BB39+BF39 -> 2756.3 | AU39: =AY39+BC39+BG39 -> 0 | AV39: =IFERROR(AU39-AT39,"-") -> -2756.3 | AW39: =IFERROR(AU39/AT39,"-") -> 0 | AX39: ='2. ГПП-ОГХК'!BS21+'2. ГПП-ОГХК'!BS25+'2. ГПП-ОГХК'!BS27+'2. ГПП-ОГХК'!BS29+'2. ГПП-ОГХК'!BS31+'2. ГПП-ОГХК'!BS33+'2. ГПП-ОГХК'!BS35 -> 877 | AY39: ='2. ГПП-ОГХК'!BU21+'2. ГПП-ОГХК'!BU25+'2. ГПП-ОГХК'!BU27+'2. ГПП-ОГХК'!BU29+'2. ГПП-ОГХК'!BU31+'2. ГПП-ОГХК'!BU33+'2. ГПП-ОГХК'!BU35 -> 0 | AZ39: =IFERROR(AY39-AX39,"-") -> -877 | BA39: =IFERROR(AY39/AX39,"-") -> 0 | BB39: ='2. ГПП-ОГХК'!BY21+'2. ГПП-ОГХК'!BY25+'2. ГПП-ОГХК'!BY27+'2. ГПП-ОГХК'!BY29+'2. ГПП-ОГХК'!BY31+'2. ГПП-ОГХК'!BY33+'2. ГПП-ОГХК'!BY35 -> 877.6 | BC39: ='2. ГПП-ОГХК'!CA21+'2. ГПП-ОГХК'!CA25+'2. ГПП-ОГХК'!CA27+'2. ГПП-ОГХК'!CA29+'2. ГПП-ОГХК'!CA31+'2. ГПП-ОГХК'!CA33+'2. ГПП-ОГХК'!CA35 -> 0 | BD39: =IFERROR(BC39-BB39,"-") -> -877.6 | BE39: =IFERROR(BC39/BB39,"-") -> 0 | BF39: ='2. ГПП-ОГХК'!CE21+'2. ГПП-ОГХК'!CE25+'2. ГПП-ОГХК'!CE27+'2. ГПП-ОГХК'!CE29+'2. ГПП-ОГХК'!CE31+'2. ГПП-ОГХК'!CE33+'2. ГПП-ОГХК'!CE35 -> 1001.7 | BG39: ='2. ГПП-ОГХК'!CG21+'2. ГПП-ОГХК'!CG25+'2. ГПП-ОГХК'!CG27+'2. ГПП-ОГХК'!CG29+'2. ГПП-ОГХК'!CG31+'2. ГПП-ОГХК'!CG33+'2. ГПП-ОГХК'!CG35 -> 0 | BH39: =IFERROR(BG39-BF39,"-") -> -1001.7 | BI39: =IFERROR(BG39/BF39,"-") -> 0 | BJ39: =BN39+BR39+BV39 -> 3216.5 | BK39: =BO39+BS39+BW39 -> 0 | BL39: =IFERROR(BK39-BJ39,"-") -> -3216.5 | BM39: =IFERROR(BK39/BJ39,"-") -> 0 | BN39: ='2. ГПП-ОГХК'!CQ21+'2. ГПП-ОГХК'!CQ25+'2. ГПП-ОГХК'!CQ27+'2. ГПП-ОГХК'!CQ29+'2. ГПП-ОГХК'!CQ31+'2. ГПП-ОГХК'!CQ33+'2. ГПП-ОГХК'!CQ35 -> 1084.8 | BO39: ='2. ГПП-ОГХК'!CS21+'2. ГПП-ОГХК'!CS25+'2. ГПП-ОГХК'!CS27+'2. ГПП-ОГХК'!CS29+'2. ГПП-ОГХК'!CS31+'2. ГПП-ОГХК'!CS33+'2. ГПП-ОГХК'!CS35 -> 0 | BP39: =IFERROR(BO39-BN39,"-") -> -1084.8 | BQ39: =IFERROR(BO39/BN39,"-") -> 0 | BR39: ='2. ГПП-ОГХК'!CW21+'2. ГПП-ОГХК'!CW25+'2. ГПП-ОГХК'!CW27+'2. ГПП-ОГХК'!CW29+'2. ГПП-ОГХК'!CW31+'2. ГПП-ОГХК'!CW33+'2. ГПП-ОГХК'!CW35 -> 1048.7 | BS39: ='2. ГПП-ОГХК'!CY21+'2. ГПП-ОГХК'!CY25+'2. ГПП-ОГХК'!CY27+'2. ГПП-ОГХК'!CY29+'2. ГПП-ОГХК'!CY31+'2. ГПП-ОГХК'!CY33+'2. ГПП-ОГХК'!CY35 -> 0 | BT39: =IFERROR(BS39-BR39,"-") -> -1048.7 | BU39: =IFERROR(BS39/BR39,"-") -> 0 | BV39: ='2. ГПП-ОГХК'!DC21+'2. ГПП-ОГХК'!DC25+'2. ГПП-ОГХК'!DC27+'2. ГПП-ОГХК'!DC29+'2. ГПП-ОГХК'!DC31+'2. ГПП-ОГХК'!DC33+'2. ГПП-ОГХК'!DC35 -> 1083 | BW39: ='2. ГПП-ОГХК'!DE21+'2. ГПП-ОГХК'!DE25+'2. ГПП-ОГХК'!DE27+'2. ГПП-ОГХК'!DE29+'2. ГПП-ОГХК'!DE31+'2. ГПП-ОГХК'!DE33+'2. ГПП-ОГХК'!DE35 -> 0 | BX39: =IFERROR(BW39-BV39,"-") -> -1083 | BY39: =IFERROR(BW39/BV39,"-") -> 0
C40: в т.ч. Газпром добыча Оренбург | G40: 2_100332038 | I40: млн куб.м. | J40: =N40+AD40+AT40+BJ40 -> 8866 | K40: =O40+AE40+AU40+BK40 -> 0 | L40: =IFERROR(K40-J40,"-") -> -8866 | M40: =IFERROR(K40/J40,"-") -> 0 | N40: =R40+V40+Z40 -> 2327.5 | O40: =S40+W40+AA40 -> 0 | P40: =IFERROR(O40-N40,"-") -> -2327.5 | Q40: =IFERROR(O40/N40,"-") -> 0 | R40: ='2. ГПП-ОГХК'!W21 -> 802.3 | S40: ='2. ГПП-ОГХК'!Y21 -> 0 | T40: =IFERROR(S40-R40,"-") -> -802.3 | U40: =IFERROR(S40/R40,"-") -> 0 | V40: ='2. ГПП-ОГХК'!AC21 -> 724.5 | W40: ='2. ГПП-ОГХК'!AE21 -> 0 | X40: =IFERROR(W40-V40,"-") -> -724.5 | Y40: =IFERROR(W40/V40,"-") -> 0 | Z40: ='2. ГПП-ОГХК'!AI21 -> 800.7 | AA40: ='2. ГПП-ОГХК'!AK21 -> 0 | AB40: =IFERROR(AA40-Z40,"-") -> -800.7 | AC40: =IFERROR(AA40/Z40,"-") -> 0 | AD40: =AH40+AL40+AP40 -> 2042.9 | AE40: =AI40+AM40+AQ40 -> 0 | AF40: =IFERROR(AE40-AD40,"-") -> -2042.9 | AG40: =IFERROR(AE40/AD40,"-") -> 0 | AH40: ='2. ГПП-ОГХК'!AU21 -> 707.5 | AI40: ='2. ГПП-ОГХК'!AW21 -> 0 | AJ40: =IFERROR(AI40-AH40,"-") -> -707.5 | AK40: =IFERROR(AI40/AH40,"-") -> 0 | AL40: ='2. ГПП-ОГХК'!BA21 -> 683.1 | AM40: ='2. ГПП-ОГХК'!BC21 -> 0 | AN40: =IFERROR(AM40-AL40,"-") -> -683.1 | AO40: =IFERROR(AM40/AL40,"-") -> 0 | AP40: ='2. ГПП-ОГХК'!BG21 -> 652.3 | AQ40: ='2. ГПП-ОГХК'!BI21 -> 0 | AR40: =IFERROR(AQ40-AP40,"-") -> -652.3 | AS40: =IFERROR(AQ40/AP40,"-") -> 0 | AT40: =AX40+BB40+BF40 -> 2139.4 | AU40: =AY40+BC40+BG40 -> 0 | AV40: =IFERROR(AU40-AT40,"-") -> -2139.4 | AW40: =IFERROR(AU40/AT40,"-") -> 0 | AX40: ='2. ГПП-ОГХК'!BS21 -> 699 | AY40: ='2. ГПП-ОГХК'!BU21 -> 0 | AZ40: =IFERROR(AY40-AX40,"-") -> -699 | BA40: =IFERROR(AY40/AX40,"-") -> 0 | BB40: ='2. ГПП-ОГХК'!BY21 -> 699.6 | BC40: ='2. ГПП-ОГХК'!CA21 -> 0 | BD40: =IFERROR(BC40-BB40,"-") -> -699.6 | BE40: =IFERROR(BC40/BB40,"-") -> 0 | BF40: ='2. ГПП-ОГХК'!CE21 -> 740.8 | BG40: ='2. ГПП-ОГХК'!CG21 -> 0 | BH40: =IFERROR(BG40-BF40,"-") -> -740.8 | BI40: =IFERROR(BG40/BF40,"-") -> 0 | BJ40: =BN40+BR40+BV40 -> 2356.2 | BK40: =BO40+BS40+BW40 -> 0 | BL40: =IFERROR(BK40-BJ40,"-") -> -2356.2 | BM40: =IFERROR(BK40/BJ40,"-") -> 0 | BN40: ='2. ГПП-ОГХК'!CQ21 -> 794.9 | BO40: ='2. ГПП-ОГХК'!CS21 -> 0 | BP40: =IFERROR(BO40-BN40,"-") -> -794.9 | BQ40: =IFERROR(BO40/BN40,"-") -> 0 | BR40: ='2. ГПП-ОГХК'!CW21 -> 768.2 | BS40: ='2. ГПП-ОГХК'!CY21 -> 0 | BT40: =IFERROR(BS40-BR40,"-") -> -768.2 | BU40: =IFERROR(BS40/BR40,"-") -> 0 | BV40: ='2. ГПП-ОГХК'!DC21 -> 793.1 | BW40: ='2. ГПП-ОГХК'!DE21 -> 0 | BX40: =IFERROR(BW40-BV40,"-") -> -793.1 | BY40: =IFERROR(BW40/BV40,"-") -> 0
C41: Газпром нефть | G41: 2_100332040 | I41: млн куб.м. | J41: =N41+AD41+AT41+BJ41 -> 2634.9 | K41: =O41+AE41+AU41+BK41 -> 0 | L41: =IFERROR(K41-J41,"-") -> -2634.9 | M41: =IFERROR(K41/J41,"-") -> 0 | N41: =R41+V41+Z41 -> 769.2 | O41: =S41+W41+AA41 -> 0 | P41: =IFERROR(O41-N41,"-") -> -769.2 | Q41: =IFERROR(O41/N41,"-") -> 0 | R41: ='2. ГПП-ОГХК'!W25 -> 271.6 | S41: ='2. ГПП-ОГХК'!Y25 -> 0 | T41: =IFERROR(S41-R41,"-") -> -271.6 | U41: =IFERROR(S41/R41,"-") -> 0 | V41: ='2. ГПП-ОГХК'!AC25 -> 245.3 | W41: ='2. ГПП-ОГХК'!AE25 -> 0 | X41: =IFERROR(W41-V41,"-") -> -245.3 | Y41: =IFERROR(W41/V41,"-") -> 0 | Z41: ='2. ГПП-ОГХК'!AI25 -> 252.3 | AA41: ='2. ГПП-ОГХК'!AK25 -> 0 | AB41: =IFERROR(AA41-Z41,"-") -> -252.3 | AC41: =IFERROR(AA41/Z41,"-") -> 0 | AD41: =AH41+AL41+AP41 -> 489.6 | AE41: =AI41+AM41+AQ41 -> 0 | AF41: =IFERROR(AE41-AD41,"-") -> -489.6 | AG41: =IFERROR(AE41/AD41,"-") -> 0 | AH41: ='2. ГПП-ОГХК'!AU25 -> 173.4 | AI41: ='2. ГПП-ОГХК'!AW25 -> 0 | AJ41: =IFERROR(AI41-AH41,"-") -> -173.4 | AK41: =IFERROR(AI41/AH41,"-") -> 0 | AL41: ='2. ГПП-ОГХК'!BA25 -> 160.7 | AM41: ='2. ГПП-ОГХК'!BC25 -> 0 | AN41: =IFERROR(AM41-AL41,"-") -> -160.7 | AO41: =IFERROR(AM41/AL41,"-") -> 0 | AP41: ='2. ГПП-ОГХК'!BG25 -> 155.5 | AQ41: ='2. ГПП-ОГХК'!BI25 -> 0 | AR41: =IFERROR(AQ41-AP41,"-") -> -155.5 | AS41: =IFERROR(AQ41/AP41,"-") -> 0 | AT41: =AX41+BB41+BF41 -> 565.7 | AU41: =AY41+BC41+BG41 -> 0 | AV41: =IFERROR(AU41-AT41,"-") -> -565.7 | AW41: =IFERROR(AU41/AT41,"-") -> 0 | AX41: ='2. ГПП-ОГХК'!BS25 -> 160.7 | AY41: ='2. ГПП-ОГХК'!BU25 -> 0 | AZ41: =IFERROR(AY41-AX41,"-") -> -160.7 | BA41: =IFERROR(AY41/AX41,"-") -> 0 | BB41: ='2. ГПП-ОГХК'!BY25 -> 160.7 | BC41: ='2. ГПП-ОГХК'!CA25 -> 0 | BD41: =IFERROR(BC41-BB41,"-") -> -160.7 | BE41: =IFERROR(BC41/BB41,"-") -> 0 | BF41: ='2. ГПП-ОГХК'!CE25 -> 244.3 | BG41: ='2. ГПП-ОГХК'!CG25 -> 0 | BH41: =IFERROR(BG41-BF41,"-") -> -244.3 | BI41: =IFERROR(BG41/BF41,"-") -> 0 | BJ41: =BN41+BR41+BV41 -> 810.4 | BK41: =BO41+BS41+BW41 -> 0 | BL41: =IFERROR(BK41-BJ41,"-") -> -810.4 | BM41: =IFERROR(BK41/BJ41,"-") -> 0 | BN41: ='2. ГПП-ОГХК'!CQ25 -> 273 | BO41: ='2. ГПП-ОГХК'!CS25 -> 0 | BP41: =IFERROR(BO41-BN41,"-") -> -273 | BQ41: =IFERROR(BO41/BN41,"-") -> 0 | BR41: ='2. ГПП-ОГХК'!CW25 -> 264.2 | BS41: ='2. ГПП-ОГХК'!CY25 -> 0 | BT41: =IFERROR(BS41-BR41,"-") -> -264.2 | BU41: =IFERROR(BS41/BR41,"-") -> 0 | BV41: ='2. ГПП-ОГХК'!DC25 -> 273.2 | BW41: ='2. ГПП-ОГХК'!DE25 -> 0 | BX41: =IFERROR(BW41-BV41,"-") -> -273.2 | BY41: =IFERROR(BW41/BV41,"-") -> 0
C42: УНГП | G42: 2_100332042 | I42: млн куб.м. | J42: =N42+AD42+AT42+BJ42 -> 177.4 | K42: =O42+AE42+AU42+BK42 -> 0 | L42: =IFERROR(K42-J42,"-") -> -177.4 | M42: =IFERROR(K42/J42,"-") -> 0 | N42: =R42+V42+Z42 -> 44.3 | O42: =S42+W42+AA42 -> 0 | P42: =IFERROR(O42-N42,"-") -> -44.3 | Q42: =IFERROR(O42/N42,"-") -> 0 | R42: ='2. ГПП-ОГХК'!W27 -> 15.4 | S42: ='2. ГПП-ОГХК'!Y27 -> 0 | T42: =IFERROR(S42-R42,"-") -> -15.4 | U42: =IFERROR(S42/R42,"-") -> 0 | V42: ='2. ГПП-ОГХК'!AC27 -> 13.8 | W42: ='2. ГПП-ОГХК'!AE27 -> 0 | X42: =IFERROR(W42-V42,"-") -> -13.8 | Y42: =IFERROR(W42/V42,"-") -> 0 | Z42: ='2. ГПП-ОГХК'!AI27 -> 15.1 | AA42: ='2. ГПП-ОГХК'!AK27 -> 0 | AB42: =IFERROR(AA42-Z42,"-") -> -15.1 | AC42: =IFERROR(AA42/Z42,"-") -> 0 | AD42: =AH42+AL42+AP42 -> 42.4 | AE42: =AI42+AM42+AQ42 -> 0 | AF42: =IFERROR(AE42-AD42,"-") -> -42.4 | AG42: =IFERROR(AE42/AD42,"-") -> 0 | AH42: ='2. ГПП-ОГХК'!AU27 -> 12.1 | AI42: ='2. ГПП-ОГХК'!AW27 -> 0 | AJ42: =IFERROR(AI42-AH42,"-") -> -12.1 | AK42: =IFERROR(AI42/AH42,"-") -> 0 | AL42: ='2. ГПП-ОГХК'!BA27 -> 15.5 | AM42: ='2. ГПП-ОГХК'!BC27 -> 0 | AN42: =IFERROR(AM42-AL42,"-") -> -15.5 | AO42: =IFERROR(AM42/AL42,"-") -> 0 | AP42: ='2. ГПП-ОГХК'!BG27 -> 14.8 | AQ42: ='2. ГПП-ОГХК'!BI27 -> 0 | AR42: =IFERROR(AQ42-AP42,"-") -> -14.8 | AS42: =IFERROR(AQ42/AP42,"-") -> 0 | AT42: =AX42+BB42+BF42 -> 45.9 | AU42: =AY42+BC42+BG42 -> 0 | AV42: =IFERROR(AU42-AT42,"-") -> -45.9 | AW42: =IFERROR(AU42/AT42,"-") -> 0 | AX42: ='2. ГПП-ОГХК'!BS27 -> 15.5 | AY42: ='2. ГПП-ОГХК'!BU27 -> 0 | AZ42: =IFERROR(AY42-AX42,"-") -> -15.5 | BA42: =IFERROR(AY42/AX42,"-") -> 0 | BB42: ='2. ГПП-ОГХК'!BY27 -> 15.5 | BC42: ='2. ГПП-ОГХК'!CA27 -> 0 | BD42: =IFERROR(BC42-BB42,"-") -> -15.5 | BE42: =IFERROR(BC42/BB42,"-") -> 0 | BF42: ='2. ГПП-ОГХК'!CE27 -> 14.9 | BG42: ='2. ГПП-ОГХК'!CG27 -> 0 | BH42: =IFERROR(BG42-BF42,"-") -> -14.9 | BI42: =IFERROR(BG42/BF42,"-") -> 0 | BJ42: =BN42+BR42+BV42 -> 44.8 | BK42: =BO42+BS42+BW42 -> 0 | BL42: =IFERROR(BK42-BJ42,"-") -> -44.8 | BM42: =IFERROR(BK42/BJ42,"-") -> 0 | BN42: ='2. ГПП-ОГХК'!CQ27 -> 15.2 | BO42: ='2. ГПП-ОГХК'!CS27 -> 0 | BP42: =IFERROR(BO42-BN42,"-") -> -15.2 | BQ42: =IFERROR(BO42/BN42,"-") -> 0 | BR42: ='2. ГПП-ОГХК'!CW27 -> 14.6 | BS42: ='2. ГПП-ОГХК'!CY27 -> 0 | BT42: =IFERROR(BS42-BR42,"-") -> -14.6 | BU42: =IFERROR(BS42/BR42,"-") -> 0 | BV42: ='2. ГПП-ОГХК'!DC27 -> 15 | BW42: ='2. ГПП-ОГХК'!DE27 -> 0 | BX42: =IFERROR(BW42-BV42,"-") -> -15 | BY42: =IFERROR(BW42/BV42,"-") -> 0
C43: Сервиснефтегаз | G43: 2_100332044 | I43: млн куб.м. | J43: =N43+AD43+AT43+BJ43 -> 8.1 | K43: =O43+AE43+AU43+BK43 -> 0 | L43: =IFERROR(K43-J43,"-") -> -8.1 | M43: =IFERROR(K43/J43,"-") -> 0 | N43: =R43+V43+Z43 -> 2 | O43: =S43+W43+AA43 -> 0 | P43: =IFERROR(O43-N43,"-") -> -2 | Q43: =IFERROR(O43/N43,"-") -> 0 | R43: ='2. ГПП-ОГХК'!W29 -> 0.7 | S43: ='2. ГПП-ОГХК'!Y29 -> 0 | T43: =IFERROR(S43-R43,"-") -> -0.7 | U43: =IFERROR(S43/R43,"-") -> 0 | V43: ='2. ГПП-ОГХК'!AC29 -> 0.6 | W43: ='2. ГПП-ОГХК'!AE29 -> 0 | X43: =IFERROR(W43-V43,"-") -> -0.6 | Y43: =IFERROR(W43/V43,"-") -> 0 | Z43: ='2. ГПП-ОГХК'!AI29 -> 0.7 | AA43: ='2. ГПП-ОГХК'!AK29 -> 0 | AB43: =IFERROR(AA43-Z43,"-") -> -0.7 | AC43: =IFERROR(AA43/Z43,"-") -> 0 | AD43: =AH43+AL43+AP43 -> 2 | AE43: =AI43+AM43+AQ43 -> 0 | AF43: =IFERROR(AE43-AD43,"-") -> -2 | AG43: =IFERROR(AE43/AD43,"-") -> 0 | AH43: ='2. ГПП-ОГХК'!AU29 -> 0.6 | AI43: ='2. ГПП-ОГХК'!AW29 -> 0 | AJ43: =IFERROR(AI43-AH43,"-") -> -0.6 | AK43: =IFERROR(AI43/AH43,"-") -> 0 | AL43: ='2. ГПП-ОГХК'!BA29 -> 0.7 | AM43: ='2. ГПП-ОГХК'!BC29 -> 0 | AN43: =IFERROR(AM43-AL43,"-") -> -0.7 | AO43: =IFERROR(AM43/AL43,"-") -> 0 | AP43: ='2. ГПП-ОГХК'!BG29 -> 0.7 | AQ43: ='2. ГПП-ОГХК'!BI29 -> 0 | AR43: =IFERROR(AQ43-AP43,"-") -> -0.7 | AS43: =IFERROR(AQ43/AP43,"-") -> 0 | AT43: =AX43+BB43+BF43 -> 2 | AU43: =AY43+BC43+BG43 -> 0 | AV43: =IFERROR(AU43-AT43,"-") -> -2 | AW43: =IFERROR(AU43/AT43,"-") -> 0 | AX43: ='2. ГПП-ОГХК'!BS29 -> 0.7 | AY43: ='2. ГПП-ОГХК'!BU29 -> 0 | AZ43: =IFERROR(AY43-AX43,"-") -> -0.7 | BA43: =IFERROR(AY43/AX43,"-") -> 0 | BB43: ='2. ГПП-ОГХК'!BY29 -> 0.7 | BC43: ='2. ГПП-ОГХК'!CA29 -> 0 | BD43: =IFERROR(BC43-BB43,"-") -> -0.7 | BE43: =IFERROR(BC43/BB43,"-") -> 0 | BF43: ='2. ГПП-ОГХК'!CE29 -> 0.6 | BG43: ='2. ГПП-ОГХК'!CG29 -> 0 | BH43: =IFERROR(BG43-BF43,"-") -> -0.6 | BI43: =IFERROR(BG43/BF43,"-") -> 0 | BJ43: =BN43+BR43+BV43 -> 2.1 | BK43: =BO43+BS43+BW43 -> 0 | BL43: =IFERROR(BK43-BJ43,"-") -> -2.1 | BM43: =IFERROR(BK43/BJ43,"-") -> 0 | BN43: ='2. ГПП-ОГХК'!CQ29 -> 0.7 | BO43: ='2. ГПП-ОГХК'!CS29 -> 0 | BP43: =IFERROR(BO43-BN43,"-") -> -0.7 | BQ43: =IFERROR(BO43/BN43,"-") -> 0 | BR43: ='2. ГПП-ОГХК'!CW29 -> 0.7 | BS43: ='2. ГПП-ОГХК'!CY29 -> 0 | BT43: =IFERROR(BS43-BR43,"-") -> -0.7 | BU43: =IFERROR(BS43/BR43,"-") -> 0 | BV43: ='2. ГПП-ОГХК'!DC29 -> 0.7 | BW43: ='2. ГПП-ОГХК'!DE29 -> 0 | BX43: =IFERROR(BW43-BV43,"-") -> -0.7 | BY43: =IFERROR(BW43/BV43,"-") -> 0
C44: Карбон | G44: 2_100332916 | I44: млн куб.м. | J44: =N44+AD44+AT44+BJ44 -> 12.7 | K44: =O44+AE44+AU44+BK44 -> 0 | L44: =IFERROR(K44-J44,"-") -> -12.7 | M44: =IFERROR(K44/J44,"-") -> 0 | N44: =R44+V44+Z44 -> 3.3 | O44: =S44+W44+AA44 -> 0 | P44: =IFERROR(O44-N44,"-") -> -3.3 | Q44: =IFERROR(O44/N44,"-") -> 0 | R44: ='2. ГПП-ОГХК'!W31 -> 1.1 | S44: ='2. ГПП-ОГХК'!Y31 -> 0 | T44: =IFERROR(S44-R44,"-") -> -1.1 | U44: =IFERROR(S44/R44,"-") -> 0 | V44: ='2. ГПП-ОГХК'!AC31 -> 1.1 | W44: ='2. ГПП-ОГХК'!AE31 -> 0 | X44: =IFERROR(W44-V44,"-") -> -1.1 | Y44: =IFERROR(W44/V44,"-") -> 0 | Z44: ='2. ГПП-ОГХК'!AI31 -> 1.1 | AA44: ='2. ГПП-ОГХК'!AK31 -> 0 | AB44: =IFERROR(AA44-Z44,"-") -> -1.1 | AC44: =IFERROR(AA44/Z44,"-") -> 0 | AD44: =AH44+AL44+AP44 -> 3.1 | AE44: =AI44+AM44+AQ44 -> 0 | AF44: =IFERROR(AE44-AD44,"-") -> -3.1 | AG44: =IFERROR(AE44/AD44,"-") -> 0 | AH44: ='2. ГПП-ОГХК'!AU31 -> 0.9 | AI44: ='2. ГПП-ОГХК'!AW31 -> 0 | AJ44: =IFERROR(AI44-AH44,"-") -> -0.9 | AK44: =IFERROR(AI44/AH44,"-") -> 0 | AL44: ='2. ГПП-ОГХК'!BA31 -> 1.1 | AM44: ='2. ГПП-ОГХК'!BC31 -> 0 | AN44: =IFERROR(AM44-AL44,"-") -> -1.1 | AO44: =IFERROR(AM44/AL44,"-") -> 0 | AP44: ='2. ГПП-ОГХК'!BG31 -> 1.1 | AQ44: ='2. ГПП-ОГХК'!BI31 -> 0 | AR44: =IFERROR(AQ44-AP44,"-") -> -1.1 | AS44: =IFERROR(AQ44/AP44,"-") -> 0 | AT44: =AX44+BB44+BF44 -> 3.3 | AU44: =AY44+BC44+BG44 -> 0 | AV44: =IFERROR(AU44-AT44,"-") -> -3.3 | AW44: =IFERROR(AU44/AT44,"-") -> 0 | AX44: ='2. ГПП-ОГХК'!BS31 -> 1.1 | AY44: ='2. ГПП-ОГХК'!BU31 -> 0 | AZ44: =IFERROR(AY44-AX44,"-") -> -1.1 | BA44: =IFERROR(AY44/AX44,"-") -> 0 | BB44: ='2. ГПП-ОГХК'!BY31 -> 1.1 | BC44: ='2. ГПП-ОГХК'!CA31 -> 0 | BD44: =IFERROR(BC44-BB44,"-") -> -1.1 | BE44: =IFERROR(BC44/BB44,"-") -> 0 | BF44: ='2. ГПП-ОГХК'!CE31 -> 1.1 | BG44: ='2. ГПП-ОГХК'!CG31 -> 0 | BH44: =IFERROR(BG44-BF44,"-") -> -1.1 | BI44: =IFERROR(BG44/BF44,"-") -> 0 | BJ44: =BN44+BR44+BV44 -> 3 | BK44: =BO44+BS44+BW44 -> 0 | BL44: =IFERROR(BK44-BJ44,"-") -> -3 | BM44: =IFERROR(BK44/BJ44,"-") -> 0 | BN44: ='2. ГПП-ОГХК'!CQ31 -> 1 | BO44: ='2. ГПП-ОГХК'!CS31 -> 0 | BP44: =IFERROR(BO44-BN44,"-") -> -1 | BQ44: =IFERROR(BO44/BN44,"-") -> 0 | BR44: ='2. ГПП-ОГХК'!CW31 -> 1 | BS44: ='2. ГПП-ОГХК'!CY31 -> 0 | BT44: =IFERROR(BS44-BR44,"-") -> -1 | BU44: =IFERROR(BS44/BR44,"-") -> 0 | BV44: ='2. ГПП-ОГХК'!DC31 -> 1 | BW44: ='2. ГПП-ОГХК'!DE31 -> 0 | BX44: =IFERROR(BW44-BV44,"-") -> -1 | BY44: =IFERROR(BW44/BV44,"-") -> 0
C45: Газпромнефть-Заполярье | G45: 2_100332944 | I45: млн куб.м. | J45: =N45+AD45+AT45+BJ45 -> 0 | K45: =O45+AE45+AU45+BK45 -> 0 | L45: =IFERROR(K45-J45,"-") -> 0 | M45: =IFERROR(K45/J45,"-") -> - | N45: =R45+V45+Z45 -> 0 | O45: =S45+W45+AA45 -> 0 | P45: =IFERROR(O45-N45,"-") -> 0 | Q45: =IFERROR(O45/N45,"-") -> - | R45: ='2. ГПП-ОГХК'!W33 -> 0 | S45: ='2. ГПП-ОГХК'!Y33 -> 0 | T45: =IFERROR(S45-R45,"-") -> 0 | U45: =IFERROR(S45/R45,"-") -> - | V45: ='2. ГПП-ОГХК'!AC33 -> 0 | W45: ='2. ГПП-ОГХК'!AE33 -> 0 | X45: =IFERROR(W45-V45,"-") -> 0 | Y45: =IFERROR(W45/V45,"-") -> - | Z45: ='2. ГПП-ОГХК'!AI33 -> 0 | AA45: ='2. ГПП-ОГХК'!AK33 -> 0 | AB45: =IFERROR(AA45-Z45,"-") -> 0 | AC45: =IFERROR(AA45/Z45,"-") -> - | AD45: =AH45+AL45+AP45 -> 0 | AE45: =AI45+AM45+AQ45 -> 0 | AF45: =IFERROR(AE45-AD45,"-") -> 0 | AG45: =IFERROR(AE45/AD45,"-") -> - | AH45: ='2. ГПП-ОГХК'!AU33 -> 0 | AI45: ='2. ГПП-ОГХК'!AW33 -> 0 | AJ45: =IFERROR(AI45-AH45,"-") -> 0 | AK45: =IFERROR(AI45/AH45,"-") -> - | AL45: ='2. ГПП-ОГХК'!BA33 -> 0 | AM45: ='2. ГПП-ОГХК'!BC33 -> 0 | AN45: =IFERROR(AM45-AL45,"-") -> 0 | AO45: =IFERROR(AM45/AL45,"-") -> - | AP45: ='2. ГПП-ОГХК'!BG33 -> 0 | AQ45: ='2. ГПП-ОГХК'!BI33 -> 0 | AR45: =IFERROR(AQ45-AP45,"-") -> 0 | AS45: =IFERROR(AQ45/AP45,"-") -> - | AT45: =AX45+BB45+BF45 -> 0 | AU45: =AY45+BC45+BG45 -> 0 | AV45: =IFERROR(AU45-AT45,"-") -> 0 | AW45: =IFERROR(AU45/AT45,"-") -> - | AX45: ='2. ГПП-ОГХК'!BS33 -> 0 | AY45: ='2. ГПП-ОГХК'!BU33 -> 0 | AZ45: =IFERROR(AY45-AX45,"-") -> 0 | BA45: =IFERROR(AY45/AX45,"-") -> - | BB45: ='2. ГПП-ОГХК'!BY33 -> 0 | BC45: ='2. ГПП-ОГХК'!CA33 -> 0 | BD45: =IFERROR(BC45-BB45,"-") -> 0 | BE45: =IFERROR(BC45/BB45,"-") -> - | BF45: ='2. ГПП-ОГХК'!CE33 -> 0 | BG45: ='2. ГПП-ОГХК'!CG33 -> 0 | BH45: =IFERROR(BG45-BF45,"-") -> 0 | BI45: =IFERROR(BG45/BF45,"-") -> - | BJ45: =BN45+BR45+BV45 -> 0 | BK45: =BO45+BS45+BW45 -> 0 | BL45: =IFERROR(BK45-BJ45,"-") -> 0 | BM45: =IFERROR(BK45/BJ45,"-") -> - | BN45: ='2. ГПП-ОГХК'!CQ33 -> 0 | BO45: ='2. ГПП-ОГХК'!CS33 -> 0 | BP45: =IFERROR(BO45-BN45,"-") -> 0 | BQ45: =IFERROR(BO45/BN45,"-") -> - | BR45: ='2. ГПП-ОГХК'!CW33 -> 0 | BS45: ='2. ГПП-ОГХК'!CY33 -> 0 | BT45: =IFERROR(BS45-BR45,"-") -> 0 | BU45: =IFERROR(BS45/BR45,"-") -> - | BV45: ='2. ГПП-ОГХК'!DC33 -> 0 | BW45: ='2. ГПП-ОГХК'!DE33 -> 0 | BX45: =IFERROR(BW45-BV45,"-") -> 0 | BY45: =IFERROR(BW45/BV45,"-") -> -
C46: Сладковско-Заречное | G46: 2_100335129 | I46: млн куб.м. | J46: =N46+AD46+AT46+BJ46 -> 0 | K46: =O46+AE46+AU46+BK46 -> 0 | L46: =IFERROR(K46-J46,"-") -> 0 | M46: =IFERROR(K46/J46,"-") -> - | N46: =R46+V46+Z46 -> 0 | O46: =S46+W46+AA46 -> 0 | P46: =IFERROR(O46-N46,"-") -> 0 | Q46: =IFERROR(O46/N46,"-") -> - | R46: ='2. ГПП-ОГХК'!W35 -> 0 | S46: ='2. ГПП-ОГХК'!Y35 -> 0 | T46: =IFERROR(S46-R46,"-") -> 0 | U46: =IFERROR(S46/R46,"-") -> - | V46: ='2. ГПП-ОГХК'!AC35 -> 0 | W46: ='2. ГПП-ОГХК'!AE35 -> 0 | X46: =IFERROR(W46-V46,"-") -> 0 | Y46: =IFERROR(W46/V46,"-") -> - | Z46: ='2. ГПП-ОГХК'!AI35 -> 0 | AA46: ='2. ГПП-ОГХК'!AK35 -> 0 | AB46: =IFERROR(AA46-Z46,"-") -> 0 | AC46: =IFERROR(AA46/Z46,"-") -> - | AD46: =AH46+AL46+AP46 -> 0 | AE46: =AI46+AM46+AQ46 -> 0 | AF46: =IFERROR(AE46-AD46,"-") -> 0 | AG46: =IFERROR(AE46/AD46,"-") -> - | AH46: ='2. ГПП-ОГХК'!AU35 -> 0 | AI46: ='2. ГПП-ОГХК'!AW35 -> 0 | AJ46: =IFERROR(AI46-AH46,"-") -> 0 | AK46: =IFERROR(AI46/AH46,"-") -> - | AL46: ='2. ГПП-ОГХК'!BA35 -> 0 | AM46: ='2. ГПП-ОГХК'!BC35 -> 0 | AN46: =IFERROR(AM46-AL46,"-") -> 0 | AO46: =IFERROR(AM46/AL46,"-") -> - | AP46: ='2. ГПП-ОГХК'!BG35 -> 0 | AQ46: ='2. ГПП-ОГХК'!BI35 -> 0 | AR46: =IFERROR(AQ46-AP46,"-") -> 0 | AS46: =IFERROR(AQ46/AP46,"-") -> - | AT46: =AX46+BB46+BF46 -> 0 | AU46: =AY46+BC46+BG46 -> 0 | AV46: =IFERROR(AU46-AT46,"-") -> 0 | AW46: =IFERROR(AU46/AT46,"-") -> - | AX46: ='2. ГПП-ОГХК'!BS35 -> 0 | AY46: ='2. ГПП-ОГХК'!BU35 -> 0 | AZ46: =IFERROR(AY46-AX46,"-") -> 0 | BA46: =IFERROR(AY46/AX46,"-") -> - | BB46: ='2. ГПП-ОГХК'!BY35 -> 0 | BC46: ='2. ГПП-ОГХК'!CA35 -> 0 | BD46: =IFERROR(BC46-BB46,"-") -> 0 | BE46: =IFERROR(BC46/BB46,"-") -> - | BF46: ='2. ГПП-ОГХК'!CE35 -> 0 | BG46: ='2. ГПП-ОГХК'!CG35 -> 0 | BH46: =IFERROR(BG46-BF46,"-") -> 0 | BI46: =IFERROR(BG46/BF46,"-") -> - | BJ46: =BN46+BR46+BV46 -> 0 | BK46: =BO46+BS46+BW46 -> 0 | BL46: =IFERROR(BK46-BJ46,"-") -> 0 | BM46: =IFERROR(BK46/BJ46,"-") -> - | BN46: ='2. ГПП-ОГХК'!CQ35 -> 0 | BO46: ='2. ГПП-ОГХК'!CS35 -> 0 | BP46: =IFERROR(BO46-BN46,"-") -> 0 | BQ46: =IFERROR(BO46/BN46,"-") -> - | BR46: ='2. ГПП-ОГХК'!CW35 -> 0 | BS46: ='2. ГПП-ОГХК'!CY35 -> 0 | BT46: =IFERROR(BS46-BR46,"-") -> 0 | BU46: =IFERROR(BS46/BR46,"-") -> - | BV46: ='2. ГПП-ОГХК'!DC35 -> 0 | BW46: ='2. ГПП-ОГХК'!DE35 -> 0 | BX46: =IFERROR(BW46-BV46,"-") -> 0 | BY46: =IFERROR(BW46/BV46,"-") -> -
C47: Газпром ГНП холдинг | G47: 3_100330552 | I47: млн куб.м. | J47: =N47+AD47+AT47+BJ47 -> 12 | K47: =O47+AE47+AU47+BK47 -> 0 | L47: =IFERROR(K47-J47,"-") -> -12 | M47: =IFERROR(K47/J47,"-") -> 0 | N47: =R47+V47+Z47 -> 3 | O47: =S47+W47+AA47 -> 0 | P47: =IFERROR(O47-N47,"-") -> -3 | Q47: =IFERROR(O47/N47,"-") -> 0 | R47: ='3. ГПП-СГПЗ'!W18 -> 1 | S47: ='3. ГПП-СГПЗ'!Y18 -> 0 | T47: =IFERROR(S47-R47,"-") -> -1 | U47: =IFERROR(S47/R47,"-") -> 0 | V47: ='3. ГПП-СГПЗ'!AC18 -> 1 | W47: ='3. ГПП-СГПЗ'!AE18 -> 0 | X47: =IFERROR(W47-V47,"-") -> -1 | Y47: =IFERROR(W47/V47,"-") -> 0 | Z47: ='3. ГПП-СГПЗ'!AI18 -> 1 | AA47: ='3. ГПП-СГПЗ'!AK18 -> 0 | AB47: =IFERROR(AA47-Z47,"-") -> -1 | AC47: =IFERROR(AA47/Z47,"-") -> 0 | AD47: =AH47+AL47+AP47 -> 3 | AE47: =AI47+AM47+AQ47 -> 0 | AF47: =IFERROR(AE47-AD47,"-") -> -3 | AG47: =IFERROR(AE47/AD47,"-") -> 0 | AH47: ='3. ГПП-СГПЗ'!AU18 -> 1 | AI47: ='3. ГПП-СГПЗ'!AW18 -> 0 | AJ47: =IFERROR(AI47-AH47,"-") -> -1 | AK47: =IFERROR(AI47/AH47,"-") -> 0 | AL47: ='3. ГПП-СГПЗ'!BA18 -> 1 | AM47: ='3. ГПП-СГПЗ'!BC18 -> 0 | AN47: =IFERROR(AM47-AL47,"-") -> -1 | AO47: =IFERROR(AM47/AL47,"-") -> 0 | AP47: ='3. ГПП-СГПЗ'!BG18 -> 1 | AQ47: ='3. ГПП-СГПЗ'!BI18 -> 0 | AR47: =IFERROR(AQ47-AP47,"-") -> -1 | AS47: =IFERROR(AQ47/AP47,"-") -> 0 | AT47: =AX47+BB47+BF47 -> 3 | AU47: =AY47+BC47+BG47 -> 0 | AV47: =IFERROR(AU47-AT47,"-") -> -3 | AW47: =IFERROR(AU47/AT47,"-") -> 0 | AX47: ='3. ГПП-СГПЗ'!BS18 -> 1 | AY47: ='3. ГПП-СГПЗ'!BU18 -> 0 | AZ47: =IFERROR(AY47-AX47,"-") -> -1 | BA47: =IFERROR(AY47/AX47,"-") -> 0 | BB47: ='3. ГПП-СГПЗ'!BY18 -> 1 | BC47: ='3. ГПП-СГПЗ'!CA18 -> 0 | BD47: =IFERROR(BC47-BB47,"-") -> -1 | BE47: =IFERROR(BC47/BB47,"-") -> 0 | BF47: ='3. ГПП-СГПЗ'!CE18 -> 1 | BG47: ='3. ГПП-СГПЗ'!CG18 -> 0 | BH47: =IFERROR(BG47-BF47,"-") -> -1 | BI47: =IFERROR(BG47/BF47,"-") -> 0 | BJ47: =BN47+BR47+BV47 -> 3 | BK47: =BO47+BS47+BW47 -> 0 | BL47: =IFERROR(BK47-BJ47,"-") -> -3 | BM47: =IFERROR(BK47/BJ47,"-") -> 0 | BN47: ='3. ГПП-СГПЗ'!CQ18 -> 1 | BO47: ='3. ГПП-СГПЗ'!CS18 -> 0 | BP47: =IFERROR(BO47-BN47,"-") -> -1 | BQ47: =IFERROR(BO47/BN47,"-") -> 0 | BR47: ='3. ГПП-СГПЗ'!CW18 -> 1 | BS47: ='3. ГПП-СГПЗ'!CY18 -> 0 | BT47: =IFERROR(BS47-BR47,"-") -> -1 | BU47: =IFERROR(BS47/BR47,"-") -> 0 | BV47: ='3. ГПП-СГПЗ'!DC18 -> 1 | BW47: ='3. ГПП-СГПЗ'!DE18 -> 0 | BX47: =IFERROR(BW47-BV47,"-") -> -1 | BY47: =IFERROR(BW47/BV47,"-") -> 0
C48: Сосногорский ГПЗ | G48: 3_100330552 | I48: млн куб.м. | J48: =N48+AD48+AT48+BJ48 -> 12 | K48: =O48+AE48+AU48+BK48 -> 0 | L48: =IFERROR(K48-J48,"-") -> -12 | M48: =IFERROR(K48/J48,"-") -> 0 | N48: =R48+V48+Z48 -> 3 | O48: =S48+W48+AA48 -> 0 | P48: =IFERROR(O48-N48,"-") -> -3 | Q48: =IFERROR(O48/N48,"-") -> 0 | R48: ='3. ГПП-СГПЗ'!W18 -> 1 | S48: ='3. ГПП-СГПЗ'!Y18 -> 0 | T48: =IFERROR(S48-R48,"-") -> -1 | U48: =IFERROR(S48/R48,"-") -> 0 | V48: ='3. ГПП-СГПЗ'!AC18 -> 1 | W48: ='3. ГПП-СГПЗ'!AE18 -> 0 | X48: =IFERROR(W48-V48,"-") -> -1 | Y48: =IFERROR(W48/V48,"-") -> 0 | Z48: ='3. ГПП-СГПЗ'!AI18 -> 1 | AA48: ='3. ГПП-СГПЗ'!AK18 -> 0 | AB48: =IFERROR(AA48-Z48,"-") -> -1 | AC48: =IFERROR(AA48/Z48,"-") -> 0 | AD48: =AH48+AL48+AP48 -> 3 | AE48: =AI48+AM48+AQ48 -> 0 | AF48: =IFERROR(AE48-AD48,"-") -> -3 | AG48: =IFERROR(AE48/AD48,"-") -> 0 | AH48: ='3. ГПП-СГПЗ'!AU18 -> 1 | AI48: ='3. ГПП-СГПЗ'!AW18 -> 0 | AJ48: =IFERROR(AI48-AH48,"-") -> -1 | AK48: =IFERROR(AI48/AH48,"-") -> 0 | AL48: ='3. ГПП-СГПЗ'!BA18 -> 1 | AM48: ='3. ГПП-СГПЗ'!BC18 -> 0 | AN48: =IFERROR(AM48-AL48,"-") -> -1 | AO48: =IFERROR(AM48/AL48,"-") -> 0 | AP48: ='3. ГПП-СГПЗ'!BG18 -> 1 | AQ48: ='3. ГПП-СГПЗ'!BI18 -> 0 | AR48: =IFERROR(AQ48-AP48,"-") -> -1 | AS48: =IFERROR(AQ48/AP48,"-") -> 0 | AT48: =AX48+BB48+BF48 -> 3 | AU48: =AY48+BC48+BG48 -> 0 | AV48: =IFERROR(AU48-AT48,"-") -> -3 | AW48: =IFERROR(AU48/AT48,"-") -> 0 | AX48: ='3. ГПП-СГПЗ'!BS18 -> 1 | AY48: ='3. ГПП-СГПЗ'!BU18 -> 0 | AZ48: =IFERROR(AY48-AX48,"-") -> -1 | BA48: =IFERROR(AY48/AX48,"-") -> 0 | BB48: ='3. ГПП-СГПЗ'!BY18 -> 1 | BC48: ='3. ГПП-СГПЗ'!CA18 -> 0 | BD48: =IFERROR(BC48-BB48,"-") -> -1 | BE48: =IFERROR(BC48/BB48,"-") -> 0 | BF48: ='3. ГПП-СГПЗ'!CE18 -> 1 | BG48: ='3. ГПП-СГПЗ'!CG18 -> 0 | BH48: =IFERROR(BG48-BF48,"-") -> -1 | BI48: =IFERROR(BG48/BF48,"-") -> 0 | BJ48: =BN48+BR48+BV48 -> 3 | BK48: =BO48+BS48+BW48 -> 0 | BL48: =IFERROR(BK48-BJ48,"-") -> -3 | BM48: =IFERROR(BK48/BJ48,"-") -> 0 | BN48: ='3. ГПП-СГПЗ'!CQ18 -> 1 | BO48: ='3. ГПП-СГПЗ'!CS18 -> 0 | BP48: =IFERROR(BO48-BN48,"-") -> -1 | BQ48: =IFERROR(BO48/BN48,"-") -> 0 | BR48: ='3. ГПП-СГПЗ'!CW18 -> 1 | BS48: ='3. ГПП-СГПЗ'!CY18 -> 0 | BT48: =IFERROR(BS48-BR48,"-") -> -1 | BU48: =IFERROR(BS48/BR48,"-") -> 0 | BV48: ='3. ГПП-СГПЗ'!DC18 -> 1 | BW48: ='3. ГПП-СГПЗ'!DE18 -> 0 | BX48: =IFERROR(BW48-BV48,"-") -> -1 | BY48: =IFERROR(BW48/BV48,"-") -> 0
C49: Лукойл-Коми | G49: 3_100330552 | I49: млн куб.м. | J49: =N49+AD49+AT49+BJ49 -> 12 | K49: =O49+AE49+AU49+BK49 -> 0 | L49: =IFERROR(K49-J49,"-") -> -12 | M49: =IFERROR(K49/J49,"-") -> 0 | N49: =R49+V49+Z49 -> 3 | O49: =S49+W49+AA49 -> 0 | P49: =IFERROR(O49-N49,"-") -> -3 | Q49: =IFERROR(O49/N49,"-") -> 0 | R49: ='3. ГПП-СГПЗ'!W18 -> 1 | S49: ='3. ГПП-СГПЗ'!Y18 -> 0 | T49: =IFERROR(S49-R49,"-") -> -1 | U49: =IFERROR(S49/R49,"-") -> 0 | V49: ='3. ГПП-СГПЗ'!AC18 -> 1 | W49: ='3. ГПП-СГПЗ'!AE18 -> 0 | X49: =IFERROR(W49-V49,"-") -> -1 | Y49: =IFERROR(W49/V49,"-") -> 0 | Z49: ='3. ГПП-СГПЗ'!AI18 -> 1 | AA49: ='3. ГПП-СГПЗ'!AK18 -> 0 | AB49: =IFERROR(AA49-Z49,"-") -> -1 | AC49: =IFERROR(AA49/Z49,"-") -> 0 | AD49: =AH49+AL49+AP49 -> 3 | AE49: =AI49+AM49+AQ49 -> 0 | AF49: =IFERROR(AE49-AD49,"-") -> -3 | AG49: =IFERROR(AE49/AD49,"-") -> 0 | AH49: ='3. ГПП-СГПЗ'!AU18 -> 1 | AI49: ='3. ГПП-СГПЗ'!AW18 -> 0 | AJ49: =IFERROR(AI49-AH49,"-") -> -1 | AK49: =IFERROR(AI49/AH49,"-") -> 0 | AL49: ='3. ГПП-СГПЗ'!BA18 -> 1 | AM49: ='3. ГПП-СГПЗ'!BC18 -> 0 | AN49: =IFERROR(AM49-AL49,"-") -> -1 | AO49: =IFERROR(AM49/AL49,"-") -> 0 | AP49: ='3. ГПП-СГПЗ'!BG18 -> 1 | AQ49: ='3. ГПП-СГПЗ'!BI18 -> 0 | AR49: =IFERROR(AQ49-AP49,"-") -> -1 | AS49: =IFERROR(AQ49/AP49,"-") -> 0 | AT49: =AX49+BB49+BF49 -> 3 | AU49: =AY49+BC49+BG49 -> 0 | AV49: =IFERROR(AU49-AT49,"-") -> -3 | AW49: =IFERROR(AU49/AT49,"-") -> 0 | AX49: ='3. ГПП-СГПЗ'!BS18 -> 1 | AY49: ='3. ГПП-СГПЗ'!BU18 -> 0 | AZ49: =IFERROR(AY49-AX49,"-") -> -1 | BA49: =IFERROR(AY49/AX49,"-") -> 0 | BB49: ='3. ГПП-СГПЗ'!BY18 -> 1 | BC49: ='3. ГПП-СГПЗ'!CA18 -> 0 | BD49: =IFERROR(BC49-BB49,"-") -> -1 | BE49: =IFERROR(BC49/BB49,"-") -> 0 | BF49: ='3. ГПП-СГПЗ'!CE18 -> 1 | BG49: ='3. ГПП-СГПЗ'!CG18 -> 0 | BH49: =IFERROR(BG49-BF49,"-") -> -1 | BI49: =IFERROR(BG49/BF49,"-") -> 0 | BJ49: =BN49+BR49+BV49 -> 3 | BK49: =BO49+BS49+BW49 -> 0 | BL49: =IFERROR(BK49-BJ49,"-") -> -3 | BM49: =IFERROR(BK49/BJ49,"-") -> 0 | BN49: ='3. ГПП-СГПЗ'!CQ18 -> 1 | BO49: ='3. ГПП-СГПЗ'!CS18 -> 0 | BP49: =IFERROR(BO49-BN49,"-") -> -1 | BQ49: =IFERROR(BO49/BN49,"-") -> 0 | BR49: ='3. ГПП-СГПЗ'!CW18 -> 1 | BS49: ='3. ГПП-СГПЗ'!CY18 -> 0 | BT49: =IFERROR(BS49-BR49,"-") -> -1 | BU49: =IFERROR(BS49/BR49,"-") -> 0 | BV49: ='3. ГПП-СГПЗ'!DC18 -> 1 | BW49: ='3. ГПП-СГПЗ'!DE18 -> 0 | BX49: =IFERROR(BW49-BV49,"-") -> -1 | BY49: =IFERROR(BW49/BV49,"-") -> 0
C50: Газпром переработка Благовещенск | G50: 14_100335076 | I50: млн куб.м. | J50: =N50+AD50+AT50+BJ50 -> 0 | K50: =O50+AE50+AU50+BK50 -> 0 | L50: =IFERROR(K50-J50,"-") -> 0 | M50: =IFERROR(K50/J50,"-") -> - | N50: =R50+V50+Z50 -> 0 | O50: =S50+W50+AA50 -> 0 | P50: =IFERROR(O50-N50,"-") -> 0 | Q50: =IFERROR(O50/N50,"-") -> - | R50: ='14. ГП Благовещенск (Ам ГПЗ)'!W33 -> 0 | S50: ='14. ГП Благовещенск (Ам ГПЗ)'!Y33 -> 0 | T50: =IFERROR(S50-R50,"-") -> 0 | U50: =IFERROR(S50/R50,"-") -> - | V50: ='14. ГП Благовещенск (Ам ГПЗ)'!AC33 -> 0 | W50: ='14. ГП Благовещенск (Ам ГПЗ)'!AE33 -> 0 | X50: =IFERROR(W50-V50,"-") -> 0 | Y50: =IFERROR(W50/V50,"-") -> - | Z50: ='14. ГП Благовещенск (Ам ГПЗ)'!AI33 -> 0 | AA50: ='14. ГП Благовещенск (Ам ГПЗ)'!AK33 -> 0 | AB50: =IFERROR(AA50-Z50,"-") -> 0 | AC50: =IFERROR(AA50/Z50,"-") -> - | AD50: =AH50+AL50+AP50 -> 0 | AE50: =AI50+AM50+AQ50 -> 0 | AF50: =IFERROR(AE50-AD50,"-") -> 0 | AG50: =IFERROR(AE50/AD50,"-") -> - | AH50: ='14. ГП Благовещенск (Ам ГПЗ)'!AU33 -> 0 | AI50: ='14. ГП Благовещенск (Ам ГПЗ)'!AW33 -> 0 | AJ50: =IFERROR(AI50-AH50,"-") -> 0 | AK50: =IFERROR(AI50/AH50,"-") -> - | AL50: ='14. ГП Благовещенск (Ам ГПЗ)'!BA33 -> 0 | AM50: ='14. ГП Благовещенск (Ам ГПЗ)'!BC33 -> 0 | AN50: =IFERROR(AM50-AL50,"-") -> 0 | AO50: =IFERROR(AM50/AL50,"-") -> - | AP50: ='14. ГП Благовещенск (Ам ГПЗ)'!BG33 -> 0 | AQ50: ='14. ГП Благовещенск (Ам ГПЗ)'!BI33 -> 0 | AR50: =IFERROR(AQ50-AP50,"-") -> 0 | AS50: =IFERROR(AQ50/AP50,"-") -> - | AT50: =AX50+BB50+BF50 -> 0 | AU50: =AY50+BC50+BG50 -> 0 | AV50: =IFERROR(AU50-AT50,"-") -> 0 | AW50: =IFERROR(AU50/AT50,"-") -> - | AX50: ='14. ГП Благовещенск (Ам ГПЗ)'!BS33 -> 0 | AY50: ='14. ГП Благовещенск (Ам ГПЗ)'!BU33 -> 0 | AZ50: =IFERROR(AY50-AX50,"-") -> 0 | BA50: =IFERROR(AY50/AX50,"-") -> - | BB50: ='14. ГП Благовещенск (Ам ГПЗ)'!BY33 -> 0 | BC50: ='14. ГП Благовещенск (Ам ГПЗ)'!CA33 -> 0 | BD50: =IFERROR(BC50-BB50,"-") -> 0 | BE50: =IFERROR(BC50/BB50,"-") -> - | BF50: ='14. ГП Благовещенск (Ам ГПЗ)'!CE33 -> 0 | BG50: ='14. ГП Благовещенск (Ам ГПЗ)'!CG33 -> 0 | BH50: =IFERROR(BG50-BF50,"-") -> 0 | BI50: =IFERROR(BG50/BF50,"-") -> - | BJ50: =BN50+BR50+BV50 -> 0 | BK50: =BO50+BS50+BW50 -> 0 | BL50: =IFERROR(BK50-BJ50,"-") -> 0 | BM50: =IFERROR(BK50/BJ50,"-") -> - | BN50: ='14. ГП Благовещенск (Ам ГПЗ)'!CQ33 -> 0 | BO50: ='14. ГП Благовещенск (Ам ГПЗ)'!CS33 -> 0 | BP50: =IFERROR(BO50-BN50,"-") -> 0 | BQ50: =IFERROR(BO50/BN50,"-") -> - | BR50: ='14. ГП Благовещенск (Ам ГПЗ)'!CW33 -> 0 | BS50: ='14. ГП Благовещенск (Ам ГПЗ)'!CY33 -> 0 | BT50: =IFERROR(BS50-BR50,"-") -> 0 | BU50: =IFERROR(BS50/BR50,"-") -> - | BV50: ='14. ГП Благовещенск (Ам ГПЗ)'!DC33 -> 0 | BW50: ='14. ГП Благовещенск (Ам ГПЗ)'!DE33 -> 0 | BX50: =IFERROR(BW50-BV50,"-") -> 0 | BY50: =IFERROR(BW50/BV50,"-") -> -
C51: Амурский ГПЗ | G51: 14_100335076 | I51: млн куб.м. | J51: =N51+AD51+AT51+BJ51 -> 0 | K51: =O51+AE51+AU51+BK51 -> 0 | L51: =IFERROR(K51-J51,"-") -> 0 | M51: =IFERROR(K51/J51,"-") -> - | N51: =R51+V51+Z51 -> 0 | O51: =S51+W51+AA51 -> 0 | P51: =IFERROR(O51-N51,"-") -> 0 | Q51: =IFERROR(O51/N51,"-") -> - | R51: ='14. ГП Благовещенск (Ам ГПЗ)'!W33 -> 0 | S51: ='14. ГП Благовещенск (Ам ГПЗ)'!Y33 -> 0 | T51: =IFERROR(S51-R51,"-") -> 0 | U51: =IFERROR(S51/R51,"-") -> - | V51: ='14. ГП Благовещенск (Ам ГПЗ)'!AC33 -> 0 | W51: ='14. ГП Благовещенск (Ам ГПЗ)'!AE33 -> 0 | X51: =IFERROR(W51-V51,"-") -> 0 | Y51: =IFERROR(W51/V51,"-") -> - | Z51: ='14. ГП Благовещенск (Ам ГПЗ)'!AI33 -> 0 | AA51: ='14. ГП Благовещенск (Ам ГПЗ)'!AK33 -> 0 | AB51: =IFERROR(AA51-Z51,"-") -> 0 | AC51: =IFERROR(AA51/Z51,"-") -> - | AD51: =AH51+AL51+AP51 -> 0 | AE51: =AI51+AM51+AQ51 -> 0 | AF51: =IFERROR(AE51-AD51,"-") -> 0 | AG51: =IFERROR(AE51/AD51,"-") -> - | AH51: ='14. ГП Благовещенск (Ам ГПЗ)'!AU33 -> 0 | AI51: ='14. ГП Благовещенск (Ам ГПЗ)'!AW33 -> 0 | AJ51: =IFERROR(AI51-AH51,"-") -> 0 | AK51: =IFERROR(AI51/AH51,"-") -> - | AL51: ='14. ГП Благовещенск (Ам ГПЗ)'!BA33 -> 0 | AM51: ='14. ГП Благовещенск (Ам ГПЗ)'!BC33 -> 0 | AN51: =IFERROR(AM51-AL51,"-") -> 0 | AO51: =IFERROR(AM51/AL51,"-") -> - | AP51: ='14. ГП Благовещенск (Ам ГПЗ)'!BG33 -> 0 | AQ51: ='14. ГП Благовещенск (Ам ГПЗ)'!BI33 -> 0 | AR51: =IFERROR(AQ51-AP51,"-") -> 0 | AS51: =IFERROR(AQ51/AP51,"-") -> - | AT51: =AX51+BB51+BF51 -> 0 | AU51: =AY51+BC51+BG51 -> 0 | AV51: =IFERROR(AU51-AT51,"-") -> 0 | AW51: =IFERROR(AU51/AT51,"-") -> - | AX51: ='14. ГП Благовещенск (Ам ГПЗ)'!BS33 -> 0 | AY51: ='14. ГП Благовещенск (Ам ГПЗ)'!BU33 -> 0 | AZ51: =IFERROR(AY51-AX51,"-") -> 0 | BA51: =IFERROR(AY51/AX51,"-") -> - | BB51: ='14. ГП Благовещенск (Ам ГПЗ)'!BY33 -> 0 | BC51: ='14. ГП Благовещенск (Ам ГПЗ)'!CA33 -> 0 | BD51: =IFERROR(BC51-BB51,"-") -> 0 | BE51: =IFERROR(BC51/BB51,"-") -> - | BF51: ='14. ГП Благовещенск (Ам ГПЗ)'!CE33 -> 0 | BG51: ='14. ГП Благовещенск (Ам ГПЗ)'!CG33 -> 0 | BH51: =IFERROR(BG51-BF51,"-") -> 0 | BI51: =IFERROR(BG51/BF51,"-") -> - | BJ51: =BN51+BR51+BV51 -> 0 | BK51: =BO51+BS51+BW51 -> 0 | BL51: =IFERROR(BK51-BJ51,"-") -> 0 | BM51: =IFERROR(BK51/BJ51,"-") -> - | BN51: ='14. ГП Благовещенск (Ам ГПЗ)'!CQ33 -> 0 | BO51: ='14. ГП Благовещенск (Ам ГПЗ)'!CS33 -> 0 | BP51: =IFERROR(BO51-BN51,"-") -> 0 | BQ51: =IFERROR(BO51/BN51,"-") -> - | BR51: ='14. ГП Благовещенск (Ам ГПЗ)'!CW33 -> 0 | BS51: ='14. ГП Благовещенск (Ам ГПЗ)'!CY33 -> 0 | BT51: =IFERROR(BS51-BR51,"-") -> 0 | BU51: =IFERROR(BS51/BR51,"-") -> - | BV51: ='14. ГП Благовещенск (Ам ГПЗ)'!DC33 -> 0 | BW51: ='14. ГП Благовещенск (Ам ГПЗ)'!DE33 -> 0 | BX51: =IFERROR(BW51-BV51,"-") -> 0 | BY51: =IFERROR(BW51/BV51,"-") -> -
C52: Газпром СПГ Портовая | I52: млн куб.м.
C53: КСПГ КС Портовая | I53: млн куб.м.
C54: в т.ч. СТН при переработке | I54: млн куб.м.
C55: в т.ч. СТН при пусковых операциях | I55: млн куб.м.
B56: 2. | C56: Поставка газа на Амурский ГПЗ
C57: Газпром переработка Благовещенск | G57: 14_100332979-14_100335059-14_100335057-14_100335425+14_100335428+14_100335059 | I57: млн куб.м. | J57: =N57+AD57+AT57+BJ57 -> 42824.9 | K57: =O57+AE57+AU57+BK57 -> 0 | L57: =IFERROR(K57-J57,"-") -> -42824.9 | M57: =IFERROR(K57/J57,"-") -> 0 | N57: =R57+V57+Z57 -> 10609 | O57: =S57+W57+AA57 -> 0 | P57: =IFERROR(O57-N57,"-") -> -10609 | Q57: =IFERROR(O57/N57,"-") -> 0 | R57: ='14. ГП Благовещенск (Ам ГПЗ)'!W11-'14. ГП Благовещенск (Ам ГПЗ)'!W19-'14. ГП Благовещенск (Ам ГПЗ)'!W14-'14. ГП Благовещенск (Ам ГПЗ)'!W27+'14. ГП Благовещенск (Ам ГПЗ)'!W74+'14. ГП Благовещенск (Ам ГПЗ)'!W19 -> 3824.8 | S57: ='14. ГП Благовещенск (Ам ГПЗ)'!Y11-'14. ГП Благовещенск (Ам ГПЗ)'!Y19-'14. ГП Благовещенск (Ам ГПЗ)'!Y14-'14. ГП Благовещенск (Ам ГПЗ)'!Y27+'14. ГП Благовещенск (Ам ГПЗ)'!Y74+'14. ГП Благовещенск (Ам ГПЗ)'!Y19 -> 0 | T57: =IFERROR(S57-R57,"-") -> -3824.8 | U57: =IFERROR(S57/R57,"-") -> 0 | V57: ='14. ГП Благовещенск (Ам ГПЗ)'!AC11-'14. ГП Благовещенск (Ам ГПЗ)'!AC19-'14. ГП Благовещенск (Ам ГПЗ)'!AC14-'14. ГП Благовещенск (Ам ГПЗ)'!AC27+'14. ГП Благовещенск (Ам ГПЗ)'!AC74+'14. ГП Благовещенск (Ам ГПЗ)'!AC19 -> 3454.4 | W57: ='14. ГП Благовещенск (Ам ГПЗ)'!AE11-'14. ГП Благовещенск (Ам ГПЗ)'!AE19-'14. ГП Благовещенск (Ам ГПЗ)'!AE14-'14. ГП Благовещенск (Ам ГПЗ)'!AE27+'14. ГП Благовещенск (Ам ГПЗ)'!AE74+'14. ГП Благовещенск (Ам ГПЗ)'!AE19 -> 0 | X57: =IFERROR(W57-V57,"-") -> -3454.4 | Y57: =IFERROR(W57/V57,"-") -> 0 | Z57: ='14. ГП Благовещенск (Ам ГПЗ)'!AI11-'14. ГП Благовещенск (Ам ГПЗ)'!AI19-'14. ГП Благовещенск (Ам ГПЗ)'!AI14-'14. ГП Благовещенск (Ам ГПЗ)'!AI27+'14. ГП Благовещенск (Ам ГПЗ)'!AI74+'14. ГП Благовещенск (Ам ГПЗ)'!AI19 -> 3329.8 | AA57: ='14. ГП Благовещенск (Ам ГПЗ)'!AK11-'14. ГП Благовещенск (Ам ГПЗ)'!AK19-'14. ГП Благовещенск (Ам ГПЗ)'!AK14-'14. ГП Благовещенск (Ам ГПЗ)'!AK27+'14. ГП Благовещенск (Ам ГПЗ)'!AK74+'14. ГП Благовещенск (Ам ГПЗ)'!AK19 -> 0 | AB57: =IFERROR(AA57-Z57,"-") -> -3329.8 | AC57: =IFERROR(AA57/Z57,"-") -> 0 | AD57: =AH57+AL57+AP57 -> 10288.9 | AE57: =AI57+AM57+AQ57 -> 0 | AF57: =IFERROR(AE57-AD57,"-") -> -10288.9 | AG57: =IFERROR(AE57/AD57,"-") -> 0 | AH57: ='14. ГП Благовещенск (Ам ГПЗ)'!AU11-'14. ГП Благовещенск (Ам ГПЗ)'!AU19-'14. ГП Благовещенск (Ам ГПЗ)'!AU14-'14. ГП Благовещенск (Ам ГПЗ)'!AU27+'14. ГП Благовещенск (Ам ГПЗ)'!AU74+'14. ГП Благовещенск (Ам ГПЗ)'!AU19 -> 3102.5 | AI57: ='14. ГП Благовещенск (Ам ГПЗ)'!AW11-'14. ГП Благовещенск (Ам ГПЗ)'!AW19-'14. ГП Благовещенск (Ам ГПЗ)'!AW14-'14. ГП Благовещенск (Ам ГПЗ)'!AW27+'14. ГП Благовещенск (Ам ГПЗ)'!AW74+'14. ГП Благовещенск (Ам ГПЗ)'!AW19 -> 0 | AJ57: =IFERROR(AI57-AH57,"-") -> -3102.5 | AK57: =IFERROR(AI57/AH57,"-") -> 0 | AL57: ='14. ГП Благовещенск (Ам ГПЗ)'!BA11-'14. ГП Благовещенск (Ам ГПЗ)'!BA19-'14. ГП Благовещенск (Ам ГПЗ)'!BA14-'14. ГП Благовещенск (Ам ГПЗ)'!BA27+'14. ГП Благовещенск (Ам ГПЗ)'!BA74+'14. ГП Благовещенск (Ам ГПЗ)'!BA19 -> 3712.9 | AM57: ='14. ГП Благовещенск (Ам ГПЗ)'!BC11-'14. ГП Благовещенск (Ам ГПЗ)'!BC19-'14. ГП Благовещенск (Ам ГПЗ)'!BC14-'14. ГП Благовещенск (Ам ГПЗ)'!BC27+'14. ГП Благовещенск (Ам ГПЗ)'!BC74+'14. ГП Благовещенск (Ам ГПЗ)'!BC19 -> 0 | AN57: =IFERROR(AM57-AL57,"-") -> -3712.9 | AO57: =IFERROR(AM57/AL57,"-") -> 0 | AP57: ='14. ГП Благовещенск (Ам ГПЗ)'!BG11-'14. ГП Благовещенск (Ам ГПЗ)'!BG19-'14. ГП Благовещенск (Ам ГПЗ)'!BG14-'14. ГП Благовещенск (Ам ГПЗ)'!BG27+'14. ГП Благовещенск (Ам ГПЗ)'!BG74+'14. ГП Благовещенск (Ам ГПЗ)'!BG19 -> 3473.5 | AQ57: ='14. ГП Благовещенск (Ам ГПЗ)'!BI11-'14. ГП Благовещенск (Ам ГПЗ)'!BI19-'14. ГП Благовещенск (Ам ГПЗ)'!BI14-'14. ГП Благовещенск (Ам ГПЗ)'!BI27+'14. ГП Благовещенск (Ам ГПЗ)'!BI74+'14. ГП Благовещенск (Ам ГПЗ)'!BI19 -> 0 | AR57: =IFERROR(AQ57-AP57,"-") -> -3473.5 | AS57: =IFERROR(AQ57/AP57,"-") -> 0 | AT57: =AX57+BB57+BF57 -> 10566.5 | AU57: =AY57+BC57+BG57 -> 0 | AV57: =IFERROR(AU57-AT57,"-") -> -10566.5 | AW57: =IFERROR(AU57/AT57,"-") -> 0 | AX57: ='14. ГП Благовещенск (Ам ГПЗ)'!BS11-'14. ГП Благовещенск (Ам ГПЗ)'!BS19-'14. ГП Благовещенск (Ам ГПЗ)'!BS14-'14. ГП Благовещенск (Ам ГПЗ)'!BS27+'14. ГП Благовещенск (Ам ГПЗ)'!BS74+'14. ГП Благовещенск (Ам ГПЗ)'!BS19 -> 3798.8 | AY57: ='14. ГП Благовещенск (Ам ГПЗ)'!BU11-'14. ГП Благовещенск (Ам ГПЗ)'!BU19-'14. ГП Благовещенск (Ам ГПЗ)'!BU14-'14. ГП Благовещенск (Ам ГПЗ)'!BU27+'14. ГП Благовещенск (Ам ГПЗ)'!BU74+'14. ГП Благовещенск (Ам ГПЗ)'!BU19 -> 0 | AZ57: =IFERROR(AY57-AX57,"-") -> -3798.8 | BA57: =IFERROR(AY57/AX57,"-") -> 0 | BB57: ='14. ГП Благовещенск (Ам ГПЗ)'!BY11-'14. ГП Благовещенск (Ам ГПЗ)'!BY19-'14. ГП Благовещенск (Ам ГПЗ)'!BY14-'14. ГП Благовещенск (Ам ГПЗ)'!BY27+'14. ГП Благовещенск (Ам ГПЗ)'!BY74+'14. ГП Благовещенск (Ам ГПЗ)'!BY19 -> 3877 | BC57: ='14. ГП Благовещенск (Ам ГПЗ)'!CA11-'14. ГП Благовещенск (Ам ГПЗ)'!CA19-'14. ГП Благовещенск (Ам ГПЗ)'!CA14-'14. ГП Благовещенск (Ам ГПЗ)'!CA27+'14. ГП Благовещенск (Ам ГПЗ)'!CA74+'14. ГП Благовещенск (Ам ГПЗ)'!CA19 -> 0 | BD57: =IFERROR(BC57-BB57,"-") -> -3877 | BE57: =IFERROR(BC57/BB57,"-") -> 0 | BF57: ='14. ГП Благовещенск (Ам ГПЗ)'!CE11-'14. ГП Благовещенск (Ам ГПЗ)'!CE19-'14. ГП Благовещенск (Ам ГПЗ)'!CE14-'14. ГП Благовещенск (Ам ГПЗ)'!CE27+'14. ГП Благовещенск (Ам ГПЗ)'!CE74+'14. ГП Благовещенск (Ам ГПЗ)'!CE19 -> 2890.7 | BG57: ='14. ГП Благовещенск (Ам ГПЗ)'!CG11-'14. ГП Благовещенск (Ам ГПЗ)'!CG19-'14. ГП Благовещенск (Ам ГПЗ)'!CG14-'14. ГП Благовещенск (Ам ГПЗ)'!CG27+'14. ГП Благовещенск (Ам ГПЗ)'!CG74+'14. ГП Благовещенск (Ам ГПЗ)'!CG19 -> 0 | BH57: =IFERROR(BG57-BF57,"-") -> -2890.7 | BI57: =IFERROR(BG57/BF57,"-") -> 0 | BJ57: =BN57+BR57+BV57 -> 11360.5 | BK57: =BO57+BS57+BW57 -> 0 | BL57: =IFERROR(BK57-BJ57,"-") -> -11360.5 | BM57: =IFERROR(BK57/BJ57,"-") -> 0 | BN57: ='14. ГП Благовещенск (Ам ГПЗ)'!CQ11-'14. ГП Благовещенск (Ам ГПЗ)'!CQ19-'14. ГП Благовещенск (Ам ГПЗ)'!CQ14-'14. ГП Благовещенск (Ам ГПЗ)'!CQ27+'14. ГП Благовещенск (Ам ГПЗ)'!CQ74+'14. ГП Благовещенск (Ам ГПЗ)'!CQ19 -> 3808.3 | BO57: ='14. ГП Благовещенск (Ам ГПЗ)'!CS11-'14. ГП Благовещенск (Ам ГПЗ)'!CS19-'14. ГП Благовещенск (Ам ГПЗ)'!CS14-'14. ГП Благовещенск (Ам ГПЗ)'!CS27+'14. ГП Благовещенск (Ам ГПЗ)'!CS74+'14. ГП Благовещенск (Ам ГПЗ)'!CS19 -> 0 | BP57: =IFERROR(BO57-BN57,"-") -> -3808.3 | BQ57: =IFERROR(BO57/BN57,"-") -> 0 | BR57: ='14. ГП Благовещенск (Ам ГПЗ)'!CW11-'14. ГП Благовещенск (Ам ГПЗ)'!CW19-'14. ГП Благовещенск (Ам ГПЗ)'!CW14-'14. ГП Благовещенск (Ам ГПЗ)'!CW27+'14. ГП Благовещенск (Ам ГПЗ)'!CW74+'14. ГП Благовещенск (Ам ГПЗ)'!CW19 -> 3701.2 | BS57: ='14. ГП Благовещенск (Ам ГПЗ)'!CY11-'14. ГП Благовещенск (Ам ГПЗ)'!CY19-'14. ГП Благовещенск (Ам ГПЗ)'!CY14-'14. ГП Благовещенск (Ам ГПЗ)'!CY27+'14. ГП Благовещенск (Ам ГПЗ)'!CY74+'14. ГП Благовещенск (Ам ГПЗ)'!CY19 -> 0 | BT57: =IFERROR(BS57-BR57,"-") -> -3701.2 | BU57: =IFERROR(BS57/BR57,"-") -> 0 | BV57: ='14. ГП Благовещенск (Ам ГПЗ)'!DC11-'14. ГП Благовещенск (Ам ГПЗ)'!DC19-'14. ГП Благовещенск (Ам ГПЗ)'!DC14-'14. ГП Благовещенск (Ам ГПЗ)'!DC27+'14. ГП Благовещенск (Ам ГПЗ)'!DC74+'14. ГП Благовещенск (Ам ГПЗ)'!DC19 -> 3851 | BW57: ='14. ГП Благовещенск (Ам ГПЗ)'!DE11-'14. ГП Благовещенск (Ам ГПЗ)'!DE19-'14. ГП Благовещенск (Ам ГПЗ)'!DE14-'14. ГП Благовещенск (Ам ГПЗ)'!DE27+'14. ГП Благовещенск (Ам ГПЗ)'!DE74+'14. ГП Благовещенск (Ам ГПЗ)'!DE19 -> 0 | BX57: =IFERROR(BW57-BV57,"-") -> -3851 | BY57: =IFERROR(BW57/BV57,"-") -> 0
C58: Амурский ГПЗ | G58: 14_100332979-14_100335059-14_100335057-14_100335425+14_100335428+14_100335059 | I58: млн куб.м. | J58: =N58+AD58+AT58+BJ58 -> 42824.9 | K58: =O58+AE58+AU58+BK58 -> 0 | L58: =IFERROR(K58-J58,"-") -> -42824.9 | M58: =IFERROR(K58/J58,"-") -> 0 | N58: =R58+V58+Z58 -> 10609 | O58: =S58+W58+AA58 -> 0 | P58: =IFERROR(O58-N58,"-") -> -10609 | Q58: =IFERROR(O58/N58,"-") -> 0 | R58: ='14. ГП Благовещенск (Ам ГПЗ)'!W11-'14. ГП Благовещенск (Ам ГПЗ)'!W19-'14. ГП Благовещенск (Ам ГПЗ)'!W14-'14. ГП Благовещенск (Ам ГПЗ)'!W27+'14. ГП Благовещенск (Ам ГПЗ)'!W74+'14. ГП Благовещенск (Ам ГПЗ)'!W19 -> 3824.8 | S58: ='14. ГП Благовещенск (Ам ГПЗ)'!Y11-'14. ГП Благовещенск (Ам ГПЗ)'!Y19-'14. ГП Благовещенск (Ам ГПЗ)'!Y14-'14. ГП Благовещенск (Ам ГПЗ)'!Y27+'14. ГП Благовещенск (Ам ГПЗ)'!Y74+'14. ГП Благовещенск (Ам ГПЗ)'!Y19 -> 0 | T58: =IFERROR(S58-R58,"-") -> -3824.8 | U58: =IFERROR(S58/R58,"-") -> 0 | V58: ='14. ГП Благовещенск (Ам ГПЗ)'!AC11-'14. ГП Благовещенск (Ам ГПЗ)'!AC19-'14. ГП Благовещенск (Ам ГПЗ)'!AC14-'14. ГП Благовещенск (Ам ГПЗ)'!AC27+'14. ГП Благовещенск (Ам ГПЗ)'!AC74+'14. ГП Благовещенск (Ам ГПЗ)'!AC19 -> 3454.4 | W58: ='14. ГП Благовещенск (Ам ГПЗ)'!AE11-'14. ГП Благовещенск (Ам ГПЗ)'!AE19-'14. ГП Благовещенск (Ам ГПЗ)'!AE14-'14. ГП Благовещенск (Ам ГПЗ)'!AE27+'14. ГП Благовещенск (Ам ГПЗ)'!AE74+'14. ГП Благовещенск (Ам ГПЗ)'!AE19 -> 0 | X58: =IFERROR(W58-V58,"-") -> -3454.4 | Y58: =IFERROR(W58/V58,"-") -> 0 | Z58: ='14. ГП Благовещенск (Ам ГПЗ)'!AI11-'14. ГП Благовещенск (Ам ГПЗ)'!AI19-'14. ГП Благовещенск (Ам ГПЗ)'!AI14-'14. ГП Благовещенск (Ам ГПЗ)'!AI27+'14. ГП Благовещенск (Ам ГПЗ)'!AI74+'14. ГП Благовещенск (Ам ГПЗ)'!AI19 -> 3329.8 | AA58: ='14. ГП Благовещенск (Ам ГПЗ)'!AK11-'14. ГП Благовещенск (Ам ГПЗ)'!AK19-'14. ГП Благовещенск (Ам ГПЗ)'!AK14-'14. ГП Благовещенск (Ам ГПЗ)'!AK27+'14. ГП Благовещенск (Ам ГПЗ)'!AK74+'14. ГП Благовещенск (Ам ГПЗ)'!AK19 -> 0 | AB58: =IFERROR(AA58-Z58,"-") -> -3329.8 | AC58: =IFERROR(AA58/Z58,"-") -> 0 | AD58: =AH58+AL58+AP58 -> 10288.9 | AE58: =AI58+AM58+AQ58 -> 0 | AF58: =IFERROR(AE58-AD58,"-") -> -10288.9 | AG58: =IFERROR(AE58/AD58,"-") -> 0 | AH58: ='14. ГП Благовещенск (Ам ГПЗ)'!AU11-'14. ГП Благовещенск (Ам ГПЗ)'!AU19-'14. ГП Благовещенск (Ам ГПЗ)'!AU14-'14. ГП Благовещенск (Ам ГПЗ)'!AU27+'14. ГП Благовещенск (Ам ГПЗ)'!AU74+'14. ГП Благовещенск (Ам ГПЗ)'!AU19 -> 3102.5 | AI58: ='14. ГП Благовещенск (Ам ГПЗ)'!AW11-'14. ГП Благовещенск (Ам ГПЗ)'!AW19-'14. ГП Благовещенск (Ам ГПЗ)'!AW14-'14. ГП Благовещенск (Ам ГПЗ)'!AW27+'14. ГП Благовещенск (Ам ГПЗ)'!AW74+'14. ГП Благовещенск (Ам ГПЗ)'!AW19 -> 0 | AJ58: =IFERROR(AI58-AH58,"-") -> -3102.5 | AK58: =IFERROR(AI58/AH58,"-") -> 0 | AL58: ='14. ГП Благовещенск (Ам ГПЗ)'!BA11-'14. ГП Благовещенск (Ам ГПЗ)'!BA19-'14. ГП Благовещенск (Ам ГПЗ)'!BA14-'14. ГП Благовещенск (Ам ГПЗ)'!BA27+'14. ГП Благовещенск (Ам ГПЗ)'!BA74+'14. ГП Благовещенск (Ам ГПЗ)'!BA19 -> 3712.9 | AM58: ='14. ГП Благовещенск (Ам ГПЗ)'!BC11-'14. ГП Благовещенск (Ам ГПЗ)'!BC19-'14. ГП Благовещенск (Ам ГПЗ)'!BC14-'14. ГП Благовещенск (Ам ГПЗ)'!BC27+'14. ГП Благовещенск (Ам ГПЗ)'!BC74+'14. ГП Благовещенск (Ам ГПЗ)'!BC19 -> 0 | AN58: =IFERROR(AM58-AL58,"-") -> -3712.9 | AO58: =IFERROR(AM58/AL58,"-") -> 0 | AP58: ='14. ГП Благовещенск (Ам ГПЗ)'!BG11-'14. ГП Благовещенск (Ам ГПЗ)'!BG19-'14. ГП Благовещенск (Ам ГПЗ)'!BG14-'14. ГП Благовещенск (Ам ГПЗ)'!BG27+'14. ГП Благовещенск (Ам ГПЗ)'!BG74+'14. ГП Благовещенск (Ам ГПЗ)'!BG19 -> 3473.5 | AQ58: ='14. ГП Благовещенск (Ам ГПЗ)'!BI11-'14. ГП Благовещенск (Ам ГПЗ)'!BI19-'14. ГП Благовещенск (Ам ГПЗ)'!BI14-'14. ГП Благовещенск (Ам ГПЗ)'!BI27+'14. ГП Благовещенск (Ам ГПЗ)'!BI74+'14. ГП Благовещенск (Ам ГПЗ)'!BI19 -> 0 | AR58: =IFERROR(AQ58-AP58,"-") -> -3473.5 | AS58: =IFERROR(AQ58/AP58,"-") -> 0 | AT58: =AX58+BB58+BF58 -> 10566.5 | AU58: =AY58+BC58+BG58 -> 0 | AV58: =IFERROR(AU58-AT58,"-") -> -10566.5 | AW58: =IFERROR(AU58/AT58,"-") -> 0 | AX58: ='14. ГП Благовещенск (Ам ГПЗ)'!BS11-'14. ГП Благовещенск (Ам ГПЗ)'!BS19-'14. ГП Благовещенск (Ам ГПЗ)'!BS14-'14. ГП Благовещенск (Ам ГПЗ)'!BS27+'14. ГП Благовещенск (Ам ГПЗ)'!BS74+'14. ГП Благовещенск (Ам ГПЗ)'!BS19 -> 3798.8 | AY58: ='14. ГП Благовещенск (Ам ГПЗ)'!BU11-'14. ГП Благовещенск (Ам ГПЗ)'!BU19-'14. ГП Благовещенск (Ам ГПЗ)'!BU14-'14. ГП Благовещенск (Ам ГПЗ)'!BU27+'14. ГП Благовещенск (Ам ГПЗ)'!BU74+'14. ГП Благовещенск (Ам ГПЗ)'!BU19 -> 0 | AZ58: =IFERROR(AY58-AX58,"-") -> -3798.8 | BA58: =IFERROR(AY58/AX58,"-") -> 0 | BB58: ='14. ГП Благовещенск (Ам ГПЗ)'!BY11-'14. ГП Благовещенск (Ам ГПЗ)'!BY19-'14. ГП Благовещенск (Ам ГПЗ)'!BY14-'14. ГП Благовещенск (Ам ГПЗ)'!BY27+'14. ГП Благовещенск (Ам ГПЗ)'!BY74+'14. ГП Благовещенск (Ам ГПЗ)'!BY19 -> 3877 | BC58: ='14. ГП Благовещенск (Ам ГПЗ)'!CA11-'14. ГП Благовещенск (Ам ГПЗ)'!CA19-'14. ГП Благовещенск (Ам ГПЗ)'!CA14-'14. ГП Благовещенск (Ам ГПЗ)'!CA27+'14. ГП Благовещенск (Ам ГПЗ)'!CA74+'14. ГП Благовещенск (Ам ГПЗ)'!CA19 -> 0 | BD58: =IFERROR(BC58-BB58,"-") -> -3877 | BE58: =IFERROR(BC58/BB58,"-") -> 0 | BF58: ='14. ГП Благовещенск (Ам ГПЗ)'!CE11-'14. ГП Благовещенск (Ам ГПЗ)'!CE19-'14. ГП Благовещенск (Ам ГПЗ)'!CE14-'14. ГП Благовещенск (Ам ГПЗ)'!CE27+'14. ГП Благовещенск (Ам ГПЗ)'!CE74+'14. ГП Благовещенск (Ам ГПЗ)'!CE19 -> 2890.7 | BG58: ='14. ГП Благовещенск (Ам ГПЗ)'!CG11-'14. ГП Благовещенск (Ам ГПЗ)'!CG19-'14. ГП Благовещенск (Ам ГПЗ)'!CG14-'14. ГП Благовещенск (Ам ГПЗ)'!CG27+'14. ГП Благовещенск (Ам ГПЗ)'!CG74+'14. ГП Благовещенск (Ам ГПЗ)'!CG19 -> 0 | BH58: =IFERROR(BG58-BF58,"-") -> -2890.7 | BI58: =IFERROR(BG58/BF58,"-") -> 0 | BJ58: =BN58+BR58+BV58 -> 11360.5 | BK58: =BO58+BS58+BW58 -> 0 | BL58: =IFERROR(BK58-BJ58,"-") -> -11360.5 | BM58: =IFERROR(BK58/BJ58,"-") -> 0 | BN58: ='14. ГП Благовещенск (Ам ГПЗ)'!CQ11-'14. ГП Благовещенск (Ам ГПЗ)'!CQ19-'14. ГП Благовещенск (Ам ГПЗ)'!CQ14-'14. ГП Благовещенск (Ам ГПЗ)'!CQ27+'14. ГП Благовещенск (Ам ГПЗ)'!CQ74+'14. ГП Благовещенск (Ам ГПЗ)'!CQ19 -> 3808.3 | BO58: ='14. ГП Благовещенск (Ам ГПЗ)'!CS11-'14. ГП Благовещенск (Ам ГПЗ)'!CS19-'14. ГП Благовещенск (Ам ГПЗ)'!CS14-'14. ГП Благовещенск (Ам ГПЗ)'!CS27+'14. ГП Благовещенск (Ам ГПЗ)'!CS74+'14. ГП Благовещенск (Ам ГПЗ)'!CS19 -> 0 | BP58: =IFERROR(BO58-BN58,"-") -> -3808.3 | BQ58: =IFERROR(BO58/BN58,"-") -> 0 | BR58: ='14. ГП Благовещенск (Ам ГПЗ)'!CW11-'14. ГП Благовещенск (Ам ГПЗ)'!CW19-'14. ГП Благовещенск (Ам ГПЗ)'!CW14-'14. ГП Благовещенск (Ам ГПЗ)'!CW27+'14. ГП Благовещенск (Ам ГПЗ)'!CW74+'14. ГП Благовещенск (Ам ГПЗ)'!CW19 -> 3701.2 | BS58: ='14. ГП Благовещенск (Ам ГПЗ)'!CY11-'14. ГП Благовещенск (Ам ГПЗ)'!CY19-'14. ГП Благовещенск (Ам ГПЗ)'!CY14-'14. ГП Благовещенск (Ам ГПЗ)'!CY27+'14. ГП Благовещенск (Ам ГПЗ)'!CY74+'14. ГП Благовещенск (Ам ГПЗ)'!CY19 -> 0 | BT58: =IFERROR(BS58-BR58,"-") -> -3701.2 | BU58: =IFERROR(BS58/BR58,"-") -> 0 | BV58: ='14. ГП Благовещенск (Ам ГПЗ)'!DC11-'14. ГП Благовещенск (Ам ГПЗ)'!DC19-'14. ГП Благовещенск (Ам ГПЗ)'!DC14-'14. ГП Благовещенск (Ам ГПЗ)'!DC27+'14. ГП Благовещенск (Ам ГПЗ)'!DC74+'14. ГП Благовещенск (Ам ГПЗ)'!DC19 -> 3851 | BW58: ='14. ГП Благовещенск (Ам ГПЗ)'!DE11-'14. ГП Благовещенск (Ам ГПЗ)'!DE19-'14. ГП Благовещенск (Ам ГПЗ)'!DE14-'14. ГП Благовещенск (Ам ГПЗ)'!DE27+'14. ГП Благовещенск (Ам ГПЗ)'!DE74+'14. ГП Благовещенск (Ам ГПЗ)'!DE19 -> 0 | BX58: =IFERROR(BW58-BV58,"-") -> -3851 | BY58: =IFERROR(BW58/BV58,"-") -> 0
B59: 2.1 | C59: Газпром
C60: Газпром переработка Благовещенск | G60: 14_100332979-14_100335059-14_100335057-14_100335425 | I60: млн куб.м. | J60: =N60+AD60+AT60+BJ60 -> 41614.7 | K60: =O60+AE60+AU60+BK60 -> 0 | L60: =IFERROR(K60-J60,"-") -> -41614.7 | M60: =IFERROR(K60/J60,"-") -> 0 | N60: =R60+V60+Z60 -> 10203 | O60: =S60+W60+AA60 -> 0 | P60: =IFERROR(O60-N60,"-") -> -10203 | Q60: =IFERROR(O60/N60,"-") -> 0 | R60: ='14. ГП Благовещенск (Ам ГПЗ)'!W11-'14. ГП Благовещенск (Ам ГПЗ)'!W19-'14. ГП Благовещенск (Ам ГПЗ)'!W14-'14. ГП Благовещенск (Ам ГПЗ)'!W27 -> 3678.6 | S60: ='14. ГП Благовещенск (Ам ГПЗ)'!Y11-'14. ГП Благовещенск (Ам ГПЗ)'!Y19-'14. ГП Благовещенск (Ам ГПЗ)'!Y14-'14. ГП Благовещенск (Ам ГПЗ)'!Y27 -> 0 | T60: =IFERROR(S60-R60,"-") -> -3678.6 | U60: =IFERROR(S60/R60,"-") -> 0 | V60: ='14. ГП Благовещенск (Ам ГПЗ)'!AC11-'14. ГП Благовещенск (Ам ГПЗ)'!AC19-'14. ГП Благовещенск (Ам ГПЗ)'!AC14-'14. ГП Благовещенск (Ам ГПЗ)'!AC27 -> 3322.3 | W60: ='14. ГП Благовещенск (Ам ГПЗ)'!AE11-'14. ГП Благовещенск (Ам ГПЗ)'!AE19-'14. ГП Благовещенск (Ам ГПЗ)'!AE14-'14. ГП Благовещенск (Ам ГПЗ)'!AE27 -> 0 | X60: =IFERROR(W60-V60,"-") -> -3322.3 | Y60: =IFERROR(W60/V60,"-") -> 0 | Z60: ='14. ГП Благовещенск (Ам ГПЗ)'!AI11-'14. ГП Благовещенск (Ам ГПЗ)'!AI19-'14. ГП Благовещенск (Ам ГПЗ)'!AI14-'14. ГП Благовещенск (Ам ГПЗ)'!AI27 -> 3202.1 | AA60: ='14. ГП Благовещенск (Ам ГПЗ)'!AK11-'14. ГП Благовещенск (Ам ГПЗ)'!AK19-'14. ГП Благовещенск (Ам ГПЗ)'!AK14-'14. ГП Благовещенск (Ам ГПЗ)'!AK27 -> 0 | AB60: =IFERROR(AA60-Z60,"-") -> -3202.1 | AC60: =IFERROR(AA60/Z60,"-") -> 0 | AD60: =AH60+AL60+AP60 -> 9933.4 | AE60: =AI60+AM60+AQ60 -> 0 | AF60: =IFERROR(AE60-AD60,"-") -> -9933.4 | AG60: =IFERROR(AE60/AD60,"-") -> 0 | AH60: ='14. ГП Благовещенск (Ам ГПЗ)'!AU11-'14. ГП Благовещенск (Ам ГПЗ)'!AU19-'14. ГП Благовещенск (Ам ГПЗ)'!AU14-'14. ГП Благовещенск (Ам ГПЗ)'!AU27 -> 2941.4 | AI60: ='14. ГП Благовещенск (Ам ГПЗ)'!AW11-'14. ГП Благовещенск (Ам ГПЗ)'!AW19-'14. ГП Благовещенск (Ам ГПЗ)'!AW14-'14. ГП Благовещенск (Ам ГПЗ)'!AW27 -> 0 | AJ60: =IFERROR(AI60-AH60,"-") -> -2941.4 | AK60: =IFERROR(AI60/AH60,"-") -> 0 | AL60: ='14. ГП Благовещенск (Ам ГПЗ)'!BA11-'14. ГП Благовещенск (Ам ГПЗ)'!BA19-'14. ГП Благовещенск (Ам ГПЗ)'!BA14-'14. ГП Благовещенск (Ам ГПЗ)'!BA27 -> 3585.4 | AM60: ='14. ГП Благовещенск (Ам ГПЗ)'!BC11-'14. ГП Благовещенск (Ам ГПЗ)'!BC19-'14. ГП Благовещенск (Ам ГПЗ)'!BC14-'14. ГП Благовещенск (Ам ГПЗ)'!BC27 -> 0 | AN60: =IFERROR(AM60-AL60,"-") -> -3585.4 | AO60: =IFERROR(AM60/AL60,"-") -> 0 | AP60: ='14. ГП Благовещенск (Ам ГПЗ)'!BG11-'14. ГП Благовещенск (Ам ГПЗ)'!BG19-'14. ГП Благовещенск (Ам ГПЗ)'!BG14-'14. ГП Благовещенск (Ам ГПЗ)'!BG27 -> 3406.6 | AQ60: ='14. ГП Благовещенск (Ам ГПЗ)'!BI11-'14. ГП Благовещенск (Ам ГПЗ)'!BI19-'14. ГП Благовещенск (Ам ГПЗ)'!BI14-'14. ГП Благовещенск (Ам ГПЗ)'!BI27 -> 0 | AR60: =IFERROR(AQ60-AP60,"-") -> -3406.6 | AS60: =IFERROR(AQ60/AP60,"-") -> 0 | AT60: =AX60+BB60+BF60 -> 10374.2 | AU60: =AY60+BC60+BG60 -> 0 | AV60: =IFERROR(AU60-AT60,"-") -> -10374.2 | AW60: =IFERROR(AU60/AT60,"-") -> 0 | AX60: ='14. ГП Благовещенск (Ам ГПЗ)'!BS11-'14. ГП Благовещенск (Ам ГПЗ)'!BS19-'14. ГП Благовещенск (Ам ГПЗ)'!BS14-'14. ГП Благовещенск (Ам ГПЗ)'!BS27 -> 3729.6 | AY60: ='14. ГП Благовещенск (Ам ГПЗ)'!BU11-'14. ГП Благовещенск (Ам ГПЗ)'!BU19-'14. ГП Благовещенск (Ам ГПЗ)'!BU14-'14. ГП Благовещенск (Ам ГПЗ)'!BU27 -> 0 | AZ60: =IFERROR(AY60-AX60,"-") -> -3729.6 | BA60: =IFERROR(AY60/AX60,"-") -> 0 | BB60: ='14. ГП Благовещенск (Ам ГПЗ)'!BY11-'14. ГП Благовещенск (Ам ГПЗ)'!BY19-'14. ГП Благовещенск (Ам ГПЗ)'!BY14-'14. ГП Благовещенск (Ам ГПЗ)'!BY27 -> 3807.8 | BC60: ='14. ГП Благовещенск (Ам ГПЗ)'!CA11-'14. ГП Благовещенск (Ам ГПЗ)'!CA19-'14. ГП Благовещенск (Ам ГПЗ)'!CA14-'14. ГП Благовещенск (Ам ГПЗ)'!CA27 -> 0 | BD60: =IFERROR(BC60-BB60,"-") -> -3807.8 | BE60: =IFERROR(BC60/BB60,"-") -> 0 | BF60: ='14. ГП Благовещенск (Ам ГПЗ)'!CE11-'14. ГП Благовещенск (Ам ГПЗ)'!CE19-'14. ГП Благовещенск (Ам ГПЗ)'!CE14-'14. ГП Благовещенск (Ам ГПЗ)'!CE27 -> 2836.8 | BG60: ='14. ГП Благовещенск (Ам ГПЗ)'!CG11-'14. ГП Благовещенск (Ам ГПЗ)'!CG19-'14. ГП Благовещенск (Ам ГПЗ)'!CG14-'14. ГП Благовещенск (Ам ГПЗ)'!CG27 -> 0 | BH60: =IFERROR(BG60-BF60,"-") -> -2836.8 | BI60: =IFERROR(BG60/BF60,"-") -> 0 | BJ60: =BN60+BR60+BV60 -> 11104.1 | BK60: =BO60+BS60+BW60 -> 0 | BL60: =IFERROR(BK60-BJ60,"-") -> -11104.1 | BM60: =IFERROR(BK60/BJ60,"-") -> 0 | BN60: ='14. ГП Благовещенск (Ам ГПЗ)'!CQ11-'14. ГП Благовещенск (Ам ГПЗ)'!CQ19-'14. ГП Благовещенск (Ам ГПЗ)'!CQ14-'14. ГП Благовещенск (Ам ГПЗ)'!CQ27 -> 3725.4 | BO60: ='14. ГП Благовещенск (Ам ГПЗ)'!CS11-'14. ГП Благовещенск (Ам ГПЗ)'!CS19-'14. ГП Благовещенск (Ам ГПЗ)'!CS14-'14. ГП Благовещенск (Ам ГПЗ)'!CS27 -> 0 | BP60: =IFERROR(BO60-BN60,"-") -> -3725.4 | BQ60: =IFERROR(BO60/BN60,"-") -> 0 | BR60: ='14. ГП Благовещенск (Ам ГПЗ)'!CW11-'14. ГП Благовещенск (Ам ГПЗ)'!CW19-'14. ГП Благовещенск (Ам ГПЗ)'!CW14-'14. ГП Благовещенск (Ам ГПЗ)'!CW27 -> 3617.1 | BS60: ='14. ГП Благовещенск (Ам ГПЗ)'!CY11-'14. ГП Благовещенск (Ам ГПЗ)'!CY19-'14. ГП Благовещенск (Ам ГПЗ)'!CY14-'14. ГП Благовещенск (Ам ГПЗ)'!CY27 -> 0 | BT60: =IFERROR(BS60-BR60,"-") -> -3617.1 | BU60: =IFERROR(BS60/BR60,"-") -> 0 | BV60: ='14. ГП Благовещенск (Ам ГПЗ)'!DC11-'14. ГП Благовещенск (Ам ГПЗ)'!DC19-'14. ГП Благовещенск (Ам ГПЗ)'!DC14-'14. ГП Благовещенск (Ам ГПЗ)'!DC27 -> 3761.6 | BW60: ='14. ГП Благовещенск (Ам ГПЗ)'!DE11-'14. ГП Благовещенск (Ам ГПЗ)'!DE19-'14. ГП Благовещенск (Ам ГПЗ)'!DE14-'14. ГП Благовещенск (Ам ГПЗ)'!DE27 -> 0 | BX60: =IFERROR(BW60-BV60,"-") -> -3761.6 | BY60: =IFERROR(BW60/BV60,"-") -> 0
C61: Амурский ГПЗ | G61: 14_100332979-14_100335059-14_100335057-14_100335425 | I61: млн куб.м. | J61: =N61+AD61+AT61+BJ61 -> 41614.7 | K61: =O61+AE61+AU61+BK61 -> 0 | L61: =IFERROR(K61-J61,"-") -> -41614.7 | M61: =IFERROR(K61/J61,"-") -> 0 | N61: =R61+V61+Z61 -> 10203 | O61: =S61+W61+AA61 -> 0 | P61: =IFERROR(O61-N61,"-") -> -10203 | Q61: =IFERROR(O61/N61,"-") -> 0 | R61: ='14. ГП Благовещенск (Ам ГПЗ)'!W11-'14. ГП Благовещенск (Ам ГПЗ)'!W19-'14. ГП Благовещенск (Ам ГПЗ)'!W14-'14. ГП Благовещенск (Ам ГПЗ)'!W27 -> 3678.6 | S61: ='14. ГП Благовещенск (Ам ГПЗ)'!Y11-'14. ГП Благовещенск (Ам ГПЗ)'!Y19-'14. ГП Благовещенск (Ам ГПЗ)'!Y14-'14. ГП Благовещенск (Ам ГПЗ)'!Y27 -> 0 | T61: =IFERROR(S61-R61,"-") -> -3678.6 | U61: =IFERROR(S61/R61,"-") -> 0 | V61: ='14. ГП Благовещенск (Ам ГПЗ)'!AC11-'14. ГП Благовещенск (Ам ГПЗ)'!AC19-'14. ГП Благовещенск (Ам ГПЗ)'!AC14-'14. ГП Благовещенск (Ам ГПЗ)'!AC27 -> 3322.3 | W61: ='14. ГП Благовещенск (Ам ГПЗ)'!AE11-'14. ГП Благовещенск (Ам ГПЗ)'!AE19-'14. ГП Благовещенск (Ам ГПЗ)'!AE14-'14. ГП Благовещенск (Ам ГПЗ)'!AE27 -> 0 | X61: =IFERROR(W61-V61,"-") -> -3322.3 | Y61: =IFERROR(W61/V61,"-") -> 0 | Z61: ='14. ГП Благовещенск (Ам ГПЗ)'!AI11-'14. ГП Благовещенск (Ам ГПЗ)'!AI19-'14. ГП Благовещенск (Ам ГПЗ)'!AI14-'14. ГП Благовещенск (Ам ГПЗ)'!AI27 -> 3202.1 | AA61: ='14. ГП Благовещенск (Ам ГПЗ)'!AK11-'14. ГП Благовещенск (Ам ГПЗ)'!AK19-'14. ГП Благовещенск (Ам ГПЗ)'!AK14-'14. ГП Благовещенск (Ам ГПЗ)'!AK27 -> 0 | AB61: =IFERROR(AA61-Z61,"-") -> -3202.1 | AC61: =IFERROR(AA61/Z61,"-") -> 0 | AD61: =AH61+AL61+AP61 -> 9933.4 | AE61: =AI61+AM61+AQ61 -> 0 | AF61: =IFERROR(AE61-AD61,"-") -> -9933.4 | AG61: =IFERROR(AE61/AD61,"-") -> 0 | AH61: ='14. ГП Благовещенск (Ам ГПЗ)'!AU11-'14. ГП Благовещенск (Ам ГПЗ)'!AU19-'14. ГП Благовещенск (Ам ГПЗ)'!AU14-'14. ГП Благовещенск (Ам ГПЗ)'!AU27 -> 2941.4 | AI61: ='14. ГП Благовещенск (Ам ГПЗ)'!AW11-'14. ГП Благовещенск (Ам ГПЗ)'!AW19-'14. ГП Благовещенск (Ам ГПЗ)'!AW14-'14. ГП Благовещенск (Ам ГПЗ)'!AW27 -> 0 | AJ61: =IFERROR(AI61-AH61,"-") -> -2941.4 | AK61: =IFERROR(AI61/AH61,"-") -> 0 | AL61: ='14. ГП Благовещенск (Ам ГПЗ)'!BA11-'14. ГП Благовещенск (Ам ГПЗ)'!BA19-'14. ГП Благовещенск (Ам ГПЗ)'!BA14-'14. ГП Благовещенск (Ам ГПЗ)'!BA27 -> 3585.4 | AM61: ='14. ГП Благовещенск (Ам ГПЗ)'!BC11-'14. ГП Благовещенск (Ам ГПЗ)'!BC19-'14. ГП Благовещенск (Ам ГПЗ)'!BC14-'14. ГП Благовещенск (Ам ГПЗ)'!BC27 -> 0 | AN61: =IFERROR(AM61-AL61,"-") -> -3585.4 | AO61: =IFERROR(AM61/AL61,"-") -> 0 | AP61: ='14. ГП Благовещенск (Ам ГПЗ)'!BG11-'14. ГП Благовещенск (Ам ГПЗ)'!BG19-'14. ГП Благовещенск (Ам ГПЗ)'!BG14-'14. ГП Благовещенск (Ам ГПЗ)'!BG27 -> 3406.6 | AQ61: ='14. ГП Благовещенск (Ам ГПЗ)'!BI11-'14. ГП Благовещенск (Ам ГПЗ)'!BI19-'14. ГП Благовещенск (Ам ГПЗ)'!BI14-'14. ГП Благовещенск (Ам ГПЗ)'!BI27 -> 0 | AR61: =IFERROR(AQ61-AP61,"-") -> -3406.6 | AS61: =IFERROR(AQ61/AP61,"-") -> 0 | AT61: =AX61+BB61+BF61 -> 10374.2 | AU61: =AY61+BC61+BG61 -> 0 | AV61: =IFERROR(AU61-AT61,"-") -> -10374.2 | AW61: =IFERROR(AU61/AT61,"-") -> 0 | AX61: ='14. ГП Благовещенск (Ам ГПЗ)'!BS11-'14. ГП Благовещенск (Ам ГПЗ)'!BS19-'14. ГП Благовещенск (Ам ГПЗ)'!BS14-'14. ГП Благовещенск (Ам ГПЗ)'!BS27 -> 3729.6 | AY61: ='14. ГП Благовещенск (Ам ГПЗ)'!BU11-'14. ГП Благовещенск (Ам ГПЗ)'!BU19-'14. ГП Благовещенск (Ам ГПЗ)'!BU14-'14. ГП Благовещенск (Ам ГПЗ)'!BU27 -> 0 | AZ61: =IFERROR(AY61-AX61,"-") -> -3729.6 | BA61: =IFERROR(AY61/AX61,"-") -> 0 | BB61: ='14. ГП Благовещенск (Ам ГПЗ)'!BY11-'14. ГП Благовещенск (Ам ГПЗ)'!BY19-'14. ГП Благовещенск (Ам ГПЗ)'!BY14-'14. ГП Благовещенск (Ам ГПЗ)'!BY27 -> 3807.8 | BC61: ='14. ГП Благовещенск (Ам ГПЗ)'!CA11-'14. ГП Благовещенск (Ам ГПЗ)'!CA19-'14. ГП Благовещенск (Ам ГПЗ)'!CA14-'14. ГП Благовещенск (Ам ГПЗ)'!CA27 -> 0 | BD61: =IFERROR(BC61-BB61,"-") -> -3807.8 | BE61: =IFERROR(BC61/BB61,"-") -> 0 | BF61: ='14. ГП Благовещенск (Ам ГПЗ)'!CE11-'14. ГП Благовещенск (Ам ГПЗ)'!CE19-'14. ГП Благовещенск (Ам ГПЗ)'!CE14-'14. ГП Благовещенск (Ам ГПЗ)'!CE27 -> 2836.8 | BG61: ='14. ГП Благовещенск (Ам ГПЗ)'!CG11-'14. ГП Благовещенск (Ам ГПЗ)'!CG19-'14. ГП Благовещенск (Ам ГПЗ)'!CG14-'14. ГП Благовещенск (Ам ГПЗ)'!CG27 -> 0 | BH61: =IFERROR(BG61-BF61,"-") -> -2836.8 | BI61: =IFERROR(BG61/BF61,"-") -> 0 | BJ61: =BN61+BR61+BV61 -> 11104.1 | BK61: =BO61+BS61+BW61 -> 0 | BL61: =IFERROR(BK61-BJ61,"-") -> -11104.1 | BM61: =IFERROR(BK61/BJ61,"-") -> 0 | BN61: ='14. ГП Благовещенск (Ам ГПЗ)'!CQ11-'14. ГП Благовещенск (Ам ГПЗ)'!CQ19-'14. ГП Благовещенск (Ам ГПЗ)'!CQ14-'14. ГП Благовещенск (Ам ГПЗ)'!CQ27 -> 3725.4 | BO61: ='14. ГП Благовещенск (Ам ГПЗ)'!CS11-'14. ГП Благовещенск (Ам ГПЗ)'!CS19-'14. ГП Благовещенск (Ам ГПЗ)'!CS14-'14. ГП Благовещенск (Ам ГПЗ)'!CS27 -> 0 | BP61: =IFERROR(BO61-BN61,"-") -> -3725.4 | BQ61: =IFERROR(BO61/BN61,"-") -> 0 | BR61: ='14. ГП Благовещенск (Ам ГПЗ)'!CW11-'14. ГП Благовещенск (Ам ГПЗ)'!CW19-'14. ГП Благовещенск (Ам ГПЗ)'!CW14-'14. ГП Благовещенск (Ам ГПЗ)'!CW27 -> 3617.1 | BS61: ='14. ГП Благовещенск (Ам ГПЗ)'!CY11-'14. ГП Благовещенск (Ам ГПЗ)'!CY19-'14. ГП Благовещенск (Ам ГПЗ)'!CY14-'14. ГП Благовещенск (Ам ГПЗ)'!CY27 -> 0 | BT61: =IFERROR(BS61-BR61,"-") -> -3617.1 | BU61: =IFERROR(BS61/BR61,"-") -> 0 | BV61: ='14. ГП Благовещенск (Ам ГПЗ)'!DC11-'14. ГП Благовещенск (Ам ГПЗ)'!DC19-'14. ГП Благовещенск (Ам ГПЗ)'!DC14-'14. ГП Благовещенск (Ам ГПЗ)'!DC27 -> 3761.6 | BW61: ='14. ГП Благовещенск (Ам ГПЗ)'!DE11-'14. ГП Благовещенск (Ам ГПЗ)'!DE19-'14. ГП Благовещенск (Ам ГПЗ)'!DE14-'14. ГП Благовещенск (Ам ГПЗ)'!DE27 -> 0 | BX61: =IFERROR(BW61-BV61,"-") -> -3761.6 | BY61: =IFERROR(BW61/BV61,"-") -> 0
B62: 2.2 | C62: Дочерние общества
C63: Газпром переработка Благовещенск | G63: 14_100335428+14_100335059 | I63: млн куб.м. | J63: =N63+AD63+AT63+BJ63 -> 1210.2 | K63: =O63+AE63+AU63+BK63 -> 0 | L63: =IFERROR(K63-J63,"-") -> -1210.2 | M63: =IFERROR(K63/J63,"-") -> 0 | N63: =R63+V63+Z63 -> 406 | O63: =S63+W63+AA63 -> 0 | P63: =IFERROR(O63-N63,"-") -> -406 | Q63: =IFERROR(O63/N63,"-") -> 0 | R63: ='14. ГП Благовещенск (Ам ГПЗ)'!W74+'14. ГП Благовещенск (Ам ГПЗ)'!W19 -> 146.2 | S63: ='14. ГП Благовещенск (Ам ГПЗ)'!Y74+'14. ГП Благовещенск (Ам ГПЗ)'!Y19 -> 0 | T63: =IFERROR(S63-R63,"-") -> -146.2 | U63: =IFERROR(S63/R63,"-") -> 0 | V63: ='14. ГП Благовещенск (Ам ГПЗ)'!AC74+'14. ГП Благовещенск (Ам ГПЗ)'!AC19 -> 132.1 | W63: ='14. ГП Благовещенск (Ам ГПЗ)'!AE74+'14. ГП Благовещенск (Ам ГПЗ)'!AE19 -> 0 | X63: =IFERROR(W63-V63,"-") -> -132.1 | Y63: =IFERROR(W63/V63,"-") -> 0 | Z63: ='14. ГП Благовещенск (Ам ГПЗ)'!AI74+'14. ГП Благовещенск (Ам ГПЗ)'!AI19 -> 127.7 | AA63: ='14. ГП Благовещенск (Ам ГПЗ)'!AK74+'14. ГП Благовещенск (Ам ГПЗ)'!AK19 -> 0 | AB63: =IFERROR(AA63-Z63,"-") -> -127.7 | AC63: =IFERROR(AA63/Z63,"-") -> 0 | AD63: =AH63+AL63+AP63 -> 355.5 | AE63: =AI63+AM63+AQ63 -> 0 | AF63: =IFERROR(AE63-AD63,"-") -> -355.5 | AG63: =IFERROR(AE63/AD63,"-") -> 0 | AH63: ='14. ГП Благовещенск (Ам ГПЗ)'!AU74+'14. ГП Благовещенск (Ам ГПЗ)'!AU19 -> 161.1 | AI63: ='14. ГП Благовещенск (Ам ГПЗ)'!AW74+'14. ГП Благовещенск (Ам ГПЗ)'!AW19 -> 0 | AJ63: =IFERROR(AI63-AH63,"-") -> -161.1 | AK63: =IFERROR(AI63/AH63,"-") -> 0 | AL63: ='14. ГП Благовещенск (Ам ГПЗ)'!BA74+'14. ГП Благовещенск (Ам ГПЗ)'!BA19 -> 127.5 | AM63: ='14. ГП Благовещенск (Ам ГПЗ)'!BC74+'14. ГП Благовещенск (Ам ГПЗ)'!BC19 -> 0 | AN63: =IFERROR(AM63-AL63,"-") -> -127.5 | AO63: =IFERROR(AM63/AL63,"-") -> 0 | AP63: ='14. ГП Благовещенск (Ам ГПЗ)'!BG74+'14. ГП Благовещенск (Ам ГПЗ)'!BG19 -> 66.9 | AQ63: ='14. ГП Благовещенск (Ам ГПЗ)'!BI74+'14. ГП Благовещенск (Ам ГПЗ)'!BI19 -> 0 | AR63: =IFERROR(AQ63-AP63,"-") -> -66.9 | AS63: =IFERROR(AQ63/AP63,"-") -> 0 | AT63: =AX63+BB63+BF63 -> 192.3 | AU63: =AY63+BC63+BG63 -> 0 | AV63: =IFERROR(AU63-AT63,"-") -> -192.3 | AW63: =IFERROR(AU63/AT63,"-") -> 0 | AX63: ='14. ГП Благовещенск (Ам ГПЗ)'!BS74+'14. ГП Благовещенск (Ам ГПЗ)'!BS19 -> 69.2 | AY63: ='14. ГП Благовещенск (Ам ГПЗ)'!BU74+'14. ГП Благовещенск (Ам ГПЗ)'!BU19 -> 0 | AZ63: =IFERROR(AY63-AX63,"-") -> -69.2 | BA63: =IFERROR(AY63/AX63,"-") -> 0 | BB63: ='14. ГП Благовещенск (Ам ГПЗ)'!BY74+'14. ГП Благовещенск (Ам ГПЗ)'!BY19 -> 69.2 | BC63: ='14. ГП Благовещенск (Ам ГПЗ)'!CA74+'14. ГП Благовещенск (Ам ГПЗ)'!CA19 -> 0 | BD63: =IFERROR(BC63-BB63,"-") -> -69.2 | BE63: =IFERROR(BC63/BB63,"-") -> 0 | BF63: ='14. ГП Благовещенск (Ам ГПЗ)'!CE74+'14. ГП Благовещенск (Ам ГПЗ)'!CE19 -> 53.9 | BG63: ='14. ГП Благовещенск (Ам ГПЗ)'!CG74+'14. ГП Благовещенск (Ам ГПЗ)'!CG19 -> 0 | BH63: =IFERROR(BG63-BF63,"-") -> -53.9 | BI63: =IFERROR(BG63/BF63,"-") -> 0 | BJ63: =BN63+BR63+BV63 -> 256.4 | BK63: =BO63+BS63+BW63 -> 0 | BL63: =IFERROR(BK63-BJ63,"-") -> -256.4 | BM63: =IFERROR(BK63/BJ63,"-") -> 0 | BN63: ='14. ГП Благовещенск (Ам ГПЗ)'!CQ74+'14. ГП Благовещенск (Ам ГПЗ)'!CQ19 -> 82.9 | BO63: ='14. ГП Благовещенск (Ам ГПЗ)'!CS74+'14. ГП Благовещенск (Ам ГПЗ)'!CS19 -> 0 | BP63: =IFERROR(BO63-BN63,"-") -> -82.9 | BQ63: =IFERROR(BO63/BN63,"-") -> 0 | BR63: ='14. ГП Благовещенск (Ам ГПЗ)'!CW74+'14. ГП Благовещенск (Ам ГПЗ)'!CW19 -> 84.1 | BS63: ='14. ГП Благовещенск (Ам ГПЗ)'!CY74+'14. ГП Благовещенск (Ам ГПЗ)'!CY19 -> 0 | BT63: =IFERROR(BS63-BR63,"-") -> -84.1 | BU63: =IFERROR(BS63/BR63,"-") -> 0 | BV63: ='14. ГП Благовещенск (Ам ГПЗ)'!DC74+'14. ГП Благовещенск (Ам ГПЗ)'!DC19 -> 89.4 | BW63: ='14. ГП Благовещенск (Ам ГПЗ)'!DE74+'14. ГП Благовещенск (Ам ГПЗ)'!DE19 -> 0 | BX63: =IFERROR(BW63-BV63,"-") -> -89.4 | BY63: =IFERROR(BW63/BV63,"-") -> 0
C64: Амурский ГПЗ | G64: 14_100335428+14_100335059 | I64: млн куб.м. | J64: =N64+AD64+AT64+BJ64 -> 1210.2 | K64: =O64+AE64+AU64+BK64 -> 0 | L64: =IFERROR(K64-J64,"-") -> -1210.2 | M64: =IFERROR(K64/J64,"-") -> 0 | N64: =R64+V64+Z64 -> 406 | O64: =S64+W64+AA64 -> 0 | P64: =IFERROR(O64-N64,"-") -> -406 | Q64: =IFERROR(O64/N64,"-") -> 0 | R64: ='14. ГП Благовещенск (Ам ГПЗ)'!W74+'14. ГП Благовещенск (Ам ГПЗ)'!W19 -> 146.2 | S64: ='14. ГП Благовещенск (Ам ГПЗ)'!Y74+'14. ГП Благовещенск (Ам ГПЗ)'!Y19 -> 0 | T64: =IFERROR(S64-R64,"-") -> -146.2 | U64: =IFERROR(S64/R64,"-") -> 0 | V64: ='14. ГП Благовещенск (Ам ГПЗ)'!AC74+'14. ГП Благовещенск (Ам ГПЗ)'!AC19 -> 132.1 | W64: ='14. ГП Благовещенск (Ам ГПЗ)'!AE74+'14. ГП Благовещенск (Ам ГПЗ)'!AE19 -> 0 | X64: =IFERROR(W64-V64,"-") -> -132.1 | Y64: =IFERROR(W64/V64,"-") -> 0 | Z64: ='14. ГП Благовещенск (Ам ГПЗ)'!AI74+'14. ГП Благовещенск (Ам ГПЗ)'!AI19 -> 127.7 | AA64: ='14. ГП Благовещенск (Ам ГПЗ)'!AK74+'14. ГП Благовещенск (Ам ГПЗ)'!AK19 -> 0 | AB64: =IFERROR(AA64-Z64,"-") -> -127.7 | AC64: =IFERROR(AA64/Z64,"-") -> 0 | AD64: =AH64+AL64+AP64 -> 355.5 | AE64: =AI64+AM64+AQ64 -> 0 | AF64: =IFERROR(AE64-AD64,"-") -> -355.5 | AG64: =IFERROR(AE64/AD64,"-") -> 0 | AH64: ='14. ГП Благовещенск (Ам ГПЗ)'!AU74+'14. ГП Благовещенск (Ам ГПЗ)'!AU19 -> 161.1 | AI64: ='14. ГП Благовещенск (Ам ГПЗ)'!AW74+'14. ГП Благовещенск (Ам ГПЗ)'!AW19 -> 0 | AJ64: =IFERROR(AI64-AH64,"-") -> -161.1 | AK64: =IFERROR(AI64/AH64,"-") -> 0 | AL64: ='14. ГП Благовещенск (Ам ГПЗ)'!BA74+'14. ГП Благовещенск (Ам ГПЗ)'!BA19 -> 127.5 | AM64: ='14. ГП Благовещенск (Ам ГПЗ)'!BC74+'14. ГП Благовещенск (Ам ГПЗ)'!BC19 -> 0 | AN64: =IFERROR(AM64-AL64,"-") -> -127.5 | AO64: =IFERROR(AM64/AL64,"-") -> 0 | AP64: ='14. ГП Благовещенск (Ам ГПЗ)'!BG74+'14. ГП Благовещенск (Ам ГПЗ)'!BG19 -> 66.9 | AQ64: ='14. ГП Благовещенск (Ам ГПЗ)'!BI74+'14. ГП Благовещенск (Ам ГПЗ)'!BI19 -> 0 | AR64: =IFERROR(AQ64-AP64,"-") -> -66.9 | AS64: =IFERROR(AQ64/AP64,"-") -> 0 | AT64: =AX64+BB64+BF64 -> 192.3 | AU64: =AY64+BC64+BG64 -> 0 | AV64: =IFERROR(AU64-AT64,"-") -> -192.3 | AW64: =IFERROR(AU64/AT64,"-") -> 0 | AX64: ='14. ГП Благовещенск (Ам ГПЗ)'!BS74+'14. ГП Благовещенск (Ам ГПЗ)'!BS19 -> 69.2 | AY64: ='14. ГП Благовещенск (Ам ГПЗ)'!BU74+'14. ГП Благовещенск (Ам ГПЗ)'!BU19 -> 0 | AZ64: =IFERROR(AY64-AX64,"-") -> -69.2 | BA64: =IFERROR(AY64/AX64,"-") -> 0 | BB64: ='14. ГП Благовещенск (Ам ГПЗ)'!BY74+'14. ГП Благовещенск (Ам ГПЗ)'!BY19 -> 69.2 | BC64: ='14. ГП Благовещенск (Ам ГПЗ)'!CA74+'14. ГП Благовещенск (Ам ГПЗ)'!CA19 -> 0 | BD64: =IFERROR(BC64-BB64,"-") -> -69.2 | BE64: =IFERROR(BC64/BB64,"-") -> 0 | BF64: ='14. ГП Благовещенск (Ам ГПЗ)'!CE74+'14. ГП Благовещенск (Ам ГПЗ)'!CE19 -> 53.9 | BG64: ='14. ГП Благовещенск (Ам ГПЗ)'!CG74+'14. ГП Благовещенск (Ам ГПЗ)'!CG19 -> 0 | BH64: =IFERROR(BG64-BF64,"-") -> -53.9 | BI64: =IFERROR(BG64/BF64,"-") -> 0 | BJ64: =BN64+BR64+BV64 -> 256.4 | BK64: =BO64+BS64+BW64 -> 0 | BL64: =IFERROR(BK64-BJ64,"-") -> -256.4 | BM64: =IFERROR(BK64/BJ64,"-") -> 0 | BN64: ='14. ГП Благовещенск (Ам ГПЗ)'!CQ74+'14. ГП Благовещенск (Ам ГПЗ)'!CQ19 -> 82.9 | BO64: ='14. ГП Благовещенск (Ам ГПЗ)'!CS74+'14. ГП Благовещенск (Ам ГПЗ)'!CS19 -> 0 | BP64: =IFERROR(BO64-BN64,"-") -> -82.9 | BQ64: =IFERROR(BO64/BN64,"-") -> 0 | BR64: ='14. ГП Благовещенск (Ам ГПЗ)'!CW74+'14. ГП Благовещенск (Ам ГПЗ)'!CW19 -> 84.1 | BS64: ='14. ГП Благовещенск (Ам ГПЗ)'!CY74+'14. ГП Благовещенск (Ам ГПЗ)'!CY19 -> 0 | BT64: =IFERROR(BS64-BR64,"-") -> -84.1 | BU64: =IFERROR(BS64/BR64,"-") -> 0 | BV64: ='14. ГП Благовещенск (Ам ГПЗ)'!DC74+'14. ГП Благовещенск (Ам ГПЗ)'!DC19 -> 89.4 | BW64: ='14. ГП Благовещенск (Ам ГПЗ)'!DE74+'14. ГП Благовещенск (Ам ГПЗ)'!DE19 -> 0 | BX64: =IFERROR(BW64-BV64,"-") -> -89.4 | BY64: =IFERROR(BW64/BV64,"-") -> 0
B65: 3. | C65: Переработка газа на Оренбургском гелиевом заводе
C66: Газпром переработка | G66: 2_100332054+2_100332056+2_100335131 | I66: млн куб.м. | J66: =N66+AD66+AT66+BJ66 -> 10484.2 | K66: =O66+AE66+AU66+BK66 -> 0 | L66: =IFERROR(K66-J66,"-") -> -10484.2 | M66: =IFERROR(K66/J66,"-") -> 0 | N66: =R66+V66+Z66 -> 2936.3 | O66: =S66+W66+AA66 -> 0 | P66: =IFERROR(O66-N66,"-") -> -2936.3 | Q66: =IFERROR(O66/N66,"-") -> 0 | R66: ='2. ГПП-ОГХК'!W46+'2. ГПП-ОГХК'!W48+'2. ГПП-ОГХК'!W50 -> 1018.1 | S66: ='2. ГПП-ОГХК'!Y46+'2. ГПП-ОГХК'!Y48+'2. ГПП-ОГХК'!Y50 -> 0 | T66: =IFERROR(S66-R66,"-") -> -1018.1 | U66: =IFERROR(S66/R66,"-") -> 0 | V66: ='2. ГПП-ОГХК'!AC46+'2. ГПП-ОГХК'!AC48+'2. ГПП-ОГХК'!AC50 -> 919.4 | W66: ='2. ГПП-ОГХК'!AE46+'2. ГПП-ОГХК'!AE48+'2. ГПП-ОГХК'!AE50 -> 0 | X66: =IFERROR(W66-V66,"-") -> -919.4 | Y66: =IFERROR(W66/V66,"-") -> 0 | Z66: ='2. ГПП-ОГХК'!AI46+'2. ГПП-ОГХК'!AI48+'2. ГПП-ОГХК'!AI50 -> 998.8 | AA66: ='2. ГПП-ОГХК'!AK46+'2. ГПП-ОГХК'!AK48+'2. ГПП-ОГХК'!AK50 -> 0 | AB66: =IFERROR(AA66-Z66,"-") -> -998.8 | AC66: =IFERROR(AA66/Z66,"-") -> 0 | AD66: =AH66+AL66+AP66 -> 2155.6 | AE66: =AI66+AM66+AQ66 -> 0 | AF66: =IFERROR(AE66-AD66,"-") -> -2155.6 | AG66: =IFERROR(AE66/AD66,"-") -> 0 | AH66: ='2. ГПП-ОГХК'!AU46+'2. ГПП-ОГХК'!AU48+'2. ГПП-ОГХК'!AU50 -> 579.1 | AI66: ='2. ГПП-ОГХК'!AW46+'2. ГПП-ОГХК'!AW48+'2. ГПП-ОГХК'!AW50 -> 0 | AJ66: =IFERROR(AI66-AH66,"-") -> -579.1 | AK66: =IFERROR(AI66/AH66,"-") -> 0 | AL66: ='2. ГПП-ОГХК'!BA46+'2. ГПП-ОГХК'!BA48+'2. ГПП-ОГХК'!BA50 -> 805.5 | AM66: ='2. ГПП-ОГХК'!BC46+'2. ГПП-ОГХК'!BC48+'2. ГПП-ОГХК'!BC50 -> 0 | AN66: =IFERROR(AM66-AL66,"-") -> -805.5 | AO66: =IFERROR(AM66/AL66,"-") -> 0 | AP66: ='2. ГПП-ОГХК'!BG46+'2. ГПП-ОГХК'!BG48+'2. ГПП-ОГХК'!BG50 -> 771 | AQ66: ='2. ГПП-ОГХК'!BI46+'2. ГПП-ОГХК'!BI48+'2. ГПП-ОГХК'!BI50 -> 0 | AR66: =IFERROR(AQ66-AP66,"-") -> -771 | AS66: =IFERROR(AQ66/AP66,"-") -> 0 | AT66: =AX66+BB66+BF66 -> 2392.7 | AU66: =AY66+BC66+BG66 -> 0 | AV66: =IFERROR(AU66-AT66,"-") -> -2392.7 | AW66: =IFERROR(AU66/AT66,"-") -> 0 | AX66: ='2. ГПП-ОГХК'!BS46+'2. ГПП-ОГХК'!BS48+'2. ГПП-ОГХК'!BS50 -> 820.3 | AY66: ='2. ГПП-ОГХК'!BU46+'2. ГПП-ОГХК'!BU48+'2. ГПП-ОГХК'!BU50 -> 0 | AZ66: =IFERROR(AY66-AX66,"-") -> -820.3 | BA66: =IFERROR(AY66/AX66,"-") -> 0 | BB66: ='2. ГПП-ОГХК'!BY46+'2. ГПП-ОГХК'!BY48+'2. ГПП-ОГХК'!BY50 -> 820.6 | BC66: ='2. ГПП-ОГХК'!CA46+'2. ГПП-ОГХК'!CA48+'2. ГПП-ОГХК'!CA50 -> 0 | BD66: =IFERROR(BC66-BB66,"-") -> -820.6 | BE66: =IFERROR(BC66/BB66,"-") -> 0 | BF66: ='2. ГПП-ОГХК'!CE46+'2. ГПП-ОГХК'!CE48+'2. ГПП-ОГХК'!CE50 -> 751.8 | BG66: ='2. ГПП-ОГХК'!CG46+'2. ГПП-ОГХК'!CG48+'2. ГПП-ОГХК'!CG50 -> 0 | BH66: =IFERROR(BG66-BF66,"-") -> -751.8 | BI66: =IFERROR(BG66/BF66,"-") -> 0 | BJ66: =BN66+BR66+BV66 -> 2999.6 | BK66: =BO66+BS66+BW66 -> 0 | BL66: =IFERROR(BK66-BJ66,"-") -> -2999.6 | BM66: =IFERROR(BK66/BJ66,"-") -> 0 | BN66: ='2. ГПП-ОГХК'!CQ46+'2. ГПП-ОГХК'!CQ48+'2. ГПП-ОГХК'!CQ50 -> 1011.7 | BO66: ='2. ГПП-ОГХК'!CS46+'2. ГПП-ОГХК'!CS48+'2. ГПП-ОГХК'!CS50 -> 0 | BP66: =IFERROR(BO66-BN66,"-") -> -1011.7 | BQ66: =IFERROR(BO66/BN66,"-") -> 0 | BR66: ='2. ГПП-ОГХК'!CW46+'2. ГПП-ОГХК'!CW48+'2. ГПП-ОГХК'!CW50 -> 978 | BS66: ='2. ГПП-ОГХК'!CY46+'2. ГПП-ОГХК'!CY48+'2. ГПП-ОГХК'!CY50 -> 0 | BT66: =IFERROR(BS66-BR66,"-") -> -978 | BU66: =IFERROR(BS66/BR66,"-") -> 0 | BV66: ='2. ГПП-ОГХК'!DC46+'2. ГПП-ОГХК'!DC48+'2. ГПП-ОГХК'!DC50 -> 1009.9 | BW66: ='2. ГПП-ОГХК'!DE46+'2. ГПП-ОГХК'!DE48+'2. ГПП-ОГХК'!DE50 -> 0 | BX66: =IFERROR(BW66-BV66,"-") -> -1009.9 | BY66: =IFERROR(BW66/BV66,"-") -> 0
C67: Оренбургский ГЗ | G67: 2_100332054+2_100332056+2_100335131 | I67: млн куб.м. | J67: =N67+AD67+AT67+BJ67 -> 10484.2 | K67: =O67+AE67+AU67+BK67 -> 0 | L67: =IFERROR(K67-J67,"-") -> -10484.2 | M67: =IFERROR(K67/J67,"-") -> 0 | N67: =R67+V67+Z67 -> 2936.3 | O67: =S67+W67+AA67 -> 0 | P67: =IFERROR(O67-N67,"-") -> -2936.3 | Q67: =IFERROR(O67/N67,"-") -> 0 | R67: ='2. ГПП-ОГХК'!W46+'2. ГПП-ОГХК'!W48+'2. ГПП-ОГХК'!W50 -> 1018.1 | S67: ='2. ГПП-ОГХК'!Y46+'2. ГПП-ОГХК'!Y48+'2. ГПП-ОГХК'!Y50 -> 0 | T67: =IFERROR(S67-R67,"-") -> -1018.1 | U67: =IFERROR(S67/R67,"-") -> 0 | V67: ='2. ГПП-ОГХК'!AC46+'2. ГПП-ОГХК'!AC48+'2. ГПП-ОГХК'!AC50 -> 919.4 | W67: ='2. ГПП-ОГХК'!AE46+'2. ГПП-ОГХК'!AE48+'2. ГПП-ОГХК'!AE50 -> 0 | X67: =IFERROR(W67-V67,"-") -> -919.4 | Y67: =IFERROR(W67/V67,"-") -> 0 | Z67: ='2. ГПП-ОГХК'!AI46+'2. ГПП-ОГХК'!AI48+'2. ГПП-ОГХК'!AI50 -> 998.8 | AA67: ='2. ГПП-ОГХК'!AK46+'2. ГПП-ОГХК'!AK48+'2. ГПП-ОГХК'!AK50 -> 0 | AB67: =IFERROR(AA67-Z67,"-") -> -998.8 | AC67: =IFERROR(AA67/Z67,"-") -> 0 | AD67: =AH67+AL67+AP67 -> 2155.6 | AE67: =AI67+AM67+AQ67 -> 0 | AF67: =IFERROR(AE67-AD67,"-") -> -2155.6 | AG67: =IFERROR(AE67/AD67,"-") -> 0 | AH67: ='2. ГПП-ОГХК'!AU46+'2. ГПП-ОГХК'!AU48+'2. ГПП-ОГХК'!AU50 -> 579.1 | AI67: ='2. ГПП-ОГХК'!AW46+'2. ГПП-ОГХК'!AW48+'2. ГПП-ОГХК'!AW50 -> 0 | AJ67: =IFERROR(AI67-AH67,"-") -> -579.1 | AK67: =IFERROR(AI67/AH67,"-") -> 0 | AL67: ='2. ГПП-ОГХК'!BA46+'2. ГПП-ОГХК'!BA48+'2. ГПП-ОГХК'!BA50 -> 805.5 | AM67: ='2. ГПП-ОГХК'!BC46+'2. ГПП-ОГХК'!BC48+'2. ГПП-ОГХК'!BC50 -> 0 | AN67: =IFERROR(AM67-AL67,"-") -> -805.5 | AO67: =IFERROR(AM67/AL67,"-") -> 0 | AP67: ='2. ГПП-ОГХК'!BG46+'2. ГПП-ОГХК'!BG48+'2. ГПП-ОГХК'!BG50 -> 771 | AQ67: ='2. ГПП-ОГХК'!BI46+'2. ГПП-ОГХК'!BI48+'2. ГПП-ОГХК'!BI50 -> 0 | AR67: =IFERROR(AQ67-AP67,"-") -> -771 | AS67: =IFERROR(AQ67/AP67,"-") -> 0 | AT67: =AX67+BB67+BF67 -> 2392.7 | AU67: =AY67+BC67+BG67 -> 0 | AV67: =IFERROR(AU67-AT67,"-") -> -2392.7 | AW67: =IFERROR(AU67/AT67,"-") -> 0 | AX67: ='2. ГПП-ОГХК'!BS46+'2. ГПП-ОГХК'!BS48+'2. ГПП-ОГХК'!BS50 -> 820.3 | AY67: ='2. ГПП-ОГХК'!BU46+'2. ГПП-ОГХК'!BU48+'2. ГПП-ОГХК'!BU50 -> 0 | AZ67: =IFERROR(AY67-AX67,"-") -> -820.3 | BA67: =IFERROR(AY67/AX67,"-") -> 0 | BB67: ='2. ГПП-ОГХК'!BY46+'2. ГПП-ОГХК'!BY48+'2. ГПП-ОГХК'!BY50 -> 820.6 | BC67: ='2. ГПП-ОГХК'!CA46+'2. ГПП-ОГХК'!CA48+'2. ГПП-ОГХК'!CA50 -> 0 | BD67: =IFERROR(BC67-BB67,"-") -> -820.6 | BE67: =IFERROR(BC67/BB67,"-") -> 0 | BF67: ='2. ГПП-ОГХК'!CE46+'2. ГПП-ОГХК'!CE48+'2. ГПП-ОГХК'!CE50 -> 751.8 | BG67: ='2. ГПП-ОГХК'!CG46+'2. ГПП-ОГХК'!CG48+'2. ГПП-ОГХК'!CG50 -> 0 | BH67: =IFERROR(BG67-BF67,"-") -> -751.8 | BI67: =IFERROR(BG67/BF67,"-") -> 0 | BJ67: =BN67+BR67+BV67 -> 2999.6 | BK67: =BO67+BS67+BW67 -> 0 | BL67: =IFERROR(BK67-BJ67,"-") -> -2999.6 | BM67: =IFERROR(BK67/BJ67,"-") -> 0 | BN67: ='2. ГПП-ОГХК'!CQ46+'2. ГПП-ОГХК'!CQ48+'2. ГПП-ОГХК'!CQ50 -> 1011.7 | BO67: ='2. ГПП-ОГХК'!CS46+'2. ГПП-ОГХК'!CS48+'2. ГПП-ОГХК'!CS50 -> 0 | BP67: =IFERROR(BO67-BN67,"-") -> -1011.7 | BQ67: =IFERROR(BO67/BN67,"-") -> 0 | BR67: ='2. ГПП-ОГХК'!CW46+'2. ГПП-ОГХК'!CW48+'2. ГПП-ОГХК'!CW50 -> 978 | BS67: ='2. ГПП-ОГХК'!CY46+'2. ГПП-ОГХК'!CY48+'2. ГПП-ОГХК'!CY50 -> 0 | BT67: =IFERROR(BS67-BR67,"-") -> -978 | BU67: =IFERROR(BS67/BR67,"-") -> 0 | BV67: ='2. ГПП-ОГХК'!DC46+'2. ГПП-ОГХК'!DC48+'2. ГПП-ОГХК'!DC50 -> 1009.9 | BW67: ='2. ГПП-ОГХК'!DE46+'2. ГПП-ОГХК'!DE48+'2. ГПП-ОГХК'!DE50 -> 0 | BX67: =IFERROR(BW67-BV67,"-") -> -1009.9 | BY67: =IFERROR(BW67/BV67,"-") -> 0
B68: 3.1 | C68: Газпром | G68: 0 | I68: млн куб.м.
B69: 3.2 | C69: Дочерние общества | G69: 2_100332054+2_100332056+2_100335131 | I69: млн куб.м. | J69: =N69+AD69+AT69+BJ69 -> 10484.2 | K69: =O69+AE69+AU69+BK69 -> 0 | L69: =IFERROR(K69-J69,"-") -> -10484.2 | M69: =IFERROR(K69/J69,"-") -> 0 | N69: =R69+V69+Z69 -> 2936.3 | O69: =S69+W69+AA69 -> 0 | P69: =IFERROR(O69-N69,"-") -> -2936.3 | Q69: =IFERROR(O69/N69,"-") -> 0 | R69: ='2. ГПП-ОГХК'!W46+'2. ГПП-ОГХК'!W48+'2. ГПП-ОГХК'!W50 -> 1018.1 | S69: ='2. ГПП-ОГХК'!Y46+'2. ГПП-ОГХК'!Y48+'2. ГПП-ОГХК'!Y50 -> 0 | T69: =IFERROR(S69-R69,"-") -> -1018.1 | U69: =IFERROR(S69/R69,"-") -> 0 | V69: ='2. ГПП-ОГХК'!AC46+'2. ГПП-ОГХК'!AC48+'2. ГПП-ОГХК'!AC50 -> 919.4 | W69: ='2. ГПП-ОГХК'!AE46+'2. ГПП-ОГХК'!AE48+'2. ГПП-ОГХК'!AE50 -> 0 | X69: =IFERROR(W69-V69,"-") -> -919.4 | Y69: =IFERROR(W69/V69,"-") -> 0 | Z69: ='2. ГПП-ОГХК'!AI46+'2. ГПП-ОГХК'!AI48+'2. ГПП-ОГХК'!AI50 -> 998.8 | AA69: ='2. ГПП-ОГХК'!AK46+'2. ГПП-ОГХК'!AK48+'2. ГПП-ОГХК'!AK50 -> 0 | AB69: =IFERROR(AA69-Z69,"-") -> -998.8 | AC69: =IFERROR(AA69/Z69,"-") -> 0 | AD69: =AH69+AL69+AP69 -> 2155.6 | AE69: =AI69+AM69+AQ69 -> 0 | AF69: =IFERROR(AE69-AD69,"-") -> -2155.6 | AG69: =IFERROR(AE69/AD69,"-") -> 0 | AH69: ='2. ГПП-ОГХК'!AU46+'2. ГПП-ОГХК'!AU48+'2. ГПП-ОГХК'!AU50 -> 579.1 | AI69: ='2. ГПП-ОГХК'!AW46+'2. ГПП-ОГХК'!AW48+'2. ГПП-ОГХК'!AW50 -> 0 | AJ69: =IFERROR(AI69-AH69,"-") -> -579.1 | AK69: =IFERROR(AI69/AH69,"-") -> 0 | AL69: ='2. ГПП-ОГХК'!BA46+'2. ГПП-ОГХК'!BA48+'2. ГПП-ОГХК'!BA50 -> 805.5 | AM69: ='2. ГПП-ОГХК'!BC46+'2. ГПП-ОГХК'!BC48+'2. ГПП-ОГХК'!BC50 -> 0 | AN69: =IFERROR(AM69-AL69,"-") -> -805.5 | AO69: =IFERROR(AM69/AL69,"-") -> 0 | AP69: ='2. ГПП-ОГХК'!BG46+'2. ГПП-ОГХК'!BG48+'2. ГПП-ОГХК'!BG50 -> 771 | AQ69: ='2. ГПП-ОГХК'!BI46+'2. ГПП-ОГХК'!BI48+'2. ГПП-ОГХК'!BI50 -> 0 | AR69: =IFERROR(AQ69-AP69,"-") -> -771 | AS69: =IFERROR(AQ69/AP69,"-") -> 0 | AT69: =AX69+BB69+BF69 -> 2392.7 | AU69: =AY69+BC69+BG69 -> 0 | AV69: =IFERROR(AU69-AT69,"-") -> -2392.7 | AW69: =IFERROR(AU69/AT69,"-") -> 0 | AX69: ='2. ГПП-ОГХК'!BS46+'2. ГПП-ОГХК'!BS48+'2. ГПП-ОГХК'!BS50 -> 820.3 | AY69: ='2. ГПП-ОГХК'!BU46+'2. ГПП-ОГХК'!BU48+'2. ГПП-ОГХК'!BU50 -> 0 | AZ69: =IFERROR(AY69-AX69,"-") -> -820.3 | BA69: =IFERROR(AY69/AX69,"-") -> 0 | BB69: ='2. ГПП-ОГХК'!BY46+'2. ГПП-ОГХК'!BY48+'2. ГПП-ОГХК'!BY50 -> 820.6 | BC69: ='2. ГПП-ОГХК'!CA46+'2. ГПП-ОГХК'!CA48+'2. ГПП-ОГХК'!CA50 -> 0 | BD69: =IFERROR(BC69-BB69,"-") -> -820.6 | BE69: =IFERROR(BC69/BB69,"-") -> 0 | BF69: ='2. ГПП-ОГХК'!CE46+'2. ГПП-ОГХК'!CE48+'2. ГПП-ОГХК'!CE50 -> 751.8 | BG69: ='2. ГПП-ОГХК'!CG46+'2. ГПП-ОГХК'!CG48+'2. ГПП-ОГХК'!CG50 -> 0 | BH69: =IFERROR(BG69-BF69,"-") -> -751.8 | BI69: =IFERROR(BG69/BF69,"-") -> 0 | BJ69: =BN69+BR69+BV69 -> 2999.6 | BK69: =BO69+BS69+BW69 -> 0 | BL69: =IFERROR(BK69-BJ69,"-") -> -2999.6 | BM69: =IFERROR(BK69/BJ69,"-") -> 0 | BN69: ='2. ГПП-ОГХК'!CQ46+'2. ГПП-ОГХК'!CQ48+'2. ГПП-ОГХК'!CQ50 -> 1011.7 | BO69: ='2. ГПП-ОГХК'!CS46+'2. ГПП-ОГХК'!CS48+'2. ГПП-ОГХК'!CS50 -> 0 | BP69: =IFERROR(BO69-BN69,"-") -> -1011.7 | BQ69: =IFERROR(BO69/BN69,"-") -> 0 | BR69: ='2. ГПП-ОГХК'!CW46+'2. ГПП-ОГХК'!CW48+'2. ГПП-ОГХК'!CW50 -> 978 | BS69: ='2. ГПП-ОГХК'!CY46+'2. ГПП-ОГХК'!CY48+'2. ГПП-ОГХК'!CY50 -> 0 | BT69: =IFERROR(BS69-BR69,"-") -> -978 | BU69: =IFERROR(BS69/BR69,"-") -> 0 | BV69: ='2. ГПП-ОГХК'!DC46+'2. ГПП-ОГХК'!DC48+'2. ГПП-ОГХК'!DC50 -> 1009.9 | BW69: ='2. ГПП-ОГХК'!DE46+'2. ГПП-ОГХК'!DE48+'2. ГПП-ОГХК'!DE50 -> 0 | BX69: =IFERROR(BW69-BV69,"-") -> -1009.9 | BY69: =IFERROR(BW69/BV69,"-") -> 0
C70: Газпром переработка | G70: 2_100332054+2_100332056+2_100335131 | I70: млн куб.м. | J70: =N70+AD70+AT70+BJ70 -> 10484.2 | K70: =O70+AE70+AU70+BK70 -> 0 | L70: =IFERROR(K70-J70,"-") -> -10484.2 | M70: =IFERROR(K70/J70,"-") -> 0 | N70: =R70+V70+Z70 -> 2936.3 | O70: =S70+W70+AA70 -> 0 | P70: =IFERROR(O70-N70,"-") -> -2936.3 | Q70: =IFERROR(O70/N70,"-") -> 0 | R70: ='2. ГПП-ОГХК'!W46+'2. ГПП-ОГХК'!W48+'2. ГПП-ОГХК'!W50 -> 1018.1 | S70: ='2. ГПП-ОГХК'!Y46+'2. ГПП-ОГХК'!Y48+'2. ГПП-ОГХК'!Y50 -> 0 | T70: =IFERROR(S70-R70,"-") -> -1018.1 | U70: =IFERROR(S70/R70,"-") -> 0 | V70: ='2. ГПП-ОГХК'!AC46+'2. ГПП-ОГХК'!AC48+'2. ГПП-ОГХК'!AC50 -> 919.4 | W70: ='2. ГПП-ОГХК'!AE46+'2. ГПП-ОГХК'!AE48+'2. ГПП-ОГХК'!AE50 -> 0 | X70: =IFERROR(W70-V70,"-") -> -919.4 | Y70: =IFERROR(W70/V70,"-") -> 0 | Z70: ='2. ГПП-ОГХК'!AI46+'2. ГПП-ОГХК'!AI48+'2. ГПП-ОГХК'!AI50 -> 998.8 | AA70: ='2. ГПП-ОГХК'!AK46+'2. ГПП-ОГХК'!AK48+'2. ГПП-ОГХК'!AK50 -> 0 | AB70: =IFERROR(AA70-Z70,"-") -> -998.8 | AC70: =IFERROR(AA70/Z70,"-") -> 0 | AD70: =AH70+AL70+AP70 -> 2155.6 | AE70: =AI70+AM70+AQ70 -> 0 | AF70: =IFERROR(AE70-AD70,"-") -> -2155.6 | AG70: =IFERROR(AE70/AD70,"-") -> 0 | AH70: ='2. ГПП-ОГХК'!AU46+'2. ГПП-ОГХК'!AU48+'2. ГПП-ОГХК'!AU50 -> 579.1 | AI70: ='2. ГПП-ОГХК'!AW46+'2. ГПП-ОГХК'!AW48+'2. ГПП-ОГХК'!AW50 -> 0 | AJ70: =IFERROR(AI70-AH70,"-") -> -579.1 | AK70: =IFERROR(AI70/AH70,"-") -> 0 | AL70: ='2. ГПП-ОГХК'!BA46+'2. ГПП-ОГХК'!BA48+'2. ГПП-ОГХК'!BA50 -> 805.5 | AM70: ='2. ГПП-ОГХК'!BC46+'2. ГПП-ОГХК'!BC48+'2. ГПП-ОГХК'!BC50 -> 0 | AN70: =IFERROR(AM70-AL70,"-") -> -805.5 | AO70: =IFERROR(AM70/AL70,"-") -> 0 | AP70: ='2. ГПП-ОГХК'!BG46+'2. ГПП-ОГХК'!BG48+'2. ГПП-ОГХК'!BG50 -> 771 | AQ70: ='2. ГПП-ОГХК'!BI46+'2. ГПП-ОГХК'!BI48+'2. ГПП-ОГХК'!BI50 -> 0 | AR70: =IFERROR(AQ70-AP70,"-") -> -771 | AS70: =IFERROR(AQ70/AP70,"-") -> 0 | AT70: =AX70+BB70+BF70 -> 2392.7 | AU70: =AY70+BC70+BG70 -> 0 | AV70: =IFERROR(AU70-AT70,"-") -> -2392.7 | AW70: =IFERROR(AU70/AT70,"-") -> 0 | AX70: ='2. ГПП-ОГХК'!BS46+'2. ГПП-ОГХК'!BS48+'2. ГПП-ОГХК'!BS50 -> 820.3 | AY70: ='2. ГПП-ОГХК'!BU46+'2. ГПП-ОГХК'!BU48+'2. ГПП-ОГХК'!BU50 -> 0 | AZ70: =IFERROR(AY70-AX70,"-") -> -820.3 | BA70: =IFERROR(AY70/AX70,"-") -> 0 | BB70: ='2. ГПП-ОГХК'!BY46+'2. ГПП-ОГХК'!BY48+'2. ГПП-ОГХК'!BY50 -> 820.6 | BC70: ='2. ГПП-ОГХК'!CA46+'2. ГПП-ОГХК'!CA48+'2. ГПП-ОГХК'!CA50 -> 0 | BD70: =IFERROR(BC70-BB70,"-") -> -820.6 | BE70: =IFERROR(BC70/BB70,"-") -> 0 | BF70: ='2. ГПП-ОГХК'!CE46+'2. ГПП-ОГХК'!CE48+'2. ГПП-ОГХК'!CE50 -> 751.8 | BG70: ='2. ГПП-ОГХК'!CG46+'2. ГПП-ОГХК'!CG48+'2. ГПП-ОГХК'!CG50 -> 0 | BH70: =IFERROR(BG70-BF70,"-") -> -751.8 | BI70: =IFERROR(BG70/BF70,"-") -> 0 | BJ70: =BN70+BR70+BV70 -> 2999.6 | BK70: =BO70+BS70+BW70 -> 0 | BL70: =IFERROR(BK70-BJ70,"-") -> -2999.6 | BM70: =IFERROR(BK70/BJ70,"-") -> 0 | BN70: ='2. ГПП-ОГХК'!CQ46+'2. ГПП-ОГХК'!CQ48+'2. ГПП-ОГХК'!CQ50 -> 1011.7 | BO70: ='2. ГПП-ОГХК'!CS46+'2. ГПП-ОГХК'!CS48+'2. ГПП-ОГХК'!CS50 -> 0 | BP70: =IFERROR(BO70-BN70,"-") -> -1011.7 | BQ70: =IFERROR(BO70/BN70,"-") -> 0 | BR70: ='2. ГПП-ОГХК'!CW46+'2. ГПП-ОГХК'!CW48+'2. ГПП-ОГХК'!CW50 -> 978 | BS70: ='2. ГПП-ОГХК'!CY46+'2. ГПП-ОГХК'!CY48+'2. ГПП-ОГХК'!CY50 -> 0 | BT70: =IFERROR(BS70-BR70,"-") -> -978 | BU70: =IFERROR(BS70/BR70,"-") -> 0 | BV70: ='2. ГПП-ОГХК'!DC46+'2. ГПП-ОГХК'!DC48+'2. ГПП-ОГХК'!DC50 -> 1009.9 | BW70: ='2. ГПП-ОГХК'!DE46+'2. ГПП-ОГХК'!DE48+'2. ГПП-ОГХК'!DE50 -> 0 | BX70: =IFERROR(BW70-BV70,"-") -> -1009.9 | BY70: =IFERROR(BW70/BV70,"-") -> 0
C71: Оренбургский ГЗ | G71: 2_100332054+2_100332056+2_100335131 | I71: млн куб.м. | J71: =N71+AD71+AT71+BJ71 -> 10484.2 | K71: =O71+AE71+AU71+BK71 -> 0 | L71: =IFERROR(K71-J71,"-") -> -10484.2 | M71: =IFERROR(K71/J71,"-") -> 0 | N71: =R71+V71+Z71 -> 2936.3 | O71: =S71+W71+AA71 -> 0 | P71: =IFERROR(O71-N71,"-") -> -2936.3 | Q71: =IFERROR(O71/N71,"-") -> 0 | R71: ='2. ГПП-ОГХК'!W46+'2. ГПП-ОГХК'!W48+'2. ГПП-ОГХК'!W50 -> 1018.1 | S71: ='2. ГПП-ОГХК'!Y46+'2. ГПП-ОГХК'!Y48+'2. ГПП-ОГХК'!Y50 -> 0 | T71: =IFERROR(S71-R71,"-") -> -1018.1 | U71: =IFERROR(S71/R71,"-") -> 0 | V71: ='2. ГПП-ОГХК'!AC46+'2. ГПП-ОГХК'!AC48+'2. ГПП-ОГХК'!AC50 -> 919.4 | W71: ='2. ГПП-ОГХК'!AE46+'2. ГПП-ОГХК'!AE48+'2. ГПП-ОГХК'!AE50 -> 0 | X71: =IFERROR(W71-V71,"-") -> -919.4 | Y71: =IFERROR(W71/V71,"-") -> 0 | Z71: ='2. ГПП-ОГХК'!AI46+'2. ГПП-ОГХК'!AI48+'2. ГПП-ОГХК'!AI50 -> 998.8 | AA71: ='2. ГПП-ОГХК'!AK46+'2. ГПП-ОГХК'!AK48+'2. ГПП-ОГХК'!AK50 -> 0 | AB71: =IFERROR(AA71-Z71,"-") -> -998.8 | AC71: =IFERROR(AA71/Z71,"-") -> 0 | AD71: =AH71+AL71+AP71 -> 2155.6 | AE71: =AI71+AM71+AQ71 -> 0 | AF71: =IFERROR(AE71-AD71,"-") -> -2155.6 | AG71: =IFERROR(AE71/AD71,"-") -> 0 | AH71: ='2. ГПП-ОГХК'!AU46+'2. ГПП-ОГХК'!AU48+'2. ГПП-ОГХК'!AU50 -> 579.1 | AI71: ='2. ГПП-ОГХК'!AW46+'2. ГПП-ОГХК'!AW48+'2. ГПП-ОГХК'!AW50 -> 0 | AJ71: =IFERROR(AI71-AH71,"-") -> -579.1 | AK71: =IFERROR(AI71/AH71,"-") -> 0 | AL71: ='2. ГПП-ОГХК'!BA46+'2. ГПП-ОГХК'!BA48+'2. ГПП-ОГХК'!BA50 -> 805.5 | AM71: ='2. ГПП-ОГХК'!BC46+'2. ГПП-ОГХК'!BC48+'2. ГПП-ОГХК'!BC50 -> 0 | AN71: =IFERROR(AM71-AL71,"-") -> -805.5 | AO71: =IFERROR(AM71/AL71,"-") -> 0 | AP71: ='2. ГПП-ОГХК'!BG46+'2. ГПП-ОГХК'!BG48+'2. ГПП-ОГХК'!BG50 -> 771 | AQ71: ='2. ГПП-ОГХК'!BI46+'2. ГПП-ОГХК'!BI48+'2. ГПП-ОГХК'!BI50 -> 0 | AR71: =IFERROR(AQ71-AP71,"-") -> -771 | AS71: =IFERROR(AQ71/AP71,"-") -> 0 | AT71: =AX71+BB71+BF71 -> 2392.7 | AU71: =AY71+BC71+BG71 -> 0 | AV71: =IFERROR(AU71-AT71,"-") -> -2392.7 | AW71: =IFERROR(AU71/AT71,"-") -> 0 | AX71: ='2. ГПП-ОГХК'!BS46+'2. ГПП-ОГХК'!BS48+'2. ГПП-ОГХК'!BS50 -> 820.3 | AY71: ='2. ГПП-ОГХК'!BU46+'2. ГПП-ОГХК'!BU48+'2. ГПП-ОГХК'!BU50 -> 0 | AZ71: =IFERROR(AY71-AX71,"-") -> -820.3 | BA71: =IFERROR(AY71/AX71,"-") -> 0 | BB71: ='2. ГПП-ОГХК'!BY46+'2. ГПП-ОГХК'!BY48+'2. ГПП-ОГХК'!BY50 -> 820.6 | BC71: ='2. ГПП-ОГХК'!CA46+'2. ГПП-ОГХК'!CA48+'2. ГПП-ОГХК'!CA50 -> 0 | BD71: =IFERROR(BC71-BB71,"-") -> -820.6 | BE71: =IFERROR(BC71/BB71,"-") -> 0 | BF71: ='2. ГПП-ОГХК'!CE46+'2. ГПП-ОГХК'!CE48+'2. ГПП-ОГХК'!CE50 -> 751.8 | BG71: ='2. ГПП-ОГХК'!CG46+'2. ГПП-ОГХК'!CG48+'2. ГПП-ОГХК'!CG50 -> 0 | BH71: =IFERROR(BG71-BF71,"-") -> -751.8 | BI71: =IFERROR(BG71/BF71,"-") -> 0 | BJ71: =BN71+BR71+BV71 -> 2999.6 | BK71: =BO71+BS71+BW71 -> 0 | BL71: =IFERROR(BK71-BJ71,"-") -> -2999.6 | BM71: =IFERROR(BK71/BJ71,"-") -> 0 | BN71: ='2. ГПП-ОГХК'!CQ46+'2. ГПП-ОГХК'!CQ48+'2. ГПП-ОГХК'!CQ50 -> 1011.7 | BO71: ='2. ГПП-ОГХК'!CS46+'2. ГПП-ОГХК'!CS48+'2. ГПП-ОГХК'!CS50 -> 0 | BP71: =IFERROR(BO71-BN71,"-") -> -1011.7 | BQ71: =IFERROR(BO71/BN71,"-") -> 0 | BR71: ='2. ГПП-ОГХК'!CW46+'2. ГПП-ОГХК'!CW48+'2. ГПП-ОГХК'!CW50 -> 978 | BS71: ='2. ГПП-ОГХК'!CY46+'2. ГПП-ОГХК'!CY48+'2. ГПП-ОГХК'!CY50 -> 0 | BT71: =IFERROR(BS71-BR71,"-") -> -978 | BU71: =IFERROR(BS71/BR71,"-") -> 0 | BV71: ='2. ГПП-ОГХК'!DC46+'2. ГПП-ОГХК'!DC48+'2. ГПП-ОГХК'!DC50 -> 1009.9 | BW71: ='2. ГПП-ОГХК'!DE46+'2. ГПП-ОГХК'!DE48+'2. ГПП-ОГХК'!DE50 -> 0 | BX71: =IFERROR(BW71-BV71,"-") -> -1009.9 | BY71: =IFERROR(BW71/BV71,"-") -> 0
C72: Газпром добыча Оренбург | G72: 2_100332054 | I72: млн куб.м. | J72: =N72+AD72+AT72+BJ72 -> 7921.8 | K72: =O72+AE72+AU72+BK72 -> 0 | L72: =IFERROR(K72-J72,"-") -> -7921.8 | M72: =IFERROR(K72/J72,"-") -> 0 | N72: =R72+V72+Z72 -> 2195.7 | O72: =S72+W72+AA72 -> 0 | P72: =IFERROR(O72-N72,"-") -> -2195.7 | Q72: =IFERROR(O72/N72,"-") -> 0 | R72: ='2. ГПП-ОГХК'!W46 -> 756.9 | S72: ='2. ГПП-ОГХК'!Y46 -> 0 | T72: =IFERROR(S72-R72,"-") -> -756.9 | U72: =IFERROR(S72/R72,"-") -> 0 | V72: ='2. ГПП-ОГХК'!AC46 -> 683.5 | W72: ='2. ГПП-ОГХК'!AE46 -> 0 | X72: =IFERROR(W72-V72,"-") -> -683.5 | Y72: =IFERROR(W72/V72,"-") -> 0 | Z72: ='2. ГПП-ОГХК'!AI46 -> 755.3 | AA72: ='2. ГПП-ОГХК'!AK46 -> 0 | AB72: =IFERROR(AA72-Z72,"-") -> -755.3 | AC72: =IFERROR(AA72/Z72,"-") -> 0 | AD72: =AH72+AL72+AP72 -> 1670 | AE72: =AI72+AM72+AQ72 -> 0 | AF72: =IFERROR(AE72-AD72,"-") -> -1670 | AG72: =IFERROR(AE72/AD72,"-") -> 0 | AH72: ='2. ГПП-ОГХК'!AU46 -> 410 | AI72: ='2. ГПП-ОГХК'!AW46 -> 0 | AJ72: =IFERROR(AI72-AH72,"-") -> -410 | AK72: =IFERROR(AI72/AH72,"-") -> 0 | AL72: ='2. ГПП-ОГХК'!BA46 -> 644.6 | AM72: ='2. ГПП-ОГХК'!BC46 -> 0 | AN72: =IFERROR(AM72-AL72,"-") -> -644.6 | AO72: =IFERROR(AM72/AL72,"-") -> 0 | AP72: ='2. ГПП-ОГХК'!BG46 -> 615.4 | AQ72: ='2. ГПП-ОГХК'!BI46 -> 0 | AR72: =IFERROR(AQ72-AP72,"-") -> -615.4 | AS72: =IFERROR(AQ72/AP72,"-") -> 0 | AT72: =AX72+BB72+BF72 -> 1834.6 | AU72: =AY72+BC72+BG72 -> 0 | AV72: =IFERROR(AU72-AT72,"-") -> -1834.6 | AW72: =IFERROR(AU72/AT72,"-") -> 0 | AX72: ='2. ГПП-ОГХК'!BS46 -> 659.4 | AY72: ='2. ГПП-ОГХК'!BU46 -> 0 | AZ72: =IFERROR(AY72-AX72,"-") -> -659.4 | BA72: =IFERROR(AY72/AX72,"-") -> 0 | BB72: ='2. ГПП-ОГХК'!BY46 -> 659.7 | BC72: ='2. ГПП-ОГХК'!CA46 -> 0 | BD72: =IFERROR(BC72-BB72,"-") -> -659.7 | BE72: =IFERROR(BC72/BB72,"-") -> 0 | BF72: ='2. ГПП-ОГХК'!CE46 -> 515.5 | BG72: ='2. ГПП-ОГХК'!CG46 -> 0 | BH72: =IFERROR(BG72-BF72,"-") -> -515.5 | BI72: =IFERROR(BG72/BF72,"-") -> 0 | BJ72: =BN72+BR72+BV72 -> 2221.5 | BK72: =BO72+BS72+BW72 -> 0 | BL72: =IFERROR(BK72-BJ72,"-") -> -2221.5 | BM72: =IFERROR(BK72/BJ72,"-") -> 0 | BN72: ='2. ГПП-ОГХК'!CQ46 -> 749.5 | BO72: ='2. ГПП-ОГХК'!CS46 -> 0 | BP72: =IFERROR(BO72-BN72,"-") -> -749.5 | BQ72: =IFERROR(BO72/BN72,"-") -> 0 | BR72: ='2. ГПП-ОГХК'!CW46 -> 724.3 | BS72: ='2. ГПП-ОГХК'!CY46 -> 0 | BT72: =IFERROR(BS72-BR72,"-") -> -724.3 | BU72: =IFERROR(BS72/BR72,"-") -> 0 | BV72: ='2. ГПП-ОГХК'!DC46 -> 747.7 | BW72: ='2. ГПП-ОГХК'!DE46 -> 0 | BX72: =IFERROR(BW72-BV72,"-") -> -747.7 | BY72: =IFERROR(BW72/BV72,"-") -> 0
C73: Газпром нефть | G73: 2_100332056 | I73: млн куб.м. | J73: =N73+AD73+AT73+BJ73 -> 2384.6 | K73: =O73+AE73+AU73+BK73 -> 0 | L73: =IFERROR(K73-J73,"-") -> -2384.6 | M73: =IFERROR(K73/J73,"-") -> 0 | N73: =R73+V73+Z73 -> 696.1 | O73: =S73+W73+AA73 -> 0 | P73: =IFERROR(O73-N73,"-") -> -696.1 | Q73: =IFERROR(O73/N73,"-") -> 0 | R73: ='2. ГПП-ОГХК'!W48 -> 245.8 | S73: ='2. ГПП-ОГХК'!Y48 -> 0 | T73: =IFERROR(S73-R73,"-") -> -245.8 | U73: =IFERROR(S73/R73,"-") -> 0 | V73: ='2. ГПП-ОГХК'!AC48 -> 222 | W73: ='2. ГПП-ОГХК'!AE48 -> 0 | X73: =IFERROR(W73-V73,"-") -> -222 | Y73: =IFERROR(W73/V73,"-") -> 0 | Z73: ='2. ГПП-ОГХК'!AI48 -> 228.3 | AA73: ='2. ГПП-ОГХК'!AK48 -> 0 | AB73: =IFERROR(AA73-Z73,"-") -> -228.3 | AC73: =IFERROR(AA73/Z73,"-") -> 0 | AD73: =AH73+AL73+AP73 -> 443 | AE73: =AI73+AM73+AQ73 -> 0 | AF73: =IFERROR(AE73-AD73,"-") -> -443 | AG73: =IFERROR(AE73/AD73,"-") -> 0 | AH73: ='2. ГПП-ОГХК'!AU48 -> 156.9 | AI73: ='2. ГПП-ОГХК'!AW48 -> 0 | AJ73: =IFERROR(AI73-AH73,"-") -> -156.9 | AK73: =IFERROR(AI73/AH73,"-") -> 0 | AL73: ='2. ГПП-ОГХК'!BA48 -> 145.4 | AM73: ='2. ГПП-ОГХК'!BC48 -> 0 | AN73: =IFERROR(AM73-AL73,"-") -> -145.4 | AO73: =IFERROR(AM73/AL73,"-") -> 0 | AP73: ='2. ГПП-ОГХК'!BG48 -> 140.7 | AQ73: ='2. ГПП-ОГХК'!BI48 -> 0 | AR73: =IFERROR(AQ73-AP73,"-") -> -140.7 | AS73: =IFERROR(AQ73/AP73,"-") -> 0 | AT73: =AX73+BB73+BF73 -> 512.2 | AU73: =AY73+BC73+BG73 -> 0 | AV73: =IFERROR(AU73-AT73,"-") -> -512.2 | AW73: =IFERROR(AU73/AT73,"-") -> 0 | AX73: ='2. ГПП-ОГХК'!BS48 -> 145.4 | AY73: ='2. ГПП-ОГХК'!BU48 -> 0 | AZ73: =IFERROR(AY73-AX73,"-") -> -145.4 | BA73: =IFERROR(AY73/AX73,"-") -> 0 | BB73: ='2. ГПП-ОГХК'!BY48 -> 145.4 | BC73: ='2. ГПП-ОГХК'!CA48 -> 0 | BD73: =IFERROR(BC73-BB73,"-") -> -145.4 | BE73: =IFERROR(BC73/BB73,"-") -> 0 | BF73: ='2. ГПП-ОГХК'!CE48 -> 221.4 | BG73: ='2. ГПП-ОГХК'!CG48 -> 0 | BH73: =IFERROR(BG73-BF73,"-") -> -221.4 | BI73: =IFERROR(BG73/BF73,"-") -> 0 | BJ73: =BN73+BR73+BV73 -> 733.3 | BK73: =BO73+BS73+BW73 -> 0 | BL73: =IFERROR(BK73-BJ73,"-") -> -733.3 | BM73: =IFERROR(BK73/BJ73,"-") -> 0 | BN73: ='2. ГПП-ОГХК'!CQ48 -> 247 | BO73: ='2. ГПП-ОГХК'!CS48 -> 0 | BP73: =IFERROR(BO73-BN73,"-") -> -247 | BQ73: =IFERROR(BO73/BN73,"-") -> 0 | BR73: ='2. ГПП-ОГХК'!CW48 -> 239.1 | BS73: ='2. ГПП-ОГХК'!CY48 -> 0 | BT73: =IFERROR(BS73-BR73,"-") -> -239.1 | BU73: =IFERROR(BS73/BR73,"-") -> 0 | BV73: ='2. ГПП-ОГХК'!DC48 -> 247.2 | BW73: ='2. ГПП-ОГХК'!DE48 -> 0 | BX73: =IFERROR(BW73-BV73,"-") -> -247.2 | BY73: =IFERROR(BW73/BV73,"-") -> 0
C74: прочие поставщики (ГПНЗ, УНГП, и.т.д.) | G74: 2_100335131 | I74: млн куб.м. | J74: =N74+AD74+AT74+BJ74 -> 177.8 | K74: =O74+AE74+AU74+BK74 -> 0 | L74: =IFERROR(K74-J74,"-") -> -177.8 | M74: =IFERROR(K74/J74,"-") -> 0 | N74: =R74+V74+Z74 -> 44.5 | O74: =S74+W74+AA74 -> 0 | P74: =IFERROR(O74-N74,"-") -> -44.5 | Q74: =IFERROR(O74/N74,"-") -> 0 | R74: ='2. ГПП-ОГХК'!W50 -> 15.4 | S74: ='2. ГПП-ОГХК'!Y50 -> 0 | T74: =IFERROR(S74-R74,"-") -> -15.4 | U74: =IFERROR(S74/R74,"-") -> 0 | V74: ='2. ГПП-ОГХК'!AC50 -> 13.9 | W74: ='2. ГПП-ОГХК'!AE50 -> 0 | X74: =IFERROR(W74-V74,"-") -> -13.9 | Y74: =IFERROR(W74/V74,"-") -> 0 | Z74: ='2. ГПП-ОГХК'!AI50 -> 15.2 | AA74: ='2. ГПП-ОГХК'!AK50 -> 0 | AB74: =IFERROR(AA74-Z74,"-") -> -15.2 | AC74: =IFERROR(AA74/Z74,"-") -> 0 | AD74: =AH74+AL74+AP74 -> 42.6 | AE74: =AI74+AM74+AQ74 -> 0 | AF74: =IFERROR(AE74-AD74,"-") -> -42.6 | AG74: =IFERROR(AE74/AD74,"-") -> 0 | AH74: ='2. ГПП-ОГХК'!AU50 -> 12.2 | AI74: ='2. ГПП-ОГХК'!AW50 -> 0 | AJ74: =IFERROR(AI74-AH74,"-") -> -12.2 | AK74: =IFERROR(AI74/AH74,"-") -> 0 | AL74: ='2. ГПП-ОГХК'!BA50 -> 15.5 | AM74: ='2. ГПП-ОГХК'!BC50 -> 0 | AN74: =IFERROR(AM74-AL74,"-") -> -15.5 | AO74: =IFERROR(AM74/AL74,"-") -> 0 | AP74: ='2. ГПП-ОГХК'!BG50 -> 14.9 | AQ74: ='2. ГПП-ОГХК'!BI50 -> 0 | AR74: =IFERROR(AQ74-AP74,"-") -> -14.9 | AS74: =IFERROR(AQ74/AP74,"-") -> 0 | AT74: =AX74+BB74+BF74 -> 45.9 | AU74: =AY74+BC74+BG74 -> 0 | AV74: =IFERROR(AU74-AT74,"-") -> -45.9 | AW74: =IFERROR(AU74/AT74,"-") -> 0 | AX74: ='2. ГПП-ОГХК'!BS50 -> 15.5 | AY74: ='2. ГПП-ОГХК'!BU50 -> 0 | AZ74: =IFERROR(AY74-AX74,"-") -> -15.5 | BA74: =IFERROR(AY74/AX74,"-") -> 0 | BB74: ='2. ГПП-ОГХК'!BY50 -> 15.5 | BC74: ='2. ГПП-ОГХК'!CA50 -> 0 | BD74: =IFERROR(BC74-BB74,"-") -> -15.5 | BE74: =IFERROR(BC74/BB74,"-") -> 0 | BF74: ='2. ГПП-ОГХК'!CE50 -> 14.9 | BG74: ='2. ГПП-ОГХК'!CG50 -> 0 | BH74: =IFERROR(BG74-BF74,"-") -> -14.9 | BI74: =IFERROR(BG74/BF74,"-") -> 0 | BJ74: =BN74+BR74+BV74 -> 44.8 | BK74: =BO74+BS74+BW74 -> 0 | BL74: =IFERROR(BK74-BJ74,"-") -> -44.8 | BM74: =IFERROR(BK74/BJ74,"-") -> 0 | BN74: ='2. ГПП-ОГХК'!CQ50 -> 15.2 | BO74: ='2. ГПП-ОГХК'!CS50 -> 0 | BP74: =IFERROR(BO74-BN74,"-") -> -15.2 | BQ74: =IFERROR(BO74/BN74,"-") -> 0 | BR74: ='2. ГПП-ОГХК'!CW50 -> 14.6 | BS74: ='2. ГПП-ОГХК'!CY50 -> 0 | BT74: =IFERROR(BS74-BR74,"-") -> -14.6 | BU74: =IFERROR(BS74/BR74,"-") -> 0 | BV74: ='2. ГПП-ОГХК'!DC50 -> 15 | BW74: ='2. ГПП-ОГХК'!DE50 -> 0 | BX74: =IFERROR(BW74-BV74,"-") -> -15 | BY74: =IFERROR(BW74/BV74,"-") -> 0
B75: 4. | C75: Переработка нестабильного газового конденсата и нефти | G75: 1_100331985+2_100332062+2_100335697+2_100332061+3_100330017+4_100333682+4_100331828+4_100331835+4_100331804+4_100335033+7_100330595+12_100330735+0+13_100330000+10_100330715+10_100330861+10_100330718+11_100330015+9_100330671+2_100332068+2_100332947+2_100332066+2_100332067+2_100332069+3_100330196+4_100331838+4_100335093+4_100333678+9_100330672 | I75: тыс.т | J75: =N75+AD75+AT75+BJ75 -> 20095.7 | K75: =O75+AE75+AU75+BK75 -> 0 | L75: =IFERROR(K75-J75,"-") -> -20095.7 | M75: =IFERROR(K75/J75,"-") -> 0 | N75: =R75+V75+Z75 -> 5245.9 | O75: =S75+W75+AA75 -> 0 | P75: =IFERROR(O75-N75,"-") -> -5245.9 | Q75: =IFERROR(O75/N75,"-") -> 0 | R75: ='1. ГПП-АГПЗ+'!W23+'2. ГПП-ОГХК'!W56+'2. ГПП-ОГХК'!W57+'2. ГПП-ОГХК'!W54+'3. ГПП-СГПЗ'!W23+'4. ГПП-УЗПКТ-СЗСК'!W40+'4. ГПП-УЗПКТ-СЗСК'!W54+'4. ГПП-УЗПКТ-СЗСК'!W71+'4. ГПП-УЗПКТ-СЗСК'!W18+'4. ГПП-УЗПКТ-СЗСК'!W32+'7. ГД Ямбург'!W28+'12. ГД Иркутск'!W11+0+0+'10. ГД Ноябрьск'!W15+'10. ГД Ноябрьск'!W51+'10. ГД Ноябрьск'!W18+'11. ГД Надым'!W11+'9. ГД Краснодар'!W29+'2. ГПП-ОГХК'!W63+'2. ГПП-ОГХК'!W64+'2. ГПП-ОГХК'!W60+'2. ГПП-ОГХК'!W62+'2. ГПП-ОГХК'!W65+'3. ГПП-СГПЗ'!W24+'4. ГПП-УЗПКТ-СЗСК'!W209+'4. ГПП-УЗПКТ-СЗСК'!W199+'4. ГПП-УЗПКТ-СЗСК'!W47+'9. ГД Краснодар'!W30 -> 1822 | S75: ='1. ГПП-АГПЗ+'!Y23+'2. ГПП-ОГХК'!Y56+'2. ГПП-ОГХК'!Y57+'2. ГПП-ОГХК'!Y54+'3. ГПП-СГПЗ'!Y23+'4. ГПП-УЗПКТ-СЗСК'!Y40+'4. ГПП-УЗПКТ-СЗСК'!Y54+'4. ГПП-УЗПКТ-СЗСК'!Y71+'4. ГПП-УЗПКТ-СЗСК'!Y18+'4. ГПП-УЗПКТ-СЗСК'!Y32+'7. ГД Ямбург'!Y28+'12. ГД Иркутск'!Y11+0+0+'10. ГД Ноябрьск'!Y15+'10. ГД Ноябрьск'!Y51+'10. ГД Ноябрьск'!Y18+'11. ГД Надым'!Y11+'9. ГД Краснодар'!Y29+'2. ГПП-ОГХК'!Y63+'2. ГПП-ОГХК'!Y64+'2. ГПП-ОГХК'!Y60+'2. ГПП-ОГХК'!Y62+'2. ГПП-ОГХК'!Y65+'3. ГПП-СГПЗ'!Y24+'4. ГПП-УЗПКТ-СЗСК'!Y209+'4. ГПП-УЗПКТ-СЗСК'!Y199+'4. ГПП-УЗПКТ-СЗСК'!Y47+'9. ГД Краснодар'!Y30 -> 0 | T75: =IFERROR(S75-R75,"-") -> -1822 | U75: =IFERROR(S75/R75,"-") -> 0 | V75: ='1. ГПП-АГПЗ+'!AC23+'2. ГПП-ОГХК'!AC56+'2. ГПП-ОГХК'!AC57+'2. ГПП-ОГХК'!AC54+'3. ГПП-СГПЗ'!AC23+'4. ГПП-УЗПКТ-СЗСК'!AC40+'4. ГПП-УЗПКТ-СЗСК'!AC54+'4. ГПП-УЗПКТ-СЗСК'!AC71+'4. ГПП-УЗПКТ-СЗСК'!AC18+'4. ГПП-УЗПКТ-СЗСК'!AC32+'7. ГД Ямбург'!AC28+'12. ГД Иркутск'!AC11+0+0+'10. ГД Ноябрьск'!AC15+'10. ГД Ноябрьск'!AC51+'10. ГД Ноябрьск'!AC18+'11. ГД Надым'!AC11+'9. ГД Краснодар'!AC29+'2. ГПП-ОГХК'!AC63+'2. ГПП-ОГХК'!AC64+'2. ГПП-ОГХК'!AC60+'2. ГПП-ОГХК'!AC62+'2. ГПП-ОГХК'!AC65+'3. ГПП-СГПЗ'!AC24+'4. ГПП-УЗПКТ-СЗСК'!AC209+'4. ГПП-УЗПКТ-СЗСК'!AC199+'4. ГПП-УЗПКТ-СЗСК'!AC47+'9. ГД Краснодар'!AC30 -> 1640 | W75: ='1. ГПП-АГПЗ+'!AE23+'2. ГПП-ОГХК'!AE56+'2. ГПП-ОГХК'!AE57+'2. ГПП-ОГХК'!AE54+'3. ГПП-СГПЗ'!AE23+'4. ГПП-УЗПКТ-СЗСК'!AE40+'4. ГПП-УЗПКТ-СЗСК'!AE54+'4. ГПП-УЗПКТ-СЗСК'!AE71+'4. ГПП-УЗПКТ-СЗСК'!AE18+'4. ГПП-УЗПКТ-СЗСК'!AE32+'7. ГД Ямбург'!AE28+'12. ГД Иркутск'!AE11+0+0+'10. ГД Ноябрьск'!AE15+'10. ГД Ноябрьск'!AE51+'10. ГД Ноябрьск'!AE18+'11. ГД Надым'!AE11+'9. ГД Краснодар'!AE29+'2. ГПП-ОГХК'!AE63+'2. ГПП-ОГХК'!AE64+'2. ГПП-ОГХК'!AE60+'2. ГПП-ОГХК'!AE62+'2. ГПП-ОГХК'!AE65+'3. ГПП-СГПЗ'!AE24+'4. ГПП-УЗПКТ-СЗСК'!AE209+'4. ГПП-УЗПКТ-СЗСК'!AE199+'4. ГПП-УЗПКТ-СЗСК'!AE47+'9. ГД Краснодар'!AE30 -> 0 | X75: =IFERROR(W75-V75,"-") -> -1640 | Y75: =IFERROR(W75/V75,"-") -> 0 | Z75: ='1. ГПП-АГПЗ+'!AI23+'2. ГПП-ОГХК'!AI56+'2. ГПП-ОГХК'!AI57+'2. ГПП-ОГХК'!AI54+'3. ГПП-СГПЗ'!AI23+'4. ГПП-УЗПКТ-СЗСК'!AI40+'4. ГПП-УЗПКТ-СЗСК'!AI54+'4. ГПП-УЗПКТ-СЗСК'!AI71+'4. ГПП-УЗПКТ-СЗСК'!AI18+'4. ГПП-УЗПКТ-СЗСК'!AI32+'7. ГД Ямбург'!AI28+'12. ГД Иркутск'!AI11+0+0+'10. ГД Ноябрьск'!AI15+'10. ГД Ноябрьск'!AI51+'10. ГД Ноябрьск'!AI18+'11. ГД Надым'!AI11+'9. ГД Краснодар'!AI29+'2. ГПП-ОГХК'!AI63+'2. ГПП-ОГХК'!AI64+'2. ГПП-ОГХК'!AI60+'2. ГПП-ОГХК'!AI62+'2. ГПП-ОГХК'!AI65+'3. ГПП-СГПЗ'!AI24+'4. ГПП-УЗПКТ-СЗСК'!AI209+'4. ГПП-УЗПКТ-СЗСК'!AI199+'4. ГПП-УЗПКТ-СЗСК'!AI47+'9. ГД Краснодар'!AI30 -> 1783.9 | AA75: ='1. ГПП-АГПЗ+'!AK23+'2. ГПП-ОГХК'!AK56+'2. ГПП-ОГХК'!AK57+'2. ГПП-ОГХК'!AK54+'3. ГПП-СГПЗ'!AK23+'4. ГПП-УЗПКТ-СЗСК'!AK40+'4. ГПП-УЗПКТ-СЗСК'!AK54+'4. ГПП-УЗПКТ-СЗСК'!AK71+'4. ГПП-УЗПКТ-СЗСК'!AK18+'4. ГПП-УЗПКТ-СЗСК'!AK32+'7. ГД Ямбург'!AK28+'12. ГД Иркутск'!AK11+0+0+'10. ГД Ноябрьск'!AK15+'10. ГД Ноябрьск'!AK51+'10. ГД Ноябрьск'!AK18+'11. ГД Надым'!AK11+'9. ГД Краснодар'!AK29+'2. ГПП-ОГХК'!AK63+'2. ГПП-ОГХК'!AK64+'2. ГПП-ОГХК'!AK60+'2. ГПП-ОГХК'!AK62+'2. ГПП-ОГХК'!AK65+'3. ГПП-СГПЗ'!AK24+'4. ГПП-УЗПКТ-СЗСК'!AK209+'4. ГПП-УЗПКТ-СЗСК'!AK199+'4. ГПП-УЗПКТ-СЗСК'!AK47+'9. ГД Краснодар'!AK30 -> 0 | AB75: =IFERROR(AA75-Z75,"-") -> -1783.9 | AC75: =IFERROR(AA75/Z75,"-") -> 0 | AD75: =AH75+AL75+AP75 -> 4870 | AE75: =AI75+AM75+AQ75 -> 0 | AF75: =IFERROR(AE75-AD75,"-") -> -4870 | AG75: =IFERROR(AE75/AD75,"-") -> 0 | AH75: ='1. ГПП-АГПЗ+'!AU23+'2. ГПП-ОГХК'!AU56+'2. ГПП-ОГХК'!AU57+'2. ГПП-ОГХК'!AU54+'3. ГПП-СГПЗ'!AU23+'4. ГПП-УЗПКТ-СЗСК'!AU40+'4. ГПП-УЗПКТ-СЗСК'!AU54+'4. ГПП-УЗПКТ-СЗСК'!AU71+'4. ГПП-УЗПКТ-СЗСК'!AU18+'4. ГПП-УЗПКТ-СЗСК'!AU32+'7. ГД Ямбург'!AU28+'12. ГД Иркутск'!AU11+0+0+'10. ГД Ноябрьск'!AU15+'10. ГД Ноябрьск'!AU51+'10. ГД Ноябрьск'!AU18+'11. ГД Надым'!AU11+'9. ГД Краснодар'!AU29+'2. ГПП-ОГХК'!AU63+'2. ГПП-ОГХК'!AU64+'2. ГПП-ОГХК'!AU60+'2. ГПП-ОГХК'!AU62+'2. ГПП-ОГХК'!AU65+'3. ГПП-СГПЗ'!AU24+'4. ГПП-УЗПКТ-СЗСК'!AU209+'4. ГПП-УЗПКТ-СЗСК'!AU199+'4. ГПП-УЗПКТ-СЗСК'!AU47+'9. ГД Краснодар'!AU30 -> 1687.1 | AI75: ='1. ГПП-АГПЗ+'!AW23+'2. ГПП-ОГХК'!AW56+'2. ГПП-ОГХК'!AW57+'2. ГПП-ОГХК'!AW54+'3. ГПП-СГПЗ'!AW23+'4. ГПП-УЗПКТ-СЗСК'!AW40+'4. ГПП-УЗПКТ-СЗСК'!AW54+'4. ГПП-УЗПКТ-СЗСК'!AW71+'4. ГПП-УЗПКТ-СЗСК'!AW18+'4. ГПП-УЗПКТ-СЗСК'!AW32+'7. ГД Ямбург'!AW28+'12. ГД Иркутск'!AW11+0+0+'10. ГД Ноябрьск'!AW15+'10. ГД Ноябрьск'!AW51+'10. ГД Ноябрьск'!AW18+'11. ГД Надым'!AW11+'9. ГД Краснодар'!AW29+'2. ГПП-ОГХК'!AW63+'2. ГПП-ОГХК'!AW64+'2. ГПП-ОГХК'!AW60+'2. ГПП-ОГХК'!AW62+'2. ГПП-ОГХК'!AW65+'3. ГПП-СГПЗ'!AW24+'4. ГПП-УЗПКТ-СЗСК'!AW209+'4. ГПП-УЗПКТ-СЗСК'!AW199+'4. ГПП-УЗПКТ-СЗСК'!AW47+'9. ГД Краснодар'!AW30 -> 0 | AJ75: =IFERROR(AI75-AH75,"-") -> -1687.1 | AK75: =IFERROR(AI75/AH75,"-") -> 0 | AL75: ='1. ГПП-АГПЗ+'!BA23+'2. ГПП-ОГХК'!BA56+'2. ГПП-ОГХК'!BA57+'2. ГПП-ОГХК'!BA54+'3. ГПП-СГПЗ'!BA23+'4. ГПП-УЗПКТ-СЗСК'!BA40+'4. ГПП-УЗПКТ-СЗСК'!BA54+'4. ГПП-УЗПКТ-СЗСК'!BA71+'4. ГПП-УЗПКТ-СЗСК'!BA18+'4. ГПП-УЗПКТ-СЗСК'!BA32+'7. ГД Ямбург'!BA28+'12. ГД Иркутск'!BA11+0+0+'10. ГД Ноябрьск'!BA15+'10. ГД Ноябрьск'!BA51+'10. ГД Ноябрьск'!BA18+'11. ГД Надым'!BA11+'9. ГД Краснодар'!BA29+'2. ГПП-ОГХК'!BA63+'2. ГПП-ОГХК'!BA64+'2. ГПП-ОГХК'!BA60+'2. ГПП-ОГХК'!BA62+'2. ГПП-ОГХК'!BA65+'3. ГПП-СГПЗ'!BA24+'4. ГПП-УЗПКТ-СЗСК'!BA209+'4. ГПП-УЗПКТ-СЗСК'!BA199+'4. ГПП-УЗПКТ-СЗСК'!BA47+'9. ГД Краснодар'!BA30 -> 1669 | AM75: ='1. ГПП-АГПЗ+'!BC23+'2. ГПП-ОГХК'!BC56+'2. ГПП-ОГХК'!BC57+'2. ГПП-ОГХК'!BC54+'3. ГПП-СГПЗ'!BC23+'4. ГПП-УЗПКТ-СЗСК'!BC40+'4. ГПП-УЗПКТ-СЗСК'!BC54+'4. ГПП-УЗПКТ-СЗСК'!BC71+'4. ГПП-УЗПКТ-СЗСК'!BC18+'4. ГПП-УЗПКТ-СЗСК'!BC32+'7. ГД Ямбург'!BC28+'12. ГД Иркутск'!BC11+0+0+'10. ГД Ноябрьск'!BC15+'10. ГД Ноябрьск'!BC51+'10. ГД Ноябрьск'!BC18+'11. ГД Надым'!BC11+'9. ГД Краснодар'!BC29+'2. ГПП-ОГХК'!BC63+'2. ГПП-ОГХК'!BC64+'2. ГПП-ОГХК'!BC60+'2. ГПП-ОГХК'!BC62+'2. ГПП-ОГХК'!BC65+'3. ГПП-СГПЗ'!BC24+'4. ГПП-УЗПКТ-СЗСК'!BC209+'4. ГПП-УЗПКТ-СЗСК'!BC199+'4. ГПП-УЗПКТ-СЗСК'!BC47+'9. ГД Краснодар'!BC30 -> 0 | AN75: =IFERROR(AM75-AL75,"-") -> -1669 | AO75: =IFERROR(AM75/AL75,"-") -> 0 | AP75: ='1. ГПП-АГПЗ+'!BG23+'2. ГПП-ОГХК'!BG56+'2. ГПП-ОГХК'!BG57+'2. ГПП-ОГХК'!BG54+'3. ГПП-СГПЗ'!BG23+'4. ГПП-УЗПКТ-СЗСК'!BG40+'4. ГПП-УЗПКТ-СЗСК'!BG54+'4. ГПП-УЗПКТ-СЗСК'!BG71+'4. ГПП-УЗПКТ-СЗСК'!BG18+'4. ГПП-УЗПКТ-СЗСК'!BG32+'7. ГД Ямбург'!BG28+'12. ГД Иркутск'!BG11+0+0+'10. ГД Ноябрьск'!BG15+'10. ГД Ноябрьск'!BG51+'10. ГД Ноябрьск'!BG18+'11. ГД Надым'!BG11+'9. ГД Краснодар'!BG29+'2. ГПП-ОГХК'!BG63+'2. ГПП-ОГХК'!BG64+'2. ГПП-ОГХК'!BG60+'2. ГПП-ОГХК'!BG62+'2. ГПП-ОГХК'!BG65+'3. ГПП-СГПЗ'!BG24+'4. ГПП-УЗПКТ-СЗСК'!BG209+'4. ГПП-УЗПКТ-СЗСК'!BG199+'4. ГПП-УЗПКТ-СЗСК'!BG47+'9. ГД Краснодар'!BG30 -> 1513.9 | AQ75: ='1. ГПП-АГПЗ+'!BI23+'2. ГПП-ОГХК'!BI56+'2. ГПП-ОГХК'!BI57+'2. ГПП-ОГХК'!BI54+'3. ГПП-СГПЗ'!BI23+'4. ГПП-УЗПКТ-СЗСК'!BI40+'4. ГПП-УЗПКТ-СЗСК'!BI54+'4. ГПП-УЗПКТ-СЗСК'!BI71+'4. ГПП-УЗПКТ-СЗСК'!BI18+'4. ГПП-УЗПКТ-СЗСК'!BI32+'7. ГД Ямбург'!BI28+'12. ГД Иркутск'!BI11+0+0+'10. ГД Ноябрьск'!BI15+'10. ГД Ноябрьск'!BI51+'10. ГД Ноябрьск'!BI18+'11. ГД Надым'!BI11+'9. ГД Краснодар'!BI29+'2. ГПП-ОГХК'!BI63+'2. ГПП-ОГХК'!BI64+'2. ГПП-ОГХК'!BI60+'2. ГПП-ОГХК'!BI62+'2. ГПП-ОГХК'!BI65+'3. ГПП-СГПЗ'!BI24+'4. ГПП-УЗПКТ-СЗСК'!BI209+'4. ГПП-УЗПКТ-СЗСК'!BI199+'4. ГПП-УЗПКТ-СЗСК'!BI47+'9. ГД Краснодар'!BI30 -> 0 | AR75: =IFERROR(AQ75-AP75,"-") -> -1513.9 | AS75: =IFERROR(AQ75/AP75,"-") -> 0 | AT75: =AX75+BB75+BF75 -> 4664.3 | AU75: =AY75+BC75+BG75 -> 0 | AV75: =IFERROR(AU75-AT75,"-") -> -4664.3 | AW75: =IFERROR(AU75/AT75,"-") -> 0 | AX75: ='1. ГПП-АГПЗ+'!BS23+'2. ГПП-ОГХК'!BS56+'2. ГПП-ОГХК'!BS57+'2. ГПП-ОГХК'!BS54+'3. ГПП-СГПЗ'!BS23+'4. ГПП-УЗПКТ-СЗСК'!BS40+'4. ГПП-УЗПКТ-СЗСК'!BS54+'4. ГПП-УЗПКТ-СЗСК'!BS71+'4. ГПП-УЗПКТ-СЗСК'!BS18+'4. ГПП-УЗПКТ-СЗСК'!BS32+'7. ГД Ямбург'!BS28+'12. ГД Иркутск'!BS11+0+0+'10. ГД Ноябрьск'!BS15+'10. ГД Ноябрьск'!BS51+'10. ГД Ноябрьск'!BS18+'11. ГД Надым'!BS11+'9. ГД Краснодар'!BS29+'2. ГПП-ОГХК'!BS63+'2. ГПП-ОГХК'!BS64+'2. ГПП-ОГХК'!BS60+'2. ГПП-ОГХК'!BS62+'2. ГПП-ОГХК'!BS65+'3. ГПП-СГПЗ'!BS24+'4. ГПП-УЗПКТ-СЗСК'!BS209+'4. ГПП-УЗПКТ-СЗСК'!BS199+'4. ГПП-УЗПКТ-СЗСК'!BS47+'9. ГД Краснодар'!BS30 -> 1457.9 | AY75: ='1. ГПП-АГПЗ+'!BU23+'2. ГПП-ОГХК'!BU56+'2. ГПП-ОГХК'!BU57+'2. ГПП-ОГХК'!BU54+'3. ГПП-СГПЗ'!BU23+'4. ГПП-УЗПКТ-СЗСК'!BU40+'4. ГПП-УЗПКТ-СЗСК'!BU54+'4. ГПП-УЗПКТ-СЗСК'!BU71+'4. ГПП-УЗПКТ-СЗСК'!BU18+'4. ГПП-УЗПКТ-СЗСК'!BU32+'7. ГД Ямбург'!BU28+'12. ГД Иркутск'!BU11+0+0+'10. ГД Ноябрьск'!BU15+'10. ГД Ноябрьск'!BU51+'10. ГД Ноябрьск'!BU18+'11. ГД Надым'!BU11+'9. ГД Краснодар'!BU29+'2. ГПП-ОГХК'!BU63+'2. ГПП-ОГХК'!BU64+'2. ГПП-ОГХК'!BU60+'2. ГПП-ОГХК'!BU62+'2. ГПП-ОГХК'!BU65+'3. ГПП-СГПЗ'!BU24+'4. ГПП-УЗПКТ-СЗСК'!BU209+'4. ГПП-УЗПКТ-СЗСК'!BU199+'4. ГПП-УЗПКТ-СЗСК'!BU47+'9. ГД Краснодар'!BU30 -> 0 | AZ75: =IFERROR(AY75-AX75,"-") -> -1457.9 | BA75: =IFERROR(AY75/AX75,"-") -> 0 | BB75: ='1. ГПП-АГПЗ+'!BY23+'2. ГПП-ОГХК'!BY56+'2. ГПП-ОГХК'!BY57+'2. ГПП-ОГХК'!BY54+'3. ГПП-СГПЗ'!BY23+'4. ГПП-УЗПКТ-СЗСК'!BY40+'4. ГПП-УЗПКТ-СЗСК'!BY54+'4. ГПП-УЗПКТ-СЗСК'!BY71+'4. ГПП-УЗПКТ-СЗСК'!BY18+'4. ГПП-УЗПКТ-СЗСК'!BY32+'7. ГД Ямбург'!BY28+'12. ГД Иркутск'!BY11+0+0+'10. ГД Ноябрьск'!BY15+'10. ГД Ноябрьск'!BY51+'10. ГД Ноябрьск'!BY18+'11. ГД Надым'!BY11+'9. ГД Краснодар'!BY29+'2. ГПП-ОГХК'!BY63+'2. ГПП-ОГХК'!BY64+'2. ГПП-ОГХК'!BY60+'2. ГПП-ОГХК'!BY62+'2. ГПП-ОГХК'!BY65+'3. ГПП-СГПЗ'!BY24+'4. ГПП-УЗПКТ-СЗСК'!BY209+'4. ГПП-УЗПКТ-СЗСК'!BY199+'4. ГПП-УЗПКТ-СЗСК'!BY47+'9. ГД Краснодар'!BY30 -> 1608.1 | BC75: ='1. ГПП-АГПЗ+'!CA23+'2. ГПП-ОГХК'!CA56+'2. ГПП-ОГХК'!CA57+'2. ГПП-ОГХК'!CA54+'3. ГПП-СГПЗ'!CA23+'4. ГПП-УЗПКТ-СЗСК'!CA40+'4. ГПП-УЗПКТ-СЗСК'!CA54+'4. ГПП-УЗПКТ-СЗСК'!CA71+'4. ГПП-УЗПКТ-СЗСК'!CA18+'4. ГПП-УЗПКТ-СЗСК'!CA32+'7. ГД Ямбург'!CA28+'12. ГД Иркутск'!CA11+0+0+'10. ГД Ноябрьск'!CA15+'10. ГД Ноябрьск'!CA51+'10. ГД Ноябрьск'!CA18+'11. ГД Надым'!CA11+'9. ГД Краснодар'!CA29+'2. ГПП-ОГХК'!CA63+'2. ГПП-ОГХК'!CA64+'2. ГПП-ОГХК'!CA60+'2. ГПП-ОГХК'!CA62+'2. ГПП-ОГХК'!CA65+'3. ГПП-СГПЗ'!CA24+'4. ГПП-УЗПКТ-СЗСК'!CA209+'4. ГПП-УЗПКТ-СЗСК'!CA199+'4. ГПП-УЗПКТ-СЗСК'!CA47+'9. ГД Краснодар'!CA30 -> 0 | BD75: =IFERROR(BC75-BB75,"-") -> -1608.1 | BE75: =IFERROR(BC75/BB75,"-") -> 0 | BF75: ='1. ГПП-АГПЗ+'!CE23+'2. ГПП-ОГХК'!CE56+'2. ГПП-ОГХК'!CE57+'2. ГПП-ОГХК'!CE54+'3. ГПП-СГПЗ'!CE23+'4. ГПП-УЗПКТ-СЗСК'!CE40+'4. ГПП-УЗПКТ-СЗСК'!CE54+'4. ГПП-УЗПКТ-СЗСК'!CE71+'4. ГПП-УЗПКТ-СЗСК'!CE18+'4. ГПП-УЗПКТ-СЗСК'!CE32+'7. ГД Ямбург'!CE28+'12. ГД Иркутск'!CE11+0+0+'10. ГД Ноябрьск'!CE15+'10. ГД Ноябрьск'!CE51+'10. ГД Ноябрьск'!CE18+'11. ГД Надым'!CE11+'9. ГД Краснодар'!CE29+'2. ГПП-ОГХК'!CE63+'2. ГПП-ОГХК'!CE64+'2. ГПП-ОГХК'!CE60+'2. ГПП-ОГХК'!CE62+'2. ГПП-ОГХК'!CE65+'3. ГПП-СГПЗ'!CE24+'4. ГПП-УЗПКТ-СЗСК'!CE209+'4. ГПП-УЗПКТ-СЗСК'!CE199+'4. ГПП-УЗПКТ-СЗСК'!CE47+'9. ГД Краснодар'!CE30 -> 1598.3 | BG75: ='1. ГПП-АГПЗ+'!CG23+'2. ГПП-ОГХК'!CG56+'2. ГПП-ОГХК'!CG57+'2. ГПП-ОГХК'!CG54+'3. ГПП-СГПЗ'!CG23+'4. ГПП-УЗПКТ-СЗСК'!CG40+'4. ГПП-УЗПКТ-СЗСК'!CG54+'4. ГПП-УЗПКТ-СЗСК'!CG71+'4. ГПП-УЗПКТ-СЗСК'!CG18+'4. ГПП-УЗПКТ-СЗСК'!CG32+'7. ГД Ямбург'!CG28+'12. ГД Иркутск'!CG11+0+0+'10. ГД Ноябрьск'!CG15+'10. ГД Ноябрьск'!CG51+'10. ГД Ноябрьск'!CG18+'11. ГД Надым'!CG11+'9. ГД Краснодар'!CG29+'2. ГПП-ОГХК'!CG63+'2. ГПП-ОГХК'!CG64+'2. ГПП-ОГХК'!CG60+'2. ГПП-ОГХК'!CG62+'2. ГПП-ОГХК'!CG65+'3. ГПП-СГПЗ'!CG24+'4. ГПП-УЗПКТ-СЗСК'!CG209+'4. ГПП-УЗПКТ-СЗСК'!CG199+'4. ГПП-УЗПКТ-СЗСК'!CG47+'9. ГД Краснодар'!CG30 -> 0 | BH75: =IFERROR(BG75-BF75,"-") -> -1598.3 | BI75: =IFERROR(BG75/BF75,"-") -> 0 | BJ75: =BN75+BR75+BV75 -> 5315.5 | BK75: =BO75+BS75+BW75 -> 0 | BL75: =IFERROR(BK75-BJ75,"-") -> -5315.5 | BM75: =IFERROR(BK75/BJ75,"-") -> 0 | BN75: ='1. ГПП-АГПЗ+'!CQ23+'2. ГПП-ОГХК'!CQ56+'2. ГПП-ОГХК'!CQ57+'2. ГПП-ОГХК'!CQ54+'3. ГПП-СГПЗ'!CQ23+'4. ГПП-УЗПКТ-СЗСК'!CQ40+'4. ГПП-УЗПКТ-СЗСК'!CQ54+'4. ГПП-УЗПКТ-СЗСК'!CQ71+'4. ГПП-УЗПКТ-СЗСК'!CQ18+'4. ГПП-УЗПКТ-СЗСК'!CQ32+'7. ГД Ямбург'!CQ28+'12. ГД Иркутск'!CQ11+0+0+'10. ГД Ноябрьск'!CQ15+'10. ГД Ноябрьск'!CQ51+'10. ГД Ноябрьск'!CQ18+'11. ГД Надым'!CQ11+'9. ГД Краснодар'!CQ29+'2. ГПП-ОГХК'!CQ63+'2. ГПП-ОГХК'!CQ64+'2. ГПП-ОГХК'!CQ60+'2. ГПП-ОГХК'!CQ62+'2. ГПП-ОГХК'!CQ65+'3. ГПП-СГПЗ'!CQ24+'4. ГПП-УЗПКТ-СЗСК'!CQ209+'4. ГПП-УЗПКТ-СЗСК'!CQ199+'4. ГПП-УЗПКТ-СЗСК'!CQ47+'9. ГД Краснодар'!CQ30 -> 1786.7 | BO75: ='1. ГПП-АГПЗ+'!CS23+'2. ГПП-ОГХК'!CS56+'2. ГПП-ОГХК'!CS57+'2. ГПП-ОГХК'!CS54+'3. ГПП-СГПЗ'!CS23+'4. ГПП-УЗПКТ-СЗСК'!CS40+'4. ГПП-УЗПКТ-СЗСК'!CS54+'4. ГПП-УЗПКТ-СЗСК'!CS71+'4. ГПП-УЗПКТ-СЗСК'!CS18+'4. ГПП-УЗПКТ-СЗСК'!CS32+'7. ГД Ямбург'!CS28+'12. ГД Иркутск'!CS11+0+0+'10. ГД Ноябрьск'!CS15+'10. ГД Ноябрьск'!CS51+'10. ГД Ноябрьск'!CS18+'11. ГД Надым'!CS11+'9. ГД Краснодар'!CS29+'2. ГПП-ОГХК'!CS63+'2. ГПП-ОГХК'!CS64+'2. ГПП-ОГХК'!CS60+'2. ГПП-ОГХК'!CS62+'2. ГПП-ОГХК'!CS65+'3. ГПП-СГПЗ'!CS24+'4. ГПП-УЗПКТ-СЗСК'!CS209+'4. ГПП-УЗПКТ-СЗСК'!CS199+'4. ГПП-УЗПКТ-СЗСК'!CS47+'9. ГД Краснодар'!CS30 -> 0 | BP75: =IFERROR(BO75-BN75,"-") -> -1786.7 | BQ75: =IFERROR(BO75/BN75,"-") -> 0 | BR75: ='1. ГПП-АГПЗ+'!CW23+'2. ГПП-ОГХК'!CW56+'2. ГПП-ОГХК'!CW57+'2. ГПП-ОГХК'!CW54+'3. ГПП-СГПЗ'!CW23+'4. ГПП-УЗПКТ-СЗСК'!CW40+'4. ГПП-УЗПКТ-СЗСК'!CW54+'4. ГПП-УЗПКТ-СЗСК'!CW71+'4. ГПП-УЗПКТ-СЗСК'!CW18+'4. ГПП-УЗПКТ-СЗСК'!CW32+'7. ГД Ямбург'!CW28+'12. ГД Иркутск'!CW11+0+0+'10. ГД Ноябрьск'!CW15+'10. ГД Ноябрьск'!CW51+'10. ГД Ноябрьск'!CW18+'11. ГД Надым'!CW11+'9. ГД Краснодар'!CW29+'2. ГПП-ОГХК'!CW63+'2. ГПП-ОГХК'!CW64+'2. ГПП-ОГХК'!CW60+'2. ГПП-ОГХК'!CW62+'2. ГПП-ОГХК'!CW65+'3. ГПП-СГПЗ'!CW24+'4. ГПП-УЗПКТ-СЗСК'!CW209+'4. ГПП-УЗПКТ-СЗСК'!CW199+'4. ГПП-УЗПКТ-СЗСК'!CW47+'9. ГД Краснодар'!CW30 -> 1733.5 | BS75: ='1. ГПП-АГПЗ+'!CY23+'2. ГПП-ОГХК'!CY56+'2. ГПП-ОГХК'!CY57+'2. ГПП-ОГХК'!CY54+'3. ГПП-СГПЗ'!CY23+'4. ГПП-УЗПКТ-СЗСК'!CY40+'4. ГПП-УЗПКТ-СЗСК'!CY54+'4. ГПП-УЗПКТ-СЗСК'!CY71+'4. ГПП-УЗПКТ-СЗСК'!CY18+'4. ГПП-УЗПКТ-СЗСК'!CY32+'7. ГД Ямбург'!CY28+'12. ГД Иркутск'!CY11+0+0+'10. ГД Ноябрьск'!CY15+'10. ГД Ноябрьск'!CY51+'10. ГД Ноябрьск'!CY18+'11. ГД Надым'!CY11+'9. ГД Краснодар'!CY29+'2. ГПП-ОГХК'!CY63+'2. ГПП-ОГХК'!CY64+'2. ГПП-ОГХК'!CY60+'2. ГПП-ОГХК'!CY62+'2. ГПП-ОГХК'!CY65+'3. ГПП-СГПЗ'!CY24+'4. ГПП-УЗПКТ-СЗСК'!CY209+'4. ГПП-УЗПКТ-СЗСК'!CY199+'4. ГПП-УЗПКТ-СЗСК'!CY47+'9. ГД Краснодар'!CY30 -> 0 | BT75: =IFERROR(BS75-BR75,"-") -> -1733.5 | BU75: =IFERROR(BS75/BR75,"-") -> 0 | BV75: ='1. ГПП-АГПЗ+'!DC23+'2. ГПП-ОГХК'!DC56+'2. ГПП-ОГХК'!DC57+'2. ГПП-ОГХК'!DC54+'3. ГПП-СГПЗ'!DC23+'4. ГПП-УЗПКТ-СЗСК'!DC40+'4. ГПП-УЗПКТ-СЗСК'!DC54+'4. ГПП-УЗПКТ-СЗСК'!DC71+'4. ГПП-УЗПКТ-СЗСК'!DC18+'4. ГПП-УЗПКТ-СЗСК'!DC32+'7. ГД Ямбург'!DC28+'12. ГД Иркутск'!DC11+0+0+'10. ГД Ноябрьск'!DC15+'10. ГД Ноябрьск'!DC51+'10. ГД Ноябрьск'!DC18+'11. ГД Надым'!DC11+'9. ГД Краснодар'!DC29+'2. ГПП-ОГХК'!DC63+'2. ГПП-ОГХК'!DC64+'2. ГПП-ОГХК'!DC60+'2. ГПП-ОГХК'!DC62+'2. ГПП-ОГХК'!DC65+'3. ГПП-СГПЗ'!DC24+'4. ГПП-УЗПКТ-СЗСК'!DC209+'4. ГПП-УЗПКТ-СЗСК'!DC199+'4. ГПП-УЗПКТ-СЗСК'!DC47+'9. ГД Краснодар'!DC30 -> 1795.3 | BW75: ='1. ГПП-АГПЗ+'!DE23+'2. ГПП-ОГХК'!DE56+'2. ГПП-ОГХК'!DE57+'2. ГПП-ОГХК'!DE54+'3. ГПП-СГПЗ'!DE23+'4. ГПП-УЗПКТ-СЗСК'!DE40+'4. ГПП-УЗПКТ-СЗСК'!DE54+'4. ГПП-УЗПКТ-СЗСК'!DE71+'4. ГПП-УЗПКТ-СЗСК'!DE18+'4. ГПП-УЗПКТ-СЗСК'!DE32+'7. ГД Ямбург'!DE28+'12. ГД Иркутск'!DE11+0+0+'10. ГД Ноябрьск'!DE15+'10. ГД Ноябрьск'!DE51+'10. ГД Ноябрьск'!DE18+'11. ГД Надым'!DE11+'9. ГД Краснодар'!DE29+'2. ГПП-ОГХК'!DE63+'2. ГПП-ОГХК'!DE64+'2. ГПП-ОГХК'!DE60+'2. ГПП-ОГХК'!DE62+'2. ГПП-ОГХК'!DE65+'3. ГПП-СГПЗ'!DE24+'4. ГПП-УЗПКТ-СЗСК'!DE209+'4. ГПП-УЗПКТ-СЗСК'!DE199+'4. ГПП-УЗПКТ-СЗСК'!DE47+'9. ГД Краснодар'!DE30 -> 0 | BX75: =IFERROR(BW75-BV75,"-") -> -1795.3 | BY75: =IFERROR(BW75/BV75,"-") -> 0
