Workbook
Name _INTERNAL_KEY1: Лист1!$5:$5
Name _INTERNAL_KEY2: 'Лист1 (2)'!$5:$5
Name _SET_ROW1: Лист1!$C:$H
Name _SET_ROW2: 'Лист1 (2)'!$C:$H
Name _SHEET_ID1: 1
Name _SHEET_ID2: 1
Name _SHEET_ID20: 1
Name _SHEET_ID21: 1
Name _SHEET_ID22: 1
Name _STATIC_REP_INTERNAL_KEY1: 'Отчёт КПД ДО'!$5:$5
Name _STATIC_REP_SET_ROW1: 'Отчёт КПД ДО'!$C:$D
Name _SUM_REP_INTERNAL_KEY1: 'План общий '!$5:$5
Name _SUM_REP_INTERNAL_KEY2: 'Баланс ЗС'!$5:$5
Name _SUM_REP_SET_ROW1: 'План общий '!$C:$H
Name _SUM_REP_SET_ROW2: 'Баланс ЗС'!$C:$H

Sheet План общий 
B2: Показатели | C2: Внутренние настройки листа | I2: Ед. изм.
C3: Ключ статьи | D3: Ключ спец расчётов | E3: Ключ ввод данных | F3: Формула месяц | G3: Формула % Выхода | H3: Строка проверка
B6: Объемы реализации ЖУВ | E6: 1 | I6: тыс.т
B7: в т.ч. на экспорт | E7: 2 | I7: тыс.т
B8: в т.ч. на внутренний рынок | E8: 3 | I8: тыс.т
B9: Поступление денежных средств | E9: 4 | I9: млрд руб. с НДС
B10: в т.ч. на экспорт | E10: 5 | I10: млрд руб. с НДС
B11: в т.ч. на внутренний рынок | E11: 6 | I11: млрд руб. с НДС
B12: Объем производства ООО "ГПП" для реализации ПАО "Газпром" | E12: 7 | I12: тыс.т
B13: Объем реализации продукции ООО "ГПП" с учетом остатков | E13: 8 | I13: тыс.т
E14: 9
B15: Раздел 1. Прогнозные показатели по переработке углеводородного сырья и производству продукции | E15: 10
B16: ПАО "Газпром" и основных дочерних обществ | E16: 11
B17: CЫРЬЕ | E17: 12
E18: 13
B19: 1. Переработка газа на ГПЗ-всего | F19: 1_1003335807+2_100332038+2_100332040+2_100332042+2_100332044+2_100332916+2_100332944+2_100335129+3_100330552+3_100330008+14_100335074+14_100335076 | I19: млн куб.м.
B20: без СПГ Портовой | E20: 14 | I20: млн куб.м.
B21: Газпром переработка | F21: 1_1003335807+2_100332038+2_100332040+2_100332042+2_100332044+2_100332916+2_100332944+2_100335129+3_100330552+3_100330008 | I21: млн куб.м.
B22: Астраханский ГПЗ | F22: 1_1003335807 | I22: млн куб.м.
B23: Оренбургский ГХК | F23: 2_100332038+2_100332040+2_100332042+2_100332044+2_100332916+2_100332944+2_100335129 | I23: млн куб.м.
B24: Сосногорский ГПЗ | F24: 3_100330552+3_100330008 | I24: млн куб.м.
B25: Газпром переработка Благовещенск | F25: 14_100335074+14_100335076 | I25: млн куб.м.
B26: Амурский ГПЗ | F26: 14_100335074+14_100335076 | I26: млн куб.м.
B27: Газпром СПГ Портовая | E27: 15 | I27: млн куб.м.
B28: КСПГ Портовая | E28: 16 | I28: млн куб.м.
B29: 1.1. Газпром | F29: 3_100330008+1_1003335807+14_100335074 | I29: млн куб.м.
B30: Газпром переработка | F30: 3_100330008+1_1003335807 | I30: млн куб.м.
B31: Астраханский ГПЗ | F31: 1_1003335807 | I31: млн куб.м.
B32: Сосногорский ГПЗ | F32: 3_100330008 | I32: млн куб.м.
B33: Газпром добыча Краснодар | F33: 3_100330008 | I33: млн куб.м.
B34: Газпром переработка Благовещенск | F34: 14_100335074 | I34: млн куб.м.
B35: Амурский ГПЗ | F35: 14_100335074 | I35: млн куб.м.
B36: Газпром СПГ Портовая | E36: 17 | I36: млн куб.м.
B37: КСПГ Портовая | E37: 18 | I37: млн куб.м.
B38: в т.ч. на ПНР | E38: 19 | I38: млн куб.м.
B39: в т.ч. СТН | E39: 20 | I39: млн куб.м.
B40: в т.ч. на переработку | E40: 21 | I40: млн куб.м.
B41: 1.2. Дочерние общества | F41: 2_100332038+2_100332040+2_100332042+2_100332044+2_100332916+2_100332944+2_100335129+3_100330552+14_100335076 | I41: млн куб.м.
B42: Газпром добыча Астрахань | F42: 0 | I42: млн куб.м.
B43: Астраханский ГПЗ | F43: 0 | I43: млн куб.м.
B44: Газпром добыча Астрахань | E44: 22 | I44: млн куб.м.
B45: Газпром переработка | F45: 2_100332038+2_100332040+2_100332042+2_100332044+2_100332916+2_100332944+2_100335129 | I45: млн куб.м.
B46: Оренбургский ГХК | F46: 2_100332038+2_100332040+2_100332042+2_100332044+2_100332916+2_100332944+2_100335129 | I46: млн куб.м.
B47: покупка у Газпром добыча Оренбург, всего | F47: 2_100332038+2_100332040+2_100332042+2_100332044+2_100332916+2_100332944+2_100335129 | I47: млн куб.м.
B48: в т.ч. Газпром добыча Оренбург | F48: 2_100332038 | I48: млн куб.м.
B49: Газпром нефть | F49: 2_100332040 | I49: млн куб.м.
B50: УНГП | F50: 2_100332042 | I50: млн куб.м.
B51: Сервиснефтегаз | F51: 2_100332044 | I51: млн куб.м.
B52: Карбон | F52: 2_100332916 | I52: млн куб.м.
B53: Газпромнефть-Заполярье | F53: 2_100332944 | I53: млн куб.м.
B54: Сладковско-Заречное | F54: 2_100335129 | I54: млн куб.м.
B55: Газпром ГНП холдинг | F55: 3_100330552 | I55: млн куб.м.
B56: Сосногорский ГПЗ | F56: 3_100330552 | I56: млн куб.м.
... B59: Амурский ГПЗ | F59: 14_100335076 | I59: млн куб.м.
B60: Газпром СПГ Портовая | E60: 23 | I60: млн куб.м.
B61: КСПГ КС Портовая | E61: 24 | I61: млн куб.м.
B62: в т.ч. СТН при переработке | E62: 25 | I62: млн куб.м.
B63: в т.ч. СТН при пусковых операциях | E63: 26 | I63: млн куб.м.
E64: 27
B65: 2. Поставка газа на Амурский ГПЗ | E65: 28
B66: Газпром переработка Благовещенск | F66: 14_100332979-14_100335059-14_100335057-14_100335425+14_100335428+14_100335059 | I66: млн куб.м.
B67: Амурский ГПЗ | F67: 14_100332979-14_100335059-14_100335057-14_100335425+14_100335428+14_100335059 | I67: млн куб.м.
B68: 2.1. Газпром | E68: 29
B69: Газпром переработка Благовещенск | F69: 14_100332979-14_100335059-14_100335057-14_100335425 | I69: млн куб.м.
B70: Амурский ГПЗ | F70: 14_100332979-14_100335059-14_100335057-14_100335425 | I70: млн куб.м.
B71: 2.2. Дочерние общества | E71: 30
B72: Газпром переработка Благовещенск | F72: 14_100335428+14_100335059 | I72: млн куб.м.
B73: Амурский ГПЗ | F73: 14_100335428+14_100335059 | I73: млн куб.м.
E74: 31
B75: 3. Переработка газа на Оренбургском гелиевом заводе | E75: 32
B76: Газпром переработка | F76: 2_100332054+2_100332056+2_100335131 | I76: млн куб.м.
B77: Оренбургский ГЗ | F77: 2_100332054+2_100332056+2_100335131 | I77: млн куб.м.
B78: 3.1. Газпром | F78: 0 | I78: млн куб.м.
B79: 3.2. Дочерние общества | F79: 2_100332054+2_100332056+2_100335131 | I79: млн куб.м.
B80: Газпром переработка | F80: 2_100332054+2_100332056+2_100335131 | I80: млн куб.м.
B81: Оренбургский ГЗ | F81: 2_100332054+2_100332056+2_100335131 | I81: млн куб.м.
B82: Газпром добыча Оренбург | F82: 2_100332054 | I82: млн куб.м.
B83: Газпром нефть | F83: 2_100332056 | I83: млн куб.м.
B84: прочие поставщики (ГПНЗ, УНГП, и.т.д.) | F84: 2_100335131 | I84: млн куб.м.
F85: 4_100333682+4_100331828+4_100331835+4_100331804+4_100335033+10_100330861 | I85: проверка УЗПКТ
F86: 2_100332062+2_100335697+2_100332061+2_100332068+2_100332947+2_100332066+2_100332067+2_100332069 | I86: проверка ОГПЗ
E87: 33
B88: 4. Переработка нестабильного газового конденсата и нефти | F88: 1_100331985+2_100332062+2_100335697+2_100332061+3_100330017+4_100333682+4_100331828+4_100331835+4_100331804+4_100335033+7_100330595+12_100330735+0+13_100330000+10_100330715+10_100330861+10_100330718+11_100330015+9_100330671+2_100332068+2_100332947+2_100332066+2_100332067+2_100332069+3_100330196+4_100331838+4_100335093+4_100333678+9_100330672 | I88: тыс.т
B89: 4.1. Газовый конденсат-всего | F89: 1_100331985+2_100332062+2_100335697+2_100332061+3_100330017+4_100333682+4_100331828+4_100331835+4_100331804+4_100335033+7_100330595+12_100330735+0+13_100330000+10_100330715+10_100330861+10_100330718+11_100330015+9_100330671 | I89: тыс.т
B90: Газпром переработка | F90: 1_100331985+2_100332062+2_100335697+2_100332061+3_100330017+4_100333682+4_100331828+4_100331835+4_100331804+4_100335033 | I90: тыс.т
B91: Астраханский ГПЗ | F91: 1_100331985 | I91: тыс.т
B92: Оренбургский ГХК | F92: 2_100332062+2_100335697+2_100332061 | I92: тыс.т
B93: Сосногорский ГПЗ | F93: 3_100330017 | I93: тыс.т
B94: Уренгойский ЗПКТ- Сургутский ЗСК и привлеченные мощности | F94: 4_100333682+4_100331828+4_100331835+4_100331804+4_100335033 | I94: тыс.т
B95: Газпром добыча Ямбург | F95: 7_100330595 | I95: тыс.т
B96: Газпром добыча Иркутск | F96: 12_100330735+0 | I96: тыс.т
B97: Газпром добыча шельф Южно-Сахалинск | F97: 13_100330000 | I97: тыс. т
B98: Газпром добыча Ноябрьск | F98: 10_100330715+10_100330861+10_100330718 | I98: тыс. т
B99: Газпром добыча Надым | F99: 11_100330015 | I99: тыс. т
... B116: Ковыктинское ГКМ | F116: 12_100330735 | I116: тыс.т
B117: Чиканское ГКМ | F117: 0 | I117: тыс.т
B118: Газпром добыча шельф Южно-Сахалинск | F118: 13_100330000 | I118: тыс. т
B119: Газпром добыча Ноябрьск | F119: 10_100330715+10_100330861 | I119: тыс. т
B120: Чаяндинское НГКМ | F120: 10_100330715 | I120: тыс.т
B121: Западно-Таркосалинское НГКМ на СЗСК | F121: 10_100330861 | I121: тыс.т
...

Sheet Отчёт КПД ДО
B2: Показатели | C2: Внутренние настройки листа | E2: Ед. изм. | F2: Удельный вес КПД | G2: Плановое значение | H2: Границы планового значения | J2: Фактическое значение | K2: Выполнение КПД, в % | L2: Причины отклонений фактических значений КПД от плановых значений | M2: Центр ответственности за расчёт КПД ДО
C3: формула | D3: описание
H4: пороговое | I4: максимальное
A6: 26. | B6: ООО "Газпром переработка"
B7: Контролируемые затраты | F7: 0.5 | M7: Департамент 816
B8: Объём переработки газа | C8: 1_100335807+2_100332038+2_100332040+3_100330008 | F8: 0.25 | H8: =G8*0.95 -> 0 | I8: =G8*1.1 -> 0 | K8: =G8/J8 -> #DIV/0! | M8: Департамент 816
B9: Объём переработки нестабильного газового конденсата и нефти | C9: 1_100331985+2_100332061+3_100330017+4_100331828+4_100335040+4_100331835+2_100332066+2_100332067+3_100330196+4_100335093+4_100333678+4_100331838+10_100330861 | F9: 0.25 | H9: =G9*0.95 -> 0 | I9: =G9*1.1 -> 0 | K9: =G9/J9 -> #DIV/0! | M9: Департамент 816

Sheet Баланс ЗС
B2: Показатели | C2: Внутренние настройки листа | I2: Ед. изм. | J2: 2026 | K2: 2026 | L2: 2026 | O2: 2026 год 1 квартал | P2: 2026 год 1 квартал | Q2: 2026 год 1 квартал | T2: 2026 год январь | U2: 2026 год январь | V2: 2026 год январь | Y2: 2026 год февраль | Z2: 2026 год февраль | AA2: 2026 год февраль | AD2: 2026 год март | AE2: 2026 год март | AF2: 2026 год март | AI2: 2026 год 2 квартал | AJ2: 2026 год 2 квартал | AK2: 2026 год 2 квартал | AN2: 2026 год апрель | AO2: 2026 год апрель | AP2: 2026 год апрель | AS2: 2026 год май | AT2: 2026 год май | AU2: 2026 год май | AX2: 2026 год июнь | AY2: 2026 год июнь | AZ2: 2026 год июнь | BC2: 2026 год 3 квартал | BD2: 2026 год 3 квартал | BE2: 2026 год 3 квартал | BH2: 2026 год июль | BI2: 2026 год июль | BJ2: 2026 год июль | BM2: 2026 год август | BN2: 2026 год август | BO2: 2026 год август | BR2: 2026 год сентябрь | BS2: 2026 год сентябрь | BT2: 2026 год сентябрь | BW2: 2026 год 4 квартал | BX2: 2026 год 4 квартал | BY2: 2026 год 4 квартал | CB2: 2026 год октябрь | CC2: 2026 год октябрь | CD2: 2026 год октябрь | CG2: 2026 год ноябрь | CH2: 2026 год ноябрь | CI2: 2026 год ноябрь | CL2: 2026 год декабрь | CM2: 2026 год декабрь | CN2: 2026 год декабрь
C3: Ключ статьи | D3: Ключ спец расчётов | E3: Ключ ввод данных | F3: Формула месяц | G3: Формула % Выхода | H3: Строка проверка | J3: Среднесрочн. план 2026: Вариант утвержденный | K3: Среднесрочн. план 2026 ПРЭУ: Вариант на утверждение | L3: Факт | M3: Отклонение | O3: Среднесрочн. план 2026: Вариант утвержденный | P3: Среднесрочн. план 2026 ПРЭУ: Вариант на утверждение | Q3: Факт | R3: Отклонение | T3: Среднесрочн. план 2026: Вариант утвержденный | U3: Среднесрочн. план 2026 ПРЭУ: Вариант на утверждение | V3: Факт | W3: Отклонение | Y3: Среднесрочн. план 2026: Вариант утвержденный | Z3: Среднесрочн. план 2026 ПРЭУ: Вариант на утверждение | AA3: Факт | AB3: Отклонение | AD3: Среднесрочн. план 2026: Вариант утвержденный | AE3: Среднесрочн. план 2026 ПРЭУ: Вариант на утверждение | AF3: Факт | AG3: Отклонение | AI3: Среднесрочн. план 2026: Вариант утвержденный | AJ3: Среднесрочн. план 2026 ПРЭУ: Вариант на утверждение | AK3: Факт | AL3: Отклонение | AN3: Среднесрочн. план 2026: Вариант утвержденный | AO3: Среднесрочн. план 2026 ПРЭУ: Вариант на утверждение | AP3: Факт | AQ3: Отклонение | AS3: Среднесрочн. план 2026: Вариант утвержденный | AT3: Среднесрочн. план 2026 ПРЭУ: Вариант на утверждение | AU3: Факт | AV3: Отклонение | AX3: Среднесрочн. план 2026: Вариант утвержденный | AY3: Среднесрочн. план 2026 ПРЭУ: Вариант на утверждение | AZ3: Факт | BA3: Отклонение | BC3: Среднесрочн. план 2026: Вариант утвержденный | BD3: Среднесрочн. план 2026 ПРЭУ: Вариант на утверждение | BE3: Факт | BF3: Отклонение | BH3: Среднесрочн. план 2026: Вариант утвержденный | BI3: Среднесрочн. план 2026 ПРЭУ: Вариант на утверждение | BJ3: Факт | BK3: Отклонение | BM3: Среднесрочн. план 2026: Вариант утвержденный | BN3: Среднесрочн. план 2026 ПРЭУ: Вариант на утверждение | BO3: Факт | BP3: Отклонение | BR3: Среднесрочн. план 2026: Вариант утвержденный | BS3: Среднесрочн. план 2026 ПРЭУ: Вариант на утверждение | BT3: Факт | BU3: Отклонение | BW3: Среднесрочн. план 2026: Вариант утвержденный | BX3: Среднесрочн. план 2026 ПРЭУ: Вариант на утверждение | BY3: Факт | BZ3: Отклонение | CB3: Среднесрочн. план 2026: Вариант утвержденный | CC3: Среднесрочн. план 2026 ПРЭУ: Вариант на утверждение | CD3: Факт | CE3: Отклонение | CG3: Среднесрочн. план 2026: Вариант утвержденный | CH3: Среднесрочн. план 2026 ПРЭУ: Вариант на утверждение | CI3: Факт | CJ3: Отклонение | CL3: Среднесрочн. план 2026: Вариант утвержденный | CM3: Среднесрочн. план 2026 ПРЭУ: Вариант на утверждение | CN3: Факт | CO3: Отклонение
M4: + / - | N4: % вып. | R4: + / - | S4: % вып. | W4: + / - | X4: % вып. | AB4: + / - | AC4: % вып. | AG4: + / - | AH4: % вып. | AL4: + / - | AM4: % вып. | AQ4: + / - | AR4: % вып. | AV4: + / - | AW4: % вып. | BA4: + / - | BB4: % вып. | BF4: + / - | BG4: % вып. | BK4: + / - | BL4: % вып. | BP4: + / - | BQ4: % вып. | BU4: + / - | BV4: % вып. | BZ4: + / - | CA4: % вып. | CE4: + / - | CF4: % вып. | CJ4: + / - | CK4: % вып. | CO4: + / - | CP4: % вып.
J5: year2026:1:2260099 | K5: year2026:1:2260010 | L5: year2026:15:None | O5: year2026:Q1:1:2260099 | P5: year2026:Q1:1:2260010 | Q5: year2026:Q1:15:None | T5: year2026:M1_1:1:2260099 | U5: year2026:M1_1:1:2260010 | V5: year2026:M1_1:15:None | Y5: year2026:M1_2:1:2260099 | Z5: year2026:M1_2:1:2260010 | AA5: year2026:M1_2:15:None | AD5: year2026:M1_3:1:2260099 | AE5: year2026:M1_3:1:2260010 | AF5: year2026:M1_3:15:None | AI5: year2026:Q2:1:2260099 | AJ5: year2026:Q2:1:2260010 | AK5: year2026:Q2:15:None | AN5: year2026:M2_1:1:2260099 | AO5: year2026:M2_1:1:2260010 | AP5: year2026:M2_1:15:None | AS5: year2026:M2_2:1:2260099 | AT5: year2026:M2_2:1:2260010 | AU5: year2026:M2_2:15:None | AX5: year2026:M2_3:1:2260099 | AY5: year2026:M2_3:1:2260010 | AZ5: year2026:M2_3:15:None | BC5: year2026:Q3:1:2260099 | BD5: year2026:Q3:1:2260010 | BE5: year2026:Q3:15:None | BH5: year2026:M3_1:1:2260099 | BI5: year2026:M3_1:1:2260010 | BJ5: year2026:M3_1:15:None | BM5: year2026:M3_2:1:2260099 | BN5: year2026:M3_2:1:2260010 | BO5: year2026:M3_2:15:None | BR5: year2026:M3_3:1:2260099 | BS5: year2026:M3_3:1:2260010 | BT5: year2026:M3_3:15:None | BW5: year2026:Q4:1:2260099 | BX5: year2026:Q4:1:2260010 | BY5: year2026:Q4:15:None | CB5: year2026:M4_1:1:2260099 | CC5: year2026:M4_1:1:2260010 | CD5: year2026:M4_1:15:None | CG5: year2026:M4_2:1:2260099 | CH5: year2026:M4_2:1:2260010 | CI5: year2026:M4_2:15:None | CL5: year2026:M4_3:1:2260099 | CM5: year2026:M4_3:1:2260010 | CN5: year2026:M4_3:15:None
F6: 1_100331978+1_100335798 | J6: =O6+AI6+BC6+BW6 -> 13574.2 | K6: =P6+AJ6+BD6+BX6 -> 13574.2 | L6: =Q6+AK6+BE6+BY6 -> 3725.5687 | M6: =IFERROR(K6-J6,"-") -> 0 | N6: =IFERROR(K6/J6,"-") -> 1 | O6: =T6+Y6+AD6 -> 3405.4 | P6: =U6+Z6+AE6 -> 3405.4 | Q6: =V6+AA6+AF6 -> 2363.5888 | R6: =IFERROR(P6-O6,"-") -> 0 | S6: =IFERROR(P6/O6,"-") -> 1 | T6: =Лист1!Z7+Лист1!Z9 -> 1172.9 | U6: =Лист1!AB7+Лист1!AB9 -> 1172.9 | V6: =Лист1!AD7+Лист1!AD9 -> 852.21491 | W6: =IFERROR(U6-T6,"-") -> 0 | X6: =IFERROR(U6/T6,"-") -> 1 | Y6: =Лист1!AH7+Лист1!AH9 -> 1059.5 | Z6: =Лист1!AJ7+Лист1!AJ9 -> 1059.5 | AA6: =Лист1!AL7+Лист1!AL9 -> 663.76837 | AB6: =IFERROR(Z6-Y6,"-") -> 0 | AC6: =IFERROR(Z6/Y6,"-") -> 1 | AD6: =Лист1!AP7+Лист1!AP9 -> 1173 | AE6: =Лист1!AR7+Лист1!AR9 -> 1173 | AF6: =Лист1!AT7+Лист1!AT9 -> 847.6055 | AG6: =IFERROR(AE6-AD6,"-") -> 0 | AH6: =IFERROR(AE6/AD6,"-") -> 1 | AI6: =AN6+AS6+AX6 -> 2597.4 | AJ6: =AO6+AT6+AY6 -> 2597.4 | AK6: =AP6+AU6+AZ6 -> 1361.9799 | AL6: =IFERROR(AJ6-AI6,"-") -> 0 | AM6: =IFERROR(AJ6/AI6,"-") -> 1 | AN6: =Лист1!BF7+Лист1!BF9 -> 1135.2 | AO6: =Лист1!BH7+Лист1!BH9 -> 1135.2 | AP6: =Лист1!BJ7+Лист1!BJ9 -> 807.96479 | AQ6: =IFERROR(AO6-AN6,"-") -> 0 | AR6: =IFERROR(AO6/AN6,"-") -> 1 | AS6: =Лист1!BN7+Лист1!BN9 -> 806.4 | AT6: =Лист1!BP7+Лист1!BP9 -> 806.4 | AU6: =Лист1!BR7+Лист1!BR9 -> 328.213 | AV6: =IFERROR(AT6-AS6,"-") -> 0 | AW6: =IFERROR(AT6/AS6,"-") -> 1 | AX6: =Лист1!BV7+Лист1!BV9 -> 655.8 | AY6: =Лист1!BX7+Лист1!BX9 -> 655.8 | AZ6: =Лист1!BZ7+Лист1!BZ9 -> 225.80213 | BA6: =IFERROR(AY6-AX6,"-") -> 0 | BB6: =IFERROR(AY6/AX6,"-") -> 1 | BC6: =BH6+BM6+BR6 -> 3706 | BD6: =BI6+BN6+BS6 -> 3706 | BE6: =BJ6+BO6+BT6 -> 0 | BF6: =IFERROR(BD6-BC6,"-") -> 0 | BG6: =IFERROR(BD6/BC6,"-") -> 1 | BH6: =Лист1!CL7+Лист1!CL9 -> 1219.6 | BI6: =Лист1!CN7+Лист1!CN9 -> 1219.6 | BJ6: =Лист1!CP7+Лист1!CP9 -> 0 | BK6: =IFERROR(BI6-BH6,"-") -> 0 | BL6: =IFERROR(BI6/BH6,"-") -> 1 | BM6: =Лист1!CT7+Лист1!CT9 -> 1225.1 | BN6: =Лист1!CV7+Лист1!CV9 -> 1225.1 | BO6: =Лист1!CX7+Лист1!CX9 -> 0 | BP6: =IFERROR(BN6-BM6,"-") -> 0 | BQ6: =IFERROR(BN6/BM6,"-") -> 1 | BR6: =Лист1!DB7+Лист1!DB9 -> 1261.3 | BS6: =Лист1!DD7+Лист1!DD9 -> 1261.3 | BT6: =Лист1!DF7+Лист1!DF9 -> 0 | BU6: =IFERROR(BS6-BR6,"-") -> 0 | BV6: =IFERROR(BS6/BR6,"-") -> 1 | BW6: =CB6+CG6+CL6 -> 3865.4 | BX6: =CC6+CH6+CM6 -> 3865.4 | BY6: =CD6+CI6+CN6 -> 0 | BZ6: =IFERROR(BX6-BW6,"-") -> 0 | CA6: =IFERROR(BX6/BW6,"-") -> 1 | CB6: =Лист1!DR7+Лист1!DR9 -> 1303.3 | CC6: =Лист1!DT7+Лист1!DT9 -> 1303.3 | CD6: =Лист1!DV7+Лист1!DV9 -> 0 | CE6: =IFERROR(CC6-CB6,"-") -> 0 | CF6: =IFERROR(CC6/CB6,"-") -> 1 | CG6: =Лист1!DZ7+Лист1!DZ9 -> 1261.3 | CH6: =Лист1!EB7+Лист1!EB9 -> 1261.3 | CI6: =Лист1!ED7+Лист1!ED9 -> 0 | CJ6: =IFERROR(CH6-CG6,"-") -> 0 | CK6: =IFERROR(CH6/CG6,"-") -> 1 | CL6: =Лист1!EH7+Лист1!EH9 -> 1300.8 | CM6: =Лист1!EJ7+Лист1!EJ9 -> 1300.8 | CN6: =Лист1!EL7+Лист1!EL9 -> 0 | CO6: =IFERROR(CM6-CL6,"-") -> 0 | CP6: =IFERROR(CM6/CL6,"-") -> 1
E7: 1 | J7: =O7+AI7+BC7+BW7 -> 111.99 | K7: =P7+AJ7+BD7+BX7 -> 0 | L7: =Q7+AK7+BE7+BY7 -> 0 | M7: =IFERROR(K7-J7,"-") -> -111.99 | N7: =IFERROR(K7/J7,"-") -> 0 | O7: =T7+Y7+AD7 -> 111.99 | P7: =U7+Z7+AE7 -> 0 | Q7: =V7+AA7+AF7 -> 0 | R7: =IFERROR(P7-O7,"-") -> -111.99 | S7: =IFERROR(P7/O7,"-") -> 0 | T7: 111.99 | W7: =IFERROR(U7-T7,"-") -> -111.99 | X7: =IFERROR(U7/T7,"-") -> 0 | AB7: =IFERROR(Z7-Y7,"-") -> 0 | AC7: =IFERROR(Z7/Y7,"-") -> - | AG7: =IFERROR(AE7-AD7,"-") -> 0 | AH7: =IFERROR(AE7/AD7,"-") -> - | AI7: =AN7+AS7+AX7 -> 0 | AJ7: =AO7+AT7+AY7 -> 0 | AK7: =AP7+AU7+AZ7 -> 0 | AL7: =IFERROR(AJ7-AI7,"-") -> 0 | AM7: =IFERROR(AJ7/AI7,"-") -> - | AQ7: =IFERROR(AO7-AN7,"-") -> 0 | AR7: =IFERROR(AO7/AN7,"-") -> - | AV7: =IFERROR(AT7-AS7,"-") -> 0 | AW7: =IFERROR(AT7/AS7,"-") -> - | BA7: =IFERROR(AY7-AX7,"-") -> 0 | BB7: =IFERROR(AY7/AX7,"-") -> - | BC7: =BH7+BM7+BR7 -> 0 | BD7: =BI7+BN7+BS7 -> 0 | BE7: =BJ7+BO7+BT7 -> 0 | BF7: =IFERROR(BD7-BC7,"-") -> 0 | BG7: =IFERROR(BD7/BC7,"-") -> - | BK7: =IFERROR(BI7-BH7,"-") -> 0 | BL7: =IFERROR(BI7/BH7,"-") -> - | BP7: =IFERROR(BN7-BM7,"-") -> 0 | BQ7: =IFERROR(BN7/BM7,"-") -> - | BU7: =IFERROR(BS7-BR7,"-") -> 0 | BV7: =IFERROR(BS7/BR7,"-") -> - | BW7: =CB7+CG7+CL7 -> 0 | BX7: =CC7+CH7+CM7 -> 0 | BY7: =CD7+CI7+CN7 -> 0 | BZ7: =IFERROR(BX7-BW7,"-") -> 0 | CA7: =IFERROR(BX7/BW7,"-") -> - | CE7: =IFERROR(CC7-CB7,"-") -> 0 | CF7: =IFERROR(CC7/CB7,"-") -> - | CJ7: =IFERROR(CH7-CG7,"-") -> 0 | CK7: =IFERROR(CH7/CG7,"-") -> - | CO7: =IFERROR(CM7-CL7,"-") -> 0 | CP7: =IFERROR(CM7/CL7,"-") -> -
E8: 2 | J8: =O8+AI8+BC8+BW8 -> 159.44 | K8: =P8+AJ8+BD8+BX8 -> 0 | L8: =Q8+AK8+BE8+BY8 -> 0 | M8: =IFERROR(K8-J8,"-") -> -159.44 | N8: =IFERROR(K8/J8,"-") -> 0 | O8: =T8+Y8+AD8 -> 159.44 | P8: =U8+Z8+AE8 -> 0 | Q8: =V8+AA8+AF8 -> 0 | R8: =IFERROR(P8-O8,"-") -> -159.44 | S8: =IFERROR(P8/O8,"-") -> 0 | T8: 159.44 | W8: =IFERROR(U8-T8,"-") -> -159.44 | X8: =IFERROR(U8/T8,"-") -> 0 | AB8: =IFERROR(Z8-Y8,"-") -> 0 | AC8: =IFERROR(Z8/Y8,"-") -> - | AG8: =IFERROR(AE8-AD8,"-") -> 0 | AH8: =IFERROR(AE8/AD8,"-") -> - | AI8: =AN8+AS8+AX8 -> 0 | AJ8: =AO8+AT8+AY8 -> 0 | AK8: =AP8+AU8+AZ8 -> 0 | AL8: =IFERROR(AJ8-AI8,"-") -> 0 | AM8: =IFERROR(AJ8/AI8,"-") -> - | AQ8: =IFERROR(AO8-AN8,"-") -> 0 | AR8: =IFERROR(AO8/AN8,"-") -> - | AV8: =IFERROR(AT8-AS8,"-") -> 0 | AW8: =IFERROR(AT8/AS8,"-") -> - | BA8: =IFERROR(AY8-AX8,"-") -> 0 | BB8: =IFERROR(AY8/AX8,"-") -> - | BC8: =BH8+BM8+BR8 -> 0 | BD8: =BI8+BN8+BS8 -> 0 | BE8: =BJ8+BO8+BT8 -> 0 | BF8: =IFERROR(BD8-BC8,"-") -> 0 | BG8: =IFERROR(BD8/BC8,"-") -> - | BK8: =IFERROR(BI8-BH8,"-") -> 0 | BL8: =IFERROR(BI8/BH8,"-") -> - | BP8: =IFERROR(BN8-BM8,"-") -> 0 | BQ8: =IFERROR(BN8/BM8,"-") -> - | BU8: =IFERROR(BS8-BR8,"-") -> 0 | BV8: =IFERROR(BS8/BR8,"-") -> - | BW8: =CB8+CG8+CL8 -> 0 | BX8: =CC8+CH8+CM8 -> 0 | BY8: =CD8+CI8+CN8 -> 0 | BZ8: =IFERROR(BX8-BW8,"-") -> 0 | CA8: =IFERROR(BX8/BW8,"-") -> - | CE8: =IFERROR(CC8-CB8,"-") -> 0 | CF8: =IFERROR(CC8/CB8,"-") -> - | CJ8: =IFERROR(CH8-CG8,"-") -> 0 | CK8: =IFERROR(CH8/CG8,"-") -> - | CO8: =IFERROR(CM8-CL8,"-") -> 0 | CP8: =IFERROR(CM8/CL8,"-") -> -
F9: =F10+F11+1000 -> #VALUE! | J9: =O9+AI9+BC9+BW9 -> 22328.7 | K9: =P9+AJ9+BD9+BX9 -> 22328.7 | L9: =Q9+AK9+BE9+BY9 -> 14830.981 | M9: =IFERROR(K9-J9,"-") -> 0 | N9: =IFERROR(K9/J9,"-") -> 1 | O9: =T9+Y9+AD9 -> 5591.2 | P9: =U9+Z9+AE9 -> 5591.2 | Q9: =V9+AA9+AF9 -> 4796.716 | R9: =IFERROR(P9-O9,"-") -> 0 | S9: =IFERROR(P9/O9,"-") -> 1 | T9: =T10+T11+1000 -> 1892.5 | U9: =U10+U11+1000 -> 1892.5 | V9: =V10+V11+1000 -> 1648.219 | W9: =IFERROR(U9-T9,"-") -> 0 | X9: =IFERROR(U9/T9,"-") -> 1 | Y9: =Y10+Y11+1000 -> 1806.2 | Z9: =Z10+Z11+1000 -> 1806.2 | AA9: =AA10+AA11+1000 -> 1504.768 | AB9: =IFERROR(Z9-Y9,"-") -> 0 | AC9: =IFERROR(Z9/Y9,"-") -> 1 | AD9: =AD10+AD11+1000 -> 1892.5 | AE9: =AE10+AE11+1000 -> 1892.5 | AF9: =AF10+AF11+1000 -> 1643.729 | AG9: =IFERROR(AE9-AD9,"-") -> 0 | AH9: =IFERROR(AE9/AD9,"-") -> 1 | AI9: =AN9+AS9+AX9 -> 4976.3 | AJ9: =AO9+AT9+AY9 -> 4976.3 | AK9: =AP9+AU9+AZ9 -> 4034.265 | AL9: =IFERROR(AJ9-AI9,"-") -> 0 | AM9: =IFERROR(AJ9/AI9,"-") -> 1 | AN9: =AN10+AN11+1000 -> 1863.8 | AO9: =AO10+AO11+1000 -> 1863.8 | AP9: =AP10+AP11+1000 -> 1612.959 | AQ9: =IFERROR(AO9-AN9,"-") -> 0 | AR9: =IFERROR(AO9/AN9,"-") -> 1 | AS9: =AS10+AS11+1000 -> 1613.6 | AT9: =AT10+AT11+1000 -> 1613.6 | AU9: =AU10+AU11+1000 -> 1249.514 | AV9: =IFERROR(AT9-AS9,"-") -> 0 | AW9: =IFERROR(AT9/AS9,"-") -> 1 | AX9: =AX10+AX11+1000 -> 1498.9 | AY9: =AY10+AY11+1000 -> 1498.9 | AZ9: =AZ10+AZ11+1000 -> 1171.792 | BA9: =IFERROR(AY9-AX9,"-") -> 0 | BB9: =IFERROR(AY9/AX9,"-") -> 1 | BC9: =BH9+BM9+BR9 -> 5819.9 | BD9: =BI9+BN9+BS9 -> 5819.9 | BE9: =BJ9+BO9+BT9 -> 3000 | BF9: =IFERROR(BD9-BC9,"-") -> 0 | BG9: =IFERROR(BD9/BC9,"-") -> 1 | BH9: =BH10+BH11+1000 -> 1928 | BI9: =BI10+BI11+1000 -> 1928 | BJ9: =BJ10+BJ11+1000 -> 1000 | BK9: =IFERROR(BI9-BH9,"-") -> 0 | BL9: =IFERROR(BI9/BH9,"-") -> 1 | BM9: =BM10+BM11+1000 -> 1932.2 | BN9: =BN10+BN11+1000 -> 1932.2 | BO9: =BO10+BO11+1000 -> 1000 | BP9: =IFERROR(BN9-BM9,"-") -> 0 | BQ9: =IFERROR(BN9/BM9,"-") -> 1 | BR9: =BR10+BR11+1000 -> 1959.7 | BS9: =BS10+BS11+1000 -> 1959.7 | BT9: =BT10+BT11+1000 -> 1000 | BU9: =IFERROR(BS9-BR9,"-") -> 0 | BV9: =IFERROR(BS9/BR9,"-") -> 1 | BW9: =CB9+CG9+CL9 -> 5941.3 | BX9: =CC9+CH9+CM9 -> 5941.3 | BY9: =CD9+CI9+CN9 -> 3000 | BZ9: =IFERROR(BX9-BW9,"-") -> 0 | CA9: =IFERROR(BX9/BW9,"-") -> 1 | CB9: =CB10+CB11+1000 -> 1991.7 | CC9: =CC10+CC11+1000 -> 1991.7 | CD9: =CD10+CD11+1000 -> 1000 | CE9: =IFERROR(CC9-CB9,"-") -> 0 | CF9: =IFERROR(CC9/CB9,"-") -> 1 | CG9: =CG10+CG11+1000 -> 1959.7 | CH9: =CH10+CH11+1000 -> 1959.7 | CI9: =CI10+CI11+1000 -> 1000 | CJ9: =IFERROR(CH9-CG9,"-") -> 0 | CK9: =IFERROR(CH9/CG9,"-") -> 1 | CL9: =CL10+CL11+1000 -> 1989.9 | CM9: =CM10+CM11+1000 -> 1989.9 | CN9: =CN10+CN11+1000 -> 1000 | CO9: =IFERROR(CM9-CL9,"-") -> 0 | CP9: =IFERROR(CM9/CL9,"-") -> 1
F10: 1_100335800 | J10: =O10+AI10+BC10+BW10 -> 13.6 | K10: =P10+AJ10+BD10+BX10 -> 13.6 | L10: =Q10+AK10+BE10+BY10 -> 3.721 | M10: =IFERROR(K10-J10,"-") -> 0 | N10: =IFERROR(K10/J10,"-") -> 1 | O10: =T10+Y10+AD10 -> 3.4 | P10: =U10+Z10+AE10 -> 3.4 | Q10: =V10+AA10+AF10 -> 2.362 | R10: =IFERROR(P10-O10,"-") -> 0 | S10: =IFERROR(P10/O10,"-") -> 1 | T10: =Лист1!Z11 -> 1.2 | U10: =Лист1!AB11 -> 1.2 | V10: =Лист1!AD11 -> 0.852 | W10: =IFERROR(U10-T10,"-") -> 0 | X10: =IFERROR(U10/T10,"-") -> 1 | Y10: =Лист1!AH11 -> 1.1 | Z10: =Лист1!AJ11 -> 1.1 | AA10: =Лист1!AL11 -> 0.663 | AB10: =IFERROR(Z10-Y10,"-") -> 0 | AC10: =IFERROR(Z10/Y10,"-") -> 1 | AD10: =Лист1!AP11 -> 1.1 | AE10: =Лист1!AR11 -> 1.1 | AF10: =Лист1!AT11 -> 0.847 | AG10: =IFERROR(AE10-AD10,"-") -> 0 | AH10: =IFERROR(AE10/AD10,"-") -> 1 | AI10: =AN10+AS10+AX10 -> 2.6 | AJ10: =AO10+AT10+AY10 -> 2.6 | AK10: =AP10+AU10+AZ10 -> 1.359 | AL10: =IFERROR(AJ10-AI10,"-") -> 0 | AM10: =IFERROR(AJ10/AI10,"-") -> 1 | AN10: =Лист1!BF11 -> 1.2 | AO10: =Лист1!BH11 -> 1.2 | AP10: =Лист1!BJ11 -> 0.807 | AQ10: =IFERROR(AO10-AN10,"-") -> 0 | AR10: =IFERROR(AO10/AN10,"-") -> 1 | AS10: =Лист1!BN11 -> 0.8 | AT10: =Лист1!BP11 -> 0.8 | AU10: =Лист1!BR11 -> 0.327 | AV10: =IFERROR(AT10-AS10,"-") -> 0 | AW10: =IFERROR(AT10/AS10,"-") -> 1 | AX10: =Лист1!BV11 -> 0.6 | AY10: =Лист1!BX11 -> 0.6 | AZ10: =Лист1!BZ11 -> 0.225 | BA10: =IFERROR(AY10-AX10,"-") -> 0 | BB10: =IFERROR(AY10/AX10,"-") -> 1 | BC10: =BH10+BM10+BR10 -> 3.7 | BD10: =BI10+BN10+BS10 -> 3.7 | BE10: =BJ10+BO10+BT10 -> 0 | BF10: =IFERROR(BD10-BC10,"-") -> 0 | BG10: =IFERROR(BD10/BC10,"-") -> 1 | BH10: =Лист1!CL11 -> 1.2 | BI10: =Лист1!CN11 -> 1.2 | BJ10: =Лист1!CP11 -> 0 | BK10: =IFERROR(BI10-BH10,"-") -> 0 | BL10: =IFERROR(BI10/BH10,"-") -> 1 | BM10: =Лист1!CT11 -> 1.2 | BN10: =Лист1!CV11 -> 1.2 | BO10: =Лист1!CX11 -> 0 | BP10: =IFERROR(BN10-BM10,"-") -> 0 | BQ10: =IFERROR(BN10/BM10,"-") -> 1 | BR10: =Лист1!DB11 -> 1.3 | BS10: =Лист1!DD11 -> 1.3 | BT10: =Лист1!DF11 -> 0 | BU10: =IFERROR(BS10-BR10,"-") -> 0 | BV10: =IFERROR(BS10/BR10,"-") -> 1 | BW10: =CB10+CG10+CL10 -> 3.9 | BX10: =CC10+CH10+CM10 -> 3.9 | BY10: =CD10+CI10+CN10 -> 0 | BZ10: =IFERROR(BX10-BW10,"-") -> 0 | CA10: =IFERROR(BX10/BW10,"-") -> 1 | CB10: =Лист1!DR11 -> 1.3 | CC10: =Лист1!DT11 -> 1.3 | CD10: =Лист1!DV11 -> 0 | CE10: =IFERROR(CC10-CB10,"-") -> 0 | CF10: =IFERROR(CC10/CB10,"-") -> 1 | CG10: =Лист1!DZ11 -> 1.3 | CH10: =Лист1!EB11 -> 1.3 | CI10: =Лист1!ED11 -> 0 | CJ10: =IFERROR(CH10-CG10,"-") -> 0 | CK10: =IFERROR(CH10/CG10,"-") -> 1 | CL10: =Лист1!EH11 -> 1.3 | CM10: =Лист1!EJ11 -> 1.3 | CN10: =Лист1!EL11 -> 0 | CO10: =IFERROR(CM10-CL10,"-") -> 0 | CP10: =IFERROR(CM10/CL10,"-") -> 1
F11: 1_100335802 | J11: =O11+AI11+BC11+BW11 -> 10315.1 | K11: =P11+AJ11+BD11+BX11 -> 10315.1 | L11: =Q11+AK11+BE11+BY11 -> 2827.26 | M11: =IFERROR(K11-J11,"-") -> 0 | N11: =IFERROR(K11/J11,"-") -> 1 | O11: =T11+Y11+AD11 -> 2587.8 | P11: =U11+Z11+AE11 -> 2587.8 | Q11: =V11+AA11+AF11 -> 1794.354 | R11: =IFERROR(P11-O11,"-") -> 0 | S11: =IFERROR(P11/O11,"-") -> 1 | T11: =Лист1!Z13 -> 891.3 | U11: =Лист1!AB13 -> 891.3 | V11: =Лист1!AD13 -> 647.367 | W11: =IFERROR(U11-T11,"-") -> 0 | X11: =IFERROR(U11/T11,"-") -> 1 | Y11: =Лист1!AH13 -> 805.1 | Z11: =Лист1!AJ13 -> 805.1 | AA11: =Лист1!AL13 -> 504.105 | AB11: =IFERROR(Z11-Y11,"-") -> 0 | AC11: =IFERROR(Z11/Y11,"-") -> 1 | AD11: =Лист1!AP13 -> 891.4 | AE11: =Лист1!AR13 -> 891.4 | AF11: =Лист1!AT13 -> 642.882 | AG11: =IFERROR(AE11-AD11,"-") -> 0 | AH11: =IFERROR(AE11/AD11,"-") -> 1 | AI11: =AN11+AS11+AX11 -> 1973.7 | AJ11: =AO11+AT11+AY11 -> 1973.7 | AK11: =AP11+AU11+AZ11 -> 1032.906 | AL11: =IFERROR(AJ11-AI11,"-") -> 0 | AM11: =IFERROR(AJ11/AI11,"-") -> 1 | AN11: =Лист1!BF13 -> 862.6 | AO11: =Лист1!BH13 -> 862.6 | AP11: =Лист1!BJ13 -> 612.152 | AQ11: =IFERROR(AO11-AN11,"-") -> 0 | AR11: =IFERROR(AO11/AN11,"-") -> 1 | AS11: =Лист1!BN13 -> 612.8 | AT11: =Лист1!BP13 -> 612.8 | AU11: =Лист1!BR13 -> 249.187 | AV11: =IFERROR(AT11-AS11,"-") -> 0 | AW11: =IFERROR(AT11/AS11,"-") -> 1 | AX11: =Лист1!BV13 -> 498.3 | AY11: =Лист1!BX13 -> 498.3 | AZ11: =Лист1!BZ13 -> 171.567 | BA11: =IFERROR(AY11-AX11,"-") -> 0 | BB11: =IFERROR(AY11/AX11,"-") -> 1 | BC11: =BH11+BM11+BR11 -> 2816.2 | BD11: =BI11+BN11+BS11 -> 2816.2 | BE11: =BJ11+BO11+BT11 -> 0 | BF11: =IFERROR(BD11-BC11,"-") -> 0 | BG11: =IFERROR(BD11/BC11,"-") -> 1 | BH11: =Лист1!CL13 -> 926.8 | BI11: =Лист1!CN13 -> 926.8 | BJ11: =Лист1!CP13 -> 0 | BK11: =IFERROR(BI11-BH11,"-") -> 0 | BL11: =IFERROR(BI11/BH11,"-") -> 1 | BM11: =Лист1!CT13 -> 931 | BN11: =Лист1!CV13 -> 931 | BO11: =Лист1!CX13 -> 0 | BP11: =IFERROR(BN11-BM11,"-") -> 0 | BQ11: =IFERROR(BN11/BM11,"-") -> 1 | BR11: =Лист1!DB13 -> 958.4 | BS11: =Лист1!DD13 -> 958.4 | BT11: =Лист1!DF13 -> 0 | BU11: =IFERROR(BS11-BR11,"-") -> 0 | BV11: =IFERROR(BS11/BR11,"-") -> 1 | BW11: =CB11+CG11+CL11 -> 2937.4 | BX11: =CC11+CH11+CM11 -> 2937.4 | BY11: =CD11+CI11+CN11 -> 0 | BZ11: =IFERROR(BX11-BW11,"-") -> 0 | CA11: =IFERROR(BX11/BW11,"-") -> 1 | CB11: =Лист1!DR13 -> 990.4 | CC11: =Лист1!DT13 -> 990.4 | CD11: =Лист1!DV13 -> 0 | CE11: =IFERROR(CC11-CB11,"-") -> 0 | CF11: =IFERROR(CC11/CB11,"-") -> 1 | CG11: =Лист1!DZ13 -> 958.4 | CH11: =Лист1!EB13 -> 958.4 | CI11: =Лист1!ED13 -> 0 | CJ11: =IFERROR(CH11-CG11,"-") -> 0 | CK11: =IFERROR(CH11/CG11,"-") -> 1 | CL11: =Лист1!EH13 -> 988.6 | CM11: =Лист1!EJ13 -> 988.6 | CN11: =Лист1!EL13 -> 0 | CO11: =IFERROR(CM11-CL11,"-") -> 0 | CP11: =IFERROR(CM11/CL11,"-") -> 1
F12: 1_100335802+1_100335804 | J12: =O12+AI12+BC12+BW12 -> 13560.6 | K12: =P12+AJ12+BD12+BX12 -> 13560.6 | L12: =Q12+AK12+BE12+BY12 -> 3721.8477 | M12: =IFERROR(K12-J12,"-") -> 0 | N12: =IFERROR(K12/J12,"-") -> 1 | O12: =T12+Y12+AD12 -> 3402 | P12: =U12+Z12+AE12 -> 3402 | Q12: =V12+AA12+AF12 -> 2361.2268 | R12: =IFERROR(P12-O12,"-") -> 0 | S12: =IFERROR(P12/O12,"-") -> 1 | T12: =Лист1!Z13+Лист1!Z15 -> 1171.7 | U12: =Лист1!AB13+Лист1!AB15 -> 1171.7 | V12: =Лист1!AD13+Лист1!AD15 -> 851.3629 | W12: =IFERROR(U12-T12,"-") -> 0 | X12: =IFERROR(U12/T12,"-") -> 1 | Y12: =Лист1!AH13+Лист1!AH15 -> 1058.4 | Z12: =Лист1!AJ13+Лист1!AJ15 -> 1058.4 | AA12: =Лист1!AL13+Лист1!AL15 -> 663.10537 | AB12: =IFERROR(Z12-Y12,"-") -> 0 | AC12: =IFERROR(Z12/Y12,"-") -> 1 | AD12: =Лист1!AP13+Лист1!AP15 -> 1171.9 | AE12: =Лист1!AR13+Лист1!AR15 -> 1171.9 | AF12: =Лист1!AT13+Лист1!AT15 -> 846.7585 | AG12: =IFERROR(AE12-AD12,"-") -> 0 | AH12: =IFERROR(AE12/AD12,"-") -> 1 | AI12: =AN12+AS12+AX12 -> 2594.8 | AJ12: =AO12+AT12+AY12 -> 2594.8 | AK12: =AP12+AU12+AZ12 -> 1360.6209 | AL12: =IFERROR(AJ12-AI12,"-") -> 0 | AM12: =IFERROR(AJ12/AI12,"-") -> 1 | AN12: =Лист1!BF13+Лист1!BF15 -> 1134 | AO12: =Лист1!BH13+Лист1!BH15 -> 1134 | AP12: =Лист1!BJ13+Лист1!BJ15 -> 807.15779 | AQ12: =IFERROR(AO12-AN12,"-") -> 0 | AR12: =IFERROR(AO12/AN12,"-") -> 1 | AS12: =Лист1!BN13+Лист1!BN15 -> 805.6 | AT12: =Лист1!BP13+Лист1!BP15 -> 805.6 | AU12: =Лист1!BR13+Лист1!BR15 -> 327.886 | AV12: =IFERROR(AT12-AS12,"-") -> 0 | AW12: =IFERROR(AT12/AS12,"-") -> 1 | AX12: =Лист1!BV13+Лист1!BV15 -> 655.2 | AY12: =Лист1!BX13+Лист1!BX15 -> 655.2 | AZ12: =Лист1!BZ13+Лист1!BZ15 -> 225.57713 | BA12: =IFERROR(AY12-AX12,"-") -> 0 | BB12: =IFERROR(AY12/AX12,"-") -> 1 | BC12: =BH12+BM12+BR12 -> 3702.3 | BD12: =BI12+BN12+BS12 -> 3702.3 | BE12: =BJ12+BO12+BT12 -> 0 | BF12: =IFERROR(BD12-BC12,"-") -> 0 | BG12: =IFERROR(BD12/BC12,"-") -> 1 | BH12: =Лист1!CL13+Лист1!CL15 -> 1218.4 | BI12: =Лист1!CN13+Лист1!CN15 -> 1218.4 | BJ12: =Лист1!CP13+Лист1!CP15 -> 0 | BK12: =IFERROR(BI12-BH12,"-") -> 0 | BL12: =IFERROR(BI12/BH12,"-") -> 1 | BM12: =Лист1!CT13+Лист1!CT15 -> 1223.9 | BN12: =Лист1!CV13+Лист1!CV15 -> 1223.9 | BO12: =Лист1!CX13+Лист1!CX15 -> 0 | BP12: =IFERROR(BN12-BM12,"-") -> 0 | BQ12: =IFERROR(BN12/BM12,"-") -> 1 | BR12: =Лист1!DB13+Лист1!DB15 -> 1260 | BS12: =Лист1!DD13+Лист1!DD15 -> 1260 | BT12: =Лист1!DF13+Лист1!DF15 -> 0 | BU12: =IFERROR(BS12-BR12,"-") -> 0 | BV12: =IFERROR(BS12/BR12,"-") -> 1 | BW12: =CB12+CG12+CL12 -> 3861.5 | BX12: =CC12+CH12+CM12 -> 3861.5 | BY12: =CD12+CI12+CN12 -> 0 | BZ12: =IFERROR(BX12-BW12,"-") -> 0 | CA12: =IFERROR(BX12/BW12,"-") -> 1 | CB12: =Лист1!DR13+Лист1!DR15 -> 1302 | CC12: =Лист1!DT13+Лист1!DT15 -> 1302 | CD12: =Лист1!DV13+Лист1!DV15 -> 0 | CE12: =IFERROR(CC12-CB12,"-") -> 0 | CF12: =IFERROR(CC12/CB12,"-") -> 1 | CG12: =Лист1!DZ13+Лист1!DZ15 -> 1260 | CH12: =Лист1!EB13+Лист1!EB15 -> 1260 | CI12: =Лист1!ED13+Лист1!ED15 -> 0 | CJ12: =IFERROR(CH12-CG12,"-") -> 0 | CK12: =IFERROR(CH12/CG12,"-") -> 1 | CL12: =Лист1!EH13+Лист1!EH15 -> 1299.5 | CM12: =Лист1!EJ13+Лист1!EJ15 -> 1299.5 | CN12: =Лист1!EL13+Лист1!EL15 -> 0 | CO12: =IFERROR(CM12-CL12,"-") -> 0 | CP12: =IFERROR(CM12/CL12,"-") -> 1
E13: 3 | J13: =O13+AI13+BC13+BW13 -> 0 | K13: =P13+AJ13+BD13+BX13 -> 0 | L13: =Q13+AK13+BE13+BY13 -> 0 | M13: =IFERROR(K13-J13,"-") -> 0 | N13: =IFERROR(K13/J13,"-") -> - | O13: =T13+Y13+AD13 -> 0 | P13: =U13+Z13+AE13 -> 0 | Q13: =V13+AA13+AF13 -> 0 | R13: =IFERROR(P13-O13,"-") -> 0 | S13: =IFERROR(P13/O13,"-") -> - | W13: =IFERROR(U13-T13,"-") -> 0 | X13: =IFERROR(U13/T13,"-") -> - | AB13: =IFERROR(Z13-Y13,"-") -> 0 | AC13: =IFERROR(Z13/Y13,"-") -> - | AG13: =IFERROR(AE13-AD13,"-") -> 0 | AH13: =IFERROR(AE13/AD13,"-") -> - | AI13: =AN13+AS13+AX13 -> 0 | AJ13: =AO13+AT13+AY13 -> 0 | AK13: =AP13+AU13+AZ13 -> 0 | AL13: =IFERROR(AJ13-AI13,"-") -> 0 | AM13: =IFERROR(AJ13/AI13,"-") -> - | AQ13: =IFERROR(AO13-AN13,"-") -> 0 | AR13: =IFERROR(AO13/AN13,"-") -> - | AV13: =IFERROR(AT13-AS13,"-") -> 0 | AW13: =IFERROR(AT13/AS13,"-") -> - | BA13: =IFERROR(AY13-AX13,"-") -> 0 | BB13: =IFERROR(AY13/AX13,"-") -> - | BC13: =BH13+BM13+BR13 -> 0 | BD13: =BI13+BN13+BS13 -> 0 | BE13: =BJ13+BO13+BT13 -> 0 | BF13: =IFERROR(BD13-BC13,"-") -> 0 | BG13: =IFERROR(BD13/BC13,"-") -> - | BK13: =IFERROR(BI13-BH13,"-") -> 0 | BL13: =IFERROR(BI13/BH13,"-") -> - | BP13: =IFERROR(BN13-BM13,"-") -> 0 | BQ13: =IFERROR(BN13/BM13,"-") -> - | BU13: =IFERROR(BS13-BR13,"-") -> 0 | BV13: =IFERROR(BS13/BR13,"-") -> - | BW13: =CB13+CG13+CL13 -> 0 | BX13: =CC13+CH13+CM13 -> 0 | BY13: =CD13+CI13+CN13 -> 0 | BZ13: =IFERROR(BX13-BW13,"-") -> 0 | CA13: =IFERROR(BX13/BW13,"-") -> - | CE13: =IFERROR(CC13-CB13,"-") -> 0 | CF13: =IFERROR(CC13/CB13,"-") -> - | CJ13: =IFERROR(CH13-CG13,"-") -> 0 | CK13: =IFERROR(CH13/CG13,"-") -> - | CO13: =IFERROR(CM13-CL13,"-") -> 0 | CP13: =IFERROR(CM13/CL13,"-") -> -
E14: 4 | J14: =O14+AI14+BC14+BW14 -> 0 | K14: =P14+AJ14+BD14+BX14 -> 2556 | L14: =Q14+AK14+BE14+BY14 -> 0 | M14: =IFERROR(K14-J14,"-") -> 2556 | N14: =IFERROR(K14/J14,"-") -> - | O14: =T14+Y14+AD14 -> 0 | P14: =U14+Z14+AE14 -> 2556 | Q14: =V14+AA14+AF14 -> 0 | R14: =IFERROR(P14-O14,"-") -> 2556 | S14: =IFERROR(P14/O14,"-") -> - | U14: 2556 | W14: =IFERROR(U14-T14,"-") -> 2556 | X14: =IFERROR(U14/T14,"-") -> - | AB14: =IFERROR(Z14-Y14,"-") -> 0 | AC14: =IFERROR(Z14/Y14,"-") -> - | AG14: =IFERROR(AE14-AD14,"-") -> 0 | AH14: =IFERROR(AE14/AD14,"-") -> - | AI14: =AN14+AS14+AX14 -> 0 | AJ14: =AO14+AT14+AY14 -> 0 | AK14: =AP14+AU14+AZ14 -> 0 | AL14: =IFERROR(AJ14-AI14,"-") -> 0 | AM14: =IFERROR(AJ14/AI14,"-") -> - | AQ14: =IFERROR(AO14-AN14,"-") -> 0 | AR14: =IFERROR(AO14/AN14,"-") -> - | AV14: =IFERROR(AT14-AS14,"-") -> 0 | AW14: =IFERROR(AT14/AS14,"-") -> - | BA14: =IFERROR(AY14-AX14,"-") -> 0 | BB14: =IFERROR(AY14/AX14,"-") -> - | BC14: =BH14+BM14+BR14 -> 0 | BD14: =BI14+BN14+BS14 -> 0 | BE14: =BJ14+BO14+BT14 -> 0 | BF14: =IFERROR(BD14-BC14,"-") -> 0 | BG14: =IFERROR(BD14/BC14,"-") -> - | BK14: =IFERROR(BI14-BH14,"-") -> 0 | BL14: =IFERROR(BI14/BH14,"-") -> - | BP14: =IFERROR(BN14-BM14,"-") -> 0 | BQ14: =IFERROR(BN14/BM14,"-") -> - | BU14: =IFERROR(BS14-BR14,"-") -> 0 | BV14: =IFERROR(BS14/BR14,"-") -> - | BW14: =CB14+CG14+CL14 -> 0 | BX14: =CC14+CH14+CM14 -> 0 | BY14: =CD14+CI14+CN14 -> 0 | BZ14: =IFERROR(BX14-BW14,"-") -> 0 | CA14: =IFERROR(BX14/BW14,"-") -> - | CE14: =IFERROR(CC14-CB14,"-") -> 0 | CF14: =IFERROR(CC14/CB14,"-") -> - | CJ14: =IFERROR(CH14-CG14,"-") -> 0 | CK14: =IFERROR(CH14/CG14,"-") -> - | CO14: =IFERROR(CM14-CL14,"-") -> 0 | CP14: =IFERROR(CM14/CL14,"-") -> -
E15: 5 | J15: =O15+AI15+BC15+BW15 -> 0 | K15: =P15+AJ15+BD15+BX15 -> 0 | L15: =Q15+AK15+BE15+BY15 -> 0 | M15: =IFERROR(K15-J15,"-") -> 0 | N15: =IFERROR(K15/J15,"-") -> - | O15: =T15+Y15+AD15 -> 0 | P15: =U15+Z15+AE15 -> 0 | Q15: =V15+AA15+AF15 -> 0 | R15: =IFERROR(P15-O15,"-") -> 0 | S15: =IFERROR(P15/O15,"-") -> - | W15: =IFERROR(U15-T15,"-") -> 0 | X15: =IFERROR(U15/T15,"-") -> - | AB15: =IFERROR(Z15-Y15,"-") -> 0 | AC15: =IFERROR(Z15/Y15,"-") -> - | AG15: =IFERROR(AE15-AD15,"-") -> 0 | AH15: =IFERROR(AE15/AD15,"-") -> - | AI15: =AN15+AS15+AX15 -> 0 | AJ15: =AO15+AT15+AY15 -> 0 | AK15: =AP15+AU15+AZ15 -> 0 | AL15: =IFERROR(AJ15-AI15,"-") -> 0 | AM15: =IFERROR(AJ15/AI15,"-") -> - | AQ15: =IFERROR(AO15-AN15,"-") -> 0 | AR15: =IFERROR(AO15/AN15,"-") -> - | AV15: =IFERROR(AT15-AS15,"-") -> 0 | AW15: =IFERROR(AT15/AS15,"-") -> - | BA15: =IFERROR(AY15-AX15,"-") -> 0 | BB15: =IFERROR(AY15/AX15,"-") -> - | BC15: =BH15+BM15+BR15 -> 0 | BD15: =BI15+BN15+BS15 -> 0 | BE15: =BJ15+BO15+BT15 -> 0 | BF15: =IFERROR(BD15-BC15,"-") -> 0 | BG15: =IFERROR(BD15/BC15,"-") -> - | BK15: =IFERROR(BI15-BH15,"-") -> 0 | BL15: =IFERROR(BI15/BH15,"-") -> - | BP15: =IFERROR(BN15-BM15,"-") -> 0 | BQ15: =IFERROR(BN15/BM15,"-") -> - | BU15: =IFERROR(BS15-BR15,"-") -> 0 | BV15: =IFERROR(BS15/BR15,"-") -> - | BW15: =CB15+CG15+CL15 -> 0 | BX15: =CC15+CH15+CM15 -> 0 | BY15: =CD15+CI15+CN15 -> 0 | BZ15: =IFERROR(BX15-BW15,"-") -> 0 | CA15: =IFERROR(BX15/BW15,"-") -> - | CE15: =IFERROR(CC15-CB15,"-") -> 0 | CF15: =IFERROR(CC15/CB15,"-") -> - | CJ15: =IFERROR(CH15-CG15,"-") -> 0 | CK15: =IFERROR(CH15/CG15,"-") -> - | CO15: =IFERROR(CM15-CL15,"-") -> 0 | CP15: =IFERROR(CM15/CL15,"-") -> -
F16: 1_100335806+1_100331985+1_100331986 | J16: =O16+AI16+BC16+BW16 -> 13871.102 | K16: =P16+AJ16+BD16+BX16 -> 13871.102 | L16: =Q16+AK16+BE16+BY16 -> 3869.4245 | M16: =IFERROR(K16-J16,"-") -> 0 | N16: =IFERROR(K16/J16,"-") -> 1 | O16: =T16+Y16+AD16 -> 3450.842 | P16: =U16+Z16+AE16 -> 3450.842 | Q16: =V16+AA16+AF16 -> 2460.9858 | R16: =IFERROR(P16-O16,"-") -> 0 | S16: =IFERROR(P16/O16,"-") -> 1 | T16: =Лист1!Z17+Лист1!Z19+Лист1!Z20 -> 1186.918 | U16: =Лист1!AB17+Лист1!AB19+Лист1!AB20 -> 1186.918 | V16: =Лист1!AD17+Лист1!AD19+Лист1!AD20 -> 882.73091 | W16: =IFERROR(U16-T16,"-") -> 0 | X16: =IFERROR(U16/T16,"-") -> 1 | Y16: =Лист1!AH17+Лист1!AH19+Лист1!AH20 -> 1074.907 | Z16: =Лист1!AJ17+Лист1!AJ19+Лист1!AJ20 -> 1074.907 | AA16: =Лист1!AL17+Лист1!AL19+Лист1!AL20 -> 694.34137 | AB16: =IFERROR(Z16-Y16,"-") -> 0 | AC16: =IFERROR(Z16/Y16,"-") -> 1 | AD16: =Лист1!AP17+Лист1!AP19+Лист1!AP20 -> 1189.017 | AE16: =Лист1!AR17+Лист1!AR19+Лист1!AR20 -> 1189.017 | AF16: =Лист1!AT17+Лист1!AT19+Лист1!AT20 -> 883.9135 | AG16: =IFERROR(AE16-AD16,"-") -> 0 | AH16: =IFERROR(AE16/AD16,"-") -> 1 | AI16: =AN16+AS16+AX16 -> 2665.769 | AJ16: =AO16+AT16+AY16 -> 2665.769 | AK16: =AP16+AU16+AZ16 -> 1408.4387 | AL16: =IFERROR(AJ16-AI16,"-") -> 0 | AM16: =IFERROR(AJ16/AI16,"-") -> 1 | AN16: =Лист1!BF17+Лист1!BF19+Лист1!BF20 -> 1168.842 | AO16: =Лист1!BH17+Лист1!BH19+Лист1!BH20 -> 1168.842 | AP16: =Лист1!BJ17+Лист1!BJ19+Лист1!BJ20 -> 834.79661 | AQ16: =IFERROR(AO16-AN16,"-") -> 0 | AR16: =IFERROR(AO16/AN16,"-") -> 1 | AS16: =Лист1!BN17+Лист1!BN19+Лист1!BN20 -> 829.027 | AT16: =Лист1!BP17+Лист1!BP19+Лист1!BP20 -> 829.027 | AU16: =Лист1!BR17+Лист1!BR19+Лист1!BR20 -> 340.308 | AV16: =IFERROR(AT16-AS16,"-") -> 0 | AW16: =IFERROR(AT16/AS16,"-") -> 1 | AX16: =Лист1!BV17+Лист1!BV19+Лист1!BV20 -> 667.9 | AY16: =Лист1!BX17+Лист1!BX19+Лист1!BX20 -> 667.9 | AZ16: =Лист1!BZ17+Лист1!BZ19+Лист1!BZ20 -> 233.33413 | BA16: =IFERROR(AY16-AX16,"-") -> 0 | BB16: =IFERROR(AY16/AX16,"-") -> 1 | BC16: =BH16+BM16+BR16 -> 3849.863 | BD16: =BI16+BN16+BS16 -> 3849.863 | BE16: =BJ16+BO16+BT16 -> 0 | BF16: =IFERROR(BD16-BC16,"-") -> 0 | BG16: =IFERROR(BD16/BC16,"-") -> 1 | BH16: =Лист1!CL17+Лист1!CL19+Лист1!CL20 -> 1265.972 | BI16: =Лист1!CN17+Лист1!CN19+Лист1!CN20 -> 1265.972 | BJ16: =Лист1!CP17+Лист1!CP19+Лист1!CP20 -> 0 | BK16: =IFERROR(BI16-BH16,"-") -> 0 | BL16: =IFERROR(BI16/BH16,"-") -> 1 | BM16: =Лист1!CT17+Лист1!CT19+Лист1!CT20 -> 1290.147 | BN16: =Лист1!CV17+Лист1!CV19+Лист1!CV20 -> 1290.147 | BO16: =Лист1!CX17+Лист1!CX19+Лист1!CX20 -> 0 | BP16: =IFERROR(BN16-BM16,"-") -> 0 | BQ16: =IFERROR(BN16/BM16,"-") -> 1 | BR16: =Лист1!DB17+Лист1!DB19+Лист1!DB20 -> 1293.744 | BS16: =Лист1!DD17+Лист1!DD19+Лист1!DD20 -> 1293.744 | BT16: =Лист1!DF17+Лист1!DF19+Лист1!DF20 -> 0 | BU16: =IFERROR(BS16-BR16,"-") -> 0 | BV16: =IFERROR(BS16/BR16,"-") -> 1 | BW16: =CB16+CG16+CL16 -> 3904.628 | BX16: =CC16+CH16+CM16 -> 3904.628 | BY16: =CD16+CI16+CN16 -> 0 | BZ16: =IFERROR(BX16-BW16,"-") -> 0 | CA16: =IFERROR(BX16/BW16,"-") -> 1 | CB16: =Лист1!DR17+Лист1!DR19+Лист1!DR20 -> 1317.897 | CC16: =Лист1!DT17+Лист1!DT19+Лист1!DT20 -> 1317.897 | CD16: =Лист1!DV17+Лист1!DV19+Лист1!DV20 -> 0 | CE16: =IFERROR(CC16-CB16,"-") -> 0 | CF16: =IFERROR(CC16/CB16,"-") -> 1 | CG16: =Лист1!DZ17+Лист1!DZ19+Лист1!DZ20 -> 1276.213 | CH16: =Лист1!EB17+Лист1!EB19+Лист1!EB20 -> 1276.213 | CI16: =Лист1!ED17+Лист1!ED19+Лист1!ED20 -> 0 | CJ16: =IFERROR(CH16-CG16,"-") -> 0 | CK16: =IFERROR(CH16/CG16,"-") -> 1 | CL16: =Лист1!EH17+Лист1!EH19+Лист1!EH20 -> 1310.518 | CM16: =Лист1!EJ17+Лист1!EJ19+Лист1!EJ20 -> 1310.518 | CN16: =Лист1!EL17+Лист1!EL19+Лист1!EL20 -> 0 | CO16: =IFERROR(CM16-CL16,"-") -> 0 | CP16: =IFERROR(CM16/CL16,"-") -> 1

Sheet Лист1
A2: № п/п | B2: Показатели | C2: Внутренние настройки листа | I2: Ед. изм. | J2: 2026 | L2: 2026 | N2: 2026 | R2: 2026 год 1 квартал | T2: 2026 год 1 квартал | V2: 2026 год 1 квартал | Z2: 2026 год январь | AB2: 2026 год январь | AD2: 2026 год январь | AH2: 2026 год февраль | AJ2: 2026 год февраль | AL2: 2026 год февраль | AP2: 2026 год март | AR2: 2026 год март | AT2: 2026 год март | AX2: 2026 год 2 квартал | AZ2: 2026 год 2 квартал | BB2: 2026 год 2 квартал | BF2: 2026 год апрель | BH2: 2026 год апрель | BJ2: 2026 год апрель | BN2: 2026 год май | BP2: 2026 год май | BR2: 2026 год май | BV2: 2026 год июнь | BX2: 2026 год июнь | BZ2: 2026 год июнь | CD2: 2026 год 3 квартал | CF2: 2026 год 3 квартал | CH2: 2026 год 3 квартал | CL2: 2026 год июль | CN2: 2026 год июль | CP2: 2026 год июль | CT2: 2026 год август | CV2: 2026 год август | CX2: 2026 год август | DB2: 2026 год сентябрь | DD2: 2026 год сентябрь | DF2: 2026 год сентябрь | DJ2: 2026 год 4 квартал | DL2: 2026 год 4 квартал | DN2: 2026 год 4 квартал | DR2: 2026 год октябрь | DT2: 2026 год октябрь | DV2: 2026 год октябрь | DZ2: 2026 год ноябрь | EB2: 2026 год ноябрь | ED2: 2026 год ноябрь | EH2: 2026 год декабрь | EJ2: 2026 год декабрь | EL2: 2026 год декабрь
C3: Ключ статьи | D3: Ключ спец расчётов | E3: Ключ ввод данных | F3: Формула месяц | G3: Формула % Выхода | H3: Строка проверка | J3: Среднесрочн. план 2026: Вариант утвержденный | K3: % выхода | L3: Среднесрочн. план 2026 ПРЭУ: Вариант на утверждение | M3: % выхода | N3: Факт | O3: % выхода | P3: Отклонение | R3: Среднесрочн. план 2026: Вариант утвержденный | S3: % выхода | T3: Среднесрочн. план 2026 ПРЭУ: Вариант на утверждение | U3: % выхода | V3: Факт | W3: % выхода | X3: Отклонение | Z3: Среднесрочн. план 2026: Вариант утвержденный | AA3: % выхода | AB3: Среднесрочн. план 2026 ПРЭУ: Вариант на утверждение | AC3: % выхода | AD3: Факт | AE3: % выхода | AF3: Отклонение | AH3: Среднесрочн. план 2026: Вариант утвержденный | AI3: % выхода | AJ3: Среднесрочн. план 2026 ПРЭУ: Вариант на утверждение | AK3: % выхода | AL3: Факт | AM3: % выхода | AN3: Отклонение | AP3: Среднесрочн. план 2026: Вариант утвержденный | AQ3: % выхода | AR3: Среднесрочн. план 2026 ПРЭУ: Вариант на утверждение | AS3: % выхода | AT3: Факт | AU3: % выхода | AV3: Отклонение | AX3: Среднесрочн. план 2026: Вариант утвержденный | AY3: % выхода | AZ3: Среднесрочн. план 2026 ПРЭУ: Вариант на утверждение | BA3: % выхода | BB3: Факт | BC3: % выхода | BD3: Отклонение | BF3: Среднесрочн. план 2026: Вариант утвержденный | BG3: % выхода | BH3: Среднесрочн. план 2026 ПРЭУ: Вариант на утверждение | BI3: % выхода | BJ3: Факт | BK3: % выхода | BL3: Отклонение | BN3: Среднесрочн. план 2026: Вариант утвержденный | BO3: % выхода | BP3: Среднесрочн. план 2026 ПРЭУ: Вариант на утверждение | BQ3: % выхода | BR3: Факт | BS3: % выхода | BT3: Отклонение | BV3: Среднесрочн. план 2026: Вариант утвержденный | BW3: % выхода | BX3: Среднесрочн. план 2026 ПРЭУ: Вариант на утверждение | BY3: % выхода | BZ3: Факт | CA3: % выхода | CB3: Отклонение | CD3: Среднесрочн. план 2026: Вариант утвержденный | CE3: % выхода | CF3: Среднесрочн. план 2026 ПРЭУ: Вариант на утверждение | CG3: % выхода | CH3: Факт | CI3: % выхода | CJ3: Отклонение | CL3: Среднесрочн. план 2026: Вариант утвержденный | CM3: % выхода | CN3: Среднесрочн. план 2026 ПРЭУ: Вариант на утверждение | CO3: % выхода | CP3: Факт | CQ3: % выхода | CR3: Отклонение | CT3: Среднесрочн. план 2026: Вариант утвержденный | CU3: % выхода | CV3: Среднесрочн. план 2026 ПРЭУ: Вариант на утверждение | CW3: % выхода | CX3: Факт | CY3: % выхода | CZ3: Отклонение | DB3: Среднесрочн. план 2026: Вариант утвержденный | DC3: % выхода | DD3: Среднесрочн. план 2026 ПРЭУ: Вариант на утверждение | DE3: % выхода | DF3: Факт | DG3: % выхода | DH3: Отклонение | DJ3: Среднесрочн. план 2026: Вариант утвержденный | DK3: % выхода | DL3: Среднесрочн. план 2026 ПРЭУ: Вариант на утверждение | DM3: % выхода | DN3: Факт | DO3: % выхода | DP3: Отклонение | DR3: Среднесрочн. план 2026: Вариант утвержденный | DS3: % выхода | DT3: Среднесрочн. план 2026 ПРЭУ: Вариант на утверждение | DU3: % выхода | DV3: Факт | DW3: % выхода | DX3: Отклонение | DZ3: Среднесрочн. план 2026: Вариант утвержденный | EA3: % выхода | EB3: Среднесрочн. план 2026 ПРЭУ: Вариант на утверждение | EC3: % выхода | ED3: Факт | EE3: % выхода | EF3: Отклонение | EH3: Среднесрочн. план 2026: Вариант утвержденный | EI3: % выхода | EJ3: Среднесрочн. план 2026 ПРЭУ: Вариант на утверждение | EK3: % выхода | EL3: Факт | EM3: % выхода | EN3: Отклонение
P4: + / - | Q4: % вып. | X4: + / - | Y4: % вып. | AF4: + / - | AG4: % вып. | AN4: + / - | AO4: % вып. | AV4: + / - | AW4: % вып. | BD4: + / - | BE4: % вып. | BL4: + / - | BM4: % вып. | BT4: + / - | BU4: % вып. | CB4: + / - | CC4: % вып. | CJ4: + / - | CK4: % вып. | CR4: + / - | CS4: % вып. | CZ4: + / - | DA4: % вып. | DH4: + / - | DI4: % вып. | DP4: + / - | DQ4: % вып. | DX4: + / - | DY4: % вып. | EF4: + / - | EG4: % вып. | EN4: + / - | EO4: % вып.
J5: year2026:1:2260099 | L5: year2026:1:2260010 | N5: year2026:15:None | R5: year2026:Q1:1:2260099 | T5: year2026:Q1:1:2260010 | V5: year2026:Q1:15:None | Z5: year2026:M1_1:1:2260099 | AB5: year2026:M1_1:1:2260010 | AD5: year2026:M1_1:15:None | AH5: year2026:M1_2:1:2260099 | AJ5: year2026:M1_2:1:2260010 | AL5: year2026:M1_2:15:None | AP5: year2026:M1_3:1:2260099 | AR5: year2026:M1_3:1:2260010 | AT5: year2026:M1_3:15:None | AX5: year2026:Q2:1:2260099 | AZ5: year2026:Q2:1:2260010 | BB5: year2026:Q2:15:None | BF5: year2026:M2_1:1:2260099 | BH5: year2026:M2_1:1:2260010 | BJ5: year2026:M2_1:15:None | BN5: year2026:M2_2:1:2260099 | BP5: year2026:M2_2:1:2260010 | BR5: year2026:M2_2:15:None | BV5: year2026:M2_3:1:2260099 | BX5: year2026:M2_3:1:2260010 | BZ5: year2026:M2_3:15:None | CD5: year2026:Q3:1:2260099 | CF5: year2026:Q3:1:2260010 | CH5: year2026:Q3:15:None | CL5: year2026:M3_1:1:2260099 | CN5: year2026:M3_1:1:2260010 | CP5: year2026:M3_1:15:None | CT5: year2026:M3_2:1:2260099 | CV5: year2026:M3_2:1:2260010 | CX5: year2026:M3_2:15:None | DB5: year2026:M3_3:1:2260099 | DD5: year2026:M3_3:1:2260010 | DF5: year2026:M3_3:15:None | DJ5: year2026:Q4:1:2260099 | DL5: year2026:Q4:1:2260010 | DN5: year2026:Q4:15:None | DR5: year2026:M4_1:1:2260099 | DT5: year2026:M4_1:1:2260010 | DV5: year2026:M4_1:15:None | DZ5: year2026:M4_2:1:2260099 | EB5: year2026:M4_2:1:2260010 | ED5: year2026:M4_2:15:None | EH5: year2026:M4_3:1:2260099 | EJ5: year2026:M4_3:1:2260010 | EL5: year2026:M4_3:15:None
A6: 1 | B6: ОКАЗАНИЕ УСЛУГ ПО СЕПАРАЦИИ СЫРЬЯ ООО "Газпром добыча Астрахань" | C6: 100331977 | F6: 100331978+100335798 | G6: ОКРУГЛ({100331977:-1}/{100331977:-1}*$100;$6) | H6: Да | J6: =R6+AX6+CD6+DJ6 -> 13574.2 | K6: =ROUND(J6/J6*100,6) -> 100 | L6: =T6+AZ6+CF6+DL6 -> 13574.2 | M6: =ROUND(L6/L6*100,6) -> 100 | N6: =V6+BB6+CH6+DN6 -> 3725.5687 | O6: =ROUND(N6/N6*100,6) -> 100 | P6: =IFERROR(L6-J6,"-") -> 0 | Q6: =IFERROR(L6/J6,"-") -> 1 | R6: =Z6+AH6+AP6 -> 3405.4 | S6: =ROUND(R6/R6*100,6) -> 100 | T6: =AB6+AJ6+AR6 -> 3405.4 | U6: =ROUND(T6/T6*100,6) -> 100 | V6: =AD6+AL6+AT6 -> 2363.5888 | W6: =ROUND(V6/V6*100,6) -> 100 | X6: =IFERROR(T6-R6,"-") -> 0 | Y6: =IFERROR(T6/R6,"-") -> 1 | Z6: =Z7+Z9 -> 1172.9 | AA6: =ROUND(Z6/Z6*100,6) -> 100 | AB6: =AB7+AB9 -> 1172.9 | AC6: =ROUND(AB6/AB6*100,6) -> 100 | AD6: =AD7+AD9 -> 852.21491 | AE6: =ROUND(AD6/AD6*100,6) -> 100 | AF6: =IFERROR(AB6-Z6,"-") -> 0 | AG6: =IFERROR(AB6/Z6,"-") -> 1 | AH6: =AH7+AH9 -> 1059.5 | AI6: =ROUND(AH6/AH6*100,6) -> 100 | AJ6: =AJ7+AJ9 -> 1059.5 | AK6: =ROUND(AJ6/AJ6*100,6) -> 100 | AL6: =AL7+AL9 -> 663.76837 | AM6: =ROUND(AL6/AL6*100,6) -> 100 | AN6: =IFERROR(AJ6-AH6,"-") -> 0 | AO6: =IFERROR(AJ6/AH6,"-") -> 1 | AP6: =AP7+AP9 -> 1173 | AQ6: =ROUND(AP6/AP6*100,6) -> 100 | AR6: =AR7+AR9 -> 1173 | AS6: =ROUND(AR6/AR6*100,6) -> 100 | AT6: =AT7+AT9 -> 847.6055 | AU6: =ROUND(AT6/AT6*100,6) -> 100 | AV6: =IFERROR(AR6-AP6,"-") -> 0 | AW6: =IFERROR(AR6/AP6,"-") -> 1 | AX6: =BF6+BN6+BV6 -> 2597.4 | AY6: =ROUND(AX6/AX6*100,6) -> 100 | AZ6: =BH6+BP6+BX6 -> 2597.4 | BA6: =ROUND(AZ6/AZ6*100,6) -> 100 | BB6: =BJ6+BR6+BZ6 -> 1361.9799 | BC6: =ROUND(BB6/BB6*100,6) -> 100 | BD6: =IFERROR(AZ6-AX6,"-") -> 0 | BE6: =IFERROR(AZ6/AX6,"-") -> 1 | BF6: =BF7+BF9 -> 1135.2 | BG6: =ROUND(BF6/BF6*100,6) -> 100 | BH6: =BH7+BH9 -> 1135.2 | BI6: =ROUND(BH6/BH6*100,6) -> 100 | BJ6: =BJ7+BJ9 -> 807.96479 | BK6: =ROUND(BJ6/BJ6*100,6) -> 100 | BL6: =IFERROR(BH6-BF6,"-") -> 0 | BM6: =IFERROR(BH6/BF6,"-") -> 1 | BN6: =BN7+BN9 -> 806.4 | BO6: =ROUND(BN6/BN6*100,6) -> 100 | BP6: =BP7+BP9 -> 806.4 | BQ6: =ROUND(BP6/BP6*100,6) -> 100 | BR6: =BR7+BR9 -> 328.213 | BS6: =ROUND(BR6/BR6*100,6) -> 100 | BT6: =IFERROR(BP6-BN6,"-") -> 0 | BU6: =IFERROR(BP6/BN6,"-") -> 1 | BV6: =BV7+BV9 -> 655.8 | BW6: =ROUND(BV6/BV6*100,6) -> 100 | BX6: =BX7+BX9 -> 655.8 | BY6: =ROUND(BX6/BX6*100,6) -> 100 | BZ6: =BZ7+BZ9 -> 225.80213 | CA6: =ROUND(BZ6/BZ6*100,6) -> 100 | CB6: =IFERROR(BX6-BV6,"-") -> 0 | CC6: =IFERROR(BX6/BV6,"-") -> 1 | CD6: =CL6+CT6+DB6 -> 3706 | CE6: =ROUND(CD6/CD6*100,6) -> 100 | CF6: =CN6+CV6+DD6 -> 3706 | CG6: =ROUND(CF6/CF6*100,6) -> 100 | CH6: =CP6+CX6+DF6 -> 0 | CI6: =ROUND(CH6/CH6*100,6) -> #DIV/0! | CJ6: =IFERROR(CF6-CD6,"-") -> 0 | CK6: =IFERROR(CF6/CD6,"-") -> 1 | CL6: =CL7+CL9 -> 1219.6 | CM6: =ROUND(CL6/CL6*100,6) -> 100 | CN6: =CN7+CN9 -> 1219.6 | CO6: =ROUND(CN6/CN6*100,6) -> 100 | CP6: =CP7+CP9 -> 0 | CQ6: =ROUND(CP6/CP6*100,6) -> #DIV/0! | CR6: =IFERROR(CN6-CL6,"-") -> 0 | CS6: =IFERROR(CN6/CL6,"-") -> 1 | CT6: =CT7+CT9 -> 1225.1 | CU6: =ROUND(CT6/CT6*100,6) -> 100 | CV6: =CV7+CV9 -> 1225.1 | CW6: =ROUND(CV6/CV6*100,6) -> 100 | CX6: =CX7+CX9 -> 0 | CY6: =ROUND(CX6/CX6*100,6) -> #DIV/0! | CZ6: =IFERROR(CV6-CT6,"-") -> 0 | DA6: =IFERROR(CV6/CT6,"-") -> 1 | DB6: =DB7+DB9 -> 1261.3 | DC6: =ROUND(DB6/DB6*100,6) -> 100 | DD6: =DD7+DD9 -> 1261.3 | DE6: =ROUND(DD6/DD6*100,6) -> 100 | DF6: =DF7+DF9 -> 0 | DG6: =ROUND(DF6/DF6*100,6) -> #DIV/0! | DH6: =IFERROR(DD6-DB6,"-") -> 0 | DI6: =IFERROR(DD6/DB6,"-") -> 1 | DJ6: =DR6+DZ6+EH6 -> 3865.4 | DK6: =ROUND(DJ6/DJ6*100,6) -> 100 | DL6: =DT6+EB6+EJ6 -> 3865.4 | DM6: =ROUND(DL6/DL6*100,6) -> 100 | DN6: =DV6+ED6+EL6 -> 0 | DO6: =ROUND(DN6/DN6*100,6) -> #DIV/0! | DP6: =IFERROR(DL6-DJ6,"-") -> 0 | DQ6: =IFERROR(DL6/DJ6,"-") -> 1 | DR6: =DR7+DR9 -> 1303.3 | DS6: =ROUND(DR6/DR6*100,6) -> 100 | DT6: =DT7+DT9 -> 1303.3 | DU6: =ROUND(DT6/DT6*100,6) -> 100 | DV6: =DV7+DV9 -> 0 | DW6: =ROUND(DV6/DV6*100,6) -> #DIV/0! | DX6: =IFERROR(DT6-DR6,"-") -> 0 | DY6: =IFERROR(DT6/DR6,"-") -> 1 | DZ6: =DZ7+DZ9 -> 1261.3 | EA6: =ROUND(DZ6/DZ6*100,6) -> 100 | EB6: =EB7+EB9 -> 1261.3 | EC6: =ROUND(EB6/EB6*100,6) -> 100 | ED6: =ED7+ED9 -> 0 | EE6: =ROUND(ED6/ED6*100,6) -> #DIV/0! | EF6: =IFERROR(EB6-DZ6,"-") -> 0 | EG6: =IFERROR(EB6/DZ6,"-") -> 1 | EH6: =EH7+EH9 -> 1300.8 | EI6: =ROUND(EH6/EH6*100,6) -> 100 | EJ6: =EJ7+EJ9 -> 1300.8 | EK6: =ROUND(EJ6/EJ6*100,6) -> 100 | EL6: =EL7+EL9 -> 0 | EM6: =ROUND(EL6/EL6*100,6) -> #DIV/0! | EN6: =IFERROR(EJ6-EH6,"-") -> 0 | EO6: =IFERROR(EJ6/EH6,"-") -> 1
A7: 1.1 | B7: СЕПАРАЦИЯ ПРИРОДНОГО ГАЗА, собственность ООО "Газпром добыча Астрахань" | C7: 100331978 | J7: =R7+AX7+CD7+DJ7 -> 10325.4 | L7: =T7+AZ7+CF7+DL7 -> 10325.4 | N7: =V7+BB7+CH7+DN7 -> 2830.087 | P7: =IFERROR(L7-J7,"-") -> 0 | Q7: =IFERROR(L7/J7,"-") -> 1 | R7: =Z7+AH7+AP7 -> 2590.4 | T7: =AB7+AJ7+AR7 -> 2590.4 | V7: =AD7+AL7+AT7 -> 1796.149 | X7: =IFERROR(T7-R7,"-") -> 0 | Y7: =IFERROR(T7/R7,"-") -> 1 | Z7: 892.2 | AB7: 892.2 | AD7: 648.015 | AF7: =IFERROR(AB7-Z7,"-") -> 0 | AG7: =IFERROR(AB7/Z7,"-") -> 1 | AH7: 805.9 | AJ7: 805.9 | AL7: 504.609 | AN7: =IFERROR(AJ7-AH7,"-") -> 0 | AO7: =IFERROR(AJ7/AH7,"-") -> 1 | AP7: 892.3 | AR7: 892.3 | AT7: 643.525 | AV7: =IFERROR(AR7-AP7,"-") -> 0 | AW7: =IFERROR(AR7/AP7,"-") -> 1 | AX7: =BF7+BN7+BV7 -> 1975.7 | AZ7: =BH7+BP7+BX7 -> 1975.7 | BB7: =BJ7+BR7+BZ7 -> 1033.938 | BD7: =IFERROR(AZ7-AX7,"-") -> 0 | BE7: =IFERROR(AZ7/AX7,"-") -> 1 | BF7: 863.5 | BH7: 863.5 | BJ7: 612.764 | BL7: =IFERROR(BH7-BF7,"-") -> 0 | BM7: =IFERROR(BH7/BF7,"-") -> 1 | BN7: 613.4 | BP7: 613.4 | BR7: 249.436 | BT7: =IFERROR(BP7-BN7,"-") -> 0 | BU7: =IFERROR(BP7/BN7,"-") -> 1 | BV7: 498.8 | BX7: 498.8 | BZ7: 171.738 | CB7: =IFERROR(BX7-BV7,"-") -> 0 | CC7: =IFERROR(BX7/BV7,"-") -> 1 | CD7: =CL7+CT7+DB7 -> 2819 | CF7: =CN7+CV7+DD7 -> 2819 | CH7: =CP7+CX7+DF7 -> 0 | CJ7: =IFERROR(CF7-CD7,"-") -> 0 | CK7: =IFERROR(CF7/CD7,"-") -> 1 | CL7: 927.7 | CN7: 927.7 | CR7: =IFERROR(CN7-CL7,"-") -> 0 | CS7: =IFERROR(CN7/CL7,"-") -> 1 | CT7: 931.9 | CV7: 931.9 | CZ7: =IFERROR(CV7-CT7,"-") -> 0 | DA7: =IFERROR(CV7/CT7,"-") -> 1 | DB7: 959.4 | DD7: 959.4 | DH7: =IFERROR(DD7-DB7,"-") -> 0 | DI7: =IFERROR(DD7/DB7,"-") -> 1 | DJ7: =DR7+DZ7+EH7 -> 2940.3 | DL7: =DT7+EB7+EJ7 -> 2940.3 | DN7: =DV7+ED7+EL7 -> 0 | DP7: =IFERROR(DL7-DJ7,"-") -> 0 | DQ7: =IFERROR(DL7/DJ7,"-") -> 1 | DR7: 991.4 | DT7: 991.4 | DX7: =IFERROR(DT7-DR7,"-") -> 0 | DY7: =IFERROR(DT7/DR7,"-") -> 1 | DZ7: 959.4 | EB7: 959.4 | EF7: =IFERROR(EB7-DZ7,"-") -> 0 | EG7: =IFERROR(EB7/DZ7,"-") -> 1 | EH7: 989.5 | EJ7: 989.5 | EN7: =IFERROR(EJ7-EH7,"-") -> 0 | EO7: =IFERROR(EJ7/EH7,"-") -> 1
C8: 100331979 | G8: ОКРУГЛ({100331977:-1}/{100331979:-1}*$100;$6) | H8: *+59 | J8: =R8+AX8+CD8+DJ8 -> 9686.1 | K8: =ROUND(J6/J8*100,6) -> 140.14103 | L8: =T8+AZ8+CF8+DL8 -> 9686.1 | M8: =ROUND(L6/L8*100,6) -> 140.14103 | N8: =V8+BB8+CH8+DN8 -> 2671.357 | O8: =ROUND(N6/N8*100,6) -> 139.46353 | P8: =IFERROR(L8-J8,"-") -> 0 | Q8: =IFERROR(L8/J8,"-") -> 1 | R8: =Z8+AH8+AP8 -> 2430 | S8: =ROUND(R6/R8*100,6) -> 140.13992 | T8: =AB8+AJ8+AR8 -> 2430 | U8: =ROUND(T6/T8*100,6) -> 140.13992 | V8: =AD8+AL8+AT8 -> 1691.83 | W8: =ROUND(V6/V8*100,6) -> 139.70604 | X8: =IFERROR(T8-R8,"-") -> 0 | Y8: =IFERROR(T8/R8,"-") -> 1 | Z8: 837 | AA8: =ROUND(Z6/Z8*100,6) -> 140.13142 | AB8: 837 | AC8: =ROUND(AB6/AB8*100,6) -> 140.13142 | AD8: 608.825 | AE8: =ROUND(AD6/AD8*100,6) -> 139.97699 | AF8: =IFERROR(AB8-Z8,"-") -> 0 | AG8: =IFERROR(AB8/Z8,"-") -> 1 | AH8: 756 | AI8: =ROUND(AH6/AH8*100,6) -> 140.1455 | AJ8: 756 | AK8: =ROUND(AJ6/AJ8*100,6) -> 140.1455 | AL8: 474.536 | AM8: =ROUND(AL6/AL8*100,6) -> 139.87735 | AN8: =IFERROR(AJ8-AH8,"-") -> 0 | AO8: =IFERROR(AJ8/AH8,"-") -> 1 | AP8: 837 | AQ8: =ROUND(AP6/AP8*100,6) -> 140.14337 | AR8: 837 | AS8: =ROUND(AR6/AR8*100,6) -> 140.14337 | AT8: 608.469 | AU8: =ROUND(AT6/AT8*100,6) -> 139.30134 | AV8: =IFERROR(AR8-AP8,"-") -> 0 | AW8: =IFERROR(AR8/AP8,"-") -> 1 | AX8: =BF8+BN8+BV8 -> 1853.4 | AY8: =ROUND(AX6/AX8*100,6) -> 140.14244 | AZ8: =BH8+BP8+BX8 -> 1853.4 | BA8: =ROUND(AZ6/AZ8*100,6) -> 140.14244 | BB8: =BJ8+BR8+BZ8 -> 979.527 | BC8: =ROUND(BB6/BB8*100,6) -> 139.04465 | BD8: =IFERROR(AZ8-AX8,"-") -> 0 | BE8: =IFERROR(AZ8/AX8,"-") -> 1 | BF8: 810 | BG8: =ROUND(BF6/BF8*100,6) -> 140.14815 | BH8: 810 | BI8: =ROUND(BH6/BH8*100,6) -> 140.14815 | BJ8: 581.994 | BK8: =ROUND(BJ6/BJ8*100,6) -> 138.827 | BL8: =IFERROR(BH8-BF8,"-") -> 0 | BM8: =IFERROR(BH8/BF8,"-") -> 1 | BN8: 575.4 | BO8: =ROUND(BN6/BN8*100,6) -> 140.14598 | BP8: 575.4 | BQ8: =ROUND(BP6/BP8*100,6) -> 140.14598 | BR8: 236.34 | BS8: =ROUND(BR6/BR8*100,6) -> 138.87323 | BT8: =IFERROR(BP8-BN8,"-") -> 0 | BU8: =IFERROR(BP8/BN8,"-") -> 1 | BV8: 468 | BW8: =ROUND(BV6/BV8*100,6) -> 140.12821 | BX8: 468 | BY8: =ROUND(BX6/BX8*100,6) -> 140.12821 | BZ8: 161.193 | CA8: =ROUND(BZ6/BZ8*100,6) -> 140.08185 | CB8: =IFERROR(BX8-BV8,"-") -> 0 | CC8: =IFERROR(BX8/BV8,"-") -> 1 | CD8: =CL8+CT8+DB8 -> 2644.5 | CE8: =ROUND(CD6/CD8*100,6) -> 140.13991 | CF8: =CN8+CV8+DD8 -> 2644.5 | CG8: =ROUND(CF6/CF8*100,6) -> 140.13991 | CH8: =CP8+CX8+DF8 -> 0 | CI8: =ROUND(CH6/CH8*100,6) -> #DIV/0! | CJ8: =IFERROR(CF8-CD8,"-") -> 0 | CK8: =IFERROR(CF8/CD8,"-") -> 1 | CL8: 870.3 | CM8: =ROUND(CL6/CL8*100,6) -> 140.13558 | CN8: 870.3 | CO8: =ROUND(CN6/CN8*100,6) -> 140.13558 | CQ8: =ROUND(CP6/CP8*100,6) -> #DIV/0! | CR8: =IFERROR(CN8-CL8,"-") -> 0 | CS8: =IFERROR(CN8/CL8,"-") -> 1 | CT8: 874.2 | CU8: =ROUND(CT6/CT8*100,6) -> 140.13956 | CV8: 874.2 | CW8: =ROUND(CV6/CV8*100,6) -> 140.13956 | CY8: =ROUND(CX6/CX8*100,6) -> #DIV/0! | CZ8: =IFERROR(CV8-CT8,"-") -> 0 | DA8: =IFERROR(CV8/CT8,"-") -> 1 | DB8: 900 | DC8: =ROUND(DB6/DB8*100,6) -> 140.14444 | DD8: 900 | DE8: =ROUND(DD6/DD8*100,6) -> 140.14444 | DG8: =ROUND(DF6/DF8*100,6) -> #DIV/0! | DH8: =IFERROR(DD8-DB8,"-") -> 0 | DI8: =IFERROR(DD8/DB8,"-") -> 1 | DJ8: =DR8+DZ8+EH8 -> 2758.2 | DK8: =ROUND(DJ6/DJ8*100,6) -> 140.14212 | DL8: =DT8+EB8+EJ8 -> 2758.2 | DM8: =ROUND(DL6/DL8*100,6) -> 140.14212 | DN8: =DV8+ED8+EL8 -> 0 | DO8: =ROUND(DN6/DN8*100,6) -> #DIV/0! | DP8: =IFERROR(DL8-DJ8,"-") -> 0 | DQ8: =IFERROR(DL8/DJ8,"-") -> 1 | DR8: 930 | DS8: =ROUND(DR6/DR8*100,6) -> 140.13978 | DT8: 930 | DU8: =ROUND(DT6/DT8*100,6) -> 140.13978 | DW8: =ROUND(DV6/DV8*100,6) -> #DIV/0! | DX8: =IFERROR(DT8-DR8,"-") -> 0 | DY8: =IFERROR(DT8/DR8,"-") -> 1 | DZ8: 900 | EA8: =ROUND(DZ6/DZ8*100,6) -> 140.14444 | EB8: 900 | EC8: =ROUND(EB6/EB8*100,6) -> 140.14444 | EE8: =ROUND(ED6/ED8*100,6) -> #DIV/0! | EF8: =IFERROR(EB8-DZ8,"-") -> 0 | EG8: =IFERROR(EB8/DZ8,"-") -> 1 | EH8: 928.2 | EI8: =ROUND(EH6/EH8*100,6) -> 140.14221 | EJ8: 928.2 | EK8: =ROUND(EJ6/EJ8*100,6) -> 140.14221 | EM8: =ROUND(EL6/EL8*100,6) -> #DIV/0! | EN8: =IFERROR(EJ8-EH8,"-") -> 0 | EO8: =IFERROR(EJ8/EH8,"-") -> 1
A9: 1.2 | B9: СЕПАРАЦИЯ КОНДЕНСАТА ГАЗОВОГО НЕСТАБИЛЬНОГО, собственность ООО "Газпром добыча Астрахань" | C9: 100335798 | J9: =R9+AX9+CD9+DJ9 -> 3248.8 | L9: =T9+AZ9+CF9+DL9 -> 3248.8 | N9: =V9+BB9+CH9+DN9 -> 895.4817 | P9: =IFERROR(L9-J9,"-") -> 0 | Q9: =IFERROR(L9/J9,"-") -> 1 | R9: =Z9+AH9+AP9 -> 815 | T9: =AB9+AJ9+AR9 -> 815 | V9: =AD9+AL9+AT9 -> 567.43978 | X9: =IFERROR(T9-R9,"-") -> 0 | Y9: =IFERROR(T9/R9,"-") -> 1 | Z9: 280.7 | AB9: 280.7 | AD9: 204.19991 | AF9: =IFERROR(AB9-Z9,"-") -> 0 | AG9: =IFERROR(AB9/Z9,"-") -> 1 | AH9: 253.6 | AJ9: 253.6 | AL9: 159.15937 | AN9: =IFERROR(AJ9-AH9,"-") -> 0 | AO9: =IFERROR(AJ9/AH9,"-") -> 1 | AP9: 280.7 | AR9: 280.7 | AT9: 204.0805 | AV9: =IFERROR(AR9-AP9,"-") -> 0 | AW9: =IFERROR(AR9/AP9,"-") -> 1 | AX9: =BF9+BN9+BV9 -> 621.7 | AZ9: =BH9+BP9+BX9 -> 621.7 | BB9: =BJ9+BR9+BZ9 -> 328.04192 | BD9: =IFERROR(AZ9-AX9,"-") -> 0 | BE9: =IFERROR(AZ9/AX9,"-") -> 1 | BF9: 271.7 | BH9: 271.7 | BJ9: 195.20079 | BL9: =IFERROR(BH9-BF9,"-") -> 0 | BM9: =IFERROR(BH9/BF9,"-") -> 1 | BN9: 193 | BP9: 193 | BR9: 78.777 | BT9: =IFERROR(BP9-BN9,"-") -> 0 | BU9: =IFERROR(BP9/BN9,"-") -> 1 | BV9: 157 | BX9: 157 | BZ9: 54.064132 | CB9: =IFERROR(BX9-BV9,"-") -> 0 | CC9: =IFERROR(BX9/BV9,"-") -> 1 | CD9: =CL9+CT9+DB9 -> 887 | CF9: =CN9+CV9+DD9 -> 887 | CH9: =CP9+CX9+DF9 -> 0 | CJ9: =IFERROR(CF9-CD9,"-") -> 0 | CK9: =IFERROR(CF9/CD9,"-") -> 1 | CL9: 291.9 | CN9: 291.9 | CR9: =IFERROR(CN9-CL9,"-") -> 0 | CS9: =IFERROR(CN9/CL9,"-") -> 1 | CT9: 293.2 | CV9: 293.2 | CZ9: =IFERROR(CV9-CT9,"-") -> 0 | DA9: =IFERROR(CV9/CT9,"-") -> 1 | DB9: 301.9 | DD9: 301.9 | DH9: =IFERROR(DD9-DB9,"-") -> 0 | DI9: =IFERROR(DD9/DB9,"-") -> 1 | DJ9: =DR9+DZ9+EH9 -> 925.1 | DL9: =DT9+EB9+EJ9 -> 925.1 | DN9: =DV9+ED9+EL9 -> 0 | DP9: =IFERROR(DL9-DJ9,"-") -> 0 | DQ9: =IFERROR(DL9/DJ9,"-") -> 1 | DR9: 311.9 | DT9: 311.9 | DX9: =IFERROR(DT9-DR9,"-") -> 0 | DY9: =IFERROR(DT9/DR9,"-") -> 1 | DZ9: 301.9 | EB9: 301.9 | EF9: =IFERROR(EB9-DZ9,"-") -> 0 | EG9: =IFERROR(EB9/DZ9,"-") -> 1 | EH9: 311.3 | EJ9: 311.3 | EN9: =IFERROR(EJ9-EH9,"-") -> 0 | EO9: =IFERROR(EJ9/EH9,"-") -> 1
B10: ПОТЕРИ СЫРЬЯ ПРИ ПЕРЕРАБОТКЕ (УСЛОВНЫЕ), собственность ООО "Газпром добыча Астрахань": | C10: 100335799 | F10: 1_100335800 | J10: =R10+AX10+CD10+DJ10 -> 13.6 | L10: =T10+AZ10+CF10+DL10 -> 13.6 | N10: =V10+BB10+CH10+DN10 -> 3.721 | P10: =IFERROR(L10-J10,"-") -> 0 | Q10: =IFERROR(L10/J10,"-") -> 1 | R10: =Z10+AH10+AP10 -> 3.4 | T10: =AB10+AJ10+AR10 -> 3.4 | V10: =AD10+AL10+AT10 -> 2.362 | X10: =IFERROR(T10-R10,"-") -> 0 | Y10: =IFERROR(T10/R10,"-") -> 1 | Z10: =Лист1!Z11 -> 1.2 | AB10: =Лист1!AB11 -> 1.2 | AD10: =Лист1!AD11 -> 0.852 | AF10: =IFERROR(AB10-Z10,"-") -> 0 | AG10: =IFERROR(AB10/Z10,"-") -> 1 | AH10: =Лист1!AH11 -> 1.1 | AJ10: =Лист1!AJ11 -> 1.1 | AL10: =Лист1!AL11 -> 0.663 | AN10: =IFERROR(AJ10-AH10,"-") -> 0 | AO10: =IFERROR(AJ10/AH10,"-") -> 1 | AP10: =Лист1!AP11 -> 1.1 | AR10: =Лист1!AR11 -> 1.1 | AT10: =Лист1!AT11 -> 0.847 | AV10: =IFERROR(AR10-AP10,"-") -> 0 | AW10: =IFERROR(AR10/AP10,"-") -> 1 | AX10: =BF10+BN10+BV10 -> 2.6 | AZ10: =BH10+BP10+BX10 -> 2.6 | BB10: =BJ10+BR10+BZ10 -> 1.359 | BD10: =IFERROR(AZ10-AX10,"-") -> 0 | BE10: =IFERROR(AZ10/AX10,"-") -> 1 | BF10: =Лист1!BF11 -> 1.2 | BH10: =Лист1!BH11 -> 1.2 | BJ10: =Лист1!BJ11 -> 0.807 | BL10: =IFERROR(BH10-BF10,"-") -> 0 | BM10: =IFERROR(BH10/BF10,"-") -> 1 | BN10: =Лист1!BN11 -> 0.8 | BP10: =Лист1!BP11 -> 0.8 | BR10: =Лист1!BR11 -> 0.327 | BT10: =IFERROR(BP10-BN10,"-") -> 0 | BU10: =IFERROR(BP10/BN10,"-") -> 1 | BV10: =Лист1!BV11 -> 0.6 | BX10: =Лист1!BX11 -> 0.6 | BZ10: =Лист1!BZ11 -> 0.225 | CB10: =IFERROR(BX10-BV10,"-") -> 0 | CC10: =IFERROR(BX10/BV10,"-") -> 1 | CD10: =CL10+CT10+DB10 -> 3.7 | CF10: =CN10+CV10+DD10 -> 3.7 | CH10: =CP10+CX10+DF10 -> 0 | CJ10: =IFERROR(CF10-CD10,"-") -> 0 | CK10: =IFERROR(CF10/CD10,"-") -> 1 | CL10: =Лист1!CL11 -> 1.2 | CN10: =Лист1!CN11 -> 1.2 | CP10: =Лист1!CP11 -> 0 | CR10: =IFERROR(CN10-CL10,"-") -> 0 | CS10: =IFERROR(CN10/CL10,"-") -> 1 | CT10: =Лист1!CT11 -> 1.2 | CV10: =Лист1!CV11 -> 1.2 | CX10: =Лист1!CX11 -> 0 | CZ10: =IFERROR(CV10-CT10,"-") -> 0 | DA10: =IFERROR(CV10/CT10,"-") -> 1 | DB10: =Лист1!DB11 -> 1.3 | DD10: =Лист1!DD11 -> 1.3 | DF10: =Лист1!DF11 -> 0 | DH10: =IFERROR(DD10-DB10,"-") -> 0 | DI10: =IFERROR(DD10/DB10,"-") -> 1 | DJ10: =DR10+DZ10+EH10 -> 3.9 | DL10: =DT10+EB10+EJ10 -> 3.9 | DN10: =DV10+ED10+EL10 -> 0 | DP10: =IFERROR(DL10-DJ10,"-") -> 0 | DQ10: =IFERROR(DL10/DJ10,"-") -> 1 | DR10: =Лист1!DR11 -> 1.3 | DT10: =Лист1!DT11 -> 1.3 | DV10: =Лист1!DV11 -> 0 | DX10: =IFERROR(DT10-DR10,"-") -> 0 | DY10: =IFERROR(DT10/DR10,"-") -> 1 | DZ10: =Лист1!DZ11 -> 1.3 | EB10: =Лист1!EB11 -> 1.3 | ED10: =Лист1!ED11 -> 0 | EF10: =IFERROR(EB10-DZ10,"-") -> 0 | EG10: =IFERROR(EB10/DZ10,"-") -> 1 | EH10: =Лист1!EH11 -> 1.3 | EJ10: =Лист1!EJ11 -> 1.3 | EL10: =Лист1!EL11 -> 0 | EN10: =IFERROR(EJ10-EH10,"-") -> 0 | EO10: =IFERROR(EJ10/EH10,"-") -> 1
B11: Природного газа и нестабильного конденсата | C11: 100335800 | G11: {100331977:0}-{100331979:0} | J11: =R11+AX11+CD11+DJ11 -> 13.6 | K11: =K6-K8 -> -40.141027 | L11: =T11+AZ11+CF11+DL11 -> 13.6 | M11: =M6-M8 -> -40.141027 | N11: =V11+BB11+CH11+DN11 -> 3.721 | O11: =O6-O8 -> -39.463527 | P11: =IFERROR(L11-J11,"-") -> 0 | Q11: =IFERROR(L11/J11,"-") -> 1 | R11: =Z11+AH11+AP11 -> 3.4 | S11: =S6-S8 -> -40.139918 | T11: =AB11+AJ11+AR11 -> 3.4 | U11: =U6-U8 -> -40.139918 | V11: =AD11+AL11+AT11 -> 2.362 | W11: =W6-W8 -> -39.706045 | X11: =IFERROR(T11-R11,"-") -> 0 | Y11: =IFERROR(T11/R11,"-") -> 1 | Z11: 1.2 | AA11: =AA6-AA8 -> -40.131422 | AB11: 1.2 | AC11: =AC6-AC8 -> -40.131422 | AD11: 0.852 | AE11: =AE6-AE8 -> -39.976989 | AF11: =IFERROR(AB11-Z11,"-") -> 0 | AG11: =IFERROR(AB11/Z11,"-") -> 1 | AH11: 1.1 | AI11: =AI6-AI8 -> -40.145503 | AJ11: 1.1 | AK11: =AK6-AK8 -> -40.145503 | AL11: 0.663 | AM11: =AM6-AM8 -> -39.877348 | AN11: =IFERROR(AJ11-AH11,"-") -> 0 | AO11: =IFERROR(AJ11/AH11,"-") -> 1 | AP11: 1.1 | AQ11: =AQ6-AQ8 -> -40.143369 | AR11: 1.1 | AS11: =AS6-AS8 -> -40.143369 | AT11: 0.847 | AU11: =AU6-AU8 -> -39.301345 | AV11: =IFERROR(AR11-AP11,"-") -> 0 | AW11: =IFERROR(AR11/AP11,"-") -> 1 | AX11: =BF11+BN11+BV11 -> 2.6 | AY11: =AY6-AY8 -> -40.142441 | AZ11: =BH11+BP11+BX11 -> 2.6 | BA11: =BA6-BA8 -> -40.142441 | BB11: =BJ11+BR11+BZ11 -> 1.359 | BC11: =BC6-BC8 -> -39.044653 | BD11: =IFERROR(AZ11-AX11,"-") -> 0 | BE11: =IFERROR(AZ11/AX11,"-") -> 1 | BF11: 1.2 | BG11: =BG6-BG8 -> -40.148148 | BH11: 1.2 | BI11: =BI6-BI8 -> -40.148148 | BJ11: 0.807 | BK11: =BK6-BK8 -> -38.826996 | BL11: =IFERROR(BH11-BF11,"-") -> 0 | BM11: =IFERROR(BH11/BF11,"-") -> 1 | BN11: 0.8 | BO11: =BO6-BO8 -> -40.145985 | BP11: 0.8 | BQ11: =BQ6-BQ8 -> -40.145985 | BR11: 0.327 | BS11: =BS6-BS8 -> -38.873233 | BT11: =IFERROR(BP11-BN11,"-") -> 0 | BU11: =IFERROR(BP11/BN11,"-") -> 1 | BV11: 0.6 | BW11: =BW6-BW8 -> -40.128205 | BX11: 0.6 | BY11: =BY6-BY8 -> -40.128205 | BZ11: 0.225 | CA11: =CA6-CA8 -> -40.081847 | CB11: =IFERROR(BX11-BV11,"-") -> 0 | CC11: =IFERROR(BX11/BV11,"-") -> 1 | CD11: =CL11+CT11+DB11 -> 3.7 | CE11: =CE6-CE8 -> -40.139913 | CF11: =CN11+CV11+DD11 -> 3.7 | CG11: =CG6-CG8 -> -40.139913 | CH11: =CP11+CX11+DF11 -> 0 | CI11: =CI6-CI8 -> #DIV/0! | CJ11: =IFERROR(CF11-CD11,"-") -> 0 | CK11: =IFERROR(CF11/CD11,"-") -> 1 | CL11: 1.2 | CM11: =CM6-CM8 -> -40.135585 | CN11: 1.2 | CO11: =CO6-CO8 -> -40.135585 | CQ11: =CQ6-CQ8 -> #DIV/0! | CR11: =IFERROR(CN11-CL11,"-") -> 0 | CS11: =IFERROR(CN11/CL11,"-") -> 1 | CT11: 1.2 | CU11: =CU6-CU8 -> -40.139556 | CV11: 1.2 | CW11: =CW6-CW8 -> -40.139556 | CY11: =CY6-CY8 -> #DIV/0! | CZ11: =IFERROR(CV11-CT11,"-") -> 0 | DA11: =IFERROR(CV11/CT11,"-") -> 1 | DB11: 1.3 | DC11: =DC6-DC8 -> -40.144444 | DD11: 1.3 | DE11: =DE6-DE8 -> -40.144444 | DG11: =DG6-DG8 -> #DIV/0! | DH11: =IFERROR(DD11-DB11,"-") -> 0 | DI11: =IFERROR(DD11/DB11,"-") -> 1 | DJ11: =DR11+DZ11+EH11 -> 3.9 | DK11: =DK6-DK8 -> -40.142122 | DL11: =DT11+EB11+EJ11 -> 3.9 | DM11: =DM6-DM8 -> -40.142122 | DN11: =DV11+ED11+EL11 -> 0 | DO11: =DO6-DO8 -> #DIV/0! | DP11: =IFERROR(DL11-DJ11,"-") -> 0 | DQ11: =IFERROR(DL11/DJ11,"-") -> 1 | DR11: 1.3 | DS11: =DS6-DS8 -> -40.139785 | DT11: 1.3 | DU11: =DU6-DU8 -> -40.139785 | DW11: =DW6-DW8 -> #DIV/0! | DX11: =IFERROR(DT11-DR11,"-") -> 0 | DY11: =IFERROR(DT11/DR11,"-") -> 1 | DZ11: 1.3 | EA11: =EA6-EA8 -> -40.144444 | EB11: 1.3 | EC11: =EC6-EC8 -> -40.144444 | EE11: =EE6-EE8 -> #DIV/0! | EF11: =IFERROR(EB11-DZ11,"-") -> 0 | EG11: =IFERROR(EB11/DZ11,"-") -> 1 | EH11: 1.3 | EI11: =EI6-EI8 -> -40.142211 | EJ11: 1.3 | EK11: =EK6-EK8 -> -40.142211 | EM11: =EM6-EM8 -> #DIV/0! | EN11: =IFERROR(EJ11-EH11,"-") -> 0 | EO11: =IFERROR(EJ11/EH11,"-") -> 1
A12: 1.3 | B12: ПРОИЗВОДСТВО ПРОДУКЦИИ, собственность ООО "Газпром добыча Астрахань" ВСЕГО: | C12: 100335801 | F12: 1_100335802+1_100335804 | G12: {100331977:0}+{100331979:0}+$10000 | J12: =R12+AX12+CD12+DJ12 -> 13560.6 | K12: =K6+K8+10000 -> 10240.141 | L12: =T12+AZ12+CF12+DL12 -> 13560.6 | M12: =M6+M8+10000 -> 10240.141 | N12: =V12+BB12+CH12+DN12 -> 3721.8477 | O12: =O6+O8+10000 -> 10239.464 | P12: =IFERROR(L12-J12,"-") -> 0 | Q12: =IFERROR(L12/J12,"-") -> 1 | R12: =Z12+AH12+AP12 -> 3402 | S12: =S6+S8+10000 -> 10240.14 | T12: =AB12+AJ12+AR12 -> 3402 | U12: =U6+U8+10000 -> 10240.14 | V12: =AD12+AL12+AT12 -> 2361.2268 | W12: =W6+W8+10000 -> 10239.706 | X12: =IFERROR(T12-R12,"-") -> 0 | Y12: =IFERROR(T12/R12,"-") -> 1 | Z12: =Лист1!Z13+Лист1!Z15 -> 1171.7 | AA12: =AA6+AA8+10000 -> 10240.131 | AB12: =Лист1!AB13+Лист1!AB15 -> 1171.7 | AC12: =AC6+AC8+10000 -> 10240.131 | AD12: =Лист1!AD13+Лист1!AD15 -> 851.3629 | AE12: =AE6+AE8+10000 -> 10239.977 | AF12: =IFERROR(AB12-Z12,"-") -> 0 | AG12: =IFERROR(AB12/Z12,"-") -> 1 | AH12: =Лист1!AH13+Лист1!AH15 -> 1058.4 | AI12: =AI6+AI8+10000 -> 10240.146 | AJ12: =Лист1!AJ13+Лист1!AJ15 -> 1058.4 | AK12: =AK6+AK8+10000 -> 10240.146 | AL12: =Лист1!AL13+Лист1!AL15 -> 663.10537 | AM12: =AM6+AM8+10000 -> 10239.877 | AN12: =IFERROR(AJ12-AH12,"-") -> 0 | AO12: =IFERROR(AJ12/AH12,"-") -> 1 | AP12: =Лист1!AP13+Лист1!AP15 -> 1171.9 | AQ12: =AQ6+AQ8+10000 -> 10240.143 | AR12: =Лист1!AR13+Лист1!AR15 -> 1171.9 | AS12: =AS6+AS8+10000 -> 10240.143 | AT12: =Лист1!AT13+Лист1!AT15 -> 846.7585 | AU12: =AU6+AU8+10000 -> 10239.301 | AV12: =IFERROR(AR12-AP12,"-") -> 0 | AW12: =IFERROR(AR12/AP12,"-") -> 1 | AX12: =BF12+BN12+BV12 -> 2594.8 | AY12: =AY6+AY8+10000 -> 10240.142 | AZ12: =BH12+BP12+BX12 -> 2594.8 | BA12: =BA6+BA8+10000 -> 10240.142 | BB12: =BJ12+BR12+BZ12 -> 1360.6209 | BC12: =BC6+BC8+10000 -> 10239.045 | BD12: =IFERROR(AZ12-AX12,"-") -> 0 | BE12: =IFERROR(AZ12/AX12,"-") -> 1 | BF12: =Лист1!BF13+Лист1!BF15 -> 1134 | BG12: =BG6+BG8+10000 -> 10240.148 | BH12: =Лист1!BH13+Лист1!BH15 -> 1134 | BI12: =BI6+BI8+10000 -> 10240.148 | BJ12: =Лист1!BJ13+Лист1!BJ15 -> 807.15779 | BK12: =BK6+BK8+10000 -> 10238.827 | BL12: =IFERROR(BH12-BF12,"-") -> 0 | BM12: =IFERROR(BH12/BF12,"-") -> 1 | BN12: =Лист1!BN13+Лист1!BN15 -> 805.6 | BO12: =BO6+BO8+10000 -> 10240.146 | BP12: =Лист1!BP13+Лист1!BP15 -> 805.6 | BQ12: =BQ6+BQ8+10000 -> 10240.146 | BR12: =Лист1!BR13+Лист1!BR15 -> 327.886 | BS12: =BS6+BS8+10000 -> 10238.873 | BT12: =IFERROR(BP12-BN12,"-") -> 0 | BU12: =IFERROR(BP12/BN12,"-") -> 1 | BV12: =Лист1!BV13+Лист1!BV15 -> 655.2 | BW12: =BW6+BW8+10000 -> 10240.128 | BX12: =Лист1!BX13+Лист1!BX15 -> 655.2 | BY12: =BY6+BY8+10000 -> 10240.128 | BZ12: =Лист1!BZ13+Лист1!BZ15 -> 225.57713 | CA12: =CA6+CA8+10000 -> 10240.082 | CB12: =IFERROR(BX12-BV12,"-") -> 0 | CC12: =IFERROR(BX12/BV12,"-") -> 1 | CD12: =CL12+CT12+DB12 -> 3702.3 | CE12: =CE6+CE8+10000 -> 10240.14 | CF12: =CN12+CV12+DD12 -> 3702.3 | CG12: =CG6+CG8+10000 -> 10240.14 | CH12: =CP12+CX12+DF12 -> 0 | CI12: =CI6+CI8+10000 -> #DIV/0! | CJ12: =IFERROR(CF12-CD12,"-") -> 0 | CK12: =IFERROR(CF12/CD12,"-") -> 1 | CL12: =Лист1!CL13+Лист1!CL15 -> 1218.4 | CM12: =CM6+CM8+10000 -> 10240.136 | CN12: =Лист1!CN13+Лист1!CN15 -> 1218.4 | CO12: =CO6+CO8+10000 -> 10240.136 | CP12: =Лист1!CP13+Лист1!CP15 -> 0 | CQ12: =CQ6+CQ8+10000 -> #DIV/0! | CR12: =IFERROR(CN12-CL12,"-") -> 0 | CS12: =IFERROR(CN12/CL12,"-") -> 1 | CT12: =Лист1!CT13+Лист1!CT15 -> 1223.9 | CU12: =CU6+CU8+10000 -> 10240.14 | CV12: =Лист1!CV13+Лист1!CV15 -> 1223.9 | CW12: =CW6+CW8+10000 -> 10240.14 | CX12: =Лист1!CX13+Лист1!CX15 -> 0 | CY12: =CY6+CY8+10000 -> #DIV/0! | CZ12: =IFERROR(CV12-CT12,"-") -> 0 | DA12: =IFERROR(CV12/CT12,"-") -> 1 | DB12: =Лист1!DB13+Лист1!DB15 -> 1260 | DC12: =DC6+DC8+10000 -> 10240.144 | DD12: =Лист1!DD13+Лист1!DD15 -> 1260 | DE12: =DE6+DE8+10000 -> 10240.144 | DF12: =Лист1!DF13+Лист1!DF15 -> 0 | DG12: =DG6+DG8+10000 -> #DIV/0! | DH12: =IFERROR(DD12-DB12,"-") -> 0 | DI12: =IFERROR(DD12/DB12,"-") -> 1 | DJ12: =DR12+DZ12+EH12 -> 3861.5 | DK12: =DK6+DK8+10000 -> 10240.142 | DL12: =DT12+EB12+EJ12 -> 3861.5 | DM12: =DM6+DM8+10000 -> 10240.142 | DN12: =DV12+ED12+EL12 -> 0 | DO12: =DO6+DO8+10000 -> #DIV/0! | DP12: =IFERROR(DL12-DJ12,"-") -> 0 | DQ12: =IFERROR(DL12/DJ12,"-") -> 1 | DR12: =Лист1!DR13+Лист1!DR15 -> 1302 | DS12: =DS6+DS8+10000 -> 10240.14 | DT12: =Лист1!DT13+Лист1!DT15 -> 1302 | DU12: =DU6+DU8+10000 -> 10240.14 | DV12: =Лист1!DV13+Лист1!DV15 -> 0 | DW12: =DW6+DW8+10000 -> #DIV/0! | DX12: =IFERROR(DT12-DR12,"-") -> 0 | DY12: =IFERROR(DT12/DR12,"-") -> 1 | DZ12: =Лист1!DZ13+Лист1!DZ15 -> 1260 | EA12: =EA6+EA8+10000 -> 10240.144 | EB12: =Лист1!EB13+Лист1!EB15 -> 1260 | EC12: =EC6+EC8+10000 -> 10240.144 | ED12: =Лист1!ED13+Лист1!ED15 -> 0 | EE12: =EE6+EE8+10000 -> #DIV/0! | EF12: =IFERROR(EB12-DZ12,"-") -> 0 | EG12: =IFERROR(EB12/DZ12,"-") -> 1 | EH12: =Лист1!EH13+Лист1!EH15 -> 1299.5 | EI12: =EI6+EI8+10000 -> 10240.142 | EJ12: =Лист1!EJ13+Лист1!EJ15 -> 1299.5 | EK12: =EK6+EK8+10000 -> 10240.142 | EL12: =Лист1!EL13+Лист1!EL15 -> 0 | EM12: =EM6+EM8+10000 -> #DIV/0! | EN12: =IFERROR(EJ12-EH12,"-") -> 0 | EO12: =IFERROR(EJ12/EH12,"-") -> 1
A13: 1.3.1 | B13: Газ сырой отсепарированный | C13: 100335802 | J13: =R13+AX13+CD13+DJ13 -> 10315.1 | L13: =T13+AZ13+CF13+DL13 -> 10315.1 | N13: =V13+BB13+CH13+DN13 -> 2827.26 | P13: =IFERROR(L13-J13,"-") -> 0 | Q13: =IFERROR(L13/J13,"-") -> 1 | R13: =Z13+AH13+AP13 -> 2587.8 | T13: =AB13+AJ13+AR13 -> 2587.8 | V13: =AD13+AL13+AT13 -> 1794.354 | X13: =IFERROR(T13-R13,"-") -> 0 | Y13: =IFERROR(T13/R13,"-") -> 1 | Z13: 891.3 | AB13: 891.3 | AD13: 647.367 | AF13: =IFERROR(AB13-Z13,"-") -> 0 | AG13: =IFERROR(AB13/Z13,"-") -> 1 | AH13: 805.1 | AJ13: 805.1 | AL13: 504.105 | AN13: =IFERROR(AJ13-AH13,"-") -> 0 | AO13: =IFERROR(AJ13/AH13,"-") -> 1 | AP13: 891.4 | AR13: 891.4 | AT13: 642.882 | AV13: =IFERROR(AR13-AP13,"-") -> 0 | AW13: =IFERROR(AR13/AP13,"-") -> 1 | AX13: =BF13+BN13+BV13 -> 1973.7 | AZ13: =BH13+BP13+BX13 -> 1973.7 | BB13: =BJ13+BR13+BZ13 -> 1032.906 | BD13: =IFERROR(AZ13-AX13,"-") -> 0 | BE13: =IFERROR(AZ13/AX13,"-") -> 1 | BF13: 862.6 | BH13: 862.6 | BJ13: 612.152 | BL13: =IFERROR(BH13-BF13,"-") -> 0 | BM13: =IFERROR(BH13/BF13,"-") -> 1 | BN13: 612.8 | BP13: 612.8 | BR13: 249.187 | BT13: =IFERROR(BP13-BN13,"-") -> 0 | BU13: =IFERROR(BP13/BN13,"-") -> 1 | BV13: 498.3 | BX13: 498.3 | BZ13: 171.567 | CB13: =IFERROR(BX13-BV13,"-") -> 0 | CC13: =IFERROR(BX13/BV13,"-") -> 1 | CD13: =CL13+CT13+DB13 -> 2816.2 | CF13: =CN13+CV13+DD13 -> 2816.2 | CH13: =CP13+CX13+DF13 -> 0 | CJ13: =IFERROR(CF13-CD13,"-") -> 0 | CK13: =IFERROR(CF13/CD13,"-") -> 1 | CL13: 926.8 | CN13: 926.8 | CR13: =IFERROR(CN13-CL13,"-") -> 0 | CS13: =IFERROR(CN13/CL13,"-") -> 1 | CT13: 931 | CV13: 931 | CZ13: =IFERROR(CV13-CT13,"-") -> 0 | DA13: =IFERROR(CV13/CT13,"-") -> 1 | DB13: 958.4 | DD13: 958.4 | DH13: =IFERROR(DD13-DB13,"-") -> 0 | DI13: =IFERROR(DD13/DB13,"-") -> 1 | DJ13: =DR13+DZ13+EH13 -> 2937.4 | DL13: =DT13+EB13+EJ13 -> 2937.4 | DN13: =DV13+ED13+EL13 -> 0 | DP13: =IFERROR(DL13-DJ13,"-") -> 0 | DQ13: =IFERROR(DL13/DJ13,"-") -> 1 | DR13: 990.4 | DT13: 990.4 | DX13: =IFERROR(DT13-DR13,"-") -> 0 | DY13: =IFERROR(DT13/DR13,"-") -> 1 | DZ13: 958.4 | EB13: 958.4 | EF13: =IFERROR(EB13-DZ13,"-") -> 0 | EG13: =IFERROR(EB13/DZ13,"-") -> 1 | EH13: 988.6 | EJ13: 988.6 | EN13: =IFERROR(EJ13-EH13,"-") -> 0 | EO13: =IFERROR(EJ13/EH13,"-") -> 1
C14: 100335803 | J14: =R14+AX14+CD14+DJ14 -> 9676.5 | L14: =T14+AZ14+CF14+DL14 -> 9676.5 | N14: =V14+BB14+CH14+DN14 -> 2668.687 | P14: =IFERROR(L14-J14,"-") -> 0 | Q14: =IFERROR(L14/J14,"-") -> 1 | R14: =Z14+AH14+AP14 -> 2427.6 | T14: =AB14+AJ14+AR14 -> 2427.6 | V14: =AD14+AL14+AT14 -> 1690.139 | X14: =IFERROR(T14-R14,"-") -> 0 | Y14: =IFERROR(T14/R14,"-") -> 1 | Z14: 836.1 | AB14: 836.1 | AD14: 608.216 | AF14: =IFERROR(AB14-Z14,"-") -> 0 | AG14: =IFERROR(AB14/Z14,"-") -> 1 | AH14: 755.3 | AJ14: 755.3 | AL14: 474.062 | AN14: =IFERROR(AJ14-AH14,"-") -> 0 | AO14: =IFERROR(AJ14/AH14,"-") -> 1 | AP14: 836.2 | AR14: 836.2 | AT14: 607.861 | AV14: =IFERROR(AR14-AP14,"-") -> 0 | AW14: =IFERROR(AR14/AP14,"-") -> 1 | AX14: =BF14+BN14+BV14 -> 1851.5 | AZ14: =BH14+BP14+BX14 -> 1851.5 | BB14: =BJ14+BR14+BZ14 -> 978.548 | BD14: =IFERROR(AZ14-AX14,"-") -> 0 | BE14: =IFERROR(AZ14/AX14,"-") -> 1 | BF14: 809.2 | BH14: 809.2 | BJ14: 581.412 | BL14: =IFERROR(BH14-BF14,"-") -> 0 | BM14: =IFERROR(BH14/BF14,"-") -> 1 | BN14: 574.9 | BP14: 574.9 | BR14: 236.104 | BT14: =IFERROR(BP14-BN14,"-") -> 0 | BU14: =IFERROR(BP14/BN14,"-") -> 1 | BV14: 467.4 | BX14: 467.4 | BZ14: 161.032 | CB14: =IFERROR(BX14-BV14,"-") -> 0 | CC14: =IFERROR(BX14/BV14,"-") -> 1 | CD14: =CL14+CT14+DB14 -> 2641.8 | CF14: =CN14+CV14+DD14 -> 2641.8 | CH14: =CP14+CX14+DF14 -> 0 | CJ14: =IFERROR(CF14-CD14,"-") -> 0 | CK14: =IFERROR(CF14/CD14,"-") -> 1 | CL14: 869.4 | CN14: 869.4 | CR14: =IFERROR(CN14-CL14,"-") -> 0 | CS14: =IFERROR(CN14/CL14,"-") -> 1 | CT14: 873.4 | CV14: 873.4 | CZ14: =IFERROR(CV14-CT14,"-") -> 0 | DA14: =IFERROR(CV14/CT14,"-") -> 1 | DB14: 899 | DD14: 899 | DH14: =IFERROR(DD14-DB14,"-") -> 0 | DI14: =IFERROR(DD14/DB14,"-") -> 1 | DJ14: =DR14+DZ14+EH14 -> 2755.6 | DL14: =DT14+EB14+EJ14 -> 2755.6 | DN14: =DV14+ED14+EL14 -> 0 | DP14: =IFERROR(DL14-DJ14,"-") -> 0 | DQ14: =IFERROR(DL14/DJ14,"-") -> 1 | DR14: 929.1 | DT14: 929.1 | DX14: =IFERROR(DT14-DR14,"-") -> 0 | DY14: =IFERROR(DT14/DR14,"-") -> 1 | DZ14: 899.1 | EB14: 899.1 | EF14: =IFERROR(EB14-DZ14,"-") -> 0 | EG14: =IFERROR(EB14/DZ14,"-") -> 1 | EH14: 927.4 | EJ14: 927.4 | EN14: =IFERROR(EJ14-EH14,"-") -> 0 | EO14: =IFERROR(EJ14/EH14,"-") -> 1
A15: 1.3.2 | B15: Конденсат газовый нестабильный | C15: 100335804 | J15: =R15+AX15+CD15+DJ15 -> 3245.5 | L15: =T15+AZ15+CF15+DL15 -> 3245.5 | N15: =V15+BB15+CH15+DN15 -> 894.5877 | P15: =IFERROR(L15-J15,"-") -> 0 | Q15: =IFERROR(L15/J15,"-") -> 1 | R15: =Z15+AH15+AP15 -> 814.2 | T15: =AB15+AJ15+AR15 -> 814.2 | V15: =AD15+AL15+AT15 -> 566.87278 | X15: =IFERROR(T15-R15,"-") -> 0 | Y15: =IFERROR(T15/R15,"-") -> 1 | Z15: 280.4 | AB15: 280.4 | AD15: 203.9959 | AF15: =IFERROR(AB15-Z15,"-") -> 0 | AG15: =IFERROR(AB15/Z15,"-") -> 1 | AH15: 253.3 | AJ15: 253.3 | AL15: 159.00037 | AN15: =IFERROR(AJ15-AH15,"-") -> 0 | AO15: =IFERROR(AJ15/AH15,"-") -> 1 | AP15: 280.5 | AR15: 280.5 | AT15: 203.8765 | AV15: =IFERROR(AR15-AP15,"-") -> 0 | AW15: =IFERROR(AR15/AP15,"-") -> 1 | AX15: =BF15+BN15+BV15 -> 621.1 | AZ15: =BH15+BP15+BX15 -> 621.1 | BB15: =BJ15+BR15+BZ15 -> 327.71492 | BD15: =IFERROR(AZ15-AX15,"-") -> 0 | BE15: =IFERROR(AZ15/AX15,"-") -> 1 | BF15: 271.4 | BH15: 271.4 | BJ15: 195.00579 | BL15: =IFERROR(BH15-BF15,"-") -> 0 | BM15: =IFERROR(BH15/BF15,"-") -> 1 | BN15: 192.8 | BP15: 192.8 | BR15: 78.699 | BT15: =IFERROR(BP15-BN15,"-") -> 0 | BU15: =IFERROR(BP15/BN15,"-") -> 1 | BV15: 156.9 | BX15: 156.9 | BZ15: 54.010132 | CB15: =IFERROR(BX15-BV15,"-") -> 0 | CC15: =IFERROR(BX15/BV15,"-") -> 1 | CD15: =CL15+CT15+DB15 -> 886.1 | CF15: =CN15+CV15+DD15 -> 886.1 | CH15: =CP15+CX15+DF15 -> 0 | CJ15: =IFERROR(CF15-CD15,"-") -> 0 | CK15: =IFERROR(CF15/CD15,"-") -> 1 | CL15: 291.6 | CN15: 291.6 | CR15: =IFERROR(CN15-CL15,"-") -> 0 | CS15: =IFERROR(CN15/CL15,"-") -> 1 | CT15: 292.9 | CV15: 292.9 | CZ15: =IFERROR(CV15-CT15,"-") -> 0 | DA15: =IFERROR(CV15/CT15,"-") -> 1 | DB15: 301.6 | DD15: 301.6 | DH15: =IFERROR(DD15-DB15,"-") -> 0 | DI15: =IFERROR(DD15/DB15,"-") -> 1 | DJ15: =DR15+DZ15+EH15 -> 924.1 | DL15: =DT15+EB15+EJ15 -> 924.1 | DN15: =DV15+ED15+EL15 -> 0 | DP15: =IFERROR(DL15-DJ15,"-") -> 0 | DQ15: =IFERROR(DL15/DJ15,"-") -> 1 | DR15: 311.6 | DT15: 311.6 | DX15: =IFERROR(DT15-DR15,"-") -> 0 | DY15: =IFERROR(DT15/DR15,"-") -> 1 | DZ15: 301.6 | EB15: 301.6 | EF15: =IFERROR(EB15-DZ15,"-") -> 0 | EG15: =IFERROR(EB15/DZ15,"-") -> 1 | EH15: 310.9 | EJ15: 310.9 | EN15: =IFERROR(EJ15-EH15,"-") -> 0 | EO15: =IFERROR(EJ15/EH15,"-") -> 1
A16: 2 | B16: ПЕРЕРАБОТКА УГЛЕВОДОРОДНОГО СЫРЬЯ, собственность ПАО "Газпром" | C16: 100335805 | F16: 1_100335806+1_100331985+1_100331986 | J16: =R16+AX16+CD16+DJ16 -> 13871.102 | L16: =T16+AZ16+CF16+DL16 -> 13871.102 | N16: =V16+BB16+CH16+DN16 -> 3869.4245 | P16: =IFERROR(L16-J16,"-") -> 0 | Q16: =IFERROR(L16/J16,"-") -> 1 | R16: =Z16+AH16+AP16 -> 3450.842 | T16: =AB16+AJ16+AR16 -> 3450.842 | V16: =AD16+AL16+AT16 -> 2460.9858 | X16: =IFERROR(T16-R16,"-") -> 0 | Y16: =IFERROR(T16/R16,"-") -> 1 | Z16: =Лист1!Z17+Лист1!Z19+Лист1!Z20 -> 1186.918 | AB16: =Лист1!AB17+Лист1!AB19+Лист1!AB20 -> 1186.918 | AD16: =Лист1!AD17+Лист1!AD19+Лист1!AD20 -> 882.73091 | AF16: =IFERROR(AB16-Z16,"-") -> 0 | AG16: =IFERROR(AB16/Z16,"-") -> 1 | AH16: =Лист1!AH17+Лист1!AH19+Лист1!AH20 -> 1074.907 | AJ16: =Лист1!AJ17+Лист1!AJ19+Лист1!AJ20 -> 1074.907 | AL16: =Лист1!AL17+Лист1!AL19+Лист1!AL20 -> 694.34137 | AN16: =IFERROR(AJ16-AH16,"-") -> 0 | AO16: =IFERROR(AJ16/AH16,"-") -> 1 | AP16: =Лист1!AP17+Лист1!AP19+Лист1!AP20 -> 1189.017 | AR16: =Лист1!AR17+Лист1!AR19+Лист1!AR20 -> 1189.017 | AT16: =Лист1!AT17+Лист1!AT19+Лист1!AT20 -> 883.9135 | AV16: =IFERROR(AR16-AP16,"-") -> 0 | AW16: =IFERROR(AR16/AP16,"-") -> 1 | AX16: =BF16+BN16+BV16 -> 2665.769 | AZ16: =BH16+BP16+BX16 -> 2665.769 | BB16: =BJ16+BR16+BZ16 -> 1408.4387 | BD16: =IFERROR(AZ16-AX16,"-") -> 0 | BE16: =IFERROR(AZ16/AX16,"-") -> 1 | BF16: =Лист1!BF17+Лист1!BF19+Лист1!BF20 -> 1168.842 | BH16: =Лист1!BH17+Лист1!BH19+Лист1!BH20 -> 1168.842 | BJ16: =Лист1!BJ17+Лист1!BJ19+Лист1!BJ20 -> 834.79661 | BL16: =IFERROR(BH16-BF16,"-") -> 0 | BM16: =IFERROR(BH16/BF16,"-") -> 1 | BN16: =Лист1!BN17+Лист1!BN19+Лист1!BN20 -> 829.027 | BP16: =Лист1!BP17+Лист1!BP19+Лист1!BP20 -> 829.027 | BR16: =Лист1!BR17+Лист1!BR19+Лист1!BR20 -> 340.308 | BT16: =IFERROR(BP16-BN16,"-") -> 0 | BU16: =IFERROR(BP16/BN16,"-") -> 1 | BV16: =Лист1!BV17+Лист1!BV19+Лист1!BV20 -> 667.9 | BX16: =Лист1!BX17+Лист1!BX19+Лист1!BX20 -> 667.9 | BZ16: =Лист1!BZ17+Лист1!BZ19+Лист1!BZ20 -> 233.33413 | CB16: =IFERROR(BX16-BV16,"-") -> 0 | CC16: =IFERROR(BX16/BV16,"-") -> 1 | CD16: =CL16+CT16+DB16 -> 3849.863 | CF16: =CN16+CV16+DD16 -> 3849.863 | CH16: =CP16+CX16+DF16 -> 0 | CJ16: =IFERROR(CF16-CD16,"-") -> 0 | CK16: =IFERROR(CF16/CD16,"-") -> 1 | CL16: =Лист1!CL17+Лист1!CL19+Лист1!CL20 -> 1265.972 | CN16: =Лист1!CN17+Лист1!CN19+Лист1!CN20 -> 1265.972 | CP16: =Лист1!CP17+Лист1!CP19+Лист1!CP20 -> 0 | CR16: =IFERROR(CN16-CL16,"-") -> 0 | CS16: =IFERROR(CN16/CL16,"-") -> 1 | CT16: =Лист1!CT17+Лист1!CT19+Лист1!CT20 -> 1290.147 | CV16: =Лист1!CV17+Лист1!CV19+Лист1!CV20 -> 1290.147 | CX16: =Лист1!CX17+Лист1!CX19+Лист1!CX20 -> 0 | CZ16: =IFERROR(CV16-CT16,"-") -> 0 | DA16: =IFERROR(CV16/CT16,"-") -> 1 | DB16: =Лист1!DB17+Лист1!DB19+Лист1!DB20 -> 1293.744 | DD16: =Лист1!DD17+Лист1!DD19+Лист1!DD20 -> 1293.744 | DF16: =Лист1!DF17+Лист1!DF19+Лист1!DF20 -> 0 | DH16: =IFERROR(DD16-DB16,"-") -> 0 | DI16: =IFERROR(DD16/DB16,"-") -> 1 | DJ16: =DR16+DZ16+EH16 -> 3904.628 | DL16: =DT16+EB16+EJ16 -> 3904.628 | DN16: =DV16+ED16+EL16 -> 0 | DP16: =IFERROR(DL16-DJ16,"-") -> 0 | DQ16: =IFERROR(DL16/DJ16,"-") -> 1 | DR16: =Лист1!DR17+Лист1!DR19+Лист1!DR20 -> 1317.897 | DT16: =Лист1!DT17+Лист1!DT19+Лист1!DT20 -> 1317.897 | DV16: =Лист1!DV17+Лист1!DV19+Лист1!DV20 -> 0 | DX16: =IFERROR(DT16-DR16,"-") -> 0 | DY16: =IFERROR(DT16/DR16,"-") -> 1 | DZ16: =Лист1!DZ17+Лист1!DZ19+Лист1!DZ20 -> 1276.213 | EB16: =Лист1!EB17+Лист1!EB19+Лист1!EB20 -> 1276.213 | ED16: =Лист1!ED17+Лист1!ED19+Лист1!ED20 -> 0 | EF16: =IFERROR(EB16-DZ16,"-") -> 0 | EG16: =IFERROR(EB16/DZ16,"-") -> 1 | EH16: =Лист1!EH17+Лист1!EH19+Лист1!EH20 -> 1310.518 | EJ16: =Лист1!EJ17+Лист1!EJ19+Лист1!EJ20 -> 1310.518 | EL16: =Лист1!EL17+Лист1!EL19+Лист1!EL20 -> 0 | EN16: =IFERROR(EJ16-EH16,"-") -> 0 | EO16: =IFERROR(EJ16/EH16,"-") -> 1
A17: 2.1 | B17: ПЕРЕРАБОТКА ГАЗА СЫРОГО ОТСЕПАРИРОВАННОГО (покупка у ООО "Газпром добыча Астрахань" ) | C17: 100335806 | J17: =R17+AX17+CD17+DJ17 -> 10315.1 | L17: =T17+AZ17+CF17+DL17 -> 10315.1 | N17: =V17+BB17+CH17+DN17 -> 2827.26 | P17: =IFERROR(L17-J17,"-") -> 0 | Q17: =IFERROR(L17/J17,"-") -> 1 | R17: =Z17+AH17+AP17 -> 2587.8 | T17: =AB17+AJ17+AR17 -> 2587.8 | V17: =AD17+AL17+AT17 -> 1794.354 | X17: =IFERROR(T17-R17,"-") -> 0 | Y17: =IFERROR(T17/R17,"-") -> 1 | Z17: 891.3 | AB17: 891.3 | AD17: 647.367 | AF17: =IFERROR(AB17-Z17,"-") -> 0 | AG17: =IFERROR(AB17/Z17,"-") -> 1 | AH17: 805.1 | AJ17: 805.1 | AL17: 504.105 | AN17: =IFERROR(AJ17-AH17,"-") -> 0 | AO17: =IFERROR(AJ17/AH17,"-") -> 1 | AP17: 891.4 | AR17: 891.4 | AT17: 642.882 | AV17: =IFERROR(AR17-AP17,"-") -> 0 | AW17: =IFERROR(AR17/AP17,"-") -> 1 | AX17: =BF17+BN17+BV17 -> 1973.7 | AZ17: =BH17+BP17+BX17 -> 1973.7 | BB17: =BJ17+BR17+BZ17 -> 1032.906 | BD17: =IFERROR(AZ17-AX17,"-") -> 0 | BE17: =IFERROR(AZ17/AX17,"-") -> 1 | BF17: 862.6 | BH17: 862.6 | BJ17: 612.152 | BL17: =IFERROR(BH17-BF17,"-") -> 0 | BM17: =IFERROR(BH17/BF17,"-") -> 1 | BN17: 612.8 | BP17: 612.8 | BR17: 249.187 | BT17: =IFERROR(BP17-BN17,"-") -> 0 | BU17: =IFERROR(BP17/BN17,"-") -> 1 | BV17: 498.3 | BX17: 498.3 | BZ17: 171.567 | CB17: =IFERROR(BX17-BV17,"-") -> 0 | CC17: =IFERROR(BX17/BV17,"-") -> 1 | CD17: =CL17+CT17+DB17 -> 2816.2 | CF17: =CN17+CV17+DD17 -> 2816.2 | CH17: =CP17+CX17+DF17 -> 0 | CJ17: =IFERROR(CF17-CD17,"-") -> 0 | CK17: =IFERROR(CF17/CD17,"-") -> 1 | CL17: 926.8 | CN17: 926.8 | CR17: =IFERROR(CN17-CL17,"-") -> 0 | CS17: =IFERROR(CN17/CL17,"-") -> 1 | CT17: 931 | CV17: 931 | CZ17: =IFERROR(CV17-CT17,"-") -> 0 | DA17: =IFERROR(CV17/CT17,"-") -> 1 | DB17: 958.4 | DD17: 958.4 | DH17: =IFERROR(DD17-DB17,"-") -> 0 | DI17: =IFERROR(DD17/DB17,"-") -> 1 | DJ17: =DR17+DZ17+EH17 -> 2937.4 | DL17: =DT17+EB17+EJ17 -> 2937.4 | DN17: =DV17+ED17+EL17 -> 0 | DP17: =IFERROR(DL17-DJ17,"-") -> 0 | DQ17: =IFERROR(DL17/DJ17,"-") -> 1 | DR17: 990.4 | DT17: 990.4 | DX17: =IFERROR(DT17-DR17,"-") -> 0 | DY17: =IFERROR(DT17/DR17,"-") -> 1 | DZ17: 958.4 | EB17: 958.4 | EF17: =IFERROR(EB17-DZ17,"-") -> 0 | EG17: =IFERROR(EB17/DZ17,"-") -> 1 | EH17: 988.6 | EJ17: 988.6 | EN17: =IFERROR(EJ17-EH17,"-") -> 0 | EO17: =IFERROR(EJ17/EH17,"-") -> 1
C18: 1003335807 | J18: =R18+AX18+CD18+DJ18 -> 0 | L18: =T18+AZ18+CF18+DL18 -> 0 | N18: =V18+BB18+CH18+DN18 -> 0 | P18: =IFERROR(L18-J18,"-") -> 0 | Q18: =IFERROR(L18/J18,"-") -> - | R18: =Z18+AH18+AP18 -> 0 | T18: =AB18+AJ18+AR18 -> 0 | V18: =AD18+AL18+AT18 -> 0 | X18: =IFERROR(T18-R18,"-") -> 0 | Y18: =IFERROR(T18/R18,"-") -> - | AF18: =IFERROR(AB18-Z18,"-") -> 0 | AG18: =IFERROR(AB18/Z18,"-") -> - | AN18: =IFERROR(AJ18-AH18,"-") -> 0 | AO18: =IFERROR(AJ18/AH18,"-") -> - | AV18: =IFERROR(AR18-AP18,"-") -> 0 | AW18: =IFERROR(AR18/AP18,"-") -> - | AX18: =BF18+BN18+BV18 -> 0 | AZ18: =BH18+BP18+BX18 -> 0 | BB18: =BJ18+BR18+BZ18 -> 0 | BD18: =IFERROR(AZ18-AX18,"-") -> 0 | BE18: =IFERROR(AZ18/AX18,"-") -> - | BL18: =IFERROR(BH18-BF18,"-") -> 0 | BM18: =IFERROR(BH18/BF18,"-") -> - | BT18: =IFERROR(BP18-BN18,"-") -> 0 | BU18: =IFERROR(BP18/BN18,"-") -> - | CB18: =IFERROR(BX18-BV18,"-") -> 0 | CC18: =IFERROR(BX18/BV18,"-") -> - | CD18: =CL18+CT18+DB18 -> 0 | CF18: =CN18+CV18+DD18 -> 0 | CH18: =CP18+CX18+DF18 -> 0 | CJ18: =IFERROR(CF18-CD18,"-") -> 0 | CK18: =IFERROR(CF18/CD18,"-") -> - | CR18: =IFERROR(CN18-CL18,"-") -> 0 | CS18: =IFERROR(CN18/CL18,"-") -> - | CZ18: =IFERROR(CV18-CT18,"-") -> 0 | DA18: =IFERROR(CV18/CT18,"-") -> - | DH18: =IFERROR(DD18-DB18,"-") -> 0 | DI18: =IFERROR(DD18/DB18,"-") -> - | DJ18: =DR18+DZ18+EH18 -> 0 | DL18: =DT18+EB18+EJ18 -> 0 | DN18: =DV18+ED18+EL18 -> 0 | DP18: =IFERROR(DL18-DJ18,"-") -> 0 | DQ18: =IFERROR(DL18/DJ18,"-") -> - | DX18: =IFERROR(DT18-DR18,"-") -> 0 | DY18: =IFERROR(DT18/DR18,"-") -> - | EF18: =IFERROR(EB18-DZ18,"-") -> 0 | EG18: =IFERROR(EB18/DZ18,"-") -> - | EN18: =IFERROR(EJ18-EH18,"-") -> 0 | EO18: =IFERROR(EJ18/EH18,"-") -> -
A19: 2.2 | B19: ПЕРЕРАБОТКА КОНДЕНСАТА ГАЗОВОГО НЕСТАБИЛЬНОГО (покупка у ООО "Газпром добыча Астрахань" ) | C19: 100331985 | J19: =R19+AX19+CD19+DJ19 -> 3245.5 | L19: =T19+AZ19+CF19+DL19 -> 3245.5 | N19: =V19+BB19+CH19+DN19 -> 894.5877 | P19: =IFERROR(L19-J19,"-") -> 0 | Q19: =IFERROR(L19/J19,"-") -> 1 | R19: =Z19+AH19+AP19 -> 814.2 | T19: =AB19+AJ19+AR19 -> 814.2 | V19: =AD19+AL19+AT19 -> 566.87278 | X19: =IFERROR(T19-R19,"-") -> 0 | Y19: =IFERROR(T19/R19,"-") -> 1 | Z19: 280.4 | AB19: 280.4 | AD19: 203.9959 | AF19: =IFERROR(AB19-Z19,"-") -> 0 | AG19: =IFERROR(AB19/Z19,"-") -> 1 | AH19: 253.3 | AJ19: 253.3 | AL19: 159.00037 | AN19: =IFERROR(AJ19-AH19,"-") -> 0 | AO19: =IFERROR(AJ19/AH19,"-") -> 1 | AP19: 280.5 | AR19: 280.5 | AT19: 203.8765 | AV19: =IFERROR(AR19-AP19,"-") -> 0 | AW19: =IFERROR(AR19/AP19,"-") -> 1 | AX19: =BF19+BN19+BV19 -> 621.1 | AZ19: =BH19+BP19+BX19 -> 621.1 | BB19: =BJ19+BR19+BZ19 -> 327.71492 | BD19: =IFERROR(AZ19-AX19,"-") -> 0 | BE19: =IFERROR(AZ19/AX19,"-") -> 1 | BF19: 271.4 | BH19: 271.4 | BJ19: 195.00579 | BL19: =IFERROR(BH19-BF19,"-") -> 0 | BM19: =IFERROR(BH19/BF19,"-") -> 1 | BN19: 192.8 | BP19: 192.8 | BR19: 78.699 | BT19: =IFERROR(BP19-BN19,"-") -> 0 | BU19: =IFERROR(BP19/BN19,"-") -> 1 | BV19: 156.9 | BX19: 156.9 | BZ19: 54.010132 | CB19: =IFERROR(BX19-BV19,"-") -> 0 | CC19: =IFERROR(BX19/BV19,"-") -> 1 | CD19: =CL19+CT19+DB19 -> 886.1 | CF19: =CN19+CV19+DD19 -> 886.1 | CH19: =CP19+CX19+DF19 -> 0 | CJ19: =IFERROR(CF19-CD19,"-") -> 0 | CK19: =IFERROR(CF19/CD19,"-") -> 1 | CL19: 291.6 | CN19: 291.6 | CR19: =IFERROR(CN19-CL19,"-") -> 0 | CS19: =IFERROR(CN19/CL19,"-") -> 1 | CT19: 292.9 | CV19: 292.9 | CZ19: =IFERROR(CV19-CT19,"-") -> 0 | DA19: =IFERROR(CV19/CT19,"-") -> 1 | DB19: 301.6 | DD19: 301.6 | DH19: =IFERROR(DD19-DB19,"-") -> 0 | DI19: =IFERROR(DD19/DB19,"-") -> 1 | DJ19: =DR19+DZ19+EH19 -> 924.1 | DL19: =DT19+EB19+EJ19 -> 924.1 | DN19: =DV19+ED19+EL19 -> 0 | DP19: =IFERROR(DL19-DJ19,"-") -> 0 | DQ19: =IFERROR(DL19/DJ19,"-") -> 1 | DR19: 311.6 | DT19: 311.6 | DX19: =IFERROR(DT19-DR19,"-") -> 0 | DY19: =IFERROR(DT19/DR19,"-") -> 1 | DZ19: 301.6 | EB19: 301.6 | EF19: =IFERROR(EB19-DZ19,"-") -> 0 | EG19: =IFERROR(EB19/DZ19,"-") -> 1 | EH19: 310.9 | EJ19: 310.9 | EN19: =IFERROR(EJ19-EH19,"-") -> 0 | EO19: =IFERROR(EJ19/EH19,"-") -> 1
A20: 2.3 | B20: ПРИСАДКИ (ДОБАВКИ), ВСЕГО: | C20: 100331986 | J20: =R20+AX20+CD20+DJ20 -> 310.502 | L20: =T20+AZ20+CF20+DL20 -> 310.502 | N20: =V20+BB20+CH20+DN20 -> 147.57682 | P20: =IFERROR(L20-J20,"-") -> 0 | Q20: =IFERROR(L20/J20,"-") -> 1 | R20: =Z20+AH20+AP20 -> 48.842 | T20: =AB20+AJ20+AR20 -> 48.842 | V20: =AD20+AL20+AT20 -> 99.759 | X20: =IFERROR(T20-R20,"-") -> 0 | Y20: =IFERROR(T20/R20,"-") -> 1 | Z20: 15.218 | AB20: 15.218 | AD20: 31.368 | AF20: =IFERROR(AB20-Z20,"-") -> 0 | AG20: =IFERROR(AB20/Z20,"-") -> 1 | AH20: 16.507 | AJ20: 16.507 | AL20: 31.236 | AN20: =IFERROR(AJ20-AH20,"-") -> 0 | AO20: =IFERROR(AJ20/AH20,"-") -> 1 | AP20: 17.117 | AR20: 17.117 | AT20: 37.155 | AV20: =IFERROR(AR20-AP20,"-") -> 0 | AW20: =IFERROR(AR20/AP20,"-") -> 1 | AX20: =BF20+BN20+BV20 -> 70.969 | AZ20: =BH20+BP20+BX20 -> 70.969 | BB20: =BJ20+BR20+BZ20 -> 47.817821 | BD20: =IFERROR(AZ20-AX20,"-") -> 0 | BE20: =IFERROR(AZ20/AX20,"-") -> 1 | BF20: 34.842 | BH20: 34.842 | BJ20: 27.638821 | BL20: =IFERROR(BH20-BF20,"-") -> 0 | BM20: =IFERROR(BH20/BF20,"-") -> 1 | BN20: 23.427 | BP20: 23.427 | BR20: 12.422 | BT20: =IFERROR(BP20-BN20,"-") -> 0 | BU20: =IFERROR(BP20/BN20,"-") -> 1 | BV20: 12.7 | BX20: 12.7 | BZ20: 7.757 | CB20: =IFERROR(BX20-BV20,"-") -> 0 | CC20: =IFERROR(BX20/BV20,"-") -> 1 | CD20: =CL20+CT20+DB20 -> 147.563 | CF20: =CN20+CV20+DD20 -> 147.563 | CH20: =CP20+CX20+DF20 -> 0 | CJ20: =IFERROR(CF20-CD20,"-") -> 0 | CK20: =IFERROR(CF20/CD20,"-") -> 1 | CL20: 47.572 | CN20: 47.572 | CR20: =IFERROR(CN20-CL20,"-") -> 0 | CS20: =IFERROR(CN20/CL20,"-") -> 1 | CT20: 66.247 | CV20: 66.247 | CZ20: =IFERROR(CV20-CT20,"-") -> 0 | DA20: =IFERROR(CV20/CT20,"-") -> 1 | DB20: 33.744 | DD20: 33.744 | DH20: =IFERROR(DD20-DB20,"-") -> 0 | DI20: =IFERROR(DD20/DB20,"-") -> 1 | DJ20: =DR20+DZ20+EH20 -> 43.128 | DL20: =DT20+EB20+EJ20 -> 43.128 | DN20: =DV20+ED20+EL20 -> 0 | DP20: =IFERROR(DL20-DJ20,"-") -> 0 | DQ20: =IFERROR(DL20/DJ20,"-") -> 1 | DR20: 15.897 | DT20: 15.897 | DX20: =IFERROR(DT20-DR20,"-") -> 0 | DY20: =IFERROR(DT20/DR20,"-") -> 1 | DZ20: 16.213 | EB20: 16.213 | EF20: =IFERROR(EB20-DZ20,"-") -> 0 | EG20: =IFERROR(EB20/DZ20,"-") -> 1 | EH20: 11.018 | EJ20: 11.018 | EN20: =IFERROR(EJ20-EH20,"-") -> 0 | EO20: =IFERROR(EJ20/EH20,"-") -> 1
A21: 2.3.1 | B21: Присадки (добавки) для нефтепродуктов, собственность ПАО "Газпром" | C21: 100331987 | F21: СУММ(1_100335805+1_100335804) | J21: =R21+AX21+CD21+DJ21 -> 17116.602 | L21: =T21+AZ21+CF21+DL21 -> 17116.602 | N21: =V21+BB21+CH21+DN21 -> 4764.0122 | P21: =IFERROR(L21-J21,"-") -> 0 | Q21: =IFERROR(L21/J21,"-") -> 1 | R21: =Z21+AH21+AP21 -> 4265.042 | T21: =AB21+AJ21+AR21 -> 4265.042 | V21: =AD21+AL21+AT21 -> 3027.8586 | X21: =IFERROR(T21-R21,"-") -> 0 | Y21: =IFERROR(T21/R21,"-") -> 1 | Z21: =SUM(Лист1!Z16+Лист1!Z15) -> 1467.318 | AB21: =SUM(Лист1!AB16+Лист1!AB15) -> 1467.318 | AD21: =SUM(Лист1!AD16+Лист1!AD15) -> 1086.7268 | AF21: =IFERROR(AB21-Z21,"-") -> 0 | AG21: =IFERROR(AB21/Z21,"-") -> 1 | AH21: =SUM(Лист1!AH16+Лист1!AH15) -> 1328.207 | AJ21: =SUM(Лист1!AJ16+Лист1!AJ15) -> 1328.207 | AL21: =SUM(Лист1!AL16+Лист1!AL15) -> 853.34175 | AN21: =IFERROR(AJ21-AH21,"-") -> 0 | AO21: =IFERROR(AJ21/AH21,"-") -> 1 | AP21: =SUM(Лист1!AP16+Лист1!AP15) -> 1469.517 | AR21: =SUM(Лист1!AR16+Лист1!AR15) -> 1469.517 | AT21: =SUM(Лист1!AT16+Лист1!AT15) -> 1087.79 | AV21: =IFERROR(AR21-AP21,"-") -> 0 | AW21: =IFERROR(AR21/AP21,"-") -> 1 | AX21: =BF21+BN21+BV21 -> 3286.869 | AZ21: =BH21+BP21+BX21 -> 3286.869 | BB21: =BJ21+BR21+BZ21 -> 1736.1537 | BD21: =IFERROR(AZ21-AX21,"-") -> 0 | BE21: =IFERROR(AZ21/AX21,"-") -> 1 | BF21: =SUM(Лист1!BF16+Лист1!BF15) -> 1440.242 | BH21: =SUM(Лист1!BH16+Лист1!BH15) -> 1440.242 | BJ21: =SUM(Лист1!BJ16+Лист1!BJ15) -> 1029.8024 | BL21: =IFERROR(BH21-BF21,"-") -> 0 | BM21: =IFERROR(BH21/BF21,"-") -> 1 | BN21: =SUM(Лист1!BN16+Лист1!BN15) -> 1021.827 | BP21: =SUM(Лист1!BP16+Лист1!BP15) -> 1021.827 | BR21: =SUM(Лист1!BR16+Лист1!BR15) -> 419.007 | BT21: =IFERROR(BP21-BN21,"-") -> 0 | BU21: =IFERROR(BP21/BN21,"-") -> 1 | BV21: =SUM(Лист1!BV16+Лист1!BV15) -> 824.8 | BX21: =SUM(Лист1!BX16+Лист1!BX15) -> 824.8 | BZ21: =SUM(Лист1!BZ16+Лист1!BZ15) -> 287.34426 | CB21: =IFERROR(BX21-BV21,"-") -> 0 | CC21: =IFERROR(BX21/BV21,"-") -> 1 | CD21: =CL21+CT21+DB21 -> 4735.963 | CF21: =CN21+CV21+DD21 -> 4735.963 | CH21: =CP21+CX21+DF21 -> 0 | CJ21: =IFERROR(CF21-CD21,"-") -> 0 | CK21: =IFERROR(CF21/CD21,"-") -> 1 | CL21: =SUM(Лист1!CL16+Лист1!CL15) -> 1557.572 | CN21: =SUM(Лист1!CN16+Лист1!CN15) -> 1557.572 | CP21: =SUM(Лист1!CP16+Лист1!CP15) -> 0 | CR21: =IFERROR(CN21-CL21,"-") -> 0 | CS21: =IFERROR(CN21/CL21,"-") -> 1 | CT21: =SUM(Лист1!CT16+Лист1!CT15) -> 1583.047 | CV21: =SUM(Лист1!CV16+Лист1!CV15) -> 1583.047 | CX21: =SUM(Лист1!CX16+Лист1!CX15) -> 0 | CZ21: =IFERROR(CV21-CT21,"-") -> 0 | DA21: =IFERROR(CV21/CT21,"-") -> 1 | DB21: =SUM(Лист1!DB16+Лист1!DB15) -> 1595.344 | DD21: =SUM(Лист1!DD16+Лист1!DD15) -> 1595.344 | DF21: =SUM(Лист1!DF16+Лист1!DF15) -> 0 | DH21: =IFERROR(DD21-DB21,"-") -> 0 | DI21: =IFERROR(DD21/DB21,"-") -> 1 | DJ21: =DR21+DZ21+EH21 -> 4828.728 | DL21: =DT21+EB21+EJ21 -> 4828.728 | DN21: =DV21+ED21+EL21 -> 0 | DP21: =IFERROR(DL21-DJ21,"-") -> 0 | DQ21: =IFERROR(DL21/DJ21,"-") -> 1 | DR21: =SUM(Лист1!DR16+Лист1!DR15) -> 1629.497 | DT21: =SUM(Лист1!DT16+Лист1!DT15) -> 1629.497 | DV21: =SUM(Лист1!DV16+Лист1!DV15) -> 0 | DX21: =IFERROR(DT21-DR21,"-") -> 0 | DY21: =IFERROR(DT21/DR21,"-") -> 1 | DZ21: =SUM(Лист1!DZ16+Лист1!DZ15) -> 1577.813 | EB21: =SUM(Лист1!EB16+Лист1!EB15) -> 1577.813 | ED21: =SUM(Лист1!ED16+Лист1!ED15) -> 0 | EF21: =IFERROR(EB21-DZ21,"-") -> 0 | EG21: =IFERROR(EB21/DZ21,"-") -> 1 | EH21: =SUM(Лист1!EH16+Лист1!EH15) -> 1621.418 | EJ21: =SUM(Лист1!EJ16+Лист1!EJ15) -> 1621.418 | EL21: =SUM(Лист1!EL16+Лист1!EL15) -> 0 | EN21: =IFERROR(EJ21-EH21,"-") -> 0 | EO21: =IFERROR(EJ21/EH21,"-") -> 1
A22: 2.3.1.1. | B22: в т.ч. МТБЭ (добавка в бензин) | C22: 100334996 | J22: =R22+AX22+CD22+DJ22 -> 20.65 | L22: =T22+AZ22+CF22+DL22 -> 20.65 | N22: =V22+BB22+CH22+DN22 -> 0.559 | P22: =IFERROR(L22-J22,"-") -> 0 | Q22: =IFERROR(L22/J22,"-") -> 1 | R22: =Z22+AH22+AP22 -> 6.3 | T22: =AB22+AJ22+AR22 -> 6.3 | V22: =AD22+AL22+AT22 -> 0 | X22: =IFERROR(T22-R22,"-") -> 0 | Y22: =IFERROR(T22/R22,"-") -> 1 | Z22: 2.1 | AB22: 2.1 | AD22: 0 | AF22: =IFERROR(AB22-Z22,"-") -> 0 | AG22: =IFERROR(AB22/Z22,"-") -> 1 | AH22: 2.1 | AJ22: 2.1 | AL22: 0 | AN22: =IFERROR(AJ22-AH22,"-") -> 0 | AO22: =IFERROR(AJ22/AH22,"-") -> 1 | AP22: 2.1 | AR22: 2.1 | AT22: 0 | AV22: =IFERROR(AR22-AP22,"-") -> 0 | AW22: =IFERROR(AR22/AP22,"-") -> 1 | AX22: =BF22+BN22+BV22 -> 3.15 | AZ22: =BH22+BP22+BX22 -> 3.15 | BB22: =BJ22+BR22+BZ22 -> 0.559 | BD22: =IFERROR(AZ22-AX22,"-") -> 0 | BE22: =IFERROR(AZ22/AX22,"-") -> 1 | BF22: 2.45 | BH22: 2.45 | BJ22: 0 | BL22: =IFERROR(BH22-BF22,"-") -> 0 | BM22: =IFERROR(BH22/BF22,"-") -> 1 | BN22: 0.7 | BP22: 0.7 | BR22: 0.559 | BT22: =IFERROR(BP22-BN22,"-") -> 0 | BU22: =IFERROR(BP22/BN22,"-") -> 1 | BV22: 0 | BX22: 0 | BZ22: 0 | CB22: =IFERROR(BX22-BV22,"-") -> 0 | CC22: =IFERROR(BX22/BV22,"-") -> - | CD22: =CL22+CT22+DB22 -> 4.9 | CF22: =CN22+CV22+DD22 -> 4.9 | CH22: =CP22+CX22+DF22 -> 0 | CJ22: =IFERROR(CF22-CD22,"-") -> 0 | CK22: =IFERROR(CF22/CD22,"-") -> 1 | CL22: 0 | CN22: 0 | CR22: =IFERROR(CN22-CL22,"-") -> 0 | CS22: =IFERROR(CN22/CL22,"-") -> - | CT22: 2.45 | CV22: 2.45 | CZ22: =IFERROR(CV22-CT22,"-") -> 0 | DA22: =IFERROR(CV22/CT22,"-") -> 1 | DB22: 2.45 | DD22: 2.45 | DH22: =IFERROR(DD22-DB22,"-") -> 0 | DI22: =IFERROR(DD22/DB22,"-") -> 1 | DJ22: =DR22+DZ22+EH22 -> 6.3 | DL22: =DT22+EB22+EJ22 -> 6.3 | DN22: =DV22+ED22+EL22 -> 0 | DP22: =IFERROR(DL22-DJ22,"-") -> 0 | DQ22: =IFERROR(DL22/DJ22,"-") -> 1 | DR22: 2.1 | DT22: 2.1 | DX22: =IFERROR(DT22-DR22,"-") -> 0 | DY22: =IFERROR(DT22/DR22,"-") -> 1 | DZ22: 2.1 | EB22: 2.1 | EF22: =IFERROR(EB22-DZ22,"-") -> 0 | EG22: =IFERROR(EB22/DZ22,"-") -> 1 | EH22: 2.1 | EJ22: 2.1 | EN22: =IFERROR(EJ22-EH22,"-") -> 0 | EO22: =IFERROR(EJ22/EH22,"-") -> 1
A23: 2.3.2 | B23: Компонент для производства серы, собственность ПАО "Газпром" | C23: 100331988 | J23: =R23+AX23+CD23+DJ23 -> 2.5 | L23: =T23+AZ23+CF23+DL23 -> 2.5 | N23: =V23+BB23+CH23+DN23 -> 2.184 | P23: =IFERROR(L23-J23,"-") -> 0 | Q23: =IFERROR(L23/J23,"-") -> 1 | R23: =Z23+AH23+AP23 -> 0.9 | T23: =AB23+AJ23+AR23 -> 0.9 | V23: =AD23+AL23+AT23 -> 0.46 | X23: =IFERROR(T23-R23,"-") -> 0 | Y23: =IFERROR(T23/R23,"-") -> 1 | Z23: 0 | AB23: 0 | AD23: 0 | AF23: =IFERROR(AB23-Z23,"-") -> 0 | AG23: =IFERROR(AB23/Z23,"-") -> - | AH23: 0 | AJ23: 0 | AL23: 0 | AN23: =IFERROR(AJ23-AH23,"-") -> 0 | AO23: =IFERROR(AJ23/AH23,"-") -> - | AP23: 0.9 | AR23: 0.9 | AT23: 0.46 | AV23: =IFERROR(AR23-AP23,"-") -> 0 | AW23: =IFERROR(AR23/AP23,"-") -> 1 | AX23: =BF23+BN23+BV23 -> 0.9 | AZ23: =BH23+BP23+BX23 -> 0.9 | BB23: =BJ23+BR23+BZ23 -> 1.724 | BD23: =IFERROR(AZ23-AX23,"-") -> 0 | BE23: =IFERROR(AZ23/AX23,"-") -> 1 | BF23: 0.9 | BH23: 0.9 | BJ23: 0.843 | BL23: =IFERROR(BH23-BF23,"-") -> 0 | BM23: =IFERROR(BH23/BF23,"-") -> 1 | BN23: 0 | BP23: 0 | BR23: 0.363 | BT23: =IFERROR(BP23-BN23,"-") -> 0 | BU23: =IFERROR(BP23/BN23,"-") -> - | BV23: 0 | BX23: 0 | BZ23: 0.518 | CB23: =IFERROR(BX23-BV23,"-") -> 0 | CC23: =IFERROR(BX23/BV23,"-") -> - | CD23: =CL23+CT23+DB23 -> 0.7 | CF23: =CN23+CV23+DD23 -> 0.7 | CH23: =CP23+CX23+DF23 -> 0 | CJ23: =IFERROR(CF23-CD23,"-") -> 0 | CK23: =IFERROR(CF23/CD23,"-") -> 1 | CL23: 0.7 | CN23: 0.7 | CR23: =IFERROR(CN23-CL23,"-") -> 0 | CS23: =IFERROR(CN23/CL23,"-") -> 1 | CT23: 0 | CV23: 0 | CZ23: =IFERROR(CV23-CT23,"-") -> 0 | DA23: =IFERROR(CV23/CT23,"-") -> - | DB23: 0 | DD23: 0 | DH23: =IFERROR(DD23-DB23,"-") -> 0 | DI23: =IFERROR(DD23/DB23,"-") -> - | DJ23: =DR23+DZ23+EH23 -> 0 | DL23: =DT23+EB23+EJ23 -> 0 | DN23: =DV23+ED23+EL23 -> 0 | DP23: =IFERROR(DL23-DJ23,"-") -> 0 | DQ23: =IFERROR(DL23/DJ23,"-") -> - | DR23: 0 | DT23: 0 | DX23: =IFERROR(DT23-DR23,"-") -> 0 | DY23: =IFERROR(DT23/DR23,"-") -> - | DZ23: 0 | EB23: 0 | EF23: =IFERROR(EB23-DZ23,"-") -> 0 | EG23: =IFERROR(EB23/DZ23,"-") -> - | EH23: 0 | EJ23: 0 | EN23: =IFERROR(EJ23-EH23,"-") -> 0 | EO23: =IFERROR(EJ23/EH23,"-") -> -
A24: 2.3.3 | B24: Компонент производства при выработке кислого газа | C24: 100332914 | J24: =R24+AX24+CD24+DJ24 -> 286.3 | L24: =T24+AZ24+CF24+DL24 -> 286.3 | N24: =V24+BB24+CH24+DN24 -> 144.829 | P24: =IFERROR(L24-J24,"-") -> 0 | Q24: =IFERROR(L24/J24,"-") -> 1 | R24: =Z24+AH24+AP24 -> 41.3 | T24: =AB24+AJ24+AR24 -> 41.3 | V24: =AD24+AL24+AT24 -> 99.299 | X24: =IFERROR(T24-R24,"-") -> 0 | Y24: =IFERROR(T24/R24,"-") -> 1 | Z24: 13 | AB24: 13 | AD24: 31.368 | AF24: =IFERROR(AB24-Z24,"-") -> 0 | AG24: =IFERROR(AB24/Z24,"-") -> 1 | AH24: 14.3 | AJ24: 14.3 | AL24: 31.236 | AN24: =IFERROR(AJ24-AH24,"-") -> 0 | AO24: =IFERROR(AJ24/AH24,"-") -> 1 | AP24: 14 | AR24: 14 | AT24: 36.695 | AV24: =IFERROR(AR24-AP24,"-") -> 0 | AW24: =IFERROR(AR24/AP24,"-") -> 1 | AX24: =BF24+BN24+BV24 -> 66.8 | AZ24: =BH24+BP24+BX24 -> 66.8 | BB24: =BJ24+BR24+BZ24 -> 45.53 | BD24: =IFERROR(AZ24-AX24,"-") -> 0 | BE24: =IFERROR(AZ24/AX24,"-") -> 1 | BF24: 31.4 | BH24: 31.4 | BJ24: 26.794 | BL24: =IFERROR(BH24-BF24,"-") -> 0 | BM24: =IFERROR(BH24/BF24,"-") -> 1 | BN24: 22.7 | BP24: 22.7 | BR24: 11.497 | BT24: =IFERROR(BP24-BN24,"-") -> 0 | BU24: =IFERROR(BP24/BN24,"-") -> 1 | BV24: 12.7 | BX24: 12.7 | BZ24: 7.239 | CB24: =IFERROR(BX24-BV24,"-") -> 0 | CC24: =IFERROR(BX24/BV24,"-") -> 1 | CD24: =CL24+CT24+DB24 -> 141.7 | CF24: =CN24+CV24+DD24 -> 141.7 | CH24: =CP24+CX24+DF24 -> 0 | CJ24: =IFERROR(CF24-CD24,"-") -> 0 | CK24: =IFERROR(CF24/CD24,"-") -> 1 | CL24: 46.8 | CN24: 46.8 | CR24: =IFERROR(CN24-CL24,"-") -> 0 | CS24: =IFERROR(CN24/CL24,"-") -> 1 | CT24: 63.7 | CV24: 63.7 | CZ24: =IFERROR(CV24-CT24,"-") -> 0 | DA24: =IFERROR(CV24/CT24,"-") -> 1 | DB24: 31.2 | DD24: 31.2 | DH24: =IFERROR(DD24-DB24,"-") -> 0 | DI24: =IFERROR(DD24/DB24,"-") -> 1 | DJ24: =DR24+DZ24+EH24 -> 36.5 | DL24: =DT24+EB24+EJ24 -> 36.5 | DN24: =DV24+ED24+EL24 -> 0 | DP24: =IFERROR(DL24-DJ24,"-") -> 0 | DQ24: =IFERROR(DL24/DJ24,"-") -> 1 | DR24: 13.7 | DT24: 13.7 | DX24: =IFERROR(DT24-DR24,"-") -> 0 | DY24: =IFERROR(DT24/DR24,"-") -> 1 | DZ24: 14 | EB24: 14 | EF24: =IFERROR(EB24-DZ24,"-") -> 0 | EG24: =IFERROR(EB24/DZ24,"-") -> 1 | EH24: 8.8 | EJ24: 8.8 | EN24: =IFERROR(EJ24-EH24,"-") -> 0 | EO24: =IFERROR(EJ24/EH24,"-") -> 1
B25: Справочно: | E25: 1 | J25: =R25+AX25+CD25+DJ25 -> 0 | L25: =T25+AZ25+CF25+DL25 -> 0 | N25: =V25+BB25+CH25+DN25 -> 0 | P25: =IFERROR(L25-J25,"-") -> 0 | Q25: =IFERROR(L25/J25,"-") -> - | R25: =Z25+AH25+AP25 -> 0 | T25: =AB25+AJ25+AR25 -> 0 | V25: =AD25+AL25+AT25 -> 0 | X25: =IFERROR(T25-R25,"-") -> 0 | Y25: =IFERROR(T25/R25,"-") -> - | AF25: =IFERROR(AB25-Z25,"-") -> 0 | AG25: =IFERROR(AB25/Z25,"-") -> - | AN25: =IFERROR(AJ25-AH25,"-") -> 0 | AO25: =IFERROR(AJ25/AH25,"-") -> - | AV25: =IFERROR(AR25-AP25,"-") -> 0 | AW25: =IFERROR(AR25/AP25,"-") -> - | AX25: =BF25+BN25+BV25 -> 0 | AZ25: =BH25+BP25+BX25 -> 0 | BB25: =BJ25+BR25+BZ25 -> 0 | BD25: =IFERROR(AZ25-AX25,"-") -> 0 | BE25: =IFERROR(AZ25/AX25,"-") -> - | BL25: =IFERROR(BH25-BF25,"-") -> 0 | BM25: =IFERROR(BH25/BF25,"-") -> - | BT25: =IFERROR(BP25-BN25,"-") -> 0 | BU25: =IFERROR(BP25/BN25,"-") -> - | CB25: =IFERROR(BX25-BV25,"-") -> 0 | CC25: =IFERROR(BX25/BV25,"-") -> - | CD25: =CL25+CT25+DB25 -> 0 | CF25: =CN25+CV25+DD25 -> 0 | CH25: =CP25+CX25+DF25 -> 0 | CJ25: =IFERROR(CF25-CD25,"-") -> 0 | CK25: =IFERROR(CF25/CD25,"-") -> - | CR25: =IFERROR(CN25-CL25,"-") -> 0 | CS25: =IFERROR(CN25/CL25,"-") -> - | CZ25: =IFERROR(CV25-CT25,"-") -> 0 | DA25: =IFERROR(CV25/CT25,"-") -> - | DH25: =IFERROR(DD25-DB25,"-") -> 0 | DI25: =IFERROR(DD25/DB25,"-") -> - | DJ25: =DR25+DZ25+EH25 -> 0 | DL25: =DT25+EB25+EJ25 -> 0 | DN25: =DV25+ED25+EL25 -> 0 | DP25: =IFERROR(DL25-DJ25,"-") -> 0 | DQ25: =IFERROR(DL25/DJ25,"-") -> - | DX25: =IFERROR(DT25-DR25,"-") -> 0 | DY25: =IFERROR(DT25/DR25,"-") -> - | EF25: =IFERROR(EB25-DZ25,"-") -> 0 | EG25: =IFERROR(EB25/DZ25,"-") -> - | EN25: =IFERROR(EJ25-EH25,"-") -> 0 | EO25: =IFERROR(EJ25/EH25,"-") -> -
A26: 3 | B26: ПОТЕРИ СЫРЬЯ ПРИ ПЕРЕРАБОТКЕ (УСЛОВНЫЕ), ВСЕГО: | C26: 100331989 | J26: =R26+AX26+CD26+DJ26 -> 3610.7 | L26: =T26+AZ26+CF26+DL26 -> 3610.7 | N26: =V26+BB26+CH26+DN26 -> 1147.8997 | P26: =IFERROR(L26-J26,"-") -> 0 | Q26: =IFERROR(L26/J26,"-") -> 1 | R26: =Z26+AH26+AP26 -> 902.5 | T26: =AB26+AJ26+AR26 -> 902.5 | V26: =AD26+AL26+AT26 -> 815.88847 | X26: =IFERROR(T26-R26,"-") -> 0 | Y26: =IFERROR(T26/R26,"-") -> 1 | Z26: 308.7 | AB26: 308.7 | AD26: 262.09888 | AF26: =IFERROR(AB26-Z26,"-") -> 0 | AG26: =IFERROR(AB26/Z26,"-") -> 1 | AH26: 281.7 | AJ26: 281.7 | AL26: 315.56417 | AN26: =IFERROR(AJ26-AH26,"-") -> 0 | AO26: =IFERROR(AJ26/AH26,"-") -> 1 | AP26: 312.1 | AR26: 312.1 | AT26: 238.22542 | AV26: =IFERROR(AR26-AP26,"-") -> 0 | AW26: =IFERROR(AR26/AP26,"-") -> 1 | AX26: =BF26+BN26+BV26 -> 676.7 | AZ26: =BH26+BP26+BX26 -> 676.7 | BB26: =BJ26+BR26+BZ26 -> 332.01124 | BD26: =IFERROR(AZ26-AX26,"-") -> 0 | BE26: =IFERROR(AZ26/AX26,"-") -> 1 | BF26: 302.9 | BH26: 302.9 | BJ26: 186.70379 | BL26: =IFERROR(BH26-BF26,"-") -> 0 | BM26: =IFERROR(BH26/BF26,"-") -> 1 | BN26: 210.5 | BP26: 210.5 | BR26: 80.474 | BT26: =IFERROR(BP26-BN26,"-") -> 0 | BU26: =IFERROR(BP26/BN26,"-") -> 1 | BV26: 163.3 | BX26: 163.3 | BZ26: 64.833455 | CB26: =IFERROR(BX26-BV26,"-") -> 0 | CC26: =IFERROR(BX26/BV26,"-") -> 1 | CD26: =CL26+CT26+DB26 -> 1027.8 | CF26: =CN26+CV26+DD26 -> 1027.8 | CH26: =CP26+CX26+DF26 -> 0 | CJ26: =IFERROR(CF26-CD26,"-") -> 0 | CK26: =IFERROR(CF26/CD26,"-") -> 1 | CL26: 332.5 | CN26: 332.5 | CR26: =IFERROR(CN26-CL26,"-") -> 0 | CS26: =IFERROR(CN26/CL26,"-") -> 1 | CT26: 359 | CV26: 359 | CZ26: =IFERROR(CV26-CT26,"-") -> 0 | DA26: =IFERROR(CV26/CT26,"-") -> 1 | DB26: 336.3 | DD26: 336.3 | DH26: =IFERROR(DD26-DB26,"-") -> 0 | DI26: =IFERROR(DD26/DB26,"-") -> 1 | DJ26: =DR26+DZ26+EH26 -> 1003.7 | DL26: =DT26+EB26+EJ26 -> 1003.7 | DN26: =DV26+ED26+EL26 -> 0 | DP26: =IFERROR(DL26-DJ26,"-") -> 0 | DQ26: =IFERROR(DL26/DJ26,"-") -> 1 | DR26: 332.5 | DT26: 332.5 | DX26: =IFERROR(DT26-DR26,"-") -> 0 | DY26: =IFERROR(DT26/DR26,"-") -> 1 | DZ26: 336.7 | EB26: 336.7 | EF26: =IFERROR(EB26-DZ26,"-") -> 0 | EG26: =IFERROR(EB26/DZ26,"-") -> 1 | EH26: 334.5 | EJ26: 334.5 | EN26: =IFERROR(EJ26-EH26,"-") -> 0 | EO26: =IFERROR(EJ26/EH26,"-") -> 1
A27: 3.1 | B27: Природный газ | C27: 100331990 | J27: =R27+AX27+CD27+DJ27 -> 3541.5 | L27: =T27+AZ27+CF27+DL27 -> 3541.5 | N27: =V27+BB27+CH27+DN27 -> 1141.019 | P27: =IFERROR(L27-J27,"-") -> 0 | Q27: =IFERROR(L27/J27,"-") -> 1 | R27: =Z27+AH27+AP27 -> 882.9 | T27: =AB27+AJ27+AR27 -> 882.9 | V27: =AD27+AL27+AT27 -> 813.15497 | X27: =IFERROR(T27-R27,"-") -> 0 | Y27: =IFERROR(T27/R27,"-") -> 1 | Z27: 301.9 | AB27: 301.9 | AD27: 261.24288 | AF27: =IFERROR(AB27-Z27,"-") -> 0 | AG27: =IFERROR(AB27/Z27,"-") -> 1 | AH27: 275.5 | AJ27: 275.5 | AL27: 314.88717 | AN27: =IFERROR(AJ27-AH27,"-") -> 0 | AO27: =IFERROR(AJ27/AH27,"-") -> 1 | AP27: 305.5 | AR27: 305.5 | AT27: 237.02492 | AV27: =IFERROR(AR27-AP27,"-") -> 0 | AW27: =IFERROR(AR27/AP27,"-") -> 1 | AX27: =BF27+BN27+BV27 -> 666.9 | AZ27: =BH27+BP27+BX27 -> 666.9 | BB27: =BJ27+BR27+BZ27 -> 327.86398 | BD27: =IFERROR(AZ27-AX27,"-") -> 0 | BE27: =IFERROR(AZ27/AX27,"-") -> 1 | BF27: 296.4 | BH27: 296.4 | BJ27: 184.61552 | BL27: =IFERROR(BH27-BF27,"-") -> 0 | BM27: =IFERROR(BH27/BF27,"-") -> 1 | BN27: 208 | BP27: 208 | BR27: 78.649 | BT27: =IFERROR(BP27-BN27,"-") -> 0 | BU27: =IFERROR(BP27/BN27,"-") -> 1 | BV27: 162.5 | BX27: 162.5 | BZ27: 64.599455 | CB27: =IFERROR(BX27-BV27,"-") -> 0 | CC27: =IFERROR(BX27/BV27,"-") -> 1 | CD27: =CL27+CT27+DB27 -> 1009.5 | CF27: =CN27+CV27+DD27 -> 1009.5 | CH27: =CP27+CX27+DF27 -> 0 | CJ27: =IFERROR(CF27-CD27,"-") -> 0 | CK27: =IFERROR(CF27/CD27,"-") -> 1 | CL27: 327.4 | CN27: 327.4 | CR27: =IFERROR(CN27-CL27,"-") -> 0 | CS27: =IFERROR(CN27/CL27,"-") -> 1 | CT27: 352.3 | CV27: 352.3 | CZ27: =IFERROR(CV27-CT27,"-") -> 0 | DA27: =IFERROR(CV27/CT27,"-") -> 1 | DB27: 329.8 | DD27: 329.8 | DH27: =IFERROR(DD27-DB27,"-") -> 0 | DI27: =IFERROR(DD27/DB27,"-") -> 1 | DJ27: =DR27+DZ27+EH27 -> 982.2 | DL27: =DT27+EB27+EJ27 -> 982.2 | DN27: =DV27+ED27+EL27 -> 0 | DP27: =IFERROR(DL27-DJ27,"-") -> 0 | DQ27: =IFERROR(DL27/DJ27,"-") -> 1 | DR27: 325.5 | DT27: 325.5 | DX27: =IFERROR(DT27-DR27,"-") -> 0 | DY27: =IFERROR(DT27/DR27,"-") -> 1 | DZ27: 329.8 | EB27: 329.8 | EF27: =IFERROR(EB27-DZ27,"-") -> 0 | EG27: =IFERROR(EB27/DZ27,"-") -> 1 | EH27: 326.9 | EJ27: 326.9 | EN27: =IFERROR(EJ27-EH27,"-") -> 0 | EO27: =IFERROR(EJ27/EH27,"-") -> 1
A28: 3.2 | B28: Конденсат газовый нестабильный - 100331991 | E28: 6 | J28: =R28+AX28+CD28+DJ28 -> 0 | L28: =T28+AZ28+CF28+DL28 -> 0 | N28: =V28+BB28+CH28+DN28 -> 0 | P28: =IFERROR(L28-J28,"-") -> 0 | Q28: =IFERROR(L28/J28,"-") -> - | R28: =Z28+AH28+AP28 -> 0 | T28: =AB28+AJ28+AR28 -> 0 | V28: =AD28+AL28+AT28 -> 0 | X28: =IFERROR(T28-R28,"-") -> 0 | Y28: =IFERROR(T28/R28,"-") -> - | AF28: =IFERROR(AB28-Z28,"-") -> 0 | AG28: =IFERROR(AB28/Z28,"-") -> - | AN28: =IFERROR(AJ28-AH28,"-") -> 0 | AO28: =IFERROR(AJ28/AH28,"-") -> - | AV28: =IFERROR(AR28-AP28,"-") -> 0 | AW28: =IFERROR(AR28/AP28,"-") -> - | AX28: =BF28+BN28+BV28 -> 0 | AZ28: =BH28+BP28+BX28 -> 0 | BB28: =BJ28+BR28+BZ28 -> 0 | BD28: =IFERROR(AZ28-AX28,"-") -> 0 | BE28: =IFERROR(AZ28/AX28,"-") -> - | BL28: =IFERROR(BH28-BF28,"-") -> 0 | BM28: =IFERROR(BH28/BF28,"-") -> - | BT28: =IFERROR(BP28-BN28,"-") -> 0 | BU28: =IFERROR(BP28/BN28,"-") -> - | CB28: =IFERROR(BX28-BV28,"-") -> 0 | CC28: =IFERROR(BX28/BV28,"-") -> - | CD28: =CL28+CT28+DB28 -> 0 | CF28: =CN28+CV28+DD28 -> 0 | CH28: =CP28+CX28+DF28 -> 0 | CJ28: =IFERROR(CF28-CD28,"-") -> 0 | CK28: =IFERROR(CF28/CD28,"-") -> - | CR28: =IFERROR(CN28-CL28,"-") -> 0 | CS28: =IFERROR(CN28/CL28,"-") -> - | CZ28: =IFERROR(CV28-CT28,"-") -> 0 | DA28: =IFERROR(CV28/CT28,"-") -> - | DH28: =IFERROR(DD28-DB28,"-") -> 0 | DI28: =IFERROR(DD28/DB28,"-") -> - | DJ28: =DR28+DZ28+EH28 -> 0 | DL28: =DT28+EB28+EJ28 -> 0 | DN28: =DV28+ED28+EL28 -> 0 | DP28: =IFERROR(DL28-DJ28,"-") -> 0 | DQ28: =IFERROR(DL28/DJ28,"-") -> - | DX28: =IFERROR(DT28-DR28,"-") -> 0 | DY28: =IFERROR(DT28/DR28,"-") -> - | EF28: =IFERROR(EB28-DZ28,"-") -> 0 | EG28: =IFERROR(EB28/DZ28,"-") -> - | EN28: =IFERROR(EJ28-EH28,"-") -> 0 | EO28: =IFERROR(EJ28/EH28,"-") -> -
A29: 4 | B29: ПРОИЗВОДСТВО ПРОДУКЦИИ, собственность ПАО "Газпром", ВСЕГО: | C29: 100331853 | J29: =R29+AX29+CD29+DJ29 -> 10260.2 | L29: =T29+AZ29+CF29+DL29 -> 10260.2 | N29: =V29+BB29+CH29+DN29 -> 2757.6774 | P29: =IFERROR(L29-J29,"-") -> 0 | Q29: =IFERROR(L29/J29,"-") -> 1 | R29: =Z29+AH29+AP29 -> 2548.3 | T29: =AB29+AJ29+AR29 -> 2548.3 | V29: =AD29+AL29+AT29 -> 1645.0973 | X29: =IFERROR(T29-R29,"-") -> 0 | Y29: =IFERROR(T29/R29,"-") -> 1 | Z29: 878.2 | AB29: 878.2 | AD29: 620.63202 | AF29: =IFERROR(AB29-Z29,"-") -> 0 | AG29: =IFERROR(AB29/Z29,"-") -> 1 | AH29: 793.2 | AJ29: 793.2 | AL29: 378.7772 | AN29: =IFERROR(AJ29-AH29,"-") -> 0 | AO29: =IFERROR(AJ29/AH29,"-") -> 1 | AP29: 876.9 | AR29: 876.9 | AT29: 645.68808 | AV29: =IFERROR(AR29-AP29,"-") -> 0 | AW29: =IFERROR(AR29/AP29,"-") -> 1 | AX29: =BF29+BN29+BV29 -> 1989 | AZ29: =BH29+BP29+BX29 -> 1989 | BB29: =BJ29+BR29+BZ29 -> 1112.5801 | BD29: =IFERROR(AZ29-AX29,"-") -> 0 | BE29: =IFERROR(AZ29/AX29,"-") -> 1 | BF29: 865.9 | BH29: 865.9 | BJ29: 648.09282 | BL29: =IFERROR(BH29-BF29,"-") -> 0 | BM29: =IFERROR(BH29/BF29,"-") -> 1 | BN29: 618.5 | BP29: 618.5 | BR29: 271.36384 | BT29: =IFERROR(BP29-BN29,"-") -> 0 | BU29: =IFERROR(BP29/BN29,"-") -> 1 | BV29: 504.6 | BX29: 504.6 | BZ29: 193.12341 | CB29: =IFERROR(BX29-BV29,"-") -> 0 | CC29: =IFERROR(BX29/BV29,"-") -> 1 | CD29: =CL29+CT29+DB29 -> 2822 | CF29: =CN29+CV29+DD29 -> 2822 | CH29: =CP29+CX29+DF29 -> 0 | CJ29: =IFERROR(CF29-CD29,"-") -> 0 | CK29: =IFERROR(CF29/CD29,"-") -> 1 | CL29: 933.5 | CN29: 933.5 | CR29: =IFERROR(CN29-CL29,"-") -> 0 | CS29: =IFERROR(CN29/CL29,"-") -> 1 | CT29: 931.1 | CV29: 931.1 | CZ29: =IFERROR(CV29-CT29,"-") -> 0 | DA29: =IFERROR(CV29/CT29,"-") -> 1 | DB29: 957.4 | DD29: 957.4 | DH29: =IFERROR(DD29-DB29,"-") -> 0 | DI29: =IFERROR(DD29/DB29,"-") -> 1 | DJ29: =DR29+DZ29+EH29 -> 2900.9 | DL29: =DT29+EB29+EJ29 -> 2900.9 | DN29: =DV29+ED29+EL29 -> 0 | DP29: =IFERROR(DL29-DJ29,"-") -> 0 | DQ29: =IFERROR(DL29/DJ29,"-") -> 1 | DR29: 985.4 | DT29: 985.4 | DX29: =IFERROR(DT29-DR29,"-") -> 0 | DY29: =IFERROR(DT29/DR29,"-") -> 1 | DZ29: 939.5 | EB29: 939.5 | EF29: =IFERROR(EB29-DZ29,"-") -> 0 | EG29: =IFERROR(EB29/DZ29,"-") -> 1 | EH29: 976 | EJ29: 976 | EN29: =IFERROR(EJ29-EH29,"-") -> 0 | EO29: =IFERROR(EJ29/EH29,"-") -> 1
A30: 4.1 | B30: ГАЗ ПРИРОДНЫЙ СУХОЙ ОТБЕНЗИНЕННЫЙ, ВСЕГО: | C30: 100331992 | J30: =R30+AX30+CD30+DJ30 -> 3682.1 | L30: =T30+AZ30+CF30+DL30 -> 3682.1 | N30: =V30+BB30+CH30+DN30 -> 883.97644 | P30: =IFERROR(L30-J30,"-") -> 0 | Q30: =IFERROR(L30/J30,"-") -> 1 | R30: =Z30+AH30+AP30 -> 900.5 | T30: =AB30+AJ30+AR30 -> 900.5 | V30: =AD30+AL30+AT30 -> 498.25886 | X30: =IFERROR(T30-R30,"-") -> 0 | Y30: =IFERROR(T30/R30,"-") -> 1 | Z30: 311 | AB30: 311 | AD30: 203.70835 | AF30: =IFERROR(AB30-Z30,"-") -> 0 | AG30: =IFERROR(AB30/Z30,"-") -> 1 | AH30: 280.7 | AJ30: 280.7 | AL30: 63.946823 | AN30: =IFERROR(AJ30-AH30,"-") -> 0 | AO30: =IFERROR(AJ30/AH30,"-") -> 1 | AP30: 308.8 | AR30: 308.8 | AT30: 230.60368 | AV30: =IFERROR(AR30-AP30,"-") -> 0 | AW30: =IFERROR(AR30/AP30,"-") -> 1 | AX30: =BF30+BN30+BV30 -> 724 | AZ30: =BH30+BP30+BX30 -> 724 | BB30: =BJ30+BR30+BZ30 -> 385.71758 | BD30: =IFERROR(AZ30-AX30,"-") -> 0 | BE30: =IFERROR(AZ30/AX30,"-") -> 1 | BF30: 314.1 | BH30: 314.1 | BJ30: 240.61239 | BL30: =IFERROR(BH30-BF30,"-") -> 0 | BM30: =IFERROR(BH30/BF30,"-") -> 1 | BN30: 225.8 | BP30: 225.8 | BR30: 89.595836 | BT30: =IFERROR(BP30-BN30,"-") -> 0 | BU30: =IFERROR(BP30/BN30,"-") -> 1 | BV30: 184.1 | BX30: 184.1 | BZ30: 55.509362 | CB30: =IFERROR(BX30-BV30,"-") -> 0 | CC30: =IFERROR(BX30/BV30,"-") -> 1 | CD30: =CL30+CT30+DB30 -> 1027.6 | CF30: =CN30+CV30+DD30 -> 1027.6 | CH30: =CP30+CX30+DF30 -> 0 | CJ30: =IFERROR(CF30-CD30,"-") -> 0 | CK30: =IFERROR(CF30/CD30,"-") -> 1 | CL30: 342.1 | CN30: 342.1 | CR30: =IFERROR(CN30-CL30,"-") -> 0 | CS30: =IFERROR(CN30/CL30,"-") -> 1 | CT30: 338.3 | CV30: 338.3 | CZ30: =IFERROR(CV30-CT30,"-") -> 0 | DA30: =IFERROR(CV30/CT30,"-") -> 1 | DB30: 347.2 | DD30: 347.2 | DH30: =IFERROR(DD30-DB30,"-") -> 0 | DI30: =IFERROR(DD30/DB30,"-") -> 1 | DJ30: =DR30+DZ30+EH30 -> 1030 | DL30: =DT30+EB30+EJ30 -> 1030 | DN30: =DV30+ED30+EL30 -> 0 | DP30: =IFERROR(DL30-DJ30,"-") -> 0 | DQ30: =IFERROR(DL30/DJ30,"-") -> 1 | DR30: 354.3 | DT30: 354.3 | DX30: =IFERROR(DT30-DR30,"-") -> 0 | DY30: =IFERROR(DT30/DR30,"-") -> 1 | DZ30: 328.6 | EB30: 328.6 | EF30: =IFERROR(EB30-DZ30,"-") -> 0 | EG30: =IFERROR(EB30/DZ30,"-") -> 1 | EH30: 347.1 | EJ30: 347.1 | EN30: =IFERROR(EJ30-EH30,"-") -> 0 | EO30: =IFERROR(EJ30/EH30,"-") -> 1
C31: 100331993 | J31: =R31+AX31+CD31+DJ31 -> 5308.6 | L31: =T31+AZ31+CF31+DL31 -> 5308.6 | N31: =V31+BB31+CH31+DN31 -> 1270.4963 | P31: =IFERROR(L31-J31,"-") -> 0 | Q31: =IFERROR(L31/J31,"-") -> 1 | R31: =Z31+AH31+AP31 -> 1298.4 | T31: =AB31+AJ31+AR31 -> 1298.4 | V31: =AD31+AL31+AT31 -> 715.07832 | X31: =IFERROR(T31-R31,"-") -> 0 | Y31: =IFERROR(T31/R31,"-") -> 1 | Z31: 448.4 | AB31: 448.4 | AD31: 293.06338 | AF31: =IFERROR(AB31-Z31,"-") -> 0 | AG31: =IFERROR(AB31/Z31,"-") -> 1 | AH31: 404.7 | AJ31: 404.7 | AL31: 90.885195 | AN31: =IFERROR(AJ31-AH31,"-") -> 0 | AO31: =IFERROR(AJ31/AH31,"-") -> 1 | AP31: 445.3 | AR31: 445.3 | AT31: 331.12975 | AV31: =IFERROR(AR31-AP31,"-") -> 0 | AW31: =IFERROR(AR31/AP31,"-") -> 1 | AX31: =BF31+BN31+BV31 -> 1043.7 | AZ31: =BH31+BP31+BX31 -> 1043.7 | BB31: =BJ31+BR31+BZ31 -> 555.418 | BD31: =IFERROR(AZ31-AX31,"-") -> 0 | BE31: =IFERROR(AZ31/AX31,"-") -> 1 | BF31: 452.9 | BH31: 452.9 | BJ31: 346.03938 | BL31: =IFERROR(BH31-BF31,"-") -> 0 | BM31: =IFERROR(BH31/BF31,"-") -> 1 | BN31: 325.5 | BP31: 325.5 | BR31: 129.18596 | BT31: =IFERROR(BP31-BN31,"-") -> 0 | BU31: =IFERROR(BP31/BN31,"-") -> 1 | BV31: 265.3 | BX31: 265.3 | BZ31: 80.192664 | CB31: =IFERROR(BX31-BV31,"-") -> 0 | CC31: =IFERROR(BX31/BV31,"-") -> 1 | CD31: =CL31+CT31+DB31 -> 1481.6 | CF31: =CN31+CV31+DD31 -> 1481.6 | CH31: =CP31+CX31+DF31 -> 0 | CJ31: =IFERROR(CF31-CD31,"-") -> 0 | CK31: =IFERROR(CF31/CD31,"-") -> 1 | CL31: 493.2 | CN31: 493.2 | CR31: =IFERROR(CN31-CL31,"-") -> 0 | CS31: =IFERROR(CN31/CL31,"-") -> 1 | CT31: 487.8 | CV31: 487.8 | CZ31: =IFERROR(CV31-CT31,"-") -> 0 | DA31: =IFERROR(CV31/CT31,"-") -> 1 | DB31: 500.6 | DD31: 500.6 | DH31: =IFERROR(DD31-DB31,"-") -> 0 | DI31: =IFERROR(DD31/DB31,"-") -> 1 | DJ31: =DR31+DZ31+EH31 -> 1484.9 | DL31: =DT31+EB31+EJ31 -> 1484.9 | DN31: =DV31+ED31+EL31 -> 0 | DP31: =IFERROR(DL31-DJ31,"-") -> 0 | DQ31: =IFERROR(DL31/DJ31,"-") -> 1 | DR31: 510.8 | DT31: 510.8 | DX31: =IFERROR(DT31-DR31,"-") -> 0 | DY31: =IFERROR(DT31/DR31,"-") -> 1 | DZ31: 473.8 | EB31: 473.8 | EF31: =IFERROR(EB31-DZ31,"-") -> 0 | EG31: =IFERROR(EB31/DZ31,"-") -> 1 | EH31: 500.3 | EJ31: 500.3 | EN31: =IFERROR(EJ31-EH31,"-") -> 0 | EO31: =IFERROR(EJ31/EH31,"-") -> 1
A32: 4.1.1 | B32: Газ горючий природный, в ГТС | C32: 100331994 | J32: =R32+AX32+CD32+DJ32 -> 3363.2 | L32: =T32+AZ32+CF32+DL32 -> 3363.2 | N32: =V32+BB32+CH32+DN32 -> 802.62981 | P32: =IFERROR(L32-J32,"-") -> 0 | Q32: =IFERROR(L32/J32,"-") -> 1 | R32: =Z32+AH32+AP32 -> 818.9 | T32: =AB32+AJ32+AR32 -> 818.9 | V32: =AD32+AL32+AT32 -> 444.94741 | X32: =IFERROR(T32-R32,"-") -> 0 | Y32: =IFERROR(T32/R32,"-") -> 1 | Z32: 282.7 | AB32: 282.7 | AD32: 184.44954 | AF32: =IFERROR(AB32-Z32,"-") -> 0 | AG32: =IFERROR(AB32/Z32,"-") -> 1 | AH32: 255.1 | AJ32: 255.1 | AL32: 52.75893 | AN32: =IFERROR(AJ32-AH32,"-") -> 0 | AO32: =IFERROR(AJ32/AH32,"-") -> 1 | AP32: 281.1 | AR32: 281.1 | AT32: 207.73893 | AV32: =IFERROR(AR32-AP32,"-") -> 0 | AW32: =IFERROR(AR32/AP32,"-") -> 1 | AX32: =BF32+BN32+BV32 -> 655 | AZ32: =BH32+BP32+BX32 -> 655 | BB32: =BJ32+BR32+BZ32 -> 357.6824 | BD32: =IFERROR(AZ32-AX32,"-") -> 0 | BE32: =IFERROR(AZ32/AX32,"-") -> 1 | BF32: 288.3 | BH32: 288.3 | BJ32: 220.01827 | BL32: =IFERROR(BH32-BF32,"-") -> 0 | BM32: =IFERROR(BH32/BF32,"-") -> 1 | BN32: 203.1 | BP32: 203.1 | BR32: 85.661017 | BT32: =IFERROR(BP32-BN32,"-") -> 0 | BU32: =IFERROR(BP32/BN32,"-") -> 1 | BV32: 163.6 | BX32: 163.6 | BZ32: 52.003116 | CB32: =IFERROR(BX32-BV32,"-") -> 0 | CC32: =IFERROR(BX32/BV32,"-") -> 1 | CD32: =CL32+CT32+DB32 -> 945.9 | CF32: =CN32+CV32+DD32 -> 945.9 | CH32: =CP32+CX32+DF32 -> 0 | CJ32: =IFERROR(CF32-CD32,"-") -> 0 | CK32: =IFERROR(CF32/CD32,"-") -> 1 | CL32: 314.3 | CN32: 314.3 | CR32: =IFERROR(CN32-CL32,"-") -> 0 | CS32: =IFERROR(CN32/CL32,"-") -> 1 | CT32: 311.6 | CV32: 311.6 | CZ32: =IFERROR(CV32-CT32,"-") -> 0 | DA32: =IFERROR(CV32/CT32,"-") -> 1 | DB32: 320 | DD32: 320 | DH32: =IFERROR(DD32-DB32,"-") -> 0 | DI32: =IFERROR(DD32/DB32,"-") -> 1 | DJ32: =DR32+DZ32+EH32 -> 943.4 | DL32: =DT32+EB32+EJ32 -> 943.4 | DN32: =DV32+ED32+EL32 -> 0 | DP32: =IFERROR(DL32-DJ32,"-") -> 0 | DQ32: =IFERROR(DL32/DJ32,"-") -> 1 | DR32: 325.4 | DT32: 325.4 | DX32: =IFERROR(DT32-DR32,"-") -> 0 | DY32: =IFERROR(DT32/DR32,"-") -> 1 | DZ32: 300.6 | EB32: 300.6 | EF32: =IFERROR(EB32-DZ32,"-") -> 0 | EG32: =IFERROR(EB32/DZ32,"-") -> 1 | EH32: 317.4 | EJ32: 317.4 | EN32: =IFERROR(EJ32-EH32,"-") -> 0 | EO32: =IFERROR(EJ32/EH32,"-") -> 1
C33: 100331995 | J33: =R33+AX33+CD33+DJ33 -> 4848.4 | L33: =T33+AZ33+CF33+DL33 -> 4848.4 | N33: =V33+BB33+CH33+DN33 -> 1155.5797 | P33: =IFERROR(L33-J33,"-") -> 0 | Q33: =IFERROR(L33/J33,"-") -> 1 | R33: =Z33+AH33+AP33 -> 1182.3 | T33: =AB33+AJ33+AR33 -> 1182.3 | V33: =AD33+AL33+AT33 -> 639.63362 | X33: =IFERROR(T33-R33,"-") -> 0 | Y33: =IFERROR(T33/R33,"-") -> 1 | Z33: 408.2 | AB33: 408.2 | AD33: 265.35684 | AF33: =IFERROR(AB33-Z33,"-") -> 0 | AG33: =IFERROR(AB33/Z33,"-") -> 1 | AH33: 368.5 | AJ33: 368.5 | AL33: 74.984267 | AN33: =IFERROR(AJ33-AH33,"-") -> 0 | AO33: =IFERROR(AJ33/AH33,"-") -> 1 | AP33: 405.6 | AR33: 405.6 | AT33: 299.29251 | AV33: =IFERROR(AR33-AP33,"-") -> 0 | AW33: =IFERROR(AR33/AP33,"-") -> 1 | AX33: =BF33+BN33+BV33 -> 944.5 | AZ33: =BH33+BP33+BX33 -> 944.5 | BB33: =BJ33+BR33+BZ33 -> 515.94611 | BD33: =IFERROR(AZ33-AX33,"-") -> 0 | BE33: =IFERROR(AZ33/AX33,"-") -> 1 | BF33: 415.7 | BH33: 415.7 | BJ33: 317.12059 | BL33: =IFERROR(BH33-BF33,"-") -> 0 | BM33: =IFERROR(BH33/BF33,"-") -> 1 | BN33: 292.6 | BP33: 292.6 | BR33: 123.69822 | BT33: =IFERROR(BP33-BN33,"-") -> 0 | BU33: =IFERROR(BP33/BN33,"-") -> 1 | BV33: 236.2 | BX33: 236.2 | BZ33: 75.127298 | CB33: =IFERROR(BX33-BV33,"-") -> 0 | CC33: =IFERROR(BX33/BV33,"-") -> 1 | CD33: =CL33+CT33+DB33 -> 1363.1 | CF33: =CN33+CV33+DD33 -> 1363.1 | CH33: =CP33+CX33+DF33 -> 0 | CJ33: =IFERROR(CF33-CD33,"-") -> 0 | CK33: =IFERROR(CF33/CD33,"-") -> 1 | CL33: 453 | CN33: 453 | CR33: =IFERROR(CN33-CL33,"-") -> 0 | CS33: =IFERROR(CN33/CL33,"-") -> 1 | CT33: 448.8 | CV33: 448.8 | CZ33: =IFERROR(CV33-CT33,"-") -> 0 | DA33: =IFERROR(CV33/CT33,"-") -> 1 | DB33: 461.3 | DD33: 461.3 | DH33: =IFERROR(DD33-DB33,"-") -> 0 | DI33: =IFERROR(DD33/DB33,"-") -> 1 | DJ33: =DR33+DZ33+EH33 -> 1358.5 | DL33: =DT33+EB33+EJ33 -> 1358.5 | DN33: =DV33+ED33+EL33 -> 0 | DP33: =IFERROR(DL33-DJ33,"-") -> 0 | DQ33: =IFERROR(DL33/DJ33,"-") -> 1 | DR33: 468.5 | DT33: 468.5 | DX33: =IFERROR(DT33-DR33,"-") -> 0 | DY33: =IFERROR(DT33/DR33,"-") -> 1 | DZ33: 433.3 | EB33: 433.3 | EF33: =IFERROR(EB33-DZ33,"-") -> 0 | EG33: =IFERROR(EB33/DZ33,"-") -> 1 | EH33: 456.7 | EJ33: 456.7 | EN33: =IFERROR(EJ33-EH33,"-") -> 0 | EO33: =IFERROR(EJ33/EH33,"-") -> 1
A34: 4.1.2 | B34: Газ на СТН ООО «Газпром добыча Астрахань», собственность ПАО "Газпром" | C34: 100331996 | J34: =R34+AX34+CD34+DJ34 -> 94.9 | L34: =T34+AZ34+CF34+DL34 -> 94.9 | N34: =V34+BB34+CH34+DN34 -> 35.561245 | P34: =IFERROR(L34-J34,"-") -> 0 | Q34: =IFERROR(L34/J34,"-") -> 1 | R34: =Z34+AH34+AP34 -> 25.7 | T34: =AB34+AJ34+AR34 -> 25.7 | V34: =AD34+AL34+AT34 -> 21.830974 | X34: =IFERROR(T34-R34,"-") -> 0 | Y34: =IFERROR(T34/R34,"-") -> 1 | Z34: 8.8 | AB34: 8.8 | AD34: 8.643992 | AF34: =IFERROR(AB34-Z34,"-") -> 0 | AG34: =IFERROR(AB34/Z34,"-") -> 1 | AH34: 8.3 | AJ34: 8.3 | AL34: 5.221277 | AN34: =IFERROR(AJ34-AH34,"-") -> 0 | AO34: =IFERROR(AJ34/AH34,"-") -> 1 | AP34: 8.6 | AR34: 8.6 | AT34: 7.965705 | AV34: =IFERROR(AR34-AP34,"-") -> 0 | AW34: =IFERROR(AR34/AP34,"-") -> 1 | AX34: =BF34+BN34+BV34 -> 21.6 | AZ34: =BH34+BP34+BX34 -> 21.6 | BB34: =BJ34+BR34+BZ34 -> 13.730271 | BD34: =IFERROR(AZ34-AX34,"-") -> 0 | BE34: =IFERROR(AZ34/AX34,"-") -> 1 | BF34: 7.7 | BH34: 7.7 | BJ34: 7.529229 | BL34: =IFERROR(BH34-BF34,"-") -> 0 | BM34: =IFERROR(BH34/BF34,"-") -> 1 | BN34: 7 | BP34: 7 | BR34: 2.817355 | BT34: =IFERROR(BP34-BN34,"-") -> 0 | BU34: =IFERROR(BP34/BN34,"-") -> 1 | BV34: 6.9 | BX34: 6.9 | BZ34: 3.383687 | CB34: =IFERROR(BX34-BV34,"-") -> 0 | CC34: =IFERROR(BX34/BV34,"-") -> 1 | CD34: =CL34+CT34+DB34 -> 22.3 | CF34: =CN34+CV34+DD34 -> 22.3 | CH34: =CP34+CX34+DF34 -> 0 | CJ34: =IFERROR(CF34-CD34,"-") -> 0 | CK34: =IFERROR(CF34/CD34,"-") -> 1 | CL34: 7.4 | CN34: 7.4 | CR34: =IFERROR(CN34-CL34,"-") -> 0 | CS34: =IFERROR(CN34/CL34,"-") -> 1 | CT34: 7.1 | CV34: 7.1 | CZ34: =IFERROR(CV34-CT34,"-") -> 0 | DA34: =IFERROR(CV34/CT34,"-") -> 1 | DB34: 7.8 | DD34: 7.8 | DH34: =IFERROR(DD34-DB34,"-") -> 0 | DI34: =IFERROR(DD34/DB34,"-") -> 1 | DJ34: =DR34+DZ34+EH34 -> 25.3 | DL34: =DT34+EB34+EJ34 -> 25.3 | DN34: =DV34+ED34+EL34 -> 0 | DP34: =IFERROR(DL34-DJ34,"-") -> 0 | DQ34: =IFERROR(DL34/DJ34,"-") -> 1 | DR34: 8.4 | DT34: 8.4 | DX34: =IFERROR(DT34-DR34,"-") -> 0 | DY34: =IFERROR(DT34/DR34,"-") -> 1 | DZ34: 8.3 | EB34: 8.3 | EF34: =IFERROR(EB34-DZ34,"-") -> 0 | EG34: =IFERROR(EB34/DZ34,"-") -> 1 | EH34: 8.6 | EJ34: 8.6 | EN34: =IFERROR(EJ34-EH34,"-") -> 0 | EO34: =IFERROR(EJ34/EH34,"-") -> 1
C35: 100331997 | J35: =R35+AX35+CD35+DJ35 -> 137.3 | L35: =T35+AZ35+CF35+DL35 -> 137.3 | N35: =V35+BB35+CH35+DN35 -> 51.141571 | P35: =IFERROR(L35-J35,"-") -> 0 | Q35: =IFERROR(L35/J35,"-") -> 1 | R35: =Z35+AH35+AP35 -> 35.5 | T35: =AB35+AJ35+AR35 -> 35.5 | V35: =AD35+AL35+AT35 -> 31.332721 | X35: =IFERROR(T35-R35,"-") -> 0 | Y35: =IFERROR(T35/R35,"-") -> 1 | Z35: 12.1 | AB35: 12.1 | AD35: 12.43561 | AF35: =IFERROR(AB35-Z35,"-") -> 0 | AG35: =IFERROR(AB35/Z35,"-") -> 1 | AH35: 11.3 | AJ35: 11.3 | AL35: 7.420803 | AN35: =IFERROR(AJ35-AH35,"-") -> 0 | AO35: =IFERROR(AJ35/AH35,"-") -> 1 | AP35: 12.1 | AR35: 12.1 | AT35: 11.476308 | AV35: =IFERROR(AR35-AP35,"-") -> 0 | AW35: =IFERROR(AR35/AP35,"-") -> 1 | AX35: =BF35+BN35+BV35 -> 30.9 | AZ35: =BH35+BP35+BX35 -> 30.9 | BB35: =BJ35+BR35+BZ35 -> 19.80885 | BD35: =IFERROR(AZ35-AX35,"-") -> 0 | BE35: =IFERROR(AZ35/AX35,"-") -> 1 | BF35: 11.1 | BH35: 11.1 | BJ35: 10.85216 | BL35: =IFERROR(BH35-BF35,"-") -> 0 | BM35: =IFERROR(BH35/BF35,"-") -> 1 | BN35: 10.3 | BP35: 10.3 | BR35: 4.068381 | BT35: =IFERROR(BP35-BN35,"-") -> 0 | BU35: =IFERROR(BP35/BN35,"-") -> 1 | BV35: 9.5 | BX35: 9.5 | BZ35: 4.888309 | CB35: =IFERROR(BX35-BV35,"-") -> 0 | CC35: =IFERROR(BX35/BV35,"-") -> 1 | CD35: =CL35+CT35+DB35 -> 32.8 | CF35: =CN35+CV35+DD35 -> 32.8 | CH35: =CP35+CX35+DF35 -> 0 | CJ35: =IFERROR(CF35-CD35,"-") -> 0 | CK35: =IFERROR(CF35/CD35,"-") -> 1 | CL35: 10.8 | CN35: 10.8 | CR35: =IFERROR(CN35-CL35,"-") -> 0 | CS35: =IFERROR(CN35/CL35,"-") -> 1 | CT35: 10.8 | CV35: 10.8 | CZ35: =IFERROR(CV35-CT35,"-") -> 0 | DA35: =IFERROR(CV35/CT35,"-") -> 1 | DB35: 11.2 | DD35: 11.2 | DH35: =IFERROR(DD35-DB35,"-") -> 0 | DI35: =IFERROR(DD35/DB35,"-") -> 1 | DJ35: =DR35+DZ35+EH35 -> 38.1 | DL35: =DT35+EB35+EJ35 -> 38.1 | DN35: =DV35+ED35+EL35 -> 0 | DP35: =IFERROR(DL35-DJ35,"-") -> 0 | DQ35: =IFERROR(DL35/DJ35,"-") -> 1 | DR35: 12.7 | DT35: 12.7 | DX35: =IFERROR(DT35-DR35,"-") -> 0 | DY35: =IFERROR(DT35/DR35,"-") -> 1 | DZ35: 12.1 | EB35: 12.1 | EF35: =IFERROR(EB35-DZ35,"-") -> 0 | EG35: =IFERROR(EB35/DZ35,"-") -> 1 | EH35: 13.3 | EJ35: 13.3 | EN35: =IFERROR(EJ35-EH35,"-") -> 0 | EO35: =IFERROR(EJ35/EH35,"-") -> 1
A36: 4.1.3 | B36: Газ на СТН Газпром переработка, собственность ПАО "Газпром" | C36: 100331998 | J36: =R36+AX36+CD36+DJ36 -> 224 | L36: =T36+AZ36+CF36+DL36 -> 224 | N36: =V36+BB36+CH36+DN36 -> 45.785389 | P36: =IFERROR(L36-J36,"-") -> 0 | Q36: =IFERROR(L36/J36,"-") -> 1 | R36: =Z36+AH36+AP36 -> 55.9 | T36: =AB36+AJ36+AR36 -> 55.9 | V36: =AD36+AL36+AT36 -> 31.480478 | X36: =IFERROR(T36-R36,"-") -> 0 | Y36: =IFERROR(T36/R36,"-") -> 1 | Z36: 19.5 | AB36: 19.5 | AD36: 10.614819 | AF36: =IFERROR(AB36-Z36,"-") -> 0 | AG36: =IFERROR(AB36/Z36,"-") -> 1 | AH36: 17.3 | AJ36: 17.3 | AL36: 5.966616 | AN36: =IFERROR(AJ36-AH36,"-") -> 0 | AO36: =IFERROR(AJ36/AH36,"-") -> 1 | AP36: 19.1 | AR36: 19.1 | AT36: 14.899043 | AV36: =IFERROR(AR36-AP36,"-") -> 0 | AW36: =IFERROR(AR36/AP36,"-") -> 1 | AX36: =BF36+BN36+BV36 -> 47.4 | AZ36: =BH36+BP36+BX36 -> 47.4 | BB36: =BJ36+BR36+BZ36 -> 14.304911 | BD36: =IFERROR(AZ36-AX36,"-") -> 0 | BE36: =IFERROR(AZ36/AX36,"-") -> 1 | BF36: 18.1 | BH36: 18.1 | BJ36: 13.064888 | BL36: =IFERROR(BH36-BF36,"-") -> 0 | BM36: =IFERROR(BH36/BF36,"-") -> 1 | BN36: 15.7 | BP36: 15.7 | BR36: 1.117464 | BT36: =IFERROR(BP36-BN36,"-") -> 0 | BU36: =IFERROR(BP36/BN36,"-") -> 1 | BV36: 13.6 | BX36: 13.6 | BZ36: 0.122559 | CB36: =IFERROR(BX36-BV36,"-") -> 0 | CC36: =IFERROR(BX36/BV36,"-") -> 1 | CD36: =CL36+CT36+DB36 -> 59.4 | CF36: =CN36+CV36+DD36 -> 59.4 | CH36: =CP36+CX36+DF36 -> 0 | CJ36: =IFERROR(CF36-CD36,"-") -> 0 | CK36: =IFERROR(CF36/CD36,"-") -> 1 | CL36: 20.4 | CN36: 20.4 | CR36: =IFERROR(CN36-CL36,"-") -> 0 | CS36: =IFERROR(CN36/CL36,"-") -> 1 | CT36: 19.6 | CV36: 19.6 | CZ36: =IFERROR(CV36-CT36,"-") -> 0 | DA36: =IFERROR(CV36/CT36,"-") -> 1 | DB36: 19.4 | DD36: 19.4 | DH36: =IFERROR(DD36-DB36,"-") -> 0 | DI36: =IFERROR(DD36/DB36,"-") -> 1 | DJ36: =DR36+DZ36+EH36 -> 61.3 | DL36: =DT36+EB36+EJ36 -> 61.3 | DN36: =DV36+ED36+EL36 -> 0 | DP36: =IFERROR(DL36-DJ36,"-") -> 0 | DQ36: =IFERROR(DL36/DJ36,"-") -> 1 | DR36: 20.5 | DT36: 20.5 | DX36: =IFERROR(DT36-DR36,"-") -> 0 | DY36: =IFERROR(DT36/DR36,"-") -> 1 | DZ36: 19.7 | EB36: 19.7 | EF36: =IFERROR(EB36-DZ36,"-") -> 0 | EG36: =IFERROR(EB36/DZ36,"-") -> 1 | EH36: 21.1 | EJ36: 21.1 | EN36: =IFERROR(EJ36-EH36,"-") -> 0 | EO36: =IFERROR(EJ36/EH36,"-") -> 1
C37: 100331999 | J37: =R37+AX37+CD37+DJ37 -> 322.9 | L37: =T37+AZ37+CF37+DL37 -> 322.9 | N37: =V37+BB37+CH37+DN37 -> 63.775015 | P37: =IFERROR(L37-J37,"-") -> 0 | Q37: =IFERROR(L37/J37,"-") -> 1 | R37: =Z37+AH37+AP37 -> 80.6 | T37: =AB37+AJ37+AR37 -> 80.6 | V37: =AD37+AL37+AT37 -> 44.111978 | X37: =IFERROR(T37-R37,"-") -> 0 | Y37: =IFERROR(T37/R37,"-") -> 1 | Z37: 28.1 | AB37: 28.1 | AD37: 15.270923 | AF37: =IFERROR(AB37-Z37,"-") -> 0 | AG37: =IFERROR(AB37/Z37,"-") -> 1 | AH37: 24.9 | AJ37: 24.9 | AL37: 8.480125 | AN37: =IFERROR(AJ37-AH37,"-") -> 0 | AO37: =IFERROR(AJ37/AH37,"-") -> 1 | AP37: 27.6 | AR37: 27.6 | AT37: 20.36093 | AV37: =IFERROR(AR37-AP37,"-") -> 0 | AW37: =IFERROR(AR37/AP37,"-") -> 1 | AX37: =BF37+BN37+BV37 -> 68.3 | AZ37: =BH37+BP37+BX37 -> 68.3 | BB37: =BJ37+BR37+BZ37 -> 19.663037 | BD37: =IFERROR(AZ37-AX37,"-") -> 0 | BE37: =IFERROR(AZ37/AX37,"-") -> 1 | BF37: 26.1 | BH37: 26.1 | BJ37: 18.066624 | BL37: =IFERROR(BH37-BF37,"-") -> 0 | BM37: =IFERROR(BH37/BF37,"-") -> 1 | BN37: 22.6 | BP37: 22.6 | BR37: 1.419356 | BT37: =IFERROR(BP37-BN37,"-") -> 0 | BU37: =IFERROR(BP37/BN37,"-") -> 1 | BV37: 19.6 | BX37: 19.6 | BZ37: 0.177057 | CB37: =IFERROR(BX37-BV37,"-") -> 0 | CC37: =IFERROR(BX37/BV37,"-") -> 1 | CD37: =CL37+CT37+DB37 -> 85.7 | CF37: =CN37+CV37+DD37 -> 85.7 | CH37: =CP37+CX37+DF37 -> 0 | CJ37: =IFERROR(CF37-CD37,"-") -> 0 | CK37: =IFERROR(CF37/CD37,"-") -> 1 | CL37: 29.4 | CN37: 29.4 | CR37: =IFERROR(CN37-CL37,"-") -> 0 | CS37: =IFERROR(CN37/CL37,"-") -> 1 | CT37: 28.2 | CV37: 28.2 | CZ37: =IFERROR(CV37-CT37,"-") -> 0 | DA37: =IFERROR(CV37/CT37,"-") -> 1 | DB37: 28.1 | DD37: 28.1 | DH37: =IFERROR(DD37-DB37,"-") -> 0 | DI37: =IFERROR(DD37/DB37,"-") -> 1 | DJ37: =DR37+DZ37+EH37 -> 88.3 | DL37: =DT37+EB37+EJ37 -> 88.3 | DN37: =DV37+ED37+EL37 -> 0 | DP37: =IFERROR(DL37-DJ37,"-") -> 0 | DQ37: =IFERROR(DL37/DJ37,"-") -> 1 | DR37: 29.6 | DT37: 29.6 | DX37: =IFERROR(DT37-DR37,"-") -> 0 | DY37: =IFERROR(DT37/DR37,"-") -> 1 | DZ37: 28.4 | EB37: 28.4 | EF37: =IFERROR(EB37-DZ37,"-") -> 0 | EG37: =IFERROR(EB37/DZ37,"-") -> 1 | EH37: 30.3 | EJ37: 30.3 | EN37: =IFERROR(EJ37-EH37,"-") -> 0 | EO37: =IFERROR(EJ37/EH37,"-") -> 1
A38: 4.2 | B38: СЕРА, ВСЕГО: | C38: 100332000 | J38: =R38+AX38+CD38+DJ38 -> 3776.1 | L38: =T38+AZ38+CF38+DL38 -> 3776.1 | N38: =V38+BB38+CH38+DN38 -> 1042.7288 | P38: =IFERROR(L38-J38,"-") -> 0 | Q38: =IFERROR(L38/J38,"-") -> 1 | R38: =Z38+AH38+AP38 -> 947.6 | T38: =AB38+AJ38+AR38 -> 947.6 | V38: =AD38+AL38+AT38 -> 659.49064 | X38: =IFERROR(T38-R38,"-") -> 0 | Y38: =IFERROR(T38/R38,"-") -> 1 | Z38: 326.1 | AB38: 326.1 | AD38: 237.15434 | AF38: =IFERROR(AB38-Z38,"-") -> 0 | AG38: =IFERROR(AB38/Z38,"-") -> 1 | AH38: 294.5 | AJ38: 294.5 | AL38: 184.85424 | AN38: =IFERROR(AJ38-AH38,"-") -> 0 | AO38: =IFERROR(AJ38/AH38,"-") -> 1 | AP38: 327 | AR38: 327 | AT38: 237.48206 | AV38: =IFERROR(AR38-AP38,"-") -> 0 | AW38: =IFERROR(AR38/AP38,"-") -> 1 | AX38: =BF38+BN38+BV38 -> 723 | AZ38: =BH38+BP38+BX38 -> 723 | BB38: =BJ38+BR38+BZ38 -> 383.23813 | BD38: =IFERROR(AZ38-AX38,"-") -> 0 | BE38: =IFERROR(AZ38/AX38,"-") -> 1 | BF38: 316.5 | BH38: 316.5 | BJ38: 227.51113 | BL38: =IFERROR(BH38-BF38,"-") -> 0 | BM38: =IFERROR(BH38/BF38,"-") -> 1 | BN38: 224.2 | BP38: 224.2 | BR38: 92.433 | BT38: =IFERROR(BP38-BN38,"-") -> 0 | BU38: =IFERROR(BP38/BN38,"-") -> 1 | BV38: 182.3 | BX38: 182.3 | BZ38: 63.294 | CB38: =IFERROR(BX38-BV38,"-") -> 0 | CC38: =IFERROR(BX38/BV38,"-") -> 1 | CD38: =CL38+CT38+DB38 -> 1031 | CF38: =CN38+CV38+DD38 -> 1031 | CH38: =CP38+CX38+DF38 -> 0 | CJ38: =IFERROR(CF38-CD38,"-") -> 0 | CK38: =IFERROR(CF38/CD38,"-") -> 1 | CL38: 339.8 | CN38: 339.8 | CR38: =IFERROR(CN38-CL38,"-") -> 0 | CS38: =IFERROR(CN38/CL38,"-") -> 1 | CT38: 340.6 | CV38: 340.6 | CZ38: =IFERROR(CV38-CT38,"-") -> 0 | DA38: =IFERROR(CV38/CT38,"-") -> 1 | DB38: 350.6 | DD38: 350.6 | DH38: =IFERROR(DD38-DB38,"-") -> 0 | DI38: =IFERROR(DD38/DB38,"-") -> 1 | DJ38: =DR38+DZ38+EH38 -> 1074.5 | DL38: =DT38+EB38+EJ38 -> 1074.5 | DN38: =DV38+ED38+EL38 -> 0 | DP38: =IFERROR(DL38-DJ38,"-") -> 0 | DQ38: =IFERROR(DL38/DJ38,"-") -> 1 | DR38: 362.3 | DT38: 362.3 | DX38: =IFERROR(DT38-DR38,"-") -> 0 | DY38: =IFERROR(DT38/DR38,"-") -> 1 | DZ38: 350.6 | EB38: 350.6 | EF38: =IFERROR(EB38-DZ38,"-") -> 0 | EG38: =IFERROR(EB38/DZ38,"-") -> 1 | EH38: 361.6 | EJ38: 361.6 | EN38: =IFERROR(EJ38-EH38,"-") -> 0 | EO38: =IFERROR(EJ38/EH38,"-") -> 1
A39: 4.2.1 | B39: Сера, : | C39: 100332001 | J39: =R39+AX39+CD39+DJ39 -> 3776.1 | L39: =T39+AZ39+CF39+DL39 -> 3776.1 | N39: =V39+BB39+CH39+DN39 -> 1042.7288 | P39: =IFERROR(L39-J39,"-") -> 0 | Q39: =IFERROR(L39/J39,"-") -> 1 | R39: =Z39+AH39+AP39 -> 947.6 | T39: =AB39+AJ39+AR39 -> 947.6 | V39: =AD39+AL39+AT39 -> 659.49064 | X39: =IFERROR(T39-R39,"-") -> 0 | Y39: =IFERROR(T39/R39,"-") -> 1 | Z39: 326.1 | AB39: 326.1 | AD39: 237.15434 | AF39: =IFERROR(AB39-Z39,"-") -> 0 | AG39: =IFERROR(AB39/Z39,"-") -> 1 | AH39: 294.5 | AJ39: 294.5 | AL39: 184.85424 | AN39: =IFERROR(AJ39-AH39,"-") -> 0 | AO39: =IFERROR(AJ39/AH39,"-") -> 1 | AP39: 327 | AR39: 327 | AT39: 237.48206 | AV39: =IFERROR(AR39-AP39,"-") -> 0 | AW39: =IFERROR(AR39/AP39,"-") -> 1 | AX39: =BF39+BN39+BV39 -> 723 | AZ39: =BH39+BP39+BX39 -> 723 | BB39: =BJ39+BR39+BZ39 -> 383.23813 | BD39: =IFERROR(AZ39-AX39,"-") -> 0 | BE39: =IFERROR(AZ39/AX39,"-") -> 1 | BF39: 316.5 | BH39: 316.5 | BJ39: 227.51113 | BL39: =IFERROR(BH39-BF39,"-") -> 0 | BM39: =IFERROR(BH39/BF39,"-") -> 1 | BN39: 224.2 | BP39: 224.2 | BR39: 92.433 | BT39: =IFERROR(BP39-BN39,"-") -> 0 | BU39: =IFERROR(BP39/BN39,"-") -> 1 | BV39: 182.3 | BX39: 182.3 | BZ39: 63.294 | CB39: =IFERROR(BX39-BV39,"-") -> 0 | CC39: =IFERROR(BX39/BV39,"-") -> 1 | CD39: =CL39+CT39+DB39 -> 1031 | CF39: =CN39+CV39+DD39 -> 1031 | CH39: =CP39+CX39+DF39 -> 0 | CJ39: =IFERROR(CF39-CD39,"-") -> 0 | CK39: =IFERROR(CF39/CD39,"-") -> 1 | CL39: 339.8 | CN39: 339.8 | CR39: =IFERROR(CN39-CL39,"-") -> 0 | CS39: =IFERROR(CN39/CL39,"-") -> 1 | CT39: 340.6 | CV39: 340.6 | CZ39: =IFERROR(CV39-CT39,"-") -> 0 | DA39: =IFERROR(CV39/CT39,"-") -> 1 | DB39: 350.6 | DD39: 350.6 | DH39: =IFERROR(DD39-DB39,"-") -> 0 | DI39: =IFERROR(DD39/DB39,"-") -> 1 | DJ39: =DR39+DZ39+EH39 -> 1074.5 | DL39: =DT39+EB39+EJ39 -> 1074.5 | DN39: =DV39+ED39+EL39 -> 0 | DP39: =IFERROR(DL39-DJ39,"-") -> 0 | DQ39: =IFERROR(DL39/DJ39,"-") -> 1 | DR39: 362.3 | DT39: 362.3 | DX39: =IFERROR(DT39-DR39,"-") -> 0 | DY39: =IFERROR(DT39/DR39,"-") -> 1 | DZ39: 350.6 | EB39: 350.6 | EF39: =IFERROR(EB39-DZ39,"-") -> 0 | EG39: =IFERROR(EB39/DZ39,"-") -> 1 | EH39: 361.6 | EJ39: 361.6 | EN39: =IFERROR(EJ39-EH39,"-") -> 0 | EO39: =IFERROR(EJ39/EH39,"-") -> 1
A40: 4.2.1.1 | B40: жидкая | C40: 100330068 | J40: =R40+AX40+CD40+DJ40 -> 1327 | L40: =T40+AZ40+CF40+DL40 -> 1327 | N40: =V40+BB40+CH40+DN40 -> 472.53732 | P40: =IFERROR(L40-J40,"-") -> 0 | Q40: =IFERROR(L40/J40,"-") -> 1 | R40: =Z40+AH40+AP40 -> 342.7 | T40: =AB40+AJ40+AR40 -> 342.7 | V40: =AD40+AL40+AT40 -> 302.77812 | X40: =IFERROR(T40-R40,"-") -> 0 | Y40: =IFERROR(T40/R40,"-") -> 1 | Z40: 112.7 | AB40: 112.7 | AD40: 119.90865 | AF40: =IFERROR(AB40-Z40,"-") -> 0 | AG40: =IFERROR(AB40/Z40,"-") -> 1 | AH40: 101.7 | AJ40: 101.7 | AL40: 81.849915 | AN40: =IFERROR(AJ40-AH40,"-") -> 0 | AO40: =IFERROR(AJ40/AH40,"-") -> 1 | AP40: 128.3 | AR40: 128.3 | AT40: 101.01956 | AV40: =IFERROR(AR40-AP40,"-") -> 0 | AW40: =IFERROR(AR40/AP40,"-") -> 1 | AX40: =BF40+BN40+BV40 -> 313.1 | AZ40: =BH40+BP40+BX40 -> 313.1 | BB40: =BJ40+BR40+BZ40 -> 169.75919 | BD40: =IFERROR(AZ40-AX40,"-") -> 0 | BE40: =IFERROR(AZ40/AX40,"-") -> 1 | BF40: 109.1 | BH40: 109.1 | BJ40: 92.199123 | BL40: =IFERROR(BH40-BF40,"-") -> 0 | BM40: =IFERROR(BH40/BF40,"-") -> 1 | BN40: 102 | BP40: 102 | BR40: 32.792 | BT40: =IFERROR(BP40-BN40,"-") -> 0 | BU40: =IFERROR(BP40/BN40,"-") -> 1 | BV40: 102 | BX40: 102 | BZ40: 44.768069 | CB40: =IFERROR(BX40-BV40,"-") -> 0 | CC40: =IFERROR(BX40/BV40,"-") -> 1 | CD40: =CL40+CT40+DB40 -> 311.9 | CF40: =CN40+CV40+DD40 -> 311.9 | CH40: =CP40+CX40+DF40 -> 0 | CJ40: =IFERROR(CF40-CD40,"-") -> 0 | CK40: =IFERROR(CF40/CD40,"-") -> 1 | CL40: 102 | CN40: 102 | CR40: =IFERROR(CN40-CL40,"-") -> 0 | CS40: =IFERROR(CN40/CL40,"-") -> 1 | CT40: 102 | CV40: 102 | CZ40: =IFERROR(CV40-CT40,"-") -> 0 | DA40: =IFERROR(CV40/CT40,"-") -> 1 | DB40: 107.9 | DD40: 107.9 | DH40: =IFERROR(DD40-DB40,"-") -> 0 | DI40: =IFERROR(DD40/DB40,"-") -> 1 | DJ40: =DR40+DZ40+EH40 -> 359.3 | DL40: =DT40+EB40+EJ40 -> 359.3 | DN40: =DV40+ED40+EL40 -> 0 | DP40: =IFERROR(DL40-DJ40,"-") -> 0 | DQ40: =IFERROR(DL40/DJ40,"-") -> 1 | DR40: 112.7 | DT40: 112.7 | DX40: =IFERROR(DT40-DR40,"-") -> 0 | DY40: =IFERROR(DT40/DR40,"-") -> 1 | DZ40: 120.7 | EB40: 120.7 | EF40: =IFERROR(EB40-DZ40,"-") -> 0 | EG40: =IFERROR(EB40/DZ40,"-") -> 1 | EH40: 125.9 | EJ40: 125.9 | EN40: =IFERROR(EJ40-EH40,"-") -> 0 | EO40: =IFERROR(EJ40/EH40,"-") -> 1
A41: 4.2.1.2 | B41: комовая | C41: 100330069 | J41: =R41+AX41+CD41+DJ41 -> 753.8 | L41: =T41+AZ41+CF41+DL41 -> 753.8 | N41: =V41+BB41+CH41+DN41 -> 54.406907 | P41: =IFERROR(L41-J41,"-") -> 0 | Q41: =IFERROR(L41/J41,"-") -> 1 | R41: =Z41+AH41+AP41 -> 317.1 | T41: =AB41+AJ41+AR41 -> 317.1 | V41: =AD41+AL41+AT41 -> 31.898221 | X41: =IFERROR(T41-R41,"-") -> 0 | Y41: =IFERROR(T41/R41,"-") -> 1 | Z41: 81 | AB41: 81 | AD41: 7.615864 | AF41: =IFERROR(AB41-Z41,"-") -> 0 | AG41: =IFERROR(AB41/Z41,"-") -> 1 | AH41: 70.9 | AJ41: 70.9 | AL41: 17.477339 | AN41: =IFERROR(AJ41-AH41,"-") -> 0 | AO41: =IFERROR(AJ41/AH41,"-") -> 1 | AP41: 165.2 | AR41: 165.2 | AT41: 6.805018 | AV41: =IFERROR(AR41-AP41,"-") -> 0 | AW41: =IFERROR(AR41/AP41,"-") -> 1 | AX41: =BF41+BN41+BV41 -> 28 | AZ41: =BH41+BP41+BX41 -> 28 | BB41: =BJ41+BR41+BZ41 -> 22.508686 | BD41: =IFERROR(AZ41-AX41,"-") -> 0 | BE41: =IFERROR(AZ41/AX41,"-") -> 1 | BF41: 21.9 | BH41: 21.9 | BJ41: 18.213205 | BL41: =IFERROR(BH41-BF41,"-") -> 0 | BM41: =IFERROR(BH41/BF41,"-") -> 1 | BN41: 3.1 | BP41: 3.1 | BR41: 4.287 | BT41: =IFERROR(BP41-BN41,"-") -> 0 | BU41: =IFERROR(BP41/BN41,"-") -> 1 | BV41: 3 | BX41: 3 | BZ41: 0.008481 | CB41: =IFERROR(BX41-BV41,"-") -> 0 | CC41: =IFERROR(BX41/BV41,"-") -> 1 | CD41: =CL41+CT41+DB41 -> 197.6 | CF41: =CN41+CV41+DD41 -> 197.6 | CH41: =CP41+CX41+DF41 -> 0 | CJ41: =IFERROR(CF41-CD41,"-") -> 0 | CK41: =IFERROR(CF41/CD41,"-") -> 1 | CL41: 43.8 | CN41: 43.8 | CR41: =IFERROR(CN41-CL41,"-") -> 0 | CS41: =IFERROR(CN41/CL41,"-") -> 1 | CT41: 75.4 | CV41: 75.4 | CZ41: =IFERROR(CV41-CT41,"-") -> 0 | DA41: =IFERROR(CV41/CT41,"-") -> 1 | DB41: 78.4 | DD41: 78.4 | DH41: =IFERROR(DD41-DB41,"-") -> 0 | DI41: =IFERROR(DD41/DB41,"-") -> 1 | DJ41: =DR41+DZ41+EH41 -> 211.1 | DL41: =DT41+EB41+EJ41 -> 211.1 | DN41: =DV41+ED41+EL41 -> 0 | DP41: =IFERROR(DL41-DJ41,"-") -> 0 | DQ41: =IFERROR(DL41/DJ41,"-") -> 1 | DR41: 79.7 | DT41: 79.7 | DX41: =IFERROR(DT41-DR41,"-") -> 0 | DY41: =IFERROR(DT41/DR41,"-") -> 1 | DZ41: 65.6 | EB41: 65.6 | EF41: =IFERROR(EB41-DZ41,"-") -> 0 | EG41: =IFERROR(EB41/DZ41,"-") -> 1 | EH41: 65.8 | EJ41: 65.8 | EN41: =IFERROR(EJ41-EH41,"-") -> 0 | EO41: =IFERROR(EJ41/EH41,"-") -> 1
A42: 4.2.1.3 | B42: марка С | C42: 100330070 | J42: =R42+AX42+CD42+DJ42 -> 1605.3 | L42: =T42+AZ42+CF42+DL42 -> 1605.3 | N42: =V42+BB42+CH42+DN42 -> 437.76692 | P42: =IFERROR(L42-J42,"-") -> 0 | Q42: =IFERROR(L42/J42,"-") -> 1 | R42: =Z42+AH42+AP42 -> 254.3 | T42: =AB42+AJ42+AR42 -> 254.3 | V42: =AD42+AL42+AT42 -> 308.37955 | X42: =IFERROR(T42-R42,"-") -> 0 | Y42: =IFERROR(T42/R42,"-") -> 1 | Z42: 132.4 | AB42: 132.4 | AD42: 109.62983 | AF42: =IFERROR(AB42-Z42,"-") -> 0 | AG42: =IFERROR(AB42/Z42,"-") -> 1 | AH42: 121.9 | AJ42: 121.9 | AL42: 85.52699 | AN42: =IFERROR(AJ42-AH42,"-") -> 0 | AO42: =IFERROR(AJ42/AH42,"-") -> 1 | AP42: 0 | AR42: 0 | AT42: 113.22272 | AV42: =IFERROR(AR42-AP42,"-") -> 0 | AW42: =IFERROR(AR42/AP42,"-") -> - | AX42: =BF42+BN42+BV42 -> 349.5 | AZ42: =BH42+BP42+BX42 -> 349.5 | BB42: =BJ42+BR42+BZ42 -> 129.38737 | BD42: =IFERROR(AZ42-AX42,"-") -> 0 | BE42: =IFERROR(AZ42/AX42,"-") -> 1 | BF42: 153.1 | BH42: 153.1 | BJ42: 86.99337 | BL42: =IFERROR(BH42-BF42,"-") -> 0 | BM42: =IFERROR(BH42/BF42,"-") -> 1 | BN42: 119.1 | BP42: 119.1 | BR42: 42.394 | BT42: =IFERROR(BP42-BN42,"-") -> 0 | BU42: =IFERROR(BP42/BN42,"-") -> 1 | BV42: 77.3 | BX42: 77.3 | BZ42: 0 | CB42: =IFERROR(BX42-BV42,"-") -> 0 | CC42: =IFERROR(BX42/BV42,"-") -> 1 | CD42: =CL42+CT42+DB42 -> 497.4 | CF42: =CN42+CV42+DD42 -> 497.4 | CH42: =CP42+CX42+DF42 -> 0 | CJ42: =IFERROR(CF42-CD42,"-") -> 0 | CK42: =IFERROR(CF42/CD42,"-") -> 1 | CL42: 169.9 | CN42: 169.9 | CR42: =IFERROR(CN42-CL42,"-") -> 0 | CS42: =IFERROR(CN42/CL42,"-") -> 1 | CT42: 163.2 | CV42: 163.2 | CZ42: =IFERROR(CV42-CT42,"-") -> 0 | DA42: =IFERROR(CV42/CT42,"-") -> 1 | DB42: 164.3 | DD42: 164.3 | DH42: =IFERROR(DD42-DB42,"-") -> 0 | DI42: =IFERROR(DD42/DB42,"-") -> 1 | DJ42: =DR42+DZ42+EH42 -> 504.1 | DL42: =DT42+EB42+EJ42 -> 504.1 | DN42: =DV42+ED42+EL42 -> 0 | DP42: =IFERROR(DL42-DJ42,"-") -> 0 | DQ42: =IFERROR(DL42/DJ42,"-") -> 1 | DR42: 169.9 | DT42: 169.9 | DX42: =IFERROR(DT42-DR42,"-") -> 0 | DY42: =IFERROR(DT42/DR42,"-") -> 1 | DZ42: 164.3 | EB42: 164.3 | EF42: =IFERROR(EB42-DZ42,"-") -> 0 | EG42: =IFERROR(EB42/DZ42,"-") -> 1 | EH42: 169.9 | EJ42: 169.9 | EN42: =IFERROR(EJ42-EH42,"-") -> 0 | EO42: =IFERROR(EJ42/EH42,"-") -> 1
A43: 4.2.1.4 | B43: марка М | C43: 100330071 | J43: =R43+AX43+CD43+DJ43 -> 90 | L43: =T43+AZ43+CF43+DL43 -> 90 | N43: =V43+BB43+CH43+DN43 -> 78.01763 | P43: =IFERROR(L43-J43,"-") -> 0 | Q43: =IFERROR(L43/J43,"-") -> 1 | R43: =Z43+AH43+AP43 -> 33.5 | T43: =AB43+AJ43+AR43 -> 33.5 | V43: =AD43+AL43+AT43 -> 16.43475 | X43: =IFERROR(T43-R43,"-") -> 0 | Y43: =IFERROR(T43/R43,"-") -> 1 | Z43: 0 | AB43: 0 | AD43: 0 | AF43: =IFERROR(AB43-Z43,"-") -> 0 | AG43: =IFERROR(AB43/Z43,"-") -> - | AH43: 0 | AJ43: 0 | AL43: 0 | AN43: =IFERROR(AJ43-AH43,"-") -> 0 | AO43: =IFERROR(AJ43/AH43,"-") -> - | AP43: 33.5 | AR43: 33.5 | AT43: 16.43475 | AV43: =IFERROR(AR43-AP43,"-") -> 0 | AW43: =IFERROR(AR43/AP43,"-") -> 1 | AX43: =BF43+BN43+BV43 -> 32.4 | AZ43: =BH43+BP43+BX43 -> 32.4 | BB43: =BJ43+BR43+BZ43 -> 61.58288 | BD43: =IFERROR(AZ43-AX43,"-") -> 0 | BE43: =IFERROR(AZ43/AX43,"-") -> 1 | BF43: 32.4 | BH43: 32.4 | BJ43: 30.10543 | BL43: =IFERROR(BH43-BF43,"-") -> 0 | BM43: =IFERROR(BH43/BF43,"-") -> 1 | BN43: 0 | BP43: 0 | BR43: 12.96 | BT43: =IFERROR(BP43-BN43,"-") -> 0 | BU43: =IFERROR(BP43/BN43,"-") -> - | BV43: 0 | BX43: 0 | BZ43: 18.51745 | CB43: =IFERROR(BX43-BV43,"-") -> 0 | CC43: =IFERROR(BX43/BV43,"-") -> - | CD43: =CL43+CT43+DB43 -> 24.1 | CF43: =CN43+CV43+DD43 -> 24.1 | CH43: =CP43+CX43+DF43 -> 0 | CJ43: =IFERROR(CF43-CD43,"-") -> 0 | CK43: =IFERROR(CF43/CD43,"-") -> 1 | CL43: 24.1 | CN43: 24.1 | CR43: =IFERROR(CN43-CL43,"-") -> 0 | CS43: =IFERROR(CN43/CL43,"-") -> 1 | CT43: 0 | CV43: 0 | CZ43: =IFERROR(CV43-CT43,"-") -> 0 | DA43: =IFERROR(CV43/CT43,"-") -> - | DB43: 0 | DD43: 0 | DH43: =IFERROR(DD43-DB43,"-") -> 0 | DI43: =IFERROR(DD43/DB43,"-") -> - | DJ43: =DR43+DZ43+EH43 -> 0 | DL43: =DT43+EB43+EJ43 -> 0 | DN43: =DV43+ED43+EL43 -> 0 | DP43: =IFERROR(DL43-DJ43,"-") -> 0 | DQ43: =IFERROR(DL43/DJ43,"-") -> - | DR43: 0 | DT43: 0 | DX43: =IFERROR(DT43-DR43,"-") -> 0 | DY43: =IFERROR(DT43/DR43,"-") -> - | DZ43: 0 | EB43: 0 | EF43: =IFERROR(EB43-DZ43,"-") -> 0 | EG43: =IFERROR(EB43/DZ43,"-") -> - | EH43: 0 | EJ43: 0 | EN43: =IFERROR(EJ43-EH43,"-") -> 0 | EO43: =IFERROR(EJ43/EH43,"-") -> -
A44: 4.2.1.5 | B44: марка СМ | C44: 100337112 | J44: =R44+AX44+CD44+DJ44 -> 0 | L44: =T44+AZ44+CF44+DL44 -> 0 | N44: =V44+BB44+CH44+DN44 -> 0 | P44: =IFERROR(L44-J44,"-") -> 0 | Q44: =IFERROR(L44/J44,"-") -> - | R44: =Z44+AH44+AP44 -> 0 | T44: =AB44+AJ44+AR44 -> 0 | V44: =AD44+AL44+AT44 -> 0 | X44: =IFERROR(T44-R44,"-") -> 0 | Y44: =IFERROR(T44/R44,"-") -> - | AD44: 0 | AF44: =IFERROR(AB44-Z44,"-") -> 0 | AG44: =IFERROR(AB44/Z44,"-") -> - | AL44: 0 | AN44: =IFERROR(AJ44-AH44,"-") -> 0 | AO44: =IFERROR(AJ44/AH44,"-") -> - | AT44: 0 | AV44: =IFERROR(AR44-AP44,"-") -> 0 | AW44: =IFERROR(AR44/AP44,"-") -> - | AX44: =BF44+BN44+BV44 -> 0 | AZ44: =BH44+BP44+BX44 -> 0 | BB44: =BJ44+BR44+BZ44 -> 0 | BD44: =IFERROR(AZ44-AX44,"-") -> 0 | BE44: =IFERROR(AZ44/AX44,"-") -> - | BJ44: 0 | BL44: =IFERROR(BH44-BF44,"-") -> 0 | BM44: =IFERROR(BH44/BF44,"-") -> - | BR44: 0 | BT44: =IFERROR(BP44-BN44,"-") -> 0 | BU44: =IFERROR(BP44/BN44,"-") -> - | BZ44: 0 | CB44: =IFERROR(BX44-BV44,"-") -> 0 | CC44: =IFERROR(BX44/BV44,"-") -> - | CD44: =CL44+CT44+DB44 -> 0 | CF44: =CN44+CV44+DD44 -> 0 | CH44: =CP44+CX44+DF44 -> 0 | CJ44: =IFERROR(CF44-CD44,"-") -> 0 | CK44: =IFERROR(CF44/CD44,"-") -> - | CR44: =IFERROR(CN44-CL44,"-") -> 0 | CS44: =IFERROR(CN44/CL44,"-") -> - | CZ44: =IFERROR(CV44-CT44,"-") -> 0 | DA44: =IFERROR(CV44/CT44,"-") -> - | DH44: =IFERROR(DD44-DB44,"-") -> 0 | DI44: =IFERROR(DD44/DB44,"-") -> - | DJ44: =DR44+DZ44+EH44 -> 0 | DL44: =DT44+EB44+EJ44 -> 0 | DN44: =DV44+ED44+EL44 -> 0 | DP44: =IFERROR(DL44-DJ44,"-") -> 0 | DQ44: =IFERROR(DL44/DJ44,"-") -> - | DX44: =IFERROR(DT44-DR44,"-") -> 0 | DY44: =IFERROR(DT44/DR44,"-") -> - | EF44: =IFERROR(EB44-DZ44,"-") -> 0 | EG44: =IFERROR(EB44/DZ44,"-") -> - | EN44: =IFERROR(EJ44-EH44,"-") -> 0 | EO44: =IFERROR(EJ44/EH44,"-") -> -
B45: Справочно: | E45: 2 | J45: =R45+AX45+CD45+DJ45 -> 0 | L45: =T45+AZ45+CF45+DL45 -> 0 | N45: =V45+BB45+CH45+DN45 -> 0 | P45: =IFERROR(L45-J45,"-") -> 0 | Q45: =IFERROR(L45/J45,"-") -> - | R45: =Z45+AH45+AP45 -> 0 | T45: =AB45+AJ45+AR45 -> 0 | V45: =AD45+AL45+AT45 -> 0 | X45: =IFERROR(T45-R45,"-") -> 0 | Y45: =IFERROR(T45/R45,"-") -> - | AF45: =IFERROR(AB45-Z45,"-") -> 0 | AG45: =IFERROR(AB45/Z45,"-") -> - | AN45: =IFERROR(AJ45-AH45,"-") -> 0 | AO45: =IFERROR(AJ45/AH45,"-") -> - | AV45: =IFERROR(AR45-AP45,"-") -> 0 | AW45: =IFERROR(AR45/AP45,"-") -> - | AX45: =BF45+BN45+BV45 -> 0 | AZ45: =BH45+BP45+BX45 -> 0 | BB45: =BJ45+BR45+BZ45 -> 0 | BD45: =IFERROR(AZ45-AX45,"-") -> 0 | BE45: =IFERROR(AZ45/AX45,"-") -> - | BL45: =IFERROR(BH45-BF45,"-") -> 0 | BM45: =IFERROR(BH45/BF45,"-") -> - | BT45: =IFERROR(BP45-BN45,"-") -> 0 | BU45: =IFERROR(BP45/BN45,"-") -> - | CB45: =IFERROR(BX45-BV45,"-") -> 0 | CC45: =IFERROR(BX45/BV45,"-") -> - | CD45: =CL45+CT45+DB45 -> 0 | CF45: =CN45+CV45+DD45 -> 0 | CH45: =CP45+CX45+DF45 -> 0 | CJ45: =IFERROR(CF45-CD45,"-") -> 0 | CK45: =IFERROR(CF45/CD45,"-") -> - | CR45: =IFERROR(CN45-CL45,"-") -> 0 | CS45: =IFERROR(CN45/CL45,"-") -> - | CZ45: =IFERROR(CV45-CT45,"-") -> 0 | DA45: =IFERROR(CV45/CT45,"-") -> - | DH45: =IFERROR(DD45-DB45,"-") -> 0 | DI45: =IFERROR(DD45/DB45,"-") -> - | DJ45: =DR45+DZ45+EH45 -> 0 | DL45: =DT45+EB45+EJ45 -> 0 | DN45: =DV45+ED45+EL45 -> 0 | DP45: =IFERROR(DL45-DJ45,"-") -> 0 | DQ45: =IFERROR(DL45/DJ45,"-") -> - | DX45: =IFERROR(DT45-DR45,"-") -> 0 | DY45: =IFERROR(DT45/DR45,"-") -> - | EF45: =IFERROR(EB45-DZ45,"-") -> 0 | EG45: =IFERROR(EB45/DZ45,"-") -> - | EN45: =IFERROR(EJ45-EH45,"-") -> 0 | EO45: =IFERROR(EJ45/EH45,"-") -> -
B46: Кислый газ, всего: | C46: 100330010 | J46: =R46+AX46+CD46+DJ46 -> 7251.8 | L46: =T46+AZ46+CF46+DL46 -> 7251.8 | N46: =V46+BB46+CH46+DN46 -> 1997.1194 | P46: =IFERROR(L46-J46,"-") -> 0 | Q46: =IFERROR(L46/J46,"-") -> 1 | R46: =Z46+AH46+AP46 -> 1813.9 | T46: =AB46+AJ46+AR46 -> 1813.9 | V46: =AD46+AL46+AT46 -> 1317.772 | X46: =IFERROR(T46-R46,"-") -> 0 | Y46: =IFERROR(T46/R46,"-") -> 1 | Z46: 622.6 | AB46: 622.6 | AD46: 460.40707 | AF46: =IFERROR(AB46-Z46,"-") -> 0 | AG46: =IFERROR(AB46/Z46,"-") -> 1 | AH46: 565.1 | AJ46: 565.1 | AL46: 400.85111 | AN46: =IFERROR(AJ46-AH46,"-") -> 0 | AO46: =IFERROR(AJ46/AH46,"-") -> 1 | AP46: 626.2 | AR46: 626.2 | AT46: 456.51385 | AV46: =IFERROR(AR46-AP46,"-") -> 0 | AW46: =IFERROR(AR46/AP46,"-") -> 1 | AX46: =BF46+BN46+BV46 -> 1376.8 | AZ46: =BH46+BP46+BX46 -> 1376.8 | BB46: =BJ46+BR46+BZ46 -> 679.34736 | BD46: =IFERROR(AZ46-AX46,"-") -> 0 | BE46: =IFERROR(AZ46/AX46,"-") -> 1 | BF46: 606.7 | BH46: 606.7 | BJ46: 402.18024 | BL46: =IFERROR(BH46-BF46,"-") -> 0 | BM46: =IFERROR(BH46/BF46,"-") -> 1 | BN46: 428.4 | BP46: 428.4 | BR46: 168.195 | BT46: =IFERROR(BP46-BN46,"-") -> 0 | BU46: =IFERROR(BP46/BN46,"-") -> 1 | BV46: 341.7 | BX46: 341.7 | BZ46: 108.97212 | CB46: =IFERROR(BX46-BV46,"-") -> 0 | CC46: =IFERROR(BX46/BV46,"-") -> 1 | CD46: =CL46+CT46+DB46 -> 2022.4 | CF46: =CN46+CV46+DD46 -> 2022.4 | CH46: =CP46+CX46+DF46 -> 0 | CJ46: =IFERROR(CF46-CD46,"-") -> 0 | CK46: =IFERROR(CF46/CD46,"-") -> 1 | CL46: 660.8 | CN46: 660.8 | CR46: =IFERROR(CN46-CL46,"-") -> 0 | CS46: =IFERROR(CN46/CL46,"-") -> 1 | CT46: 687.2 | CV46: 687.2 | CZ46: =IFERROR(CV46-CT46,"-") -> 0 | DA46: =IFERROR(CV46/CT46,"-") -> 1 | DB46: 674.4 | DD46: 674.4 | DH46: =IFERROR(DD46-DB46,"-") -> 0 | DI46: =IFERROR(DD46/DB46,"-") -> 1 | DJ46: =DR46+DZ46+EH46 -> 2038.7 | DL46: =DT46+EB46+EJ46 -> 2038.7 | DN46: =DV46+ED46+EL46 -> 0 | DP46: =IFERROR(DL46-DJ46,"-") -> 0 | DQ46: =IFERROR(DL46/DJ46,"-") -> 1 | DR46: 681.7 | DT46: 681.7 | DX46: =IFERROR(DT46-DR46,"-") -> 0 | DY46: =IFERROR(DT46/DR46,"-") -> 1 | DZ46: 674.6 | EB46: 674.6 | EF46: =IFERROR(EB46-DZ46,"-") -> 0 | EG46: =IFERROR(EB46/DZ46,"-") -> 1 | EH46: 682.4 | EJ46: 682.4 | EN46: =IFERROR(EJ46-EH46,"-") -> 0 | EO46: =IFERROR(EJ46/EH46,"-") -> 1
B47: Кислый газ с производства № 3 | C47: 100331980 | J47: =R47+AX47+CD47+DJ47 -> 12.6 | L47: =T47+AZ47+CF47+DL47 -> 12.6 | N47: =V47+BB47+CH47+DN47 -> 0.055 | P47: =IFERROR(L47-J47,"-") -> 0 | Q47: =IFERROR(L47/J47,"-") -> 1 | R47: =Z47+AH47+AP47 -> 3.8 | T47: =AB47+AJ47+AR47 -> 3.8 | V47: =AD47+AL47+AT47 -> 0 | X47: =IFERROR(T47-R47,"-") -> 0 | Y47: =IFERROR(T47/R47,"-") -> 1 | Z47: 1.4 | AB47: 1.4 | AD47: 0 | AF47: =IFERROR(AB47-Z47,"-") -> 0 | AG47: =IFERROR(AB47/Z47,"-") -> 1 | AH47: 1.2 | AJ47: 1.2 | AL47: 0 | AN47: =IFERROR(AJ47-AH47,"-") -> 0 | AO47: =IFERROR(AJ47/AH47,"-") -> 1 | AP47: 1.2 | AR47: 1.2 | AT47: 0 | AV47: =IFERROR(AR47-AP47,"-") -> 0 | AW47: =IFERROR(AR47/AP47,"-") -> 1 | AX47: =BF47+BN47+BV47 -> 1.5 | AZ47: =BH47+BP47+BX47 -> 1.5 | BB47: =BJ47+BR47+BZ47 -> 0.055 | BD47: =IFERROR(AZ47-AX47,"-") -> 0 | BE47: =IFERROR(AZ47/AX47,"-") -> 1 | BF47: 1.2 | BH47: 1.2 | BJ47: 0 | BL47: =IFERROR(BH47-BF47,"-") -> 0 | BM47: =IFERROR(BH47/BF47,"-") -> 1 | BN47: 0.3 | BP47: 0.3 | BR47: 0.055 | BT47: =IFERROR(BP47-BN47,"-") -> 0 | BU47: =IFERROR(BP47/BN47,"-") -> 1 | BV47: 0 | BX47: 0 | BZ47: 0 | CB47: =IFERROR(BX47-BV47,"-") -> 0 | CC47: =IFERROR(BX47/BV47,"-") -> - | CD47: =CL47+CT47+DB47 -> 3.4 | CF47: =CN47+CV47+DD47 -> 3.4 | CH47: =CP47+CX47+DF47 -> 0 | CJ47: =IFERROR(CF47-CD47,"-") -> 0 | CK47: =IFERROR(CF47/CD47,"-") -> 1 | CL47: 0.9 | CN47: 0.9 | CR47: =IFERROR(CN47-CL47,"-") -> 0 | CS47: =IFERROR(CN47/CL47,"-") -> 1 | CT47: 1.3 | CV47: 1.3 | CZ47: =IFERROR(CV47-CT47,"-") -> 0 | DA47: =IFERROR(CV47/CT47,"-") -> 1 | DB47: 1.2 | DD47: 1.2 | DH47: =IFERROR(DD47-DB47,"-") -> 0 | DI47: =IFERROR(DD47/DB47,"-") -> 1 | DJ47: =DR47+DZ47+EH47 -> 3.9 | DL47: =DT47+EB47+EJ47 -> 3.9 | DN47: =DV47+ED47+EL47 -> 0 | DP47: =IFERROR(DL47-DJ47,"-") -> 0 | DQ47: =IFERROR(DL47/DJ47,"-") -> 1 | DR47: 1.3 | DT47: 1.3 | DX47: =IFERROR(DT47-DR47,"-") -> 0 | DY47: =IFERROR(DT47/DR47,"-") -> 1 | DZ47: 1.2 | EB47: 1.2 | EF47: =IFERROR(EB47-DZ47,"-") -> 0 | EG47: =IFERROR(EB47/DZ47,"-") -> 1 | EH47: 1.4 | EJ47: 1.4 | EN47: =IFERROR(EJ47-EH47,"-") -> 0 | EO47: =IFERROR(EJ47/EH47,"-") -> 1
B48: Кислый газ с производства № 1,5 | C48: 100331981 | J48: =R48+AX48+CD48+DJ48 -> 7239.2 | L48: =T48+AZ48+CF48+DL48 -> 7239.2 | N48: =V48+BB48+CH48+DN48 -> 1997.0644 | P48: =IFERROR(L48-J48,"-") -> 0 | Q48: =IFERROR(L48/J48,"-") -> 1 | R48: =Z48+AH48+AP48 -> 1810.1 | T48: =AB48+AJ48+AR48 -> 1810.1 | V48: =AD48+AL48+AT48 -> 1317.772 | X48: =IFERROR(T48-R48,"-") -> 0 | Y48: =IFERROR(T48/R48,"-") -> 1 | Z48: 621.2 | AB48: 621.2 | AD48: 460.40707 | AF48: =IFERROR(AB48-Z48,"-") -> 0 | AG48: =IFERROR(AB48/Z48,"-") -> 1 | AH48: 563.9 | AJ48: 563.9 | AL48: 400.85111 | AN48: =IFERROR(AJ48-AH48,"-") -> 0 | AO48: =IFERROR(AJ48/AH48,"-") -> 1 | AP48: 625 | AR48: 625 | AT48: 456.51385 | AV48: =IFERROR(AR48-AP48,"-") -> 0 | AW48: =IFERROR(AR48/AP48,"-") -> 1 | AX48: =BF48+BN48+BV48 -> 1375.3 | AZ48: =BH48+BP48+BX48 -> 1375.3 | BB48: =BJ48+BR48+BZ48 -> 679.29236 | BD48: =IFERROR(AZ48-AX48,"-") -> 0 | BE48: =IFERROR(AZ48/AX48,"-") -> 1 | BF48: 605.5 | BH48: 605.5 | BJ48: 402.18024 | BL48: =IFERROR(BH48-BF48,"-") -> 0 | BM48: =IFERROR(BH48/BF48,"-") -> 1 | BN48: 428.1 | BP48: 428.1 | BR48: 168.14 | BT48: =IFERROR(BP48-BN48,"-") -> 0 | BU48: =IFERROR(BP48/BN48,"-") -> 1 | BV48: 341.7 | BX48: 341.7 | BZ48: 108.97212 | CB48: =IFERROR(BX48-BV48,"-") -> 0 | CC48: =IFERROR(BX48/BV48,"-") -> 1 | CD48: =CL48+CT48+DB48 -> 2019 | CF48: =CN48+CV48+DD48 -> 2019 | CH48: =CP48+CX48+DF48 -> 0 | CJ48: =IFERROR(CF48-CD48,"-") -> 0 | CK48: =IFERROR(CF48/CD48,"-") -> 1 | CL48: 659.9 | CN48: 659.9 | CR48: =IFERROR(CN48-CL48,"-") -> 0 | CS48: =IFERROR(CN48/CL48,"-") -> 1 | CT48: 685.9 | CV48: 685.9 | CZ48: =IFERROR(CV48-CT48,"-") -> 0 | DA48: =IFERROR(CV48/CT48,"-") -> 1 | DB48: 673.2 | DD48: 673.2 | DH48: =IFERROR(DD48-DB48,"-") -> 0 | DI48: =IFERROR(DD48/DB48,"-") -> 1 | DJ48: =DR48+DZ48+EH48 -> 2034.8 | DL48: =DT48+EB48+EJ48 -> 2034.8 | DN48: =DV48+ED48+EL48 -> 0 | DP48: =IFERROR(DL48-DJ48,"-") -> 0 | DQ48: =IFERROR(DL48/DJ48,"-") -> 1 | DR48: 680.4 | DT48: 680.4 | DX48: =IFERROR(DT48-DR48,"-") -> 0 | DY48: =IFERROR(DT48/DR48,"-") -> 1 | DZ48: 673.4 | EB48: 673.4 | EF48: =IFERROR(EB48-DZ48,"-") -> 0 | EG48: =IFERROR(EB48/DZ48,"-") -> 1 | EH48: 681 | EJ48: 681 | EN48: =IFERROR(EJ48-EH48,"-") -> 0 | EO48: =IFERROR(EJ48/EH48,"-") -> 1
A49: 4.3 | B49: ШФЛУ товарная, всего: | C49: 100330073 | J49: =R49+AX49+CD49+DJ49 -> 81.4 | L49: =T49+AZ49+CF49+DL49 -> 81.4 | N49: =V49+BB49+CH49+DN49 -> 47.329123 | P49: =IFERROR(L49-J49,"-") -> 0 | Q49: =IFERROR(L49/J49,"-") -> 1 | R49: =Z49+AH49+AP49 -> 0 | T49: =AB49+AJ49+AR49 -> 0 | V49: =AD49+AL49+AT49 -> 39.902088 | X49: =IFERROR(T49-R49,"-") -> 0 | Y49: =IFERROR(T49/R49,"-") -> - | AD49: 27.93316 | AF49: =IFERROR(AB49-Z49,"-") -> 0 | AG49: =IFERROR(AB49/Z49,"-") -> - | AL49: 10.476258 | AN49: =IFERROR(AJ49-AH49,"-") -> 0 | AO49: =IFERROR(AJ49/AH49,"-") -> - | AT49: 1.49267 | AV49: =IFERROR(AR49-AP49,"-") -> 0 | AW49: =IFERROR(AR49/AP49,"-") -> - | AX49: =BF49+BN49+BV49 -> 41.7 | AZ49: =BH49+BP49+BX49 -> 41.7 | BB49: =BJ49+BR49+BZ49 -> 7.427035 | BD49: =IFERROR(AZ49-AX49,"-") -> 0 | BE49: =IFERROR(AZ49/AX49,"-") -> 1 | BJ49: 0.183335 | BL49: =IFERROR(BH49-BF49,"-") -> 0 | BM49: =IFERROR(BH49/BF49,"-") -> - | BN49: 18.4 | BP49: 18.4 | BT49: =IFERROR(BP49-BN49,"-") -> 0 | BU49: =IFERROR(BP49/BN49,"-") -> 1 | BV49: 23.3 | BX49: 23.3 | BZ49: 7.2437 | CB49: =IFERROR(BX49-BV49,"-") -> 0 | CC49: =IFERROR(BX49/BV49,"-") -> 1 | CD49: =CL49+CT49+DB49 -> 31.5 | CF49: =CN49+CV49+DD49 -> 31.5 | CH49: =CP49+CX49+DF49 -> 0 | CJ49: =IFERROR(CF49-CD49,"-") -> 0 | CK49: =IFERROR(CF49/CD49,"-") -> 1 | CL49: 14.3 | CN49: 14.3 | CR49: =IFERROR(CN49-CL49,"-") -> 0 | CS49: =IFERROR(CN49/CL49,"-") -> 1 | CT49: 8.6 | CV49: 8.6 | CZ49: =IFERROR(CV49-CT49,"-") -> 0 | DA49: =IFERROR(CV49/CT49,"-") -> 1 | DB49: 8.6 | DD49: 8.6 | DH49: =IFERROR(DD49-DB49,"-") -> 0 | DI49: =IFERROR(DD49/DB49,"-") -> 1 | DJ49: =DR49+DZ49+EH49 -> 8.2 | DL49: =DT49+EB49+EJ49 -> 8.2 | DN49: =DV49+ED49+EL49 -> 0 | DP49: =IFERROR(DL49-DJ49,"-") -> 0 | DQ49: =IFERROR(DL49/DJ49,"-") -> 1 | DR49: 2.8 | DT49: 2.8 | DX49: =IFERROR(DT49-DR49,"-") -> 0 | DY49: =IFERROR(DT49/DR49,"-") -> 1 | DZ49: 2.6 | EB49: 2.6 | EF49: =IFERROR(EB49-DZ49,"-") -> 0 | EG49: =IFERROR(EB49/DZ49,"-") -> 1 | EH49: 2.8 | EJ49: 2.8 | EN49: =IFERROR(EJ49-EH49,"-") -> 0 | EO49: =IFERROR(EJ49/EH49,"-") -> 1
A50: 4.3.1 | B50: ШФЛУ товарная | C50: 100332003 | J50: =R50+AX50+CD50+DJ50 -> 81.4 | L50: =T50+AZ50+CF50+DL50 -> 81.4 | N50: =V50+BB50+CH50+DN50 -> 47.329123 | P50: =IFERROR(L50-J50,"-") -> 0 | Q50: =IFERROR(L50/J50,"-") -> 1 | R50: =Z50+AH50+AP50 -> 0 | T50: =AB50+AJ50+AR50 -> 0 | V50: =AD50+AL50+AT50 -> 39.902088 | X50: =IFERROR(T50-R50,"-") -> 0 | Y50: =IFERROR(T50/R50,"-") -> - | Z50: 0 | AB50: 0 | AD50: 27.93316 | AF50: =IFERROR(AB50-Z50,"-") -> 0 | AG50: =IFERROR(AB50/Z50,"-") -> - | AH50: 0 | AJ50: 0 | AL50: 10.476258 | AN50: =IFERROR(AJ50-AH50,"-") -> 0 | AO50: =IFERROR(AJ50/AH50,"-") -> - | AP50: 0 | AR50: 0 | AT50: 1.49267 | AV50: =IFERROR(AR50-AP50,"-") -> 0 | AW50: =IFERROR(AR50/AP50,"-") -> - | AX50: =BF50+BN50+BV50 -> 41.7 | AZ50: =BH50+BP50+BX50 -> 41.7 | BB50: =BJ50+BR50+BZ50 -> 7.427035 | BD50: =IFERROR(AZ50-AX50,"-") -> 0 | BE50: =IFERROR(AZ50/AX50,"-") -> 1 | BF50: 0 | BH50: 0 | BJ50: 0.183335 | BL50: =IFERROR(BH50-BF50,"-") -> 0 | BM50: =IFERROR(BH50/BF50,"-") -> - | BN50: 18.4 | BP50: 18.4 | BR50: 0 | BT50: =IFERROR(BP50-BN50,"-") -> 0 | BU50: =IFERROR(BP50/BN50,"-") -> 1 | BV50: 23.3 | BX50: 23.3 | BZ50: 7.2437 | CB50: =IFERROR(BX50-BV50,"-") -> 0 | CC50: =IFERROR(BX50/BV50,"-") -> 1 | CD50: =CL50+CT50+DB50 -> 31.5 | CF50: =CN50+CV50+DD50 -> 31.5 | CH50: =CP50+CX50+DF50 -> 0 | CJ50: =IFERROR(CF50-CD50,"-") -> 0 | CK50: =IFERROR(CF50/CD50,"-") -> 1 | CL50: 14.3 | CN50: 14.3 | CR50: =IFERROR(CN50-CL50,"-") -> 0 | CS50: =IFERROR(CN50/CL50,"-") -> 1 | CT50: 8.6 | CV50: 8.6 | CZ50: =IFERROR(CV50-CT50,"-") -> 0 | DA50: =IFERROR(CV50/CT50,"-") -> 1 | DB50: 8.6 | DD50: 8.6 | DH50: =IFERROR(DD50-DB50,"-") -> 0 | DI50: =IFERROR(DD50/DB50,"-") -> 1 | DJ50: =DR50+DZ50+EH50 -> 8.2 | DL50: =DT50+EB50+EJ50 -> 8.2 | DN50: =DV50+ED50+EL50 -> 0 | DP50: =IFERROR(DL50-DJ50,"-") -> 0 | DQ50: =IFERROR(DL50/DJ50,"-") -> 1 | DR50: 2.8 | DT50: 2.8 | DX50: =IFERROR(DT50-DR50,"-") -> 0 | DY50: =IFERROR(DT50/DR50,"-") -> 1 | DZ50: 2.6 | EB50: 2.6 | EF50: =IFERROR(EB50-DZ50,"-") -> 0 | EG50: =IFERROR(EB50/DZ50,"-") -> 1 | EH50: 2.8 | EJ50: 2.8 | EN50: =IFERROR(EJ50-EH50,"-") -> 0 | EO50: =IFERROR(EJ50/EH50,"-") -> 1
B51: в т.ч. аналог стабильного конденсата | C51: 100332004 | J51: =R51+AX51+CD51+DJ51 -> 13.3 | L51: =T51+AZ51+CF51+DL51 -> 13.3 | N51: =V51+BB51+CH51+DN51 -> 18.856 | P51: =IFERROR(L51-J51,"-") -> 0 | Q51: =IFERROR(L51/J51,"-") -> 1 | R51: =Z51+AH51+AP51 -> 0 | T51: =AB51+AJ51+AR51 -> 0 | V51: =AD51+AL51+AT51 -> 15.658 | X51: =IFERROR(T51-R51,"-") -> 0 | Y51: =IFERROR(T51/R51,"-") -> - | Z51: 0 | AB51: 0 | AD51: 10.832 | AF51: =IFERROR(AB51-Z51,"-") -> 0 | AG51: =IFERROR(AB51/Z51,"-") -> - | AH51: 0 | AJ51: 0 | AL51: 3.847 | AN51: =IFERROR(AJ51-AH51,"-") -> 0 | AO51: =IFERROR(AJ51/AH51,"-") -> - | AP51: 0 | AR51: 0 | AT51: 0.979 | AV51: =IFERROR(AR51-AP51,"-") -> 0 | AW51: =IFERROR(AR51/AP51,"-") -> - | AX51: =BF51+BN51+BV51 -> 7.5 | AZ51: =BH51+BP51+BX51 -> 7.5 | BB51: =BJ51+BR51+BZ51 -> 3.198 | BD51: =IFERROR(AZ51-AX51,"-") -> 0 | BE51: =IFERROR(AZ51/AX51,"-") -> 1 | BF51: 0 | BH51: 0 | BJ51: 0 | BL51: =IFERROR(BH51-BF51,"-") -> 0 | BM51: =IFERROR(BH51/BF51,"-") -> - | BN51: 3.3 | BP51: 3.3 | BR51: 0 | BT51: =IFERROR(BP51-BN51,"-") -> 0 | BU51: =IFERROR(BP51/BN51,"-") -> 1 | BV51: 4.2 | BX51: 4.2 | BZ51: 3.198 | CB51: =IFERROR(BX51-BV51,"-") -> 0 | CC51: =IFERROR(BX51/BV51,"-") -> 1 | CD51: =CL51+CT51+DB51 -> 5.8 | CF51: =CN51+CV51+DD51 -> 5.8 | CH51: =CP51+CX51+DF51 -> 0 | CJ51: =IFERROR(CF51-CD51,"-") -> 0 | CK51: =IFERROR(CF51/CD51,"-") -> 1 | CL51: 2.6 | CN51: 2.6 | CR51: =IFERROR(CN51-CL51,"-") -> 0 | CS51: =IFERROR(CN51/CL51,"-") -> 1 | CT51: 1.6 | CV51: 1.6 | CZ51: =IFERROR(CV51-CT51,"-") -> 0 | DA51: =IFERROR(CV51/CT51,"-") -> 1 | DB51: 1.6 | DD51: 1.6 | DH51: =IFERROR(DD51-DB51,"-") -> 0 | DI51: =IFERROR(DD51/DB51,"-") -> 1 | DJ51: =DR51+DZ51+EH51 -> 0 | DL51: =DT51+EB51+EJ51 -> 0 | DN51: =DV51+ED51+EL51 -> 0 | DP51: =IFERROR(DL51-DJ51,"-") -> 0 | DQ51: =IFERROR(DL51/DJ51,"-") -> - | DR51: 0 | DT51: 0 | DX51: =IFERROR(DT51-DR51,"-") -> 0 | DY51: =IFERROR(DT51/DR51,"-") -> - | DZ51: 0 | EB51: 0 | EF51: =IFERROR(EB51-DZ51,"-") -> 0 | EG51: =IFERROR(EB51/DZ51,"-") -> - | EH51: 0 | EJ51: 0 | EN51: =IFERROR(EJ51-EH51,"-") -> 0 | EO51: =IFERROR(EJ51/EH51,"-") -> -
B52: Справочно: | E52: 3 | J52: =R52+AX52+CD52+DJ52 -> 0 | L52: =T52+AZ52+CF52+DL52 -> 0 | N52: =V52+BB52+CH52+DN52 -> 0 | P52: =IFERROR(L52-J52,"-") -> 0 | Q52: =IFERROR(L52/J52,"-") -> - | R52: =Z52+AH52+AP52 -> 0 | T52: =AB52+AJ52+AR52 -> 0 | V52: =AD52+AL52+AT52 -> 0 | X52: =IFERROR(T52-R52,"-") -> 0 | Y52: =IFERROR(T52/R52,"-") -> - | AF52: =IFERROR(AB52-Z52,"-") -> 0 | AG52: =IFERROR(AB52/Z52,"-") -> - | AN52: =IFERROR(AJ52-AH52,"-") -> 0 | AO52: =IFERROR(AJ52/AH52,"-") -> - | AV52: =IFERROR(AR52-AP52,"-") -> 0 | AW52: =IFERROR(AR52/AP52,"-") -> - | AX52: =BF52+BN52+BV52 -> 0 | AZ52: =BH52+BP52+BX52 -> 0 | BB52: =BJ52+BR52+BZ52 -> 0 | BD52: =IFERROR(AZ52-AX52,"-") -> 0 | BE52: =IFERROR(AZ52/AX52,"-") -> - | BL52: =IFERROR(BH52-BF52,"-") -> 0 | BM52: =IFERROR(BH52/BF52,"-") -> - | BT52: =IFERROR(BP52-BN52,"-") -> 0 | BU52: =IFERROR(BP52/BN52,"-") -> - | CB52: =IFERROR(BX52-BV52,"-") -> 0 | CC52: =IFERROR(BX52/BV52,"-") -> - | CD52: =CL52+CT52+DB52 -> 0 | CF52: =CN52+CV52+DD52 -> 0 | CH52: =CP52+CX52+DF52 -> 0 | CJ52: =IFERROR(CF52-CD52,"-") -> 0 | CK52: =IFERROR(CF52/CD52,"-") -> - | CR52: =IFERROR(CN52-CL52,"-") -> 0 | CS52: =IFERROR(CN52/CL52,"-") -> - | CZ52: =IFERROR(CV52-CT52,"-") -> 0 | DA52: =IFERROR(CV52/CT52,"-") -> - | DH52: =IFERROR(DD52-DB52,"-") -> 0 | DI52: =IFERROR(DD52/DB52,"-") -> - | DJ52: =DR52+DZ52+EH52 -> 0 | DL52: =DT52+EB52+EJ52 -> 0 | DN52: =DV52+ED52+EL52 -> 0 | DP52: =IFERROR(DL52-DJ52,"-") -> 0 | DQ52: =IFERROR(DL52/DJ52,"-") -> - | DX52: =IFERROR(DT52-DR52,"-") -> 0 | DY52: =IFERROR(DT52/DR52,"-") -> - | EF52: =IFERROR(EB52-DZ52,"-") -> 0 | EG52: =IFERROR(EB52/DZ52,"-") -> - | EN52: =IFERROR(EJ52-EH52,"-") -> 0 | EO52: =IFERROR(EJ52/EH52,"-") -> -
B53: ШФЛУ товарная с учетом изменения остатков | C53: 100332005 | J53: =R53+AX53+CD53+DJ53 -> 81.4 | L53: =T53+AZ53+CF53+DL53 -> 81.4 | N53: =V53+BB53+CH53+DN53 -> 50.1582 | P53: =IFERROR(L53-J53,"-") -> 0 | Q53: =IFERROR(L53/J53,"-") -> 1 | R53: =Z53+AH53+AP53 -> 0 | T53: =AB53+AJ53+AR53 -> 0 | V53: =AD53+AL53+AT53 -> 42.9145 | X53: =IFERROR(T53-R53,"-") -> 0 | Y53: =IFERROR(T53/R53,"-") -> - | Z53: 0 | AB53: 0 | AD53: 30.03365 | AF53: =IFERROR(AB53-Z53,"-") -> 0 | AG53: =IFERROR(AB53/Z53,"-") -> - | AH53: 0 | AJ53: 0 | AL53: 10.1373 | AN53: =IFERROR(AJ53-AH53,"-") -> 0 | AO53: =IFERROR(AJ53/AH53,"-") -> - | AP53: 0 | AR53: 0 | AT53: 2.74355 | AV53: =IFERROR(AR53-AP53,"-") -> 0 | AW53: =IFERROR(AR53/AP53,"-") -> - | AX53: =BF53+BN53+BV53 -> 41.7 | AZ53: =BH53+BP53+BX53 -> 41.7 | BB53: =BJ53+BR53+BZ53 -> 7.2437 | BD53: =IFERROR(AZ53-AX53,"-") -> 0 | BE53: =IFERROR(AZ53/AX53,"-") -> 1 | BF53: 0 | BH53: 0 | BJ53: 0 | BL53: =IFERROR(BH53-BF53,"-") -> 0 | BM53: =IFERROR(BH53/BF53,"-") -> - | BN53: 18.4 | BP53: 18.4 | BR53: 0 | BT53: =IFERROR(BP53-BN53,"-") -> 0 | BU53: =IFERROR(BP53/BN53,"-") -> 1 | BV53: 23.3 | BX53: 23.3 | BZ53: 7.2437 | CB53: =IFERROR(BX53-BV53,"-") -> 0 | CC53: =IFERROR(BX53/BV53,"-") -> 1 | CD53: =CL53+CT53+DB53 -> 31.5 | CF53: =CN53+CV53+DD53 -> 31.5 | CH53: =CP53+CX53+DF53 -> 0 | CJ53: =IFERROR(CF53-CD53,"-") -> 0 | CK53: =IFERROR(CF53/CD53,"-") -> 1 | CL53: 14.3 | CN53: 14.3 | CR53: =IFERROR(CN53-CL53,"-") -> 0 | CS53: =IFERROR(CN53/CL53,"-") -> 1 | CT53: 8.6 | CV53: 8.6 | CZ53: =IFERROR(CV53-CT53,"-") -> 0 | DA53: =IFERROR(CV53/CT53,"-") -> 1 | DB53: 8.6 | DD53: 8.6 | DH53: =IFERROR(DD53-DB53,"-") -> 0 | DI53: =IFERROR(DD53/DB53,"-") -> 1 | DJ53: =DR53+DZ53+EH53 -> 8.2 | DL53: =DT53+EB53+EJ53 -> 8.2 | DN53: =DV53+ED53+EL53 -> 0 | DP53: =IFERROR(DL53-DJ53,"-") -> 0 | DQ53: =IFERROR(DL53/DJ53,"-") -> 1 | DR53: 2.8 | DT53: 2.8 | DX53: =IFERROR(DT53-DR53,"-") -> 0 | DY53: =IFERROR(DT53/DR53,"-") -> 1 | DZ53: 2.6 | EB53: 2.6 | EF53: =IFERROR(EB53-DZ53,"-") -> 0 | EG53: =IFERROR(EB53/DZ53,"-") -> 1 | EH53: 2.8 | EJ53: 2.8 | EN53: =IFERROR(EJ53-EH53,"-") -> 0 | EO53: =IFERROR(EJ53/EH53,"-") -> 1
B54: ШФЛУ валовая | C54: 100332006 | J54: =R54+AX54+CD54+DJ54 -> 455.6 | L54: =T54+AZ54+CF54+DL54 -> 455.6 | N54: =V54+BB54+CH54+DN54 -> 64.25011 | P54: =IFERROR(L54-J54,"-") -> 0 | Q54: =IFERROR(L54/J54,"-") -> 1 | R54: =Z54+AH54+AP54 -> 112.3 | T54: =AB54+AJ54+AR54 -> 112.3 | V54: =AD54+AL54+AT54 -> 42.9145 | X54: =IFERROR(T54-R54,"-") -> 0 | Y54: =IFERROR(T54/R54,"-") -> 1 | Z54: 39 | AB54: 39 | AD54: 30.03365 | AF54: =IFERROR(AB54-Z54,"-") -> 0 | AG54: =IFERROR(AB54/Z54,"-") -> 1 | AH54: 35 | AJ54: 35 | AL54: 10.1373 | AN54: =IFERROR(AJ54-AH54,"-") -> 0 | AO54: =IFERROR(AJ54/AH54,"-") -> 1 | AP54: 38.3 | AR54: 38.3 | AT54: 2.74355 | AV54: =IFERROR(AR54-AP54,"-") -> 0 | AW54: =IFERROR(AR54/AP54,"-") -> 1 | AX54: =BF54+BN54+BV54 -> 90.8 | AZ54: =BH54+BP54+BX54 -> 90.8 | BB54: =BJ54+BR54+BZ54 -> 21.33561 | BD54: =IFERROR(AZ54-AX54,"-") -> 0 | BE54: =IFERROR(AZ54/AX54,"-") -> 1 | BF54: 39.4 | BH54: 39.4 | BJ54: 0 | BL54: =IFERROR(BH54-BF54,"-") -> 0 | BM54: =IFERROR(BH54/BF54,"-") -> 1 | BN54: 28.1 | BP54: 28.1 | BR54: 13.348 | BT54: =IFERROR(BP54-BN54,"-") -> 0 | BU54: =IFERROR(BP54/BN54,"-") -> 1 | BV54: 23.3 | BX54: 23.3 | BZ54: 7.98761 | CB54: =IFERROR(BX54-BV54,"-") -> 0 | CC54: =IFERROR(BX54/BV54,"-") -> 1 | CD54: =CL54+CT54+DB54 -> 122.7 | CF54: =CN54+CV54+DD54 -> 122.7 | CH54: =CP54+CX54+DF54 -> 0 | CJ54: =IFERROR(CF54-CD54,"-") -> 0 | CK54: =IFERROR(CF54/CD54,"-") -> 1 | CL54: 41.5 | CN54: 41.5 | CR54: =IFERROR(CN54-CL54,"-") -> 0 | CS54: =IFERROR(CN54/CL54,"-") -> 1 | CT54: 40.2 | CV54: 40.2 | CZ54: =IFERROR(CV54-CT54,"-") -> 0 | DA54: =IFERROR(CV54/CT54,"-") -> 1 | DB54: 41 | DD54: 41 | DH54: =IFERROR(DD54-DB54,"-") -> 0 | DI54: =IFERROR(DD54/DB54,"-") -> 1 | DJ54: =DR54+DZ54+EH54 -> 129.8 | DL54: =DT54+EB54+EJ54 -> 129.8 | DN54: =DV54+ED54+EL54 -> 0 | DP54: =IFERROR(DL54-DJ54,"-") -> 0 | DQ54: =IFERROR(DL54/DJ54,"-") -> 1 | DR54: 43.9 | DT54: 43.9 | DX54: =IFERROR(DT54-DR54,"-") -> 0 | DY54: =IFERROR(DT54/DR54,"-") -> 1 | DZ54: 42.5 | EB54: 42.5 | EF54: =IFERROR(EB54-DZ54,"-") -> 0 | EG54: =IFERROR(EB54/DZ54,"-") -> 1 | EH54: 43.4 | EJ54: 43.4 | EN54: =IFERROR(EJ54-EH54,"-") -> 0 | EO54: =IFERROR(EJ54/EH54,"-") -> 1
B55: в т.ч. аналог стабильного конденсата | C55: 100334997 | J55: =R55+AX55+CD55+DJ55 -> 82.5 | L55: =T55+AZ55+CF55+DL55 -> 82.5 | N55: =V55+BB55+CH55+DN55 -> 38.44 | P55: =IFERROR(L55-J55,"-") -> 0 | Q55: =IFERROR(L55/J55,"-") -> 1 | R55: =Z55+AH55+AP55 -> 20.3 | T55: =AB55+AJ55+AR55 -> 20.3 | V55: =AD55+AL55+AT55 -> 21.877 | X55: =IFERROR(T55-R55,"-") -> 0 | Y55: =IFERROR(T55/R55,"-") -> 1 | Z55: 7.1 | AB55: 7.1 | AD55: 10.832 | AF55: =IFERROR(AB55-Z55,"-") -> 0 | AG55: =IFERROR(AB55/Z55,"-") -> 1 | AH55: 6.3 | AJ55: 6.3 | AL55: 3.847 | AN55: =IFERROR(AJ55-AH55,"-") -> 0 | AO55: =IFERROR(AJ55/AH55,"-") -> 1 | AP55: 6.9 | AR55: 6.9 | AT55: 7.198 | AV55: =IFERROR(AR55-AP55,"-") -> 0 | AW55: =IFERROR(AR55/AP55,"-") -> 1 | AX55: =BF55+BN55+BV55 -> 16.4 | AZ55: =BH55+BP55+BX55 -> 16.4 | BB55: =BJ55+BR55+BZ55 -> 16.563 | BD55: =IFERROR(AZ55-AX55,"-") -> 0 | BE55: =IFERROR(AZ55/AX55,"-") -> 1 | BF55: 7.1 | BH55: 7.1 | BJ55: 8.194 | BL55: =IFERROR(BH55-BF55,"-") -> 0 | BM55: =IFERROR(BH55/BF55,"-") -> 1 | BN55: 5.1 | BP55: 5.1 | BR55: 5.171 | BT55: =IFERROR(BP55-BN55,"-") -> 0 | BU55: =IFERROR(BP55/BN55,"-") -> 1 | BV55: 4.2 | BX55: 4.2 | BZ55: 3.198 | CB55: =IFERROR(BX55-BV55,"-") -> 0 | CC55: =IFERROR(BX55/BV55,"-") -> 1 | CD55: =CL55+CT55+DB55 -> 22.2 | CF55: =CN55+CV55+DD55 -> 22.2 | CH55: =CP55+CX55+DF55 -> 0 | CJ55: =IFERROR(CF55-CD55,"-") -> 0 | CK55: =IFERROR(CF55/CD55,"-") -> 1 | CL55: 7.5 | CN55: 7.5 | CR55: =IFERROR(CN55-CL55,"-") -> 0 | CS55: =IFERROR(CN55/CL55,"-") -> 1 | CT55: 7.3 | CV55: 7.3 | CZ55: =IFERROR(CV55-CT55,"-") -> 0 | DA55: =IFERROR(CV55/CT55,"-") -> 1 | DB55: 7.4 | DD55: 7.4 | DH55: =IFERROR(DD55-DB55,"-") -> 0 | DI55: =IFERROR(DD55/DB55,"-") -> 1 | DJ55: =DR55+DZ55+EH55 -> 23.6 | DL55: =DT55+EB55+EJ55 -> 23.6 | DN55: =DV55+ED55+EL55 -> 0 | DP55: =IFERROR(DL55-DJ55,"-") -> 0 | DQ55: =IFERROR(DL55/DJ55,"-") -> 1 | DR55: 8 | DT55: 8 | DX55: =IFERROR(DT55-DR55,"-") -> 0 | DY55: =IFERROR(DT55/DR55,"-") -> 1 | DZ55: 7.7 | EB55: 7.7 | EF55: =IFERROR(EB55-DZ55,"-") -> 0 | EG55: =IFERROR(EB55/DZ55,"-") -> 1 | EH55: 7.9 | EJ55: 7.9 | EN55: =IFERROR(EJ55-EH55,"-") -> 0 | EO55: =IFERROR(EJ55/EH55,"-") -> 1
B56: ШФЛУ - переработка | C56: 100332008 | J56: =R56+AX56+CD56+DJ56 -> 374.2 | L56: =T56+AZ56+CF56+DL56 -> 374.2 | N56: =V56+BB56+CH56+DN56 -> 54.450644 | P56: =IFERROR(L56-J56,"-") -> 0 | Q56: =IFERROR(L56/J56,"-") -> 1 | R56: =Z56+AH56+AP56 -> 112.3 | T56: =AB56+AJ56+AR56 -> 112.3 | V56: =AD56+AL56+AT56 -> 18.675241 | X56: =IFERROR(T56-R56,"-") -> 0 | Y56: =IFERROR(T56/R56,"-") -> 1 | Z56: 39 | AB56: 39 | AD56: 0 | AF56: =IFERROR(AB56-Z56,"-") -> 0 | AG56: =IFERROR(AB56/Z56,"-") -> 1 | AH56: 35 | AJ56: 35 | AL56: 0 | AN56: =IFERROR(AJ56-AH56,"-") -> 0 | AO56: =IFERROR(AJ56/AH56,"-") -> 1 | AP56: 38.3 | AR56: 38.3 | AT56: 18.675241 | AV56: =IFERROR(AR56-AP56,"-") -> 0 | AW56: =IFERROR(AR56/AP56,"-") -> 1 | AX56: =BF56+BN56+BV56 -> 49.1 | AZ56: =BH56+BP56+BX56 -> 49.1 | BB56: =BJ56+BR56+BZ56 -> 35.775403 | BD56: =IFERROR(AZ56-AX56,"-") -> 0 | BE56: =IFERROR(AZ56/AX56,"-") -> 1 | BF56: 39.4 | BH56: 39.4 | BJ56: 22.402403 | BL56: =IFERROR(BH56-BF56,"-") -> 0 | BM56: =IFERROR(BH56/BF56,"-") -> 1 | BN56: 9.7 | BP56: 9.7 | BR56: 13.373 | BT56: =IFERROR(BP56-BN56,"-") -> 0 | BU56: =IFERROR(BP56/BN56,"-") -> 1 | BV56: 0 | BX56: 0 | BZ56: 0 | CB56: =IFERROR(BX56-BV56,"-") -> 0 | CC56: =IFERROR(BX56/BV56,"-") -> - | CD56: =CL56+CT56+DB56 -> 91.2 | CF56: =CN56+CV56+DD56 -> 91.2 | CH56: =CP56+CX56+DF56 -> 0 | CJ56: =IFERROR(CF56-CD56,"-") -> 0 | CK56: =IFERROR(CF56/CD56,"-") -> 1 | CL56: 27.2 | CN56: 27.2 | CR56: =IFERROR(CN56-CL56,"-") -> 0 | CS56: =IFERROR(CN56/CL56,"-") -> 1 | CT56: 31.6 | CV56: 31.6 | CZ56: =IFERROR(CV56-CT56,"-") -> 0 | DA56: =IFERROR(CV56/CT56,"-") -> 1 | DB56: 32.4 | DD56: 32.4 | DH56: =IFERROR(DD56-DB56,"-") -> 0 | DI56: =IFERROR(DD56/DB56,"-") -> 1 | DJ56: =DR56+DZ56+EH56 -> 121.6 | DL56: =DT56+EB56+EJ56 -> 121.6 | DN56: =DV56+ED56+EL56 -> 0 | DP56: =IFERROR(DL56-DJ56,"-") -> 0 | DQ56: =IFERROR(DL56/DJ56,"-") -> 1 | DR56: 41.1 | DT56: 41.1 | DX56: =IFERROR(DT56-DR56,"-") -> 0 | DY56: =IFERROR(DT56/DR56,"-") -> 1 | DZ56: 39.9 | EB56: 39.9 | EF56: =IFERROR(EB56-DZ56,"-") -> 0 | EG56: =IFERROR(EB56/DZ56,"-") -> 1 | EH56: 40.6 | EJ56: 40.6 | EN56: =IFERROR(EJ56-EH56,"-") -> 0 | EO56: =IFERROR(EJ56/EH56,"-") -> 1
B57: в т.ч. аналог стабильного конденсата | C57: 100332009 | J57: =R57+AX57+CD57+DJ57 -> 69.2 | L57: =T57+AZ57+CF57+DL57 -> 69.2 | N57: =V57+BB57+CH57+DN57 -> 19.584 | P57: =IFERROR(L57-J57,"-") -> 0 | Q57: =IFERROR(L57/J57,"-") -> 1 | R57: =Z57+AH57+AP57 -> 20.3 | T57: =AB57+AJ57+AR57 -> 20.3 | V57: =AD57+AL57+AT57 -> 6.219 | X57: =IFERROR(T57-R57,"-") -> 0 | Y57: =IFERROR(T57/R57,"-") -> 1 | Z57: 7.1 | AB57: 7.1 | AD57: 0 | AF57: =IFERROR(AB57-Z57,"-") -> 0 | AG57: =IFERROR(AB57/Z57,"-") -> 1 | AH57: 6.3 | AJ57: 6.3 | AL57: 0 | AN57: =IFERROR(AJ57-AH57,"-") -> 0 | AO57: =IFERROR(AJ57/AH57,"-") -> 1 | AP57: 6.9 | AR57: 6.9 | AT57: 6.219 | AV57: =IFERROR(AR57-AP57,"-") -> 0 | AW57: =IFERROR(AR57/AP57,"-") -> 1 | AX57: =BF57+BN57+BV57 -> 8.9 | AZ57: =BH57+BP57+BX57 -> 8.9 | BB57: =BJ57+BR57+BZ57 -> 13.365 | BD57: =IFERROR(AZ57-AX57,"-") -> 0 | BE57: =IFERROR(AZ57/AX57,"-") -> 1 | BF57: 7.1 | BH57: 7.1 | BJ57: 8.194 | BL57: =IFERROR(BH57-BF57,"-") -> 0 | BM57: =IFERROR(BH57/BF57,"-") -> 1 | BN57: 1.8 | BP57: 1.8 | BR57: 5.171 | BT57: =IFERROR(BP57-BN57,"-") -> 0 | BU57: =IFERROR(BP57/BN57,"-") -> 1 | BV57: 0 | BX57: 0 | BZ57: 0 | CB57: =IFERROR(BX57-BV57,"-") -> 0 | CC57: =IFERROR(BX57/BV57,"-") -> - | CD57: =CL57+CT57+DB57 -> 16.4 | CF57: =CN57+CV57+DD57 -> 16.4 | CH57: =CP57+CX57+DF57 -> 0 | CJ57: =IFERROR(CF57-CD57,"-") -> 0 | CK57: =IFERROR(CF57/CD57,"-") -> 1 | CL57: 4.9 | CN57: 4.9 | CR57: =IFERROR(CN57-CL57,"-") -> 0 | CS57: =IFERROR(CN57/CL57,"-") -> 1 | CT57: 5.7 | CV57: 5.7 | CZ57: =IFERROR(CV57-CT57,"-") -> 0 | DA57: =IFERROR(CV57/CT57,"-") -> 1 | DB57: 5.8 | DD57: 5.8 | DH57: =IFERROR(DD57-DB57,"-") -> 0 | DI57: =IFERROR(DD57/DB57,"-") -> 1 | DJ57: =DR57+DZ57+EH57 -> 23.6 | DL57: =DT57+EB57+EJ57 -> 23.6 | DN57: =DV57+ED57+EL57 -> 0 | DP57: =IFERROR(DL57-DJ57,"-") -> 0 | DQ57: =IFERROR(DL57/DJ57,"-") -> 1 | DR57: 8 | DT57: 8 | DX57: =IFERROR(DT57-DR57,"-") -> 0 | DY57: =IFERROR(DT57/DR57,"-") -> 1 | DZ57: 7.7 | EB57: 7.7 | EF57: =IFERROR(EB57-DZ57,"-") -> 0 | EG57: =IFERROR(EB57/DZ57,"-") -> 1 | EH57: 7.9 | EJ57: 7.9 | EN57: =IFERROR(EJ57-EH57,"-") -> 0 | EO57: =IFERROR(EJ57/EH57,"-") -> 1
A58: 4.4 | B58: ГАЗЫ УГЛЕВОДОРОДНЫЕ СЖИЖЕННЫЕ | C58: 100332010 | J58: =R58+AX58+CD58+DJ58 -> 230.3 | L58: =T58+AZ58+CF58+DL58 -> 230.3 | N58: =V58+BB58+CH58+DN58 -> 44.425167 | P58: =IFERROR(L58-J58,"-") -> 0 | Q58: =IFERROR(L58/J58,"-") -> 1 | R58: =Z58+AH58+AP58 -> 71.6 | T58: =AB58+AJ58+AR58 -> 71.6 | V58: =AD58+AL58+AT58 -> 17.520142 | X58: =IFERROR(T58-R58,"-") -> 0 | Y58: =IFERROR(T58/R58,"-") -> 1 | Z58: 24.9 | AB58: 24.9 | AD58: 0 | AF58: =IFERROR(AB58-Z58,"-") -> 0 | AG58: =IFERROR(AB58/Z58,"-") -> 1 | AH58: 22.3 | AJ58: 22.3 | AL58: 0 | AN58: =IFERROR(AJ58-AH58,"-") -> 0 | AO58: =IFERROR(AJ58/AH58,"-") -> 1 | AP58: 24.4 | AR58: 24.4 | AT58: 17.520142 | AV58: =IFERROR(AR58-AP58,"-") -> 0 | AW58: =IFERROR(AR58/AP58,"-") -> 1 | AX58: =BF58+BN58+BV58 -> 31.3 | AZ58: =BH58+BP58+BX58 -> 31.3 | BB58: =BJ58+BR58+BZ58 -> 26.905025 | BD58: =IFERROR(AZ58-AX58,"-") -> 0 | BE58: =IFERROR(AZ58/AX58,"-") -> 1 | BF58: 25.1 | BH58: 25.1 | BJ58: 19.758025 | BL58: =IFERROR(BH58-BF58,"-") -> 0 | BM58: =IFERROR(BH58/BF58,"-") -> 1 | BN58: 6.2 | BP58: 6.2 | BR58: 7.147 | BT58: =IFERROR(BP58-BN58,"-") -> 0 | BU58: =IFERROR(BP58/BN58,"-") -> 1 | BV58: 0 | BX58: 0 | BZ58: 0 | CB58: =IFERROR(BX58-BV58,"-") -> 0 | CC58: =IFERROR(BX58/BV58,"-") -> - | CD58: =CL58+CT58+DB58 -> 49.9 | CF58: =CN58+CV58+DD58 -> 49.9 | CH58: =CP58+CX58+DF58 -> 0 | CJ58: =IFERROR(CF58-CD58,"-") -> 0 | CK58: =IFERROR(CF58/CD58,"-") -> 1 | CL58: 14.9 | CN58: 14.9 | CR58: =IFERROR(CN58-CL58,"-") -> 0 | CS58: =IFERROR(CN58/CL58,"-") -> 1 | CT58: 17.3 | CV58: 17.3 | CZ58: =IFERROR(CV58-CT58,"-") -> 0 | DA58: =IFERROR(CV58/CT58,"-") -> 1 | DB58: 17.7 | DD58: 17.7 | DH58: =IFERROR(DD58-DB58,"-") -> 0 | DI58: =IFERROR(DD58/DB58,"-") -> 1 | DJ58: =DR58+DZ58+EH58 -> 77.5 | DL58: =DT58+EB58+EJ58 -> 77.5 | DN58: =DV58+ED58+EL58 -> 0 | DP58: =IFERROR(DL58-DJ58,"-") -> 0 | DQ58: =IFERROR(DL58/DJ58,"-") -> 1 | DR58: 26.1 | DT58: 26.1 | DX58: =IFERROR(DT58-DR58,"-") -> 0 | DY58: =IFERROR(DT58/DR58,"-") -> 1 | DZ58: 25.5 | EB58: 25.5 | EF58: =IFERROR(EB58-DZ58,"-") -> 0 | EG58: =IFERROR(EB58/DZ58,"-") -> 1 | EH58: 25.9 | EJ58: 25.9 | EN58: =IFERROR(EJ58-EH58,"-") -> 0 | EO58: =IFERROR(EJ58/EH58,"-") -> 1
A59: 4.5 | B59: СТАБИЛЬНЫЙ КОНДЕНСАТ ТОВАРНЫЙ, ВСЕГО: | C59: 100332011 | J59: =R59+AX59+CD59+DJ59 -> 442.5 | L59: =T59+AZ59+CF59+DL59 -> 442.5 | N59: =V59+BB59+CH59+DN59 -> 645.85977 | P59: =IFERROR(L59-J59,"-") -> 0 | Q59: =IFERROR(L59/J59,"-") -> 1 | R59: =Z59+AH59+AP59 -> 14 | T59: =AB59+AJ59+AR59 -> 14 | V59: =AD59+AL59+AT59 -> 429.10198 | X59: =IFERROR(T59-R59,"-") -> 0 | Y59: =IFERROR(T59/R59,"-") -> 1 | Z59: 4.7 | AB59: 4.7 | AD59: 151.83617 | AF59: =IFERROR(AB59-Z59,"-") -> 0 | AG59: =IFERROR(AB59/Z59,"-") -> 1 | AH59: 4.4 | AJ59: 4.4 | AL59: 119.49988 | AN59: =IFERROR(AJ59-AH59,"-") -> 0 | AO59: =IFERROR(AJ59/AH59,"-") -> 1 | AP59: 4.9 | AR59: 4.9 | AT59: 157.76593 | AV59: =IFERROR(AR59-AP59,"-") -> 0 | AW59: =IFERROR(AR59/AP59,"-") -> 1 | AX59: =BF59+BN59+BV59 -> 210.5 | AZ59: =BH59+BP59+BX59 -> 210.5 | BB59: =BJ59+BR59+BZ59 -> 216.75779 | BD59: =IFERROR(AZ59-AX59,"-") -> 0 | BE59: =IFERROR(AZ59/AX59,"-") -> 1 | BF59: 10.1 | BH59: 10.1 | BJ59: 131.45244 | BL59: =IFERROR(BH59-BF59,"-") -> 0 | BM59: =IFERROR(BH59/BF59,"-") -> 1 | BN59: 85.5 | BP59: 85.5 | BR59: 18.229 | BT59: =IFERROR(BP59-BN59,"-") -> 0 | BU59: =IFERROR(BP59/BN59,"-") -> 1 | BV59: 114.9 | BX59: 114.9 | BZ59: 67.07635 | CB59: =IFERROR(BX59-BV59,"-") -> 0 | CC59: =IFERROR(BX59/BV59,"-") -> 1 | CD59: =CL59+CT59+DB59 -> 130.8 | CF59: =CN59+CV59+DD59 -> 130.8 | CH59: =CP59+CX59+DF59 -> 0 | CJ59: =IFERROR(CF59-CD59,"-") -> 0 | CK59: =IFERROR(CF59/CD59,"-") -> 1 | CL59: 78.2 | CN59: 78.2 | CR59: =IFERROR(CN59-CL59,"-") -> 0 | CS59: =IFERROR(CN59/CL59,"-") -> 1 | CT59: 19.9 | CV59: 19.9 | CZ59: =IFERROR(CV59-CT59,"-") -> 0 | DA59: =IFERROR(CV59/CT59,"-") -> 1 | DB59: 32.7 | DD59: 32.7 | DH59: =IFERROR(DD59-DB59,"-") -> 0 | DI59: =IFERROR(DD59/DB59,"-") -> 1 | DJ59: =DR59+DZ59+EH59 -> 87.2 | DL59: =DT59+EB59+EJ59 -> 87.2 | DN59: =DV59+ED59+EL59 -> 0 | DP59: =IFERROR(DL59-DJ59,"-") -> 0 | DQ59: =IFERROR(DL59/DJ59,"-") -> 1 | DR59: 33.4 | DT59: 33.4 | DX59: =IFERROR(DT59-DR59,"-") -> 0 | DY59: =IFERROR(DT59/DR59,"-") -> 1 | DZ59: 26.7 | EB59: 26.7 | EF59: =IFERROR(EB59-DZ59,"-") -> 0 | EG59: =IFERROR(EB59/DZ59,"-") -> 1 | EH59: 27.1 | EJ59: 27.1 | EN59: =IFERROR(EJ59-EH59,"-") -> 0 | EO59: =IFERROR(EJ59/EH59,"-") -> 1
A60: 4.5.1 | B60: СК товарный | C60: 100332012 | J60: =R60+AX60+CD60+DJ60 -> 442.5 | L60: =T60+AZ60+CF60+DL60 -> 442.5 | N60: =V60+BB60+CH60+DN60 -> 645.85977 | P60: =IFERROR(L60-J60,"-") -> 0 | Q60: =IFERROR(L60/J60,"-") -> 1 | R60: =Z60+AH60+AP60 -> 14 | T60: =AB60+AJ60+AR60 -> 14 | V60: =AD60+AL60+AT60 -> 429.10198 | X60: =IFERROR(T60-R60,"-") -> 0 | Y60: =IFERROR(T60/R60,"-") -> 1 | Z60: 4.7 | AB60: 4.7 | AD60: 151.83617 | AF60: =IFERROR(AB60-Z60,"-") -> 0 | AG60: =IFERROR(AB60/Z60,"-") -> 1 | AH60: 4.4 | AJ60: 4.4 | AL60: 119.49988 | AN60: =IFERROR(AJ60-AH60,"-") -> 0 | AO60: =IFERROR(AJ60/AH60,"-") -> 1 | AP60: 4.9 | AR60: 4.9 | AT60: 157.76593 | AV60: =IFERROR(AR60-AP60,"-") -> 0 | AW60: =IFERROR(AR60/AP60,"-") -> 1 | AX60: =BF60+BN60+BV60 -> 210.5 | AZ60: =BH60+BP60+BX60 -> 210.5 | BB60: =BJ60+BR60+BZ60 -> 216.75779 | BD60: =IFERROR(AZ60-AX60,"-") -> 0 | BE60: =IFERROR(AZ60/AX60,"-") -> 1 | BF60: 10.1 | BH60: 10.1 | BJ60: 131.45244 | BL60: =IFERROR(BH60-BF60,"-") -> 0 | BM60: =IFERROR(BH60/BF60,"-") -> 1 | BN60: 85.5 | BP60: 85.5 | BR60: 18.229 | BT60: =IFERROR(BP60-BN60,"-") -> 0 | BU60: =IFERROR(BP60/BN60,"-") -> 1 | BV60: 114.9 | BX60: 114.9 | BZ60: 67.07635 | CB60: =IFERROR(BX60-BV60,"-") -> 0 | CC60: =IFERROR(BX60/BV60,"-") -> 1 | CD60: =CL60+CT60+DB60 -> 130.8 | CF60: =CN60+CV60+DD60 -> 130.8 | CH60: =CP60+CX60+DF60 -> 0 | CJ60: =IFERROR(CF60-CD60,"-") -> 0 | CK60: =IFERROR(CF60/CD60,"-") -> 1 | CL60: 78.2 | CN60: 78.2 | CR60: =IFERROR(CN60-CL60,"-") -> 0 | CS60: =IFERROR(CN60/CL60,"-") -> 1 | CT60: 19.9 | CV60: 19.9 | CZ60: =IFERROR(CV60-CT60,"-") -> 0 | DA60: =IFERROR(CV60/CT60,"-") -> 1 | DB60: 32.7 | DD60: 32.7 | DH60: =IFERROR(DD60-DB60,"-") -> 0 | DI60: =IFERROR(DD60/DB60,"-") -> 1 | DJ60: =DR60+DZ60+EH60 -> 87.2 | DL60: =DT60+EB60+EJ60 -> 87.2 | DN60: =DV60+ED60+EL60 -> 0 | DP60: =IFERROR(DL60-DJ60,"-") -> 0 | DQ60: =IFERROR(DL60/DJ60,"-") -> 1 | DR60: 33.4 | DT60: 33.4 | DX60: =IFERROR(DT60-DR60,"-") -> 0 | DY60: =IFERROR(DT60/DR60,"-") -> 1 | DZ60: 26.7 | EB60: 26.7 | EF60: =IFERROR(EB60-DZ60,"-") -> 0 | EG60: =IFERROR(EB60/DZ60,"-") -> 1 | EH60: 27.1 | EJ60: 27.1 | EN60: =IFERROR(EJ60-EH60,"-") -> 0 | EO60: =IFERROR(EJ60/EH60,"-") -> 1
B61: Справочно: | E61: 4 | J61: =R61+AX61+CD61+DJ61 -> 0 | L61: =T61+AZ61+CF61+DL61 -> 0 | N61: =V61+BB61+CH61+DN61 -> 0 | P61: =IFERROR(L61-J61,"-") -> 0 | Q61: =IFERROR(L61/J61,"-") -> - | R61: =Z61+AH61+AP61 -> 0 | T61: =AB61+AJ61+AR61 -> 0 | V61: =AD61+AL61+AT61 -> 0 | X61: =IFERROR(T61-R61,"-") -> 0 | Y61: =IFERROR(T61/R61,"-") -> - | AF61: =IFERROR(AB61-Z61,"-") -> 0 | AG61: =IFERROR(AB61/Z61,"-") -> - | AN61: =IFERROR(AJ61-AH61,"-") -> 0 | AO61: =IFERROR(AJ61/AH61,"-") -> - | AV61: =IFERROR(AR61-AP61,"-") -> 0 | AW61: =IFERROR(AR61/AP61,"-") -> - | AX61: =BF61+BN61+BV61 -> 0 | AZ61: =BH61+BP61+BX61 -> 0 | BB61: =BJ61+BR61+BZ61 -> 0 | BD61: =IFERROR(AZ61-AX61,"-") -> 0 | BE61: =IFERROR(AZ61/AX61,"-") -> - | BL61: =IFERROR(BH61-BF61,"-") -> 0 | BM61: =IFERROR(BH61/BF61,"-") -> - | BT61: =IFERROR(BP61-BN61,"-") -> 0 | BU61: =IFERROR(BP61/BN61,"-") -> - | CB61: =IFERROR(BX61-BV61,"-") -> 0 | CC61: =IFERROR(BX61/BV61,"-") -> - | CD61: =CL61+CT61+DB61 -> 0 | CF61: =CN61+CV61+DD61 -> 0 | CH61: =CP61+CX61+DF61 -> 0 | CJ61: =IFERROR(CF61-CD61,"-") -> 0 | CK61: =IFERROR(CF61/CD61,"-") -> - | CR61: =IFERROR(CN61-CL61,"-") -> 0 | CS61: =IFERROR(CN61/CL61,"-") -> - | CZ61: =IFERROR(CV61-CT61,"-") -> 0 | DA61: =IFERROR(CV61/CT61,"-") -> - | DH61: =IFERROR(DD61-DB61,"-") -> 0 | DI61: =IFERROR(DD61/DB61,"-") -> - | DJ61: =DR61+DZ61+EH61 -> 0 | DL61: =DT61+EB61+EJ61 -> 0 | DN61: =DV61+ED61+EL61 -> 0 | DP61: =IFERROR(DL61-DJ61,"-") -> 0 | DQ61: =IFERROR(DL61/DJ61,"-") -> - | DX61: =IFERROR(DT61-DR61,"-") -> 0 | DY61: =IFERROR(DT61/DR61,"-") -> - | EF61: =IFERROR(EB61-DZ61,"-") -> 0 | EG61: =IFERROR(EB61/DZ61,"-") -> - | EN61: =IFERROR(EJ61-EH61,"-") -> 0 | EO61: =IFERROR(EJ61/EH61,"-") -> -
B62: СК товарный с учетом изменения остатков (отгрузка) | C62: 100332013 | J62: =R62+AX62+CD62+DJ62 -> 442.5 | L62: =T62+AZ62+CF62+DL62 -> 442.5 | N62: =V62+BB62+CH62+DN62 -> 630.1171 | P62: =IFERROR(L62-J62,"-") -> 0 | Q62: =IFERROR(L62/J62,"-") -> 1 | R62: =Z62+AH62+AP62 -> 14 | T62: =AB62+AJ62+AR62 -> 14 | V62: =AD62+AL62+AT62 -> 405.7997 | X62: =IFERROR(T62-R62,"-") -> 0 | Y62: =IFERROR(T62/R62,"-") -> 1 | Z62: 4.7 | AB62: 4.7 | AD62: 133.57105 | AF62: =IFERROR(AB62-Z62,"-") -> 0 | AG62: =IFERROR(AB62/Z62,"-") -> 1 | AH62: 4.4 | AJ62: 4.4 | AL62: 113.75865 | AN62: =IFERROR(AJ62-AH62,"-") -> 0 | AO62: =IFERROR(AJ62/AH62,"-") -> 1 | AP62: 4.9 | AR62: 4.9 | AT62: 158.47 | AV62: =IFERROR(AR62-AP62,"-") -> 0 | AW62: =IFERROR(AR62/AP62,"-") -> 1 | AX62: =BF62+BN62+BV62 -> 210.5 | AZ62: =BH62+BP62+BX62 -> 210.5 | BB62: =BJ62+BR62+BZ62 -> 224.3174 | BD62: =IFERROR(AZ62-AX62,"-") -> 0 | BE62: =IFERROR(AZ62/AX62,"-") -> 1 | BF62: 10.1 | BH62: 10.1 | BJ62: 139.01205 | BL62: =IFERROR(BH62-BF62,"-") -> 0 | BM62: =IFERROR(BH62/BF62,"-") -> 1 | BN62: 85.5 | BP62: 85.5 | BR62: 18.229 | BT62: =IFERROR(BP62-BN62,"-") -> 0 | BU62: =IFERROR(BP62/BN62,"-") -> 1 | BV62: 114.9 | BX62: 114.9 | BZ62: 67.07635 | CB62: =IFERROR(BX62-BV62,"-") -> 0 | CC62: =IFERROR(BX62/BV62,"-") -> 1 | CD62: =CL62+CT62+DB62 -> 130.8 | CF62: =CN62+CV62+DD62 -> 130.8 | CH62: =CP62+CX62+DF62 -> 0 | CJ62: =IFERROR(CF62-CD62,"-") -> 0 | CK62: =IFERROR(CF62/CD62,"-") -> 1 | CL62: 78.2 | CN62: 78.2 | CR62: =IFERROR(CN62-CL62,"-") -> 0 | CS62: =IFERROR(CN62/CL62,"-") -> 1 | CT62: 19.9 | CV62: 19.9 | CZ62: =IFERROR(CV62-CT62,"-") -> 0 | DA62: =IFERROR(CV62/CT62,"-") -> 1 | DB62: 32.7 | DD62: 32.7 | DH62: =IFERROR(DD62-DB62,"-") -> 0 | DI62: =IFERROR(DD62/DB62,"-") -> 1 | DJ62: =DR62+DZ62+EH62 -> 87.2 | DL62: =DT62+EB62+EJ62 -> 87.2 | DN62: =DV62+ED62+EL62 -> 0 | DP62: =IFERROR(DL62-DJ62,"-") -> 0 | DQ62: =IFERROR(DL62/DJ62,"-") -> 1 | DR62: 33.4 | DT62: 33.4 | DX62: =IFERROR(DT62-DR62,"-") -> 0 | DY62: =IFERROR(DT62/DR62,"-") -> 1 | DZ62: 26.7 | EB62: 26.7 | EF62: =IFERROR(EB62-DZ62,"-") -> 0 | EG62: =IFERROR(EB62/DZ62,"-") -> 1 | EH62: 27.1 | EJ62: 27.1 | EN62: =IFERROR(EJ62-EH62,"-") -> 0 | EO62: =IFERROR(EJ62/EH62,"-") -> 1
B63: СК валовый | C63: 100332014 | J63: =R63+AX63+CD63+DJ63 -> 2381.7 | L63: =T63+AZ63+CF63+DL63 -> 2381.7 | N63: =V63+BB63+CH63+DN63 -> 651.98346 | P63: =IFERROR(L63-J63,"-") -> 0 | Q63: =IFERROR(L63/J63,"-") -> 1 | R63: =Z63+AH63+AP63 -> 597.8 | T63: =AB63+AJ63+AR63 -> 597.8 | V63: =AD63+AL63+AT63 -> 405.7997 | X63: =IFERROR(T63-R63,"-") -> 0 | Y63: =IFERROR(T63/R63,"-") -> 1 | Z63: 205.8 | AB63: 205.8 | AD63: 133.57105 | AF63: =IFERROR(AB63-Z63,"-") -> 0 | AG63: =IFERROR(AB63/Z63,"-") -> 1 | AH63: 186 | AJ63: 186 | AL63: 113.75865 | AN63: =IFERROR(AJ63-AH63,"-") -> 0 | AO63: =IFERROR(AJ63/AH63,"-") -> 1 | AP63: 206 | AR63: 206 | AT63: 158.47 | AV63: =IFERROR(AR63-AP63,"-") -> 0 | AW63: =IFERROR(AR63/AP63,"-") -> 1 | AX63: =BF63+BN63+BV63 -> 455.2 | AZ63: =BH63+BP63+BX63 -> 455.2 | BB63: =BJ63+BR63+BZ63 -> 246.18375 | BD63: =IFERROR(AZ63-AX63,"-") -> 0 | BE63: =IFERROR(AZ63/AX63,"-") -> 1 | BF63: 199 | BH63: 199 | BJ63: 139.01205 | BL63: =IFERROR(BH63-BF63,"-") -> 0 | BM63: =IFERROR(BH63/BF63,"-") -> 1 | BN63: 141.3 | BP63: 141.3 | BR63: 65.462 | BT63: =IFERROR(BP63-BN63,"-") -> 0 | BU63: =IFERROR(BP63/BN63,"-") -> 1 | BV63: 114.9 | BX63: 114.9 | BZ63: 41.709705 | CB63: =IFERROR(BX63-BV63,"-") -> 0 | CC63: =IFERROR(BX63/BV63,"-") -> 1 | CD63: =CL63+CT63+DB63 -> 650.6 | CF63: =CN63+CV63+DD63 -> 650.6 | CH63: =CP63+CX63+DF63 -> 0 | CJ63: =IFERROR(CF63-CD63,"-") -> 0 | CK63: =IFERROR(CF63/CD63,"-") -> 1 | CL63: 213.9 | CN63: 213.9 | CR63: =IFERROR(CN63-CL63,"-") -> 0 | CS63: =IFERROR(CN63/CL63,"-") -> 1 | CT63: 215.1 | CV63: 215.1 | CZ63: =IFERROR(CV63-CT63,"-") -> 0 | DA63: =IFERROR(CV63/CT63,"-") -> 1 | DB63: 221.6 | DD63: 221.6 | DH63: =IFERROR(DD63-DB63,"-") -> 0 | DI63: =IFERROR(DD63/DB63,"-") -> 1 | DJ63: =DR63+DZ63+EH63 -> 678.1 | DL63: =DT63+EB63+EJ63 -> 678.1 | DN63: =DV63+ED63+EL63 -> 0 | DP63: =IFERROR(DL63-DJ63,"-") -> 0 | DQ63: =IFERROR(DL63/DJ63,"-") -> 1 | DR63: 228.6 | DT63: 228.6 | DX63: =IFERROR(DT63-DR63,"-") -> 0 | DY63: =IFERROR(DT63/DR63,"-") -> 1 | DZ63: 221.3 | EB63: 221.3 | EF63: =IFERROR(EB63-DZ63,"-") -> 0 | EG63: =IFERROR(EB63/DZ63,"-") -> 1 | EH63: 228.2 | EJ63: 228.2 | EN63: =IFERROR(EJ63-EH63,"-") -> 0 | EO63: =IFERROR(EJ63/EH63,"-") -> 1
B64: СК - переработка | C64: 100332016 | J64: =R64+AX64+CD64+DJ64 -> 1939.2 | L64: =T64+AZ64+CF64+DL64 -> 1939.2 | N64: =V64+BB64+CH64+DN64 -> 85.936579 | P64: =IFERROR(L64-J64,"-") -> 0 | Q64: =IFERROR(L64/J64,"-") -> 1 | R64: =Z64+AH64+AP64 -> 583.8 | T64: =AB64+AJ64+AR64 -> 583.8 | V64: =AD64+AL64+AT64 -> 0 | X64: =IFERROR(T64-R64,"-") -> 0 | Y64: =IFERROR(T64/R64,"-") -> 1 | Z64: 201.1 | AB64: 201.1 | AD64: 0 | AF64: =IFERROR(AB64-Z64,"-") -> 0 | AG64: =IFERROR(AB64/Z64,"-") -> 1 | AH64: 181.6 | AJ64: 181.6 | AL64: 0 | AN64: =IFERROR(AJ64-AH64,"-") -> 0 | AO64: =IFERROR(AJ64/AH64,"-") -> 1 | AP64: 201.1 | AR64: 201.1 | AT64: 0 | AV64: =IFERROR(AR64-AP64,"-") -> 0 | AW64: =IFERROR(AR64/AP64,"-") -> 1 | AX64: =BF64+BN64+BV64 -> 244.7 | AZ64: =BH64+BP64+BX64 -> 244.7 | BB64: =BJ64+BR64+BZ64 -> 85.936579 | BD64: =IFERROR(AZ64-AX64,"-") -> 0 | BE64: =IFERROR(AZ64/AX64,"-") -> 1 | BF64: 188.9 | BH64: 188.9 | BJ64: 27.198579 | BL64: =IFERROR(BH64-BF64,"-") -> 0 | BM64: =IFERROR(BH64/BF64,"-") -> 1 | BN64: 55.8 | BP64: 55.8 | BR64: 58.738 | BT64: =IFERROR(BP64-BN64,"-") -> 0 | BU64: =IFERROR(BP64/BN64,"-") -> 1 | BV64: 0 | BX64: 0 | BZ64: 0 | CB64: =IFERROR(BX64-BV64,"-") -> 0 | CC64: =IFERROR(BX64/BV64,"-") -> - | CD64: =CL64+CT64+DB64 -> 519.8 | CF64: =CN64+CV64+DD64 -> 519.8 | CH64: =CP64+CX64+DF64 -> 0 | CJ64: =IFERROR(CF64-CD64,"-") -> 0 | CK64: =IFERROR(CF64/CD64,"-") -> 1 | CL64: 135.7 | CN64: 135.7 | CR64: =IFERROR(CN64-CL64,"-") -> 0 | CS64: =IFERROR(CN64/CL64,"-") -> 1 | CT64: 195.2 | CV64: 195.2 | CZ64: =IFERROR(CV64-CT64,"-") -> 0 | DA64: =IFERROR(CV64/CT64,"-") -> 1 | DB64: 188.9 | DD64: 188.9 | DH64: =IFERROR(DD64-DB64,"-") -> 0 | DI64: =IFERROR(DD64/DB64,"-") -> 1 | DJ64: =DR64+DZ64+EH64 -> 590.9 | DL64: =DT64+EB64+EJ64 -> 590.9 | DN64: =DV64+ED64+EL64 -> 0 | DP64: =IFERROR(DL64-DJ64,"-") -> 0 | DQ64: =IFERROR(DL64/DJ64,"-") -> 1 | DR64: 195.2 | DT64: 195.2 | DX64: =IFERROR(DT64-DR64,"-") -> 0 | DY64: =IFERROR(DT64/DR64,"-") -> 1 | DZ64: 194.6 | EB64: 194.6 | EF64: =IFERROR(EB64-DZ64,"-") -> 0 | EG64: =IFERROR(EB64/DZ64,"-") -> 1 | EH64: 201.1 | EJ64: 201.1 | EN64: =IFERROR(EJ64-EH64,"-") -> 0 | EO64: =IFERROR(EJ64/EH64,"-") -> 1
A65: 4.6 | B65: АВТОМОБИЛЬНЫЙ БЕНЗИН, ВСЕГО: | C65: 100332017 | J65: =R65+AX65+CD65+DJ65 -> 820.3 | L65: =T65+AZ65+CF65+DL65 -> 820.3 | N65: =V65+BB65+CH65+DN65 -> 3.031 | P65: =IFERROR(L65-J65,"-") -> 0 | Q65: =IFERROR(L65/J65,"-") -> 1 | R65: =Z65+AH65+AP65 -> 247.8 | T65: =AB65+AJ65+AR65 -> 247.8 | V65: =AD65+AL65+AT65 -> 0 | X65: =IFERROR(T65-R65,"-") -> 0 | Y65: =IFERROR(T65/R65,"-") -> 1 | Z65: 85.7 | AB65: 85.7 | AF65: =IFERROR(AB65-Z65,"-") -> 0 | AG65: =IFERROR(AB65/Z65,"-") -> 1 | AH65: 77.2 | AJ65: 77.2 | AN65: =IFERROR(AJ65-AH65,"-") -> 0 | AO65: =IFERROR(AJ65/AH65,"-") -> 1 | AP65: 84.9 | AR65: 84.9 | AV65: =IFERROR(AR65-AP65,"-") -> 0 | AW65: =IFERROR(AR65/AP65,"-") -> 1 | AX65: =BF65+BN65+BV65 -> 107.1 | AZ65: =BH65+BP65+BX65 -> 107.1 | BB65: =BJ65+BR65+BZ65 -> 3.031 | BD65: =IFERROR(AZ65-AX65,"-") -> 0 | BE65: =IFERROR(AZ65/AX65,"-") -> 1 | BF65: 82.9 | BH65: 82.9 | BL65: =IFERROR(BH65-BF65,"-") -> 0 | BM65: =IFERROR(BH65/BF65,"-") -> 1 | BN65: 24.2 | BP65: 24.2 | BR65: 3.031 | BT65: =IFERROR(BP65-BN65,"-") -> 0 | BU65: =IFERROR(BP65/BN65,"-") -> 1 | CB65: =IFERROR(BX65-BV65,"-") -> 0 | CC65: =IFERROR(BX65/BV65,"-") -> - | CD65: =CL65+CT65+DB65 -> 209.1 | CF65: =CN65+CV65+DD65 -> 209.1 | CH65: =CP65+CX65+DF65 -> 0 | CJ65: =IFERROR(CF65-CD65,"-") -> 0 | CK65: =IFERROR(CF65/CD65,"-") -> 1 | CL65: 33.5 | CN65: 33.5 | CR65: =IFERROR(CN65-CL65,"-") -> 0 | CS65: =IFERROR(CN65/CL65,"-") -> 1 | CT65: 89.3 | CV65: 89.3 | CZ65: =IFERROR(CV65-CT65,"-") -> 0 | DA65: =IFERROR(CV65/CT65,"-") -> 1 | DB65: 86.3 | DD65: 86.3 | DH65: =IFERROR(DD65-DB65,"-") -> 0 | DI65: =IFERROR(DD65/DB65,"-") -> 1 | DJ65: =DR65+DZ65+EH65 -> 256.3 | DL65: =DT65+EB65+EJ65 -> 256.3 | DN65: =DV65+ED65+EL65 -> 0 | DP65: =IFERROR(DL65-DJ65,"-") -> 0 | DQ65: =IFERROR(DL65/DJ65,"-") -> 1 | DR65: 88.8 | DT65: 88.8 | DX65: =IFERROR(DT65-DR65,"-") -> 0 | DY65: =IFERROR(DT65/DR65,"-") -> 1 | DZ65: 82.4 | EB65: 82.4 | EF65: =IFERROR(EB65-DZ65,"-") -> 0 | EG65: =IFERROR(EB65/DZ65,"-") -> 1 | EH65: 85.1 | EJ65: 85.1 | EN65: =IFERROR(EJ65-EH65,"-") -> 0 | EO65: =IFERROR(EJ65/EH65,"-") -> 1
B66: ОЧ-80 | C66: 100335688 | J66: =R66+AX66+CD66+DJ66 -> 0 | L66: =T66+AZ66+CF66+DL66 -> 0 | N66: =V66+BB66+CH66+DN66 -> 0 | P66: =IFERROR(L66-J66,"-") -> 0 | Q66: =IFERROR(L66/J66,"-") -> - | R66: =Z66+AH66+AP66 -> 0 | T66: =AB66+AJ66+AR66 -> 0 | V66: =AD66+AL66+AT66 -> 0 | X66: =IFERROR(T66-R66,"-") -> 0 | Y66: =IFERROR(T66/R66,"-") -> - | Z66: 0 | AB66: 0 | AD66: 0 | AF66: =IFERROR(AB66-Z66,"-") -> 0 | AG66: =IFERROR(AB66/Z66,"-") -> - | AH66: 0 | AJ66: 0 | AL66: 0 | AN66: =IFERROR(AJ66-AH66,"-") -> 0 | AO66: =IFERROR(AJ66/AH66,"-") -> - | AP66: 0 | AR66: 0 | AT66: 0 | AV66: =IFERROR(AR66-AP66,"-") -> 0 | AW66: =IFERROR(AR66/AP66,"-") -> - | AX66: =BF66+BN66+BV66 -> 0 | AZ66: =BH66+BP66+BX66 -> 0 | BB66: =BJ66+BR66+BZ66 -> 0 | BD66: =IFERROR(AZ66-AX66,"-") -> 0 | BE66: =IFERROR(AZ66/AX66,"-") -> - | BF66: 0 | BH66: 0 | BJ66: 0 | BL66: =IFERROR(BH66-BF66,"-") -> 0 | BM66: =IFERROR(BH66/BF66,"-") -> - | BN66: 0 | BP66: 0 | BR66: 0 | BT66: =IFERROR(BP66-BN66,"-") -> 0 | BU66: =IFERROR(BP66/BN66,"-") -> - | BV66: 0 | BX66: 0 | BZ66: 0 | CB66: =IFERROR(BX66-BV66,"-") -> 0 | CC66: =IFERROR(BX66/BV66,"-") -> - | CD66: =CL66+CT66+DB66 -> 0 | CF66: =CN66+CV66+DD66 -> 0 | CH66: =CP66+CX66+DF66 -> 0 | CJ66: =IFERROR(CF66-CD66,"-") -> 0 | CK66: =IFERROR(CF66/CD66,"-") -> - | CL66: 0 | CN66: 0 | CR66: =IFERROR(CN66-CL66,"-") -> 0 | CS66: =IFERROR(CN66/CL66,"-") -> - | CT66: 0 | CV66: 0 | CZ66: =IFERROR(CV66-CT66,"-") -> 0 | DA66: =IFERROR(CV66/CT66,"-") -> - | DB66: 0 | DD66: 0 | DH66: =IFERROR(DD66-DB66,"-") -> 0 | DI66: =IFERROR(DD66/DB66,"-") -> - | DJ66: =DR66+DZ66+EH66 -> 0 | DL66: =DT66+EB66+EJ66 -> 0 | DN66: =DV66+ED66+EL66 -> 0 | DP66: =IFERROR(DL66-DJ66,"-") -> 0 | DQ66: =IFERROR(DL66/DJ66,"-") -> - | DR66: 0 | DT66: 0 | DX66: =IFERROR(DT66-DR66,"-") -> 0 | DY66: =IFERROR(DT66/DR66,"-") -> - | DZ66: 0 | EB66: 0 | EF66: =IFERROR(EB66-DZ66,"-") -> 0 | EG66: =IFERROR(EB66/DZ66,"-") -> - | EH66: 0 | EJ66: 0 | EN66: =IFERROR(EJ66-EH66,"-") -> 0 | EO66: =IFERROR(EJ66/EH66,"-") -> -
A67: 4.6.1 | B67: ОЧ-92 | C67: 100332018 | J67: =R67+AX67+CD67+DJ67 -> 525.3 | L67: =T67+AZ67+CF67+DL67 -> 525.3 | N67: =V67+BB67+CH67+DN67 -> 3.031 | P67: =IFERROR(L67-J67,"-") -> 0 | Q67: =IFERROR(L67/J67,"-") -> 1 | R67: =Z67+AH67+AP67 -> 157.8 | T67: =AB67+AJ67+AR67 -> 157.8 | V67: =AD67+AL67+AT67 -> 0 | X67: =IFERROR(T67-R67,"-") -> 0 | Y67: =IFERROR(T67/R67,"-") -> 1 | Z67: 55.7 | AB67: 55.7 | AD67: 0 | AF67: =IFERROR(AB67-Z67,"-") -> 0 | AG67: =IFERROR(AB67/Z67,"-") -> 1 | AH67: 47.2 | AJ67: 47.2 | AL67: 0 | AN67: =IFERROR(AJ67-AH67,"-") -> 0 | AO67: =IFERROR(AJ67/AH67,"-") -> 1 | AP67: 54.9 | AR67: 54.9 | AT67: 0 | AV67: =IFERROR(AR67-AP67,"-") -> 0 | AW67: =IFERROR(AR67/AP67,"-") -> 1 | AX67: =BF67+BN67+BV67 -> 62.1 | AZ67: =BH67+BP67+BX67 -> 62.1 | BB67: =BJ67+BR67+BZ67 -> 3.031 | BD67: =IFERROR(AZ67-AX67,"-") -> 0 | BE67: =IFERROR(AZ67/AX67,"-") -> 1 | BF67: 47.9 | BH67: 47.9 | BJ67: 0 | BL67: =IFERROR(BH67-BF67,"-") -> 0 | BM67: =IFERROR(BH67/BF67,"-") -> 1 | BN67: 14.2 | BP67: 14.2 | BR67: 3.031 | BT67: =IFERROR(BP67-BN67,"-") -> 0 | BU67: =IFERROR(BP67/BN67,"-") -> 1 | BV67: 0 | BX67: 0 | BZ67: 0 | CB67: =IFERROR(BX67-BV67,"-") -> 0 | CC67: =IFERROR(BX67/BV67,"-") -> - | CD67: =CL67+CT67+DB67 -> 139.1 | CF67: =CN67+CV67+DD67 -> 139.1 | CH67: =CP67+CX67+DF67 -> 0 | CJ67: =IFERROR(CF67-CD67,"-") -> 0 | CK67: =IFERROR(CF67/CD67,"-") -> 1 | CL67: 33.5 | CN67: 33.5 | CR67: =IFERROR(CN67-CL67,"-") -> 0 | CS67: =IFERROR(CN67/CL67,"-") -> 1 | CT67: 54.3 | CV67: 54.3 | CZ67: =IFERROR(CV67-CT67,"-") -> 0 | DA67: =IFERROR(CV67/CT67,"-") -> 1 | DB67: 51.3 | DD67: 51.3 | DH67: =IFERROR(DD67-DB67,"-") -> 0 | DI67: =IFERROR(DD67/DB67,"-") -> 1 | DJ67: =DR67+DZ67+EH67 -> 166.3 | DL67: =DT67+EB67+EJ67 -> 166.3 | DN67: =DV67+ED67+EL67 -> 0 | DP67: =IFERROR(DL67-DJ67,"-") -> 0 | DQ67: =IFERROR(DL67/DJ67,"-") -> 1 | DR67: 58.8 | DT67: 58.8 | DX67: =IFERROR(DT67-DR67,"-") -> 0 | DY67: =IFERROR(DT67/DR67,"-") -> 1 | DZ67: 52.4 | EB67: 52.4 | EF67: =IFERROR(EB67-DZ67,"-") -> 0 | EG67: =IFERROR(EB67/DZ67,"-") -> 1 | EH67: 55.1 | EJ67: 55.1 | EN67: =IFERROR(EJ67-EH67,"-") -> 0 | EO67: =IFERROR(EJ67/EH67,"-") -> 1
A68: 4.6.2 | B68: ОЧ-95 | C68: 100332019 | J68: =R68+AX68+CD68+DJ68 -> 295 | L68: =T68+AZ68+CF68+DL68 -> 295 | N68: =V68+BB68+CH68+DN68 -> 0 | P68: =IFERROR(L68-J68,"-") -> 0 | Q68: =IFERROR(L68/J68,"-") -> 1 | R68: =Z68+AH68+AP68 -> 90 | T68: =AB68+AJ68+AR68 -> 90 | V68: =AD68+AL68+AT68 -> 0 | X68: =IFERROR(T68-R68,"-") -> 0 | Y68: =IFERROR(T68/R68,"-") -> 1 | Z68: 30 | AB68: 30 | AD68: 0 | AF68: =IFERROR(AB68-Z68,"-") -> 0 | AG68: =IFERROR(AB68/Z68,"-") -> 1 | AH68: 30 | AJ68: 30 | AL68: 0 | AN68: =IFERROR(AJ68-AH68,"-") -> 0 | AO68: =IFERROR(AJ68/AH68,"-") -> 1 | AP68: 30 | AR68: 30 | AT68: 0 | AV68: =IFERROR(AR68-AP68,"-") -> 0 | AW68: =IFERROR(AR68/AP68,"-") -> 1 | AX68: =BF68+BN68+BV68 -> 45 | AZ68: =BH68+BP68+BX68 -> 45 | BB68: =BJ68+BR68+BZ68 -> 0 | BD68: =IFERROR(AZ68-AX68,"-") -> 0 | BE68: =IFERROR(AZ68/AX68,"-") -> 1 | BF68: 35 | BH68: 35 | BJ68: 0 | BL68: =IFERROR(BH68-BF68,"-") -> 0 | BM68: =IFERROR(BH68/BF68,"-") -> 1 | BN68: 10 | BP68: 10 | BR68: 0 | BT68: =IFERROR(BP68-BN68,"-") -> 0 | BU68: =IFERROR(BP68/BN68,"-") -> 1 | BV68: 0 | BX68: 0 | BZ68: 0 | CB68: =IFERROR(BX68-BV68,"-") -> 0 | CC68: =IFERROR(BX68/BV68,"-") -> - | CD68: =CL68+CT68+DB68 -> 70 | CF68: =CN68+CV68+DD68 -> 70 | CH68: =CP68+CX68+DF68 -> 0 | CJ68: =IFERROR(CF68-CD68,"-") -> 0 | CK68: =IFERROR(CF68/CD68,"-") -> 1 | CL68: 0 | CN68: 0 | CR68: =IFERROR(CN68-CL68,"-") -> 0 | CS68: =IFERROR(CN68/CL68,"-") -> - | CT68: 35 | CV68: 35 | CZ68: =IFERROR(CV68-CT68,"-") -> 0 | DA68: =IFERROR(CV68/CT68,"-") -> 1 | DB68: 35 | DD68: 35 | DH68: =IFERROR(DD68-DB68,"-") -> 0 | DI68: =IFERROR(DD68/DB68,"-") -> 1 | DJ68: =DR68+DZ68+EH68 -> 90 | DL68: =DT68+EB68+EJ68 -> 90 | DN68: =DV68+ED68+EL68 -> 0 | DP68: =IFERROR(DL68-DJ68,"-") -> 0 | DQ68: =IFERROR(DL68/DJ68,"-") -> 1 | DR68: 30 | DT68: 30 | DX68: =IFERROR(DT68-DR68,"-") -> 0 | DY68: =IFERROR(DT68/DR68,"-") -> 1 | DZ68: 30 | EB68: 30 | EF68: =IFERROR(EB68-DZ68,"-") -> 0 | EG68: =IFERROR(EB68/DZ68,"-") -> 1 | EH68: 30 | EJ68: 30 | EN68: =IFERROR(EJ68-EH68,"-") -> 0 | EO68: =IFERROR(EJ68/EH68,"-") -> 1
A69: 4.7 | B69: ДГКЛ | C69: 100332020 | J69: =R69+AX69+CD69+DJ69 -> 56.4 | L69: =T69+AZ69+CF69+DL69 -> 56.4 | N69: =V69+BB69+CH69+DN69 -> 41.691266 | P69: =IFERROR(L69-J69,"-") -> 0 | Q69: =IFERROR(L69/J69,"-") -> 1 | R69: =Z69+AH69+AP69 -> 6.2 | T69: =AB69+AJ69+AR69 -> 6.2 | V69: =AD69+AL69+AT69 -> 0 | X69: =IFERROR(T69-R69,"-") -> 0 | Y69: =IFERROR(T69/R69,"-") -> 1 | Z69: 1.8 | AB69: 1.8 | AD69: 0 | AF69: =IFERROR(AB69-Z69,"-") -> 0 | AG69: =IFERROR(AB69/Z69,"-") -> 1 | AH69: 1.8 | AJ69: 1.8 | AL69: 0 | AN69: =IFERROR(AJ69-AH69,"-") -> 0 | AO69: =IFERROR(AJ69/AH69,"-") -> 1 | AP69: 2.6 | AR69: 2.6 | AT69: 0 | AV69: =IFERROR(AR69-AP69,"-") -> 0 | AW69: =IFERROR(AR69/AP69,"-") -> 1 | AX69: =BF69+BN69+BV69 -> 7.3 | AZ69: =BH69+BP69+BX69 -> 7.3 | BB69: =BJ69+BR69+BZ69 -> 41.691266 | BD69: =IFERROR(AZ69-AX69,"-") -> 0 | BE69: =IFERROR(AZ69/AX69,"-") -> 1 | BF69: 5.4 | BH69: 5.4 | BJ69: 14.394266 | BL69: =IFERROR(BH69-BF69,"-") -> 0 | BM69: =IFERROR(BH69/BF69,"-") -> 1 | BN69: 1.9 | BP69: 1.9 | BR69: 27.297 | BT69: =IFERROR(BP69-BN69,"-") -> 0 | BU69: =IFERROR(BP69/BN69,"-") -> 1 | BV69: 0 | BX69: 0 | BZ69: 0 | CB69: =IFERROR(BX69-BV69,"-") -> 0 | CC69: =IFERROR(BX69/BV69,"-") -> - | CD69: =CL69+CT69+DB69 -> 37.5 | CF69: =CN69+CV69+DD69 -> 37.5 | CH69: =CP69+CX69+DF69 -> 0 | CJ69: =IFERROR(CF69-CD69,"-") -> 0 | CK69: =IFERROR(CF69/CD69,"-") -> 1 | CL69: 33.5 | CN69: 33.5 | CR69: =IFERROR(CN69-CL69,"-") -> 0 | CS69: =IFERROR(CN69/CL69,"-") -> 1 | CT69: 2 | CV69: 2 | CZ69: =IFERROR(CV69-CT69,"-") -> 0 | DA69: =IFERROR(CV69/CT69,"-") -> 1 | DB69: 2 | DD69: 2 | DH69: =IFERROR(DD69-DB69,"-") -> 0 | DI69: =IFERROR(DD69/DB69,"-") -> 1 | DJ69: =DR69+DZ69+EH69 -> 5.4 | DL69: =DT69+EB69+EJ69 -> 5.4 | DN69: =DV69+ED69+EL69 -> 0 | DP69: =IFERROR(DL69-DJ69,"-") -> 0 | DQ69: =IFERROR(DL69/DJ69,"-") -> 1 | DR69: 1.8 | DT69: 1.8 | DX69: =IFERROR(DT69-DR69,"-") -> 0 | DY69: =IFERROR(DT69/DR69,"-") -> 1 | DZ69: 1.8 | EB69: 1.8 | EF69: =IFERROR(EB69-DZ69,"-") -> 0 | EG69: =IFERROR(EB69/DZ69,"-") -> 1 | EH69: 1.8 | EJ69: 1.8 | EN69: =IFERROR(EJ69-EH69,"-") -> 0 | EO69: =IFERROR(EJ69/EH69,"-") -> 1
A70: 4.8 | B70: ДГКС | C70: 100332021 | J70: =R70+AX70+CD70+DJ70 -> 0 | L70: =T70+AZ70+CF70+DL70 -> 0 | N70: =V70+BB70+CH70+DN70 -> 22.136188 | P70: =IFERROR(L70-J70,"-") -> 0 | Q70: =IFERROR(L70/J70,"-") -> - | R70: =Z70+AH70+AP70 -> 0 | T70: =AB70+AJ70+AR70 -> 0 | V70: =AD70+AL70+AT70 -> 0 | X70: =IFERROR(T70-R70,"-") -> 0 | Y70: =IFERROR(T70/R70,"-") -> - | Z70: 0 | AB70: 0 | AD70: 0 | AF70: =IFERROR(AB70-Z70,"-") -> 0 | AG70: =IFERROR(AB70/Z70,"-") -> - | AH70: 0 | AJ70: 0 | AL70: 0 | AN70: =IFERROR(AJ70-AH70,"-") -> 0 | AO70: =IFERROR(AJ70/AH70,"-") -> - | AP70: 0 | AR70: 0 | AT70: 0 | AV70: =IFERROR(AR70-AP70,"-") -> 0 | AW70: =IFERROR(AR70/AP70,"-") -> - | AX70: =BF70+BN70+BV70 -> 0 | AZ70: =BH70+BP70+BX70 -> 0 | BB70: =BJ70+BR70+BZ70 -> 22.136188 | BD70: =IFERROR(AZ70-AX70,"-") -> 0 | BE70: =IFERROR(AZ70/AX70,"-") -> - | BF70: 0 | BH70: 0 | BJ70: 8.419188 | BL70: =IFERROR(BH70-BF70,"-") -> 0 | BM70: =IFERROR(BH70/BF70,"-") -> - | BN70: 0 | BP70: 0 | BR70: 13.717 | BT70: =IFERROR(BP70-BN70,"-") -> 0 | BU70: =IFERROR(BP70/BN70,"-") -> - | BV70: 0 | BX70: 0 | BZ70: 0 | CB70: =IFERROR(BX70-BV70,"-") -> 0 | CC70: =IFERROR(BX70/BV70,"-") -> - | CD70: =CL70+CT70+DB70 -> 0 | CF70: =CN70+CV70+DD70 -> 0 | CH70: =CP70+CX70+DF70 -> 0 | CJ70: =IFERROR(CF70-CD70,"-") -> 0 | CK70: =IFERROR(CF70/CD70,"-") -> - | CL70: 0 | CN70: 0 | CR70: =IFERROR(CN70-CL70,"-") -> 0 | CS70: =IFERROR(CN70/CL70,"-") -> - | CT70: 0 | CV70: 0 | CZ70: =IFERROR(CV70-CT70,"-") -> 0 | DA70: =IFERROR(CV70/CT70,"-") -> - | DB70: 0 | DD70: 0 | DH70: =IFERROR(DD70-DB70,"-") -> 0 | DI70: =IFERROR(DD70/DB70,"-") -> - | DJ70: =DR70+DZ70+EH70 -> 0 | DL70: =DT70+EB70+EJ70 -> 0 | DN70: =DV70+ED70+EL70 -> 0 | DP70: =IFERROR(DL70-DJ70,"-") -> 0 | DQ70: =IFERROR(DL70/DJ70,"-") -> - | DR70: 0 | DT70: 0 | DX70: =IFERROR(DT70-DR70,"-") -> 0 | DY70: =IFERROR(DT70/DR70,"-") -> - | DZ70: 0 | EB70: 0 | EF70: =IFERROR(EB70-DZ70,"-") -> 0 | EG70: =IFERROR(EB70/DZ70,"-") -> - | EH70: 0 | EJ70: 0 | EN70: =IFERROR(EJ70-EH70,"-") -> 0 | EO70: =IFERROR(EJ70/EH70,"-") -> -
